Workbook

Sheet Cover & Notes
B2: Capital Structure Analysis — Excel Workings
B3: Determinants and Impact of Capital Structure on Firm Performance: An Empirical Analysis of Textile & Apparel Companies in India using CMIE Prowess Database / Screener.in
B5: Course | C5: SY Corporate Finance | Subject Teacher: Dr. Tessy Thadathil | Division D | Academic Year 2026–27
B6: Prepared by | C6: 5804 Nikhilranjan Manishkumar Jha · 5821 Piyush Vilas Gharte · 5822 Chandan Pavan Tejnani · 5823 Prantik Mukherjee · 5871 Gravit Goyal
B7: Data collected by | C7: Chandan: KPR Mill, Welspun Living | Piyush: Indo Count, Vardhman | Nikhilranjan: Trident, Arvind | Prantik: Nitin Spinners, Sutlej | Gravit: Gokaldas, Siyaram (two companies each)
B8: Code & data (GitHub) | C8: https://github.com/tejnanichandan-ctrl/capital-structure-textiles-india
B9: Sample & period | C9: 10 NSE/BSE-listed textile & apparel companies | FY2015-16 to FY2024-25 (100 firm-years) | Standalone figures
B10: Data source | C10: Screener.in (standardised BSE/NSE filings), spot-checked against CMIE Prowess; sector context from ET Wealth (Aug 2026)
B12: Workbook Guide
B13: Sheet | C13: What it contains
B14: Raw Data | C14: Screener.in figures (Rs crore), FY2014-15 to FY2024-25; FY2014-15 is used only as the base year for sales growth.
B15: 10 company sheets | C15: Profile of each company and its 10-year ratios, with average and SD rows.
B16: Ratios Panel | C16: All 100 firm-years: D/E, ROE, ROA, EPS, Size, Sales Growth, Tangibility, Liquidity, COVID dummy, regression inputs.
B17: Descriptive Stats | C17: Mean, SD, min and max by company (report Table 5) and year-wise sector averages (Figure 2).
B18: Correlation Matrix | C18: Pearson correlations between all variables, including liquidity (report Table 6).
B19: Regression Output | C19: Live LINEST regressions: ROE model, ROA model and ROE model with COVID dummy (report Table 8).
B20: ET Wealth Link | C20: Article data, analyst ratings and a comparison of the three ET picks with the other seven companies (report Table 11, Figure 4).
B21: Theory Formulas | C21: Capital structure theory formulas (NI, NOI, Traditional, MM, Trade-off) with a worked example (report Table 1).
B22: Formulas Used | C22: Every Excel formula in this workbook, explained.
B24: Key Notes
B25: Liquidity measure | C25: Current Ratio proxy = Other Assets ÷ Other Liabilities. Screener.in groups current assets (inventory, receivables, cash) under Other Assets and non-debt current liabilities under Other Liabilities; short-term borrowings sit in Borrowings, so the proxy is higher than a textbook current ratio and is used for comparison only.
B26: COVID-19 | C26: FY2019-20 and FY2020-21 are flagged with a dummy variable and controlled for in Regression Model 3.
B27: Sample note | C27: Raymond Ltd (named in the ET Wealth article) was excluded because its FY2024 demerger makes later ratios incomparable; Siyaram Silk Mills was substituted.
B28: Validation | C28: A sample of Screener.in figures was cross-checked against CMIE Prowess; differences appeared only at the second decimal place and do not change any ratio.

Sheet Raw Data
A1: Capital Structure Analysis — Raw Financial Data (Rs. Crores)
A2: Sector: Textiles & Apparels (India, NSE/BSE-listed) | Sample: 10 companies | Source: Screener.in, standardized company financials (BSE/NSE filings). Screener.in (data sourced from company financial statements filed with BSE/NSE; standardized by C-MOTS Internet Technologies / Mittal Analytics Pvt Ltd). CMIE Prowess not directly accessible; Screener.in used as the substitute per agreed scope. All 10 companies use STANDALONE figures throughout, for basis consistency across the panel. Other Assets and Other Liabilities (columns M–N) were added from the same Screener.in standalone balance sheets for the liquidity measure; every overlapping figure was cross-checked against columns G–K.
A4: Company | B4: Basis | C4: FY Ending Mar | D4: Sales | E4: EBIT (Op. Profit) | F4: Net Profit | G4: Equity Capital | H4: Reserves & Surplus | I4: Borrowings | J4: Total Assets | K4: Fixed Assets (+CWIP) | L4: EPS (Rs.) | M4: Other Assets | N4: Other Liabilities
A5: KPR Mill | B5: Standalone | C5: 2015 | D5: 2080 | E5: 357 | F5: 146 | G5: 38 | H5: 826 | I5: 672 | J5: 1731 | K5: 924 | L5: 3.87 | M5: 727 | N5: 196
A6: KPR Mill | B6: Standalone | C6: 2016 | D6: 1961 | E6: 356 | F6: 156 | G6: 38 | H6: 943 | I6: 590 | J6: 1730 | K6: 894 | L6: 4.14 | M6: 758 | N6: 160
A7: KPR Mill | B7: Standalone | C7: 2017 | D7: 2219 | E7: 446 | F7: 238 | G7: 37 | H7: 1081 | I7: 491 | J7: 1800 | K7: 918 | L7: 6.45 | M7: 794 | N7: 191
A8: KPR Mill | B8: Standalone | C8: 2018 | D8: 2512 | E8: 429 | F8: 225 | G8: 37 | H8: 1300 | I8: 346 | J8: 1930 | K8: 865 | L8: 6.09 | M8: 975 | N8: 247
A9: KPR Mill | B9: Standalone | C9: 2019 | D9: 2979 | E9: 507 | F9: 289 | G9: 36 | H9: 1475 | I9: 654 | J9: 2397 | K9: 798 | L9: 7.97 | M9: 1519 | N9: 232
A10: KPR Mill | B10: Standalone | C10: 2020 | D10: 2898 | E10: 475 | F10: 295 | G10: 34 | H10: 1470 | I10: 472 | J10: 2187 | K10: 873 | L10: 8.56 | M10: 1225 | N10: 211
A11: KPR Mill | B11: Standalone | C11: 2021 | D11: 2954 | E11: 664 | F11: 433 | G11: 34 | H11: 1872 | I11: 317 | J11: 2485 | K11: 815 | L11: 12.57 | M11: 1250 | N11: 262
A12: KPR Mill | B12: Standalone | C12: 2022 | D12: 4074 | E12: 984 | F12: 731 | G12: 34 | H12: 2598 | I12: 418 | J12: 3359 | K12: 850 | L12: 21.24 | M12: 1656 | N12: 309
A13: KPR Mill | B13: Standalone | C13: 2023 | D13: 4740 | E13: 799 | F13: 635 | G13: 34 | H13: 2939 | I13: 498 | J13: 3874 | K13: 971 | L13: 18.58 | M13: 2018 | N13: 403
A14: KPR Mill | B14: Standalone | C14: 2024 | D14: 4054 | E14: 595 | F14: 555 | G14: 34 | H14: 3340 | I14: 287 | J14: 3919 | K14: 1070 | L14: 16.23 | M14: 2088 | N14: 258
A15: KPR Mill | B15: Standalone | C15: 2025 | D15: 4216 | E15: 764 | F15: 653 | G15: 34 | H15: 3822 | I15: 241 | J15: 4403 | K15: 1122 | L15: 19.11 | M15: 2326 | N15: 306
A16: Welspun Living | B16: Standalone | C16: 2015 | D16: 4390 | E16: 1042 | F16: 510 | G16: 100 | H16: 1332 | I16: 2467 | J16: 4827 | K16: 2052 | L16: 5.08 | M16: 2069 | N16: 928
... A114: Siyaram Silk Mills | B114: Standalone | C114: 2025 | D114: 2220 | E114: 277 | F114: 199 | G114: 9 | H114: 1279 | I114: 262 | J114: 1893 | K114: 592 | L114: 43.8 | M114: 1083 | N114: 342

Sheet KPR Mill
A1: KPR Mill
A3: Screener Ticker | B3: KPRMILL
A4: Basis | B4: Standalone
A5: Primary Business | B5: Yarn, Fabric, Garments, Apparel — vertically integrated composite mill
A6: Year Established | B6: 1984 (garment exports since 1989); incorporated as KPR Mill Ltd in 2003
A7: Headquarters | B7: Coimbatore, Tamil Nadu
A8: Promoter / Group | B8: K.P.R. Group — founder P. Nataraj and family
A9: Manufacturing Locations | B9: Sathyamangalam, Tirupur, Perundurai, Coimbatore (Tamil Nadu)
A10: Listed On | B10: NSE & BSE (BSE code: 532889)
A11: Note | B11: Anchor company — featured in the source ET Wealth article
A13: 10-Year Financials & Computed Ratios (FY2015-16 to FY2024-25)
A14: FY | B14: Sales | C14: EBIT | D14: Net Profit | E14: Total Equity | F14: Borrowings | G14: Total Assets | H14: Fixed Assets | I14: D/E Ratio | J14: ROE | K14: ROA | L14: Size (ln TA) | M14: Sales Growth % | N14: Tangibility | O14: EPS (Rs.) | P14: Liquidity (CR proxy)
A15: FY15-16 | B15: ='Raw Data'!D6 -> 1961 | C15: ='Raw Data'!E6 -> 356 | D15: ='Raw Data'!F6 -> 156 | E15: ='Raw Data'!G6+'Raw Data'!H6 -> 981 | F15: ='Raw Data'!I6 -> 590 | G15: ='Raw Data'!J6 -> 1730 | H15: ='Raw Data'!K6 -> 894 | I15: =F15/E15 -> 0.60142712 | J15: =D15/E15 -> 0.15902141 | K15: =D15/G15 -> 0.09017341 | L15: =LN(G15) -> 7.4558767 | M15: =(B15-'Raw Data'!D5)/'Raw Data'!D5 -> -0.057211538 | N15: =H15/G15 -> 0.51676301 | O15: ='Raw Data'!L6 -> 4.14 | P15: ='Raw Data'!M6/'Raw Data'!N6 -> 4.7375
A16: FY16-17 | B16: ='Raw Data'!D7 -> 2219 | C16: ='Raw Data'!E7 -> 446 | D16: ='Raw Data'!F7 -> 238 | E16: ='Raw Data'!G7+'Raw Data'!H7 -> 1118 | F16: ='Raw Data'!I7 -> 491 | G16: ='Raw Data'!J7 -> 1800 | H16: ='Raw Data'!K7 -> 918 | I16: =F16/E16 -> 0.4391771 | J16: =D16/E16 -> 0.21288014 | K16: =D16/G16 -> 0.13222222 | L16: =LN(G16) -> 7.4955419 | M16: =(B16-'Raw Data'!D6)/'Raw Data'!D6 -> 0.13156553 | N16: =H16/G16 -> 0.51 | O16: ='Raw Data'!L7 -> 6.45 | P16: ='Raw Data'!M7/'Raw Data'!N7 -> 4.1570681
A17: FY17-18 | B17: ='Raw Data'!D8 -> 2512 | C17: ='Raw Data'!E8 -> 429 | D17: ='Raw Data'!F8 -> 225 | E17: ='Raw Data'!G8+'Raw Data'!H8 -> 1337 | F17: ='Raw Data'!I8 -> 346 | G17: ='Raw Data'!J8 -> 1930 | H17: ='Raw Data'!K8 -> 865 | I17: =F17/E17 -> 0.25878833 | J17: =D17/E17 -> 0.16828721 | K17: =D17/G17 -> 0.11658031 | L17: =LN(G17) -> 7.5652753 | M17: =(B17-'Raw Data'!D7)/'Raw Data'!D7 -> 0.13204146 | N17: =H17/G17 -> 0.44818653 | O17: ='Raw Data'!L8 -> 6.09 | P17: ='Raw Data'!M8/'Raw Data'!N8 -> 3.9473684
A18: FY18-19 | B18: ='Raw Data'!D9 -> 2979 | C18: ='Raw Data'!E9 -> 507 | D18: ='Raw Data'!F9 -> 289 | E18: ='Raw Data'!G9+'Raw Data'!H9 -> 1511 | F18: ='Raw Data'!I9 -> 654 | G18: ='Raw Data'!J9 -> 2397 | H18: ='Raw Data'!K9 -> 798 | I18: =F18/E18 -> 0.43282594 | J18: =D18/E18 -> 0.19126406 | K18: =D18/G18 -> 0.12056738 | L18: =LN(G18) -> 7.7819732 | M18: =(B18-'Raw Data'!D8)/'Raw Data'!D8 -> 0.18590764 | N18: =H18/G18 -> 0.33291615 | O18: ='Raw Data'!L9 -> 7.97 | P18: ='Raw Data'!M9/'Raw Data'!N9 -> 6.5474138
A19: FY19-20 | B19: ='Raw Data'!D10 -> 2898 | C19: ='Raw Data'!E10 -> 475 | D19: ='Raw Data'!F10 -> 295 | E19: ='Raw Data'!G10+'Raw Data'!H10 -> 1504 | F19: ='Raw Data'!I10 -> 472 | G19: ='Raw Data'!J10 -> 2187 | H19: ='Raw Data'!K10 -> 873 | I19: =F19/E19 -> 0.31382979 | J19: =D19/E19 -> 0.19614362 | K19: =D19/G19 -> 0.13488797 | L19: =LN(G19) -> 7.690286 | M19: =(B19-'Raw Data'!D9)/'Raw Data'!D9 -> -0.027190332 | N19: =H19/G19 -> 0.39917695 | O19: ='Raw Data'!L10 -> 8.56 | P19: ='Raw Data'!M10/'Raw Data'!N10 -> 5.8056872
A20: FY20-21 | B20: ='Raw Data'!D11 -> 2954 | C20: ='Raw Data'!E11 -> 664 | D20: ='Raw Data'!F11 -> 433 | E20: ='Raw Data'!G11+'Raw Data'!H11 -> 1906 | F20: ='Raw Data'!I11 -> 317 | G20: ='Raw Data'!J11 -> 2485 | H20: ='Raw Data'!K11 -> 815 | I20: =F20/E20 -> 0.16631689 | J20: =D20/E20 -> 0.22717733 | K20: =D20/G20 -> 0.17424547 | L20: =LN(G20) -> 7.8180279 | M20: =(B20-'Raw Data'!D10)/'Raw Data'!D10 -> 0.019323671 | N20: =H20/G20 -> 0.32796781 | O20: ='Raw Data'!L11 -> 12.57 | P20: ='Raw Data'!M11/'Raw Data'!N11 -> 4.7709924
A21: FY21-22 | B21: ='Raw Data'!D12 -> 4074 | C21: ='Raw Data'!E12 -> 984 | D21: ='Raw Data'!F12 -> 731 | E21: ='Raw Data'!G12+'Raw Data'!H12 -> 2632 | F21: ='Raw Data'!I12 -> 418 | G21: ='Raw Data'!J12 -> 3359 | H21: ='Raw Data'!K12 -> 850 | I21: =F21/E21 -> 0.15881459 | J21: =D21/E21 -> 0.27773556 | K21: =D21/G21 -> 0.21762429 | L21: =LN(G21) -> 8.1193986 | M21: =(B21-'Raw Data'!D11)/'Raw Data'!D11 -> 0.37914692 | N21: =H21/G21 -> 0.2530515 | O21: ='Raw Data'!L12 -> 21.24 | P21: ='Raw Data'!M12/'Raw Data'!N12 -> 5.3592233
A22: FY22-23 | B22: ='Raw Data'!D13 -> 4740 | C22: ='Raw Data'!E13 -> 799 | D22: ='Raw Data'!F13 -> 635 | E22: ='Raw Data'!G13+'Raw Data'!H13 -> 2973 | F22: ='Raw Data'!I13 -> 498 | G22: ='Raw Data'!J13 -> 3874 | H22: ='Raw Data'!K13 -> 971 | I22: =F22/E22 -> 0.16750757 | J22: =D22/E22 -> 0.21358897 | K22: =D22/G22 -> 0.16391327 | L22: =LN(G22) -> 8.2620428 | M22: =(B22-'Raw Data'!D12)/'Raw Data'!D12 -> 0.1634757 | N22: =H22/G22 -> 0.25064533 | O22: ='Raw Data'!L13 -> 18.58 | P22: ='Raw Data'!M13/'Raw Data'!N13 -> 5.0074442
A23: FY23-24 | B23: ='Raw Data'!D14 -> 4054 | C23: ='Raw Data'!E14 -> 595 | D23: ='Raw Data'!F14 -> 555 | E23: ='Raw Data'!G14+'Raw Data'!H14 -> 3374 | F23: ='Raw Data'!I14 -> 287 | G23: ='Raw Data'!J14 -> 3919 | H23: ='Raw Data'!K14 -> 1070 | I23: =F23/E23 -> 0.085062241 | J23: =D23/E23 -> 0.16449318 | K23: =D23/G23 -> 0.14161776 | L23: =LN(G23) -> 8.2735918 | M23: =(B23-'Raw Data'!D13)/'Raw Data'!D13 -> -0.14472574 | N23: =H23/G23 -> 0.27302883 | O23: ='Raw Data'!L14 -> 16.23 | P23: ='Raw Data'!M14/'Raw Data'!N14 -> 8.0930233
A24: FY24-25 | B24: ='Raw Data'!D15 -> 4216 | C24: ='Raw Data'!E15 -> 764 | D24: ='Raw Data'!F15 -> 653 | E24: ='Raw Data'!G15+'Raw Data'!H15 -> 3856 | F24: ='Raw Data'!I15 -> 241 | G24: ='Raw Data'!J15 -> 4403 | H24: ='Raw Data'!K15 -> 1122 | I24: =F24/E24 -> 0.0625 | J24: =D24/E24 -> 0.16934647 | K24: =D24/G24 -> 0.14830797 | L24: =LN(G24) -> 8.3900414 | M24: =(B24-'Raw Data'!D14)/'Raw Data'!D14 -> 0.039960533 | N24: =H24/G24 -> 0.25482625 | O24: ='Raw Data'!L15 -> 19.11 | P24: ='Raw Data'!M15/'Raw Data'!N15 -> 7.6013072
A25: 10-YR AVERAGE | B25: =AVERAGE(B15:B24) -> 3260.7 | C25: =AVERAGE(C15:C24) -> 601.9 | D25: =AVERAGE(D15:D24) -> 421 | E25: =AVERAGE(E15:E24) -> 2119.2 | F25: =AVERAGE(F15:F24) -> 431.4 | G25: =AVERAGE(G15:G24) -> 2808.4 | H25: =AVERAGE(H15:H24) -> 917.6 | I25: =AVERAGE(I15:I24) -> 0.26862496 | ... P25: =AVERAGE(P15:P24) -> 5.6027028
A27: SD (10-yr) | I27: =STDEV(I15:I24) -> 0.1757145 | J27: =STDEV(J15:J24) -> 0.036618517 | K27: =STDEV(K15:K24) -> 0.035238976 | O27: =STDEV(O15:O24) -> 6.2622346 | P27: =STDEV(P15:P24) -> 1.4068768

Sheet Welspun Living
A1: Welspun Living
A3: Screener Ticker | B3: WELSPUNLIV
A4: Basis | B4: Standalone
A5: Primary Business | B5: Home Textiles (Towels, Bed Linen), Flooring
A6: Year Established | B6: 1985 (as Welspun Winilon Silk Mills, Palghar)
A7: Headquarters | B7: Mumbai, Maharashtra
A8: Promoter / Group | B8: Welspun Group — founder Balkrishan Goenka
A9: Manufacturing Locations | B9: Vapi & Anjar (Gujarat)
A10: Listed On | B10: NSE & BSE (BSE code: 514162)
A11: Note | B11: Anchor company — featured in the source ET Wealth article
A13: 10-Year Financials & Computed Ratios (FY2015-16 to FY2024-25)
A14: FY | B14: Sales | C14: EBIT | D14: Net Profit | E14: Total Equity | F14: Borrowings | G14: Total Assets | H14: Fixed Assets | I14: D/E Ratio | J14: ROE | K14: ROA | L14: Size (ln TA) | M14: Sales Growth % | N14: Tangibility | O14: EPS (Rs.) | P14: Liquidity (CR proxy)
A15: FY15-16 | B15: ='Raw Data'!D17 -> 4885 | C15: ='Raw Data'!E17 -> 1275 | D15: ='Raw Data'!F17 -> 648 | E15: ='Raw Data'!G17+'Raw Data'!H17 -> 1899 | F15: ='Raw Data'!I17 -> 2566 | G15: ='Raw Data'!J17 -> 5362 | H15: ='Raw Data'!K17 -> 2830 | I15: =F15/E15 -> 1.3512375 | J15: =D15/E15 -> 0.34123223 | K15: =D15/G15 -> 0.12085043 | L15: =LN(G15) -> 8.5870923 | M15: =(B15-'Raw Data'!D16)/'Raw Data'!D16 -> 0.11275626 | N15: =H15/G15 -> 0.52778814 | O15: ='Raw Data'!L17 -> 6.45 | P15: ='Raw Data'!M17/'Raw Data'!N17 -> 2.0546875
A16: FY16-17 | B16: ='Raw Data'!D18 -> 5639 | C16: ='Raw Data'!E18 -> 1370 | D16: ='Raw Data'!F18 -> 307 | E16: ='Raw Data'!G18+'Raw Data'!H18 -> 2201 | F16: ='Raw Data'!I18 -> 2738 | G16: ='Raw Data'!J18 -> 6248 | H16: ='Raw Data'!K18 -> 3057 | I16: =F16/E16 -> 1.24398 | J16: =D16/E16 -> 0.13948205 | K16: =D16/G16 -> 0.049135723 | L16: =LN(G16) -> 8.7400167 | M16: =(B16-'Raw Data'!D17)/'Raw Data'!D17 -> 0.15435005 | N16: =H16/G16 -> 0.48927657 | O16: ='Raw Data'!L18 -> 3.05 | P16: ='Raw Data'!M18/'Raw Data'!N18 -> 1.808104
A17: FY17-18 | B17: ='Raw Data'!D19 -> 4977 | C17: ='Raw Data'!E19 -> 894 | D17: ='Raw Data'!F19 -> 304 | E17: ='Raw Data'!G19+'Raw Data'!H19 -> 2429 | F17: ='Raw Data'!I19 -> 2721 | G17: ='Raw Data'!J19 -> 6248 | H17: ='Raw Data'!K19 -> 2846 | I17: =F17/E17 -> 1.1202141 | J17: =D17/E17 -> 0.12515438 | K17: =D17/G17 -> 0.04865557 | L17: =LN(G17) -> 8.7400167 | M17: =(B17-'Raw Data'!D18)/'Raw Data'!D18 -> -0.1173967 | N17: =H17/G17 -> 0.45550576 | O17: ='Raw Data'!L19 -> 3.03 | P17: ='Raw Data'!M19/'Raw Data'!N19 -> 2.2747953
A18: FY18-19 | B18: ='Raw Data'!D20 -> 5395 | C18: ='Raw Data'!E20 -> 795 | D18: ='Raw Data'!F20 -> 142 | E18: ='Raw Data'!G20+'Raw Data'!H20 -> 2489 | F18: ='Raw Data'!I20 -> 2510 | G18: ='Raw Data'!J20 -> 6264 | H18: ='Raw Data'!K20 -> 2654 | I18: =F18/E18 -> 1.0084371 | J18: =D18/E18 -> 0.057051025 | K18: =D18/G18 -> 0.022669221 | L18: =LN(G18) -> 8.7425742 | M18: =(B18-'Raw Data'!D19)/'Raw Data'!D19 -> 0.083986337 | N18: =H18/G18 -> 0.42369093 | O18: ='Raw Data'!L20 -> 1.41 | P18: ='Raw Data'!M20/'Raw Data'!N20 -> 2.0023734
A19: FY19-20 | B19: ='Raw Data'!D21 -> 5324 | C19: ='Raw Data'!E21 -> 1009 | D19: ='Raw Data'!F21 -> 475 | E19: ='Raw Data'!G21+'Raw Data'!H21 -> 2807 | F19: ='Raw Data'!I21 -> 2275 | G19: ='Raw Data'!J21 -> 6221 | H19: ='Raw Data'!K21 -> 2385 | I19: =F19/E19 -> 0.81047382 | J19: =D19/E19 -> 0.16921981 | K19: =D19/G19 -> 0.076354284 | L19: =LN(G19) -> 8.7356859 | M19: =(B19-'Raw Data'!D20)/'Raw Data'!D20 -> -0.013160334 | N19: =H19/G19 -> 0.38337888 | O19: ='Raw Data'!L21 -> 4.73 | P19: ='Raw Data'!M21/'Raw Data'!N21 -> 2.1826163
A20: FY20-21 | B20: ='Raw Data'!D22 -> 5956 | C20: ='Raw Data'!E22 -> 1084 | D20: ='Raw Data'!F22 -> 527 | E20: ='Raw Data'!G22+'Raw Data'!H22 -> 3338 | F20: ='Raw Data'!I22 -> 1409 | G20: ='Raw Data'!J22 -> 6098 | H20: ='Raw Data'!K22 -> 2158 | I20: =F20/E20 -> 0.42210905 | J20: =D20/E20 -> 0.15787897 | K20: =D20/G20 -> 0.086421778 | L20: =LN(G20) -> 8.7157161 | M20: =(B20-'Raw Data'!D21)/'Raw Data'!D21 -> 0.11870774 | N20: =H20/G20 -> 0.35388652 | O20: ='Raw Data'!L22 -> 5.24 | P20: ='Raw Data'!M22/'Raw Data'!N22 -> 1.8725926
A21: FY21-22 | B21: ='Raw Data'!D23 -> 6703 | C21: ='Raw Data'!E23 -> 893 | D21: ='Raw Data'!F23 -> 392 | E21: ='Raw Data'!G23+'Raw Data'!H23 -> 3475 | F21: ='Raw Data'!I23 -> 1318 | G21: ='Raw Data'!J23 -> 6191 | H21: ='Raw Data'!K23 -> 2025 | I21: =F21/E21 -> 0.37928058 | J21: =D21/E21 -> 0.11280576 | K21: =D21/G21 -> 0.063317719 | L21: =LN(G21) -> 8.7308519 | M21: =(B21-'Raw Data'!D22)/'Raw Data'!D22 -> 0.12541974 | N21: =H21/G21 -> 0.32708771 | O21: ='Raw Data'!L23 -> 3.9 | P21: ='Raw Data'!M23/'Raw Data'!N23 -> 1.6237482
A22: FY22-23 | B22: ='Raw Data'!D24 -> 6298 | C22: ='Raw Data'!E24 -> 456 | D22: ='Raw Data'!F24 -> 123 | E22: ='Raw Data'!G24+'Raw Data'!H24 -> 3408 | F22: ='Raw Data'!I24 -> 1767 | G22: ='Raw Data'!J24 -> 6880 | H22: ='Raw Data'!K24 -> 2938 | I22: =F22/E22 -> 0.51848592 | J22: =D22/E22 -> 0.036091549 | K22: =D22/G22 -> 0.017877907 | L22: =LN(G22) -> 8.8363739 | M22: =(B22-'Raw Data'!D23)/'Raw Data'!D23 -> -0.060420707 | N22: =H22/G22 -> 0.42703488 | O22: ='Raw Data'!L24 -> 1.22 | P22: ='Raw Data'!M24/'Raw Data'!N24 -> 1.5472141
A23: FY23-24 | B23: ='Raw Data'!D25 -> 8085 | C23: ='Raw Data'!E25 -> 1012 | D23: ='Raw Data'!F25 -> 596 | E23: ='Raw Data'!G25+'Raw Data'!H25 -> 3741 | F23: ='Raw Data'!I25 -> 1965 | G23: ='Raw Data'!J25 -> 7515 | H23: ='Raw Data'!K25 -> 2879 | I23: =F23/E23 -> 0.52526063 | J23: =D23/E23 -> 0.15931569 | K23: =D23/G23 -> 0.079308051 | L23: =LN(G23) -> 8.9246563 | M23: =(B23-'Raw Data'!D24)/'Raw Data'!D24 -> 0.28374087 | N23: =H23/G23 -> 0.38310047 | O23: ='Raw Data'!L25 -> 6.13 | P23: ='Raw Data'!M25/'Raw Data'!N25 -> 1.6955801
A24: FY24-25 | B24: ='Raw Data'!D26 -> 8622 | C24: ='Raw Data'!E26 -> 907 | D24: ='Raw Data'!F26 -> 507 | E24: ='Raw Data'!G26+'Raw Data'!H26 -> 3905 | F24: ='Raw Data'!I26 -> 1678 | G24: ='Raw Data'!J26 -> 7508 | H24: ='Raw Data'!K26 -> 2933 | I24: =F24/E24 -> 0.42970551 | J24: =D24/E24 -> 0.12983355 | K24: =D24/G24 -> 0.06752797 | L24: =LN(G24) -> 8.9237244 | M24: =(B24-'Raw Data'!D25)/'Raw Data'!D25 -> 0.066419295 | N24: =H24/G24 -> 0.39064997 | O24: ='Raw Data'!L26 -> 5.28 | P24: ='Raw Data'!M26/'Raw Data'!N26 -> 1.7038961
A25: 10-YR AVERAGE | B25: =AVERAGE(B15:B24) -> 6188.4 | C25: =AVERAGE(C15:C24) -> 969.5 | D25: =AVERAGE(D15:D24) -> 402.1 | E25: =AVERAGE(E15:E24) -> 2969.2 | F25: =AVERAGE(F15:F24) -> 2094.7 | G25: =AVERAGE(G15:G24) -> 6453.5 | H25: =AVERAGE(H15:H24) -> 2670.5 | I25: =AVERAGE(I15:I24) -> 0.78091842 | ... P25: =AVERAGE(P15:P24) -> 1.8765608
A27: SD (10-yr) | I27: =STDEV(I15:I24) -> 0.37343586 | J27: =STDEV(J15:J24) -> 0.082126757 | K27: =STDEV(K15:K24) -> 0.03058731 | O27: =STDEV(O15:O24) -> 1.841462 | P27: =STDEV(P15:P24) -> 0.24482903

Sheet Indo Count Industries
A1: Indo Count Industries
A3: Screener Ticker | B3: ICIL
A4: Basis | B4: Standalone
A5: Primary Business | B5: Home Textiles — Bed Linen (export-focused)
A6: Year Established | B6: 1988
A7: Headquarters | B7: Mumbai, Maharashtra
A8: Promoter / Group | B8: Lohia family
A9: Manufacturing Locations | B9: Kolhapur, Maharashtra
A10: Listed On | B10: NSE & BSE
A11: Note | B11: Anchor company — featured in the source ET Wealth article
A13: 10-Year Financials & Computed Ratios (FY2015-16 to FY2024-25)
A14: FY | B14: Sales | C14: EBIT | D14: Net Profit | E14: Total Equity | F14: Borrowings | G14: Total Assets | H14: Fixed Assets | I14: D/E Ratio | J14: ROE | K14: ROA | L14: Size (ln TA) | M14: Sales Growth % | N14: Tangibility | O14: EPS (Rs.) | P14: Liquidity (CR proxy)
A15: FY15-16 | B15: ='Raw Data'!D28 -> 2001 | C15: ='Raw Data'!E28 -> 396 | D15: ='Raw Data'!F28 -> 238 | E15: ='Raw Data'!G28+'Raw Data'!H28 -> 613 | F15: ='Raw Data'!I28 -> 340 | G15: ='Raw Data'!J28 -> 1283 | H15: ='Raw Data'!K28 -> 466 | I15: =F15/E15 -> 0.55464927 | J15: =D15/E15 -> 0.38825449 | K15: =D15/G15 -> 0.18550273 | L15: =LN(G15) -> 7.1569564 | M15: =(B15-'Raw Data'!D27)/'Raw Data'!D27 -> 0.23824257 | N15: =H15/G15 -> 0.36321122 | O15: ='Raw Data'!L28 -> 12.04 | P15: ='Raw Data'!M28/'Raw Data'!N28 -> 2.4255319
A16: FY16-17 | B16: ='Raw Data'!D29 -> 1990 | C16: ='Raw Data'!E29 -> 325 | D16: ='Raw Data'!F29 -> 228 | E16: ='Raw Data'!G29+'Raw Data'!H29 -> 826 | F16: ='Raw Data'!I29 -> 267 | G16: ='Raw Data'!J29 -> 1440 | H16: ='Raw Data'!K29 -> 511 | I16: =F16/E16 -> 0.32324455 | J16: =D16/E16 -> 0.27602906 | K16: =D16/G16 -> 0.15833333 | L16: =LN(G16) -> 7.2723984 | M16: =(B16-'Raw Data'!D28)/'Raw Data'!D28 -> -0.0054972514 | N16: =H16/G16 -> 0.35486111 | O16: ='Raw Data'!L29 -> 11.55 | P16: ='Raw Data'!M29/'Raw Data'!N29 -> 2.6271676
A17: FY17-18 | B17: ='Raw Data'!D30 -> 1709 | C17: ='Raw Data'!E30 -> 167 | D17: ='Raw Data'!F30 -> 131 | E17: ='Raw Data'!G30+'Raw Data'!H30 -> 938 | F17: ='Raw Data'!I30 -> 371 | G17: ='Raw Data'!J30 -> 1644 | H17: ='Raw Data'!K30 -> 535 | I17: =F17/E17 -> 0.39552239 | J17: =D17/E17 -> 0.13965885 | K17: =D17/G17 -> 0.079683698 | L17: =LN(G17) -> 7.4048876 | M17: =(B17-'Raw Data'!D29)/'Raw Data'!D29 -> -0.14120603 | N17: =H17/G17 -> 0.32542579 | O17: ='Raw Data'!L30 -> 6.64 | P17: ='Raw Data'!M30/'Raw Data'!N30 -> 3.2537313
A18: FY18-19 | B18: ='Raw Data'!D31 -> 1813 | C18: ='Raw Data'!E31 -> 151 | D18: ='Raw Data'!F31 -> 59 | E18: ='Raw Data'!G31+'Raw Data'!H31 -> 960 | F18: ='Raw Data'!I31 -> 309 | G18: ='Raw Data'!J31 -> 1552 | H18: ='Raw Data'!K31 -> 560 | I18: =F18/E18 -> 0.321875 | J18: =D18/E18 -> 0.061458333 | K18: =D18/G18 -> 0.038015464 | L18: =LN(G18) -> 7.3472997 | M18: =(B18-'Raw Data'!D30)/'Raw Data'!D30 -> 0.060854301 | N18: =H18/G18 -> 0.36082474 | O18: ='Raw Data'!L31 -> 3 | P18: ='Raw Data'!M31/'Raw Data'!N31 -> 3.2508834
A19: FY19-20 | B19: ='Raw Data'!D32 -> 1965 | C19: ='Raw Data'!E32 -> 178 | D19: ='Raw Data'!F32 -> 74 | E19: ='Raw Data'!G32+'Raw Data'!H32 -> 972 | F19: ='Raw Data'!I32 -> 348 | G19: ='Raw Data'!J32 -> 1659 | H19: ='Raw Data'!K32 -> 553 | I19: =F19/E19 -> 0.35802469 | J19: =D19/E19 -> 0.076131687 | K19: =D19/G19 -> 0.044605184 | L19: =LN(G19) -> 7.4139703 | M19: =(B19-'Raw Data'!D31)/'Raw Data'!D31 -> 0.083838941 | N19: =H19/G19 -> 0.33333333 | O19: ='Raw Data'!L32 -> 3.74 | P19: ='Raw Data'!M32/'Raw Data'!N32 -> 3.1982249
A20: FY20-21 | B20: ='Raw Data'!D33 -> 2515 | C20: ='Raw Data'!E33 -> 384 | D20: ='Raw Data'!F33 -> 260 | E20: ='Raw Data'!G33+'Raw Data'!H33 -> 1274 | F20: ='Raw Data'!I33 -> 546 | G20: ='Raw Data'!J33 -> 2247 | H20: ='Raw Data'!K33 -> 543 | I20: =F20/E20 -> 0.42857143 | J20: =D20/E20 -> 0.20408163 | K20: =D20/G20 -> 0.11570984 | L20: =LN(G20) -> 7.7173513 | M20: =(B20-'Raw Data'!D32)/'Raw Data'!D32 -> 0.27989822 | N20: =H20/G20 -> 0.24165554 | O20: ='Raw Data'!L33 -> 13.18 | P20: ='Raw Data'!M33/'Raw Data'!N33 -> 3.5492958
A21: FY21-22 | B21: ='Raw Data'!D34 -> 2806 | C21: ='Raw Data'!E34 -> 402 | D21: ='Raw Data'!F34 -> 339 | E21: ='Raw Data'!G34+'Raw Data'!H34 -> 1576 | F21: ='Raw Data'!I34 -> 1214 | G21: ='Raw Data'!J34 -> 3090 | H21: ='Raw Data'!K34 -> 650 | I21: =F21/E21 -> 0.77030457 | J21: =D21/E21 -> 0.21510152 | K21: =D21/G21 -> 0.10970874 | L21: =LN(G21) -> 8.0359264 | M21: =(B21-'Raw Data'!D33)/'Raw Data'!D33 -> 0.11570577 | N21: =H21/G21 -> 0.21035599 | O21: ='Raw Data'!L34 -> 17.16 | P21: ='Raw Data'!M34/'Raw Data'!N34 -> 8.0933333
A22: FY22-23 | B22: ='Raw Data'!D35 -> 2784 | C22: ='Raw Data'!E35 -> 411 | D22: ='Raw Data'!F35 -> 238 | E22: ='Raw Data'!G35+'Raw Data'!H35 -> 1765 | F22: ='Raw Data'!I35 -> 853 | G22: ='Raw Data'!J35 -> 2983 | H22: ='Raw Data'!K35 -> 1243 | I22: =F22/E22 -> 0.48328612 | J22: =D22/E22 -> 0.13484419 | K22: =D22/G22 -> 0.079785451 | L22: =LN(G22) -> 8.0006848 | M22: =(B22-'Raw Data'!D34)/'Raw Data'!D34 -> -0.0078403421 | N22: =H22/G22 -> 0.4166946 | O22: ='Raw Data'!L35 -> 12.03 | P22: ='Raw Data'!M35/'Raw Data'!N35 -> 4.3424658
A23: FY23-24 | B23: ='Raw Data'!D36 -> 3332 | C23: ='Raw Data'!E36 -> 526 | D23: ='Raw Data'!F36 -> 320 | E23: ='Raw Data'!G36+'Raw Data'!H36 -> 2048 | F23: ='Raw Data'!I36 -> 936 | G23: ='Raw Data'!J36 -> 3493 | H23: ='Raw Data'!K36 -> 1344 | I23: =F23/E23 -> 0.45703125 | J23: =D23/E23 -> 0.15625 | K23: =D23/G23 -> 0.091611795 | L23: =LN(G23) -> 8.1585162 | M23: =(B23-'Raw Data'!D35)/'Raw Data'!D35 -> 0.19683908 | N23: =H23/G23 -> 0.38476954 | O23: ='Raw Data'!L36 -> 16.17 | P23: ='Raw Data'!M36/'Raw Data'!N36 -> 3.9352941
A24: FY24-25 | B24: ='Raw Data'!D37 -> 3772 | C24: ='Raw Data'!E37 -> 465 | D24: ='Raw Data'!F37 -> 237 | E24: ='Raw Data'!G37+'Raw Data'!H37 -> 2237 | F24: ='Raw Data'!I37 -> 1061 | G24: ='Raw Data'!J37 -> 3695 | H24: ='Raw Data'!K37 -> 1381 | I24: =F24/E24 -> 0.47429593 | J24: =D24/E24 -> 0.10594546 | K24: =D24/G24 -> 0.064140731 | L24: =LN(G24) -> 8.2147358 | M24: =(B24-'Raw Data'!D36)/'Raw Data'!D36 -> 0.13205282 | N24: =H24/G24 -> 0.37374831 | O24: ='Raw Data'!L37 -> 11.98 | P24: ='Raw Data'!M37/'Raw Data'!N37 -> 5.3341709
A25: 10-YR AVERAGE | B25: =AVERAGE(B15:B24) -> 2468.7 | C25: =AVERAGE(C15:C24) -> 340.5 | D25: =AVERAGE(D15:D24) -> 212.4 | E25: =AVERAGE(E15:E24) -> 1320.9 | F25: =AVERAGE(F15:F24) -> 624.5 | G25: =AVERAGE(G15:G24) -> 2308.6 | H25: =AVERAGE(H15:H24) -> 778.6 | I25: =AVERAGE(I15:I24) -> 0.45668052 | ... P25: =AVERAGE(P15:P24) -> 4.0010099
A27: SD (10-yr) | I27: =STDEV(I15:I24) -> 0.13300681 | J27: =STDEV(J15:J24) -> 0.099320153 | K27: =STDEV(K15:K24) -> 0.047181198 | O27: =STDEV(O15:O24) -> 4.8064712 | P27: =STDEV(P15:P24) -> 1.6661512

Sheet Vardhman Textiles
A1: Vardhman Textiles
A3: Screener Ticker | B3: VTL
A4: Basis | B4: Standalone
A5: Primary Business | B5: Yarn, Fabric, Acrylic Fibre, Garments — vertically integrated composite mill
A6: Year Established | B6: 1962 (incorporated as Vardhman Spinning & General Mills); yarn production commenced 1965
A7: Headquarters | B7: Ludhiana, Punjab
A8: Promoter / Group | B8: Vardhman Group — Oswal family (founder Lala Rattan Chand Oswal; current Chairman S.P. Oswal)
A9: Manufacturing Locations | B9: 22 units across 6 states, incl. Punjab, Himachal Pradesh, Madhya Pradesh
A10: Listed On | B10: NSE & BSE
A11: Note
A13: 10-Year Financials & Computed Ratios (FY2015-16 to FY2024-25)
A14: FY | B14: Sales | C14: EBIT | D14: Net Profit | E14: Total Equity | F14: Borrowings | G14: Total Assets | H14: Fixed Assets | I14: D/E Ratio | J14: ROE | K14: ROA | L14: Size (ln TA) | M14: Sales Growth % | N14: Tangibility | O14: EPS (Rs.) | P14: Liquidity (CR proxy)
A15: FY15-16 | B15: ='Raw Data'!D39 -> 5602 | C15: ='Raw Data'!E39 -> 1108 | D15: ='Raw Data'!F39 -> 676 | E15: ='Raw Data'!G39+'Raw Data'!H39 -> 3690 | F15: ='Raw Data'!I39 -> 2596 | G15: ='Raw Data'!J39 -> 6985 | H15: ='Raw Data'!K39 -> 2585 | I15: =F15/E15 -> 0.70352304 | J15: =D15/E15 -> 0.18319783 | K15: =D15/G15 -> 0.096778812 | L15: =LN(G15) -> 8.8515203 | M15: =(B15-'Raw Data'!D38)/'Raw Data'!D38 -> -0.022338569 | N15: =H15/G15 -> 0.37007874 | O15: ='Raw Data'!L39 -> 21.25 | P15: ='Raw Data'!M39/'Raw Data'!N39 -> 4.7571429
A16: FY16-17 | B16: ='Raw Data'!D40 -> 5691 | C16: ='Raw Data'!E40 -> 1131 | D16: ='Raw Data'!F40 -> 1002 | E16: ='Raw Data'!G40+'Raw Data'!H40 -> 3986 | F16: ='Raw Data'!I40 -> 2198 | G16: ='Raw Data'!J40 -> 6959 | H16: ='Raw Data'!K40 -> 2507 | I16: =F16/E16 -> 0.55143001 | J16: =D16/E16 -> 0.25137983 | K16: =D16/G16 -> 0.1439862 | L16: =LN(G16) -> 8.8477911 | M16: =(B16-'Raw Data'!D39)/'Raw Data'!D39 -> 0.015887183 | N16: =H16/G16 -> 0.36025291 | O16: ='Raw Data'!L40 -> 34.87 | P16: ='Raw Data'!M40/'Raw Data'!N40 -> 3.6245161
A17: FY17-18 | B17: ='Raw Data'!D41 -> 5851 | C17: ='Raw Data'!E41 -> 859 | D17: ='Raw Data'!F41 -> 546 | E17: ='Raw Data'!G41+'Raw Data'!H41 -> 4632 | F17: ='Raw Data'!I41 -> 2282 | G17: ='Raw Data'!J41 -> 7696 | H17: ='Raw Data'!K41 -> 2612 | I17: =F17/E17 -> 0.49265976 | J17: =D17/E17 -> 0.11787565 | K17: =D17/G17 -> 0.070945946 | L17: =LN(G17) -> 8.948456 | M17: =(B17-'Raw Data'!D40)/'Raw Data'!D40 -> 0.028114567 | N17: =H17/G17 -> 0.33939709 | O17: ='Raw Data'!L41 -> 19 | P17: ='Raw Data'!M41/'Raw Data'!N41 -> 4.4654731
A18: FY18-19 | B18: ='Raw Data'!D42 -> 6415 | C18: ='Raw Data'!E42 -> 1132 | D18: ='Raw Data'!F42 -> 696 | E18: ='Raw Data'!G42+'Raw Data'!H42 -> 5239 | F18: ='Raw Data'!I42 -> 2238 | G18: ='Raw Data'!J42 -> 8369 | H18: ='Raw Data'!K42 -> 3333 | I18: =F18/E18 -> 0.42718076 | J18: =D18/E18 -> 0.13284978 | K18: =D18/G18 -> 0.083164058 | L18: =LN(G18) -> 9.0322897 | M18: =(B18-'Raw Data'!D41)/'Raw Data'!D41 -> 0.096393779 | N18: =H18/G18 -> 0.39825547 | O18: ='Raw Data'!L42 -> 24.21 | P18: ='Raw Data'!M42/'Raw Data'!N42 -> 4.4282511
A19: FY19-20 | B19: ='Raw Data'!D43 -> 6325 | C19: ='Raw Data'!E43 -> 883 | D19: ='Raw Data'!F43 -> 545 | E19: ='Raw Data'!G43+'Raw Data'!H43 -> 5667 | F19: ='Raw Data'!I43 -> 2197 | G19: ='Raw Data'!J43 -> 8727 | H19: ='Raw Data'!K43 -> 3620 | I19: =F19/E19 -> 0.38768308 | J19: =D19/E19 -> 0.096170813 | K19: =D19/G19 -> 0.062449868 | L19: =LN(G19) -> 9.0741769 | M19: =(B19-'Raw Data'!D42)/'Raw Data'!D42 -> -0.014029618 | N19: =H19/G19 -> 0.41480463 | O19: ='Raw Data'!L43 -> 18.97 | P19: ='Raw Data'!M43/'Raw Data'!N43 -> 4.7164352
A20: FY20-21 | B20: ='Raw Data'!D44 -> 5926 | C20: ='Raw Data'!E44 -> 767 | D20: ='Raw Data'!F44 -> 367 | E20: ='Raw Data'!G44+'Raw Data'!H44 -> 6139 | F20: ='Raw Data'!I44 -> 2132 | G20: ='Raw Data'!J44 -> 9064 | H20: ='Raw Data'!K44 -> 3546 | I20: =F20/E20 -> 0.34728783 | J20: =D20/E20 -> 0.059781723 | K20: =D20/G20 -> 0.04048985 | L20: =LN(G20) -> 9.1120658 | M20: =(B20-'Raw Data'!D43)/'Raw Data'!D43 -> -0.063083004 | N20: =H20/G20 -> 0.39121801 | O20: ='Raw Data'!L44 -> 12.74 | P20: ='Raw Data'!M44/'Raw Data'!N44 -> 5.9331652
A21: FY21-22 | B21: ='Raw Data'!D45 -> 9386 | C21: ='Raw Data'!E45 -> 2262 | D21: ='Raw Data'!F45 -> 1677 | E21: ='Raw Data'!G45+'Raw Data'!H45 -> 7539 | F21: ='Raw Data'!I45 -> 1980 | G21: ='Raw Data'!J45 -> 10576 | H21: ='Raw Data'!K45 -> 3677 | I21: =F21/E21 -> 0.2626343 | J21: =D21/E21 -> 0.22244329 | K21: =D21/G21 -> 0.15856657 | L21: =LN(G21) -> 9.2663426 | M21: =(B21-'Raw Data'!D44)/'Raw Data'!D44 -> 0.5838677 | N21: =H21/G21 -> 0.34767398 | O21: ='Raw Data'!L45 -> 58.07 | P21: ='Raw Data'!M45/'Raw Data'!N45 -> 5.1524621
A22: FY22-23 | B22: ='Raw Data'!D46 -> 9841 | C22: ='Raw Data'!E46 -> 1285 | D22: ='Raw Data'!F46 -> 749 | E22: ='Raw Data'!G46+'Raw Data'!H46 -> 8294 | F22: ='Raw Data'!I46 -> 1677 | G22: ='Raw Data'!J46 -> 10861 | H22: ='Raw Data'!K46 -> 3927 | I22: =F22/E22 -> 0.20219436 | J22: =D22/E22 -> 0.090306245 | K22: =D22/G22 -> 0.068962342 | L22: =LN(G22) -> 9.2929337 | M22: =(B22-'Raw Data'!D45)/'Raw Data'!D45 -> 0.048476454 | N22: =H22/G22 -> 0.36156892 | O22: ='Raw Data'!L46 -> 25.91 | P22: ='Raw Data'!M46/'Raw Data'!N46 -> 5.2662921
A23: FY23-24 | B23: ='Raw Data'!D47 -> 9299 | C23: ='Raw Data'!E47 -> 958 | D23: ='Raw Data'!F47 -> 608 | E23: ='Raw Data'!G47+'Raw Data'!H47 -> 8805 | F23: ='Raw Data'!I47 -> 1790 | G23: ='Raw Data'!J47 -> 11487 | H23: ='Raw Data'!K47 -> 3772 | I23: =F23/E23 -> 0.20329358 | J23: =D23/E23 -> 0.069051675 | K23: =D23/G23 -> 0.052929398 | L23: =LN(G23) -> 9.3489712 | M23: =(B23-'Raw Data'!D46)/'Raw Data'!D46 -> -0.055075704 | N23: =H23/G23 -> 0.3283712 | O23: ='Raw Data'!L47 -> 21.01 | P23: ='Raw Data'!M47/'Raw Data'!N47 -> 7.1301908
A24: FY24-25 | B24: ='Raw Data'!D48 -> 9587 | C24: ='Raw Data'!E48 -> 1257 | D24: ='Raw Data'!F48 -> 879 | E24: ='Raw Data'!G48+'Raw Data'!H48 -> 9578 | F24: ='Raw Data'!I48 -> 1238 | G24: ='Raw Data'!J48 -> 11900 | H24: ='Raw Data'!K48 -> 4342 | I24: =F24/E24 -> 0.12925454 | J24: =D24/E24 -> 0.091772813 | K24: =D24/G24 -> 0.073865546 | L24: =LN(G24) -> 9.3842937 | M24: =(B24-'Raw Data'!D47)/'Raw Data'!D47 -> 0.030971072 | N24: =H24/G24 -> 0.36487395 | O24: ='Raw Data'!L48 -> 30.4 | P24: ='Raw Data'!M48/'Raw Data'!N48 -> 5.6097786
A25: 10-YR AVERAGE | B25: =AVERAGE(B15:B24) -> 7392.3 | C25: =AVERAGE(C15:C24) -> 1164.2 | D25: =AVERAGE(D15:D24) -> 774.5 | E25: =AVERAGE(E15:E24) -> 6356.9 | F25: =AVERAGE(F15:F24) -> 2032.8 | G25: =AVERAGE(G15:G24) -> 9262.4 | H25: =AVERAGE(H15:H24) -> 3392.1 | I25: =AVERAGE(I15:I24) -> 0.37071413 | ... P25: =AVERAGE(P15:P24) -> 5.1083707
A27: SD (10-yr) | I27: =STDEV(I15:I24) -> 0.17911154 | J27: =STDEV(J15:J24) -> 0.065885924 | K27: =STDEV(K15:K24) -> 0.038195331 | O27: =STDEV(O15:O24) -> 12.681179 | P27: =STDEV(P15:P24) -> 0.96615011

Sheet Trident
A1: Trident
A3: Screener Ticker | B3: TRIDENT
A4: Basis | B4: Standalone
A5: Primary Business | B5: Yarn, Terry Towels, Bed Sheets — vertically integrated composite mill
A6: Year Established | B6: 1990 (as Abhishek Industries Ltd; renamed Trident Ltd in 2011)
A7: Headquarters | B7: Ludhiana, Punjab (registered office)
A8: Promoter / Group | B8: Trident Group — founder Rajinder Gupta
A9: Manufacturing Locations | B9: Barnala (Punjab) and Budhni (Madhya Pradesh)
A10: Listed On | B10: NSE & BSE
A11: Note
A13: 10-Year Financials & Computed Ratios (FY2015-16 to FY2024-25)
A14: FY | B14: Sales | C14: EBIT | D14: Net Profit | E14: Total Equity | F14: Borrowings | G14: Total Assets | H14: Fixed Assets | I14: D/E Ratio | J14: ROE | K14: ROA | L14: Size (ln TA) | M14: Sales Growth % | N14: Tangibility | O14: EPS (Rs.) | P14: Liquidity (CR proxy)
A15: FY15-16 | B15: ='Raw Data'!D50 -> 3665 | C15: ='Raw Data'!E50 -> 730 | D15: ='Raw Data'!F50 -> 242 | E15: ='Raw Data'!G50+'Raw Data'!H50 -> 2415 | F15: ='Raw Data'!I50 -> 3503 | G15: ='Raw Data'!J50 -> 6506 | H15: ='Raw Data'!K50 -> 4755 | I15: =F15/E15 -> 1.4505176 | J15: =D15/E15 -> 0.10020704 | K15: =D15/G15 -> 0.037196434 | L15: =LN(G15) -> 8.7804801 | M15: =(B15-'Raw Data'!D49)/'Raw Data'!D49 -> -0.018741633 | N15: =H15/G15 -> 0.73086382 | O15: ='Raw Data'!L50 -> 0.48 | P15: ='Raw Data'!M50/'Raw Data'!N50 -> 2.8894558
A16: FY16-17 | B16: ='Raw Data'!D51 -> 4617 | C16: ='Raw Data'!E51 -> 886 | D16: ='Raw Data'!F51 -> 337 | E16: ='Raw Data'!G51+'Raw Data'!H51 -> 2725 | F16: ='Raw Data'!I51 -> 2849 | G16: ='Raw Data'!J51 -> 6150 | H16: ='Raw Data'!K51 -> 4467 | I16: =F16/E16 -> 1.0455046 | J16: =D16/E16 -> 0.12366972 | K16: =D16/G16 -> 0.054796748 | L16: =LN(G16) -> 8.7242074 | M16: =(B16-'Raw Data'!D50)/'Raw Data'!D50 -> 0.25975443 | N16: =H16/G16 -> 0.72634146 | O16: ='Raw Data'!L51 -> 0.66 | P16: ='Raw Data'!M51/'Raw Data'!N51 -> 2.7916667
A17: FY17-18 | B17: ='Raw Data'!D52 -> 4566 | C17: ='Raw Data'!E52 -> 852 | D17: ='Raw Data'!F52 -> 266 | E17: ='Raw Data'!G52+'Raw Data'!H52 -> 2694 | F17: ='Raw Data'!I52 -> 2798 | G17: ='Raw Data'!J52 -> 6129 | H17: ='Raw Data'!K52 -> 4079 | I17: =F17/E17 -> 1.0386043 | J17: =D17/E17 -> 0.098737936 | K17: =D17/G17 -> 0.043400228 | L17: =LN(G17) -> 8.7207869 | M17: =(B17-'Raw Data'!D51)/'Raw Data'!D51 -> -0.011046134 | N17: =H17/G17 -> 0.66552456 | O17: ='Raw Data'!L52 -> 0.52 | P17: ='Raw Data'!M52/'Raw Data'!N52 -> 3.0830721
A18: FY18-19 | B18: ='Raw Data'!D53 -> 5220 | C18: ='Raw Data'!E53 -> 977 | D18: ='Raw Data'!F53 -> 371 | E18: ='Raw Data'!G53+'Raw Data'!H53 -> 2932 | F18: ='Raw Data'!I53 -> 2436 | G18: ='Raw Data'!J53 -> 6103 | H18: ='Raw Data'!K53 -> 3848 | I18: =F18/E18 -> 0.8308322 | J18: =D18/E18 -> 0.12653479 | K18: =D18/G18 -> 0.060789776 | L18: =LN(G18) -> 8.7165357 | M18: =(B18-'Raw Data'!D52)/'Raw Data'!D52 -> 0.14323259 | N18: =H18/G18 -> 0.63050959 | O18: ='Raw Data'!L53 -> 0.73 | P18: ='Raw Data'!M53/'Raw Data'!N53 -> 2.8464674
A19: FY19-20 | B19: ='Raw Data'!D54 -> 4699 | C19: ='Raw Data'!E54 -> 841 | D19: ='Raw Data'!F54 -> 342 | E19: ='Raw Data'!G54+'Raw Data'!H54 -> 2967 | F19: ='Raw Data'!I54 -> 1991 | G19: ='Raw Data'!J54 -> 5718 | H19: ='Raw Data'!K54 -> 3826 | I19: =F19/E19 -> 0.6710482 | J19: =D19/E19 -> 0.11526795 | K19: =D19/G19 -> 0.059811123 | L19: =LN(G19) -> 8.6513744 | M19: =(B19-'Raw Data'!D53)/'Raw Data'!D53 -> -0.099808429 | N19: =H19/G19 -> 0.66911508 | O19: ='Raw Data'!L54 -> 0.67 | P19: ='Raw Data'!M54/'Raw Data'!N54 -> 2.3823916
A20: FY20-21 | B20: ='Raw Data'!D55 -> 4519 | C20: ='Raw Data'!E55 -> 814 | D20: ='Raw Data'!F55 -> 346 | E20: ='Raw Data'!G55+'Raw Data'!H55 -> 3317 | F20: ='Raw Data'!I55 -> 1562 | G20: ='Raw Data'!J55 -> 5754 | H20: ='Raw Data'!K55 -> 3854 | I20: =F20/E20 -> 0.47090745 | J20: =D20/E20 -> 0.10431112 | K20: =D20/G20 -> 0.060132082 | L20: =LN(G20) -> 8.6576505 | M20: =(B20-'Raw Data'!D54)/'Raw Data'!D54 -> -0.038306023 | N20: =H20/G20 -> 0.66979493 | O20: ='Raw Data'!L55 -> 0.68 | P20: ='Raw Data'!M55/'Raw Data'!N55 -> 2.1643836
A21: FY21-22 | B21: ='Raw Data'!D56 -> 6919 | C21: ='Raw Data'!E56 -> 1495 | D21: ='Raw Data'!F56 -> 815 | E21: ='Raw Data'!G56+'Raw Data'!H56 -> 3798 | F21: ='Raw Data'!I56 -> 1596 | G21: ='Raw Data'!J56 -> 6431 | H21: ='Raw Data'!K56 -> 3795 | I21: =F21/E21 -> 0.42022117 | J21: =D21/E21 -> 0.21458662 | K21: =D21/G21 -> 0.1267299 | L21: =LN(G21) -> 8.7688853 | M21: =(B21-'Raw Data'!D55)/'Raw Data'!D55 -> 0.53109095 | N21: =H21/G21 -> 0.5901104 | O21: ='Raw Data'!L56 -> 1.6 | P21: ='Raw Data'!M56/'Raw Data'!N56 -> 2.5380906
A22: FY22-23 | B22: ='Raw Data'!D57 -> 6267 | C22: ='Raw Data'!E57 -> 918 | D22: ='Raw Data'!F57 -> 422 | E22: ='Raw Data'!G57+'Raw Data'!H57 -> 4126 | F22: ='Raw Data'!I57 -> 1404 | G22: ='Raw Data'!J57 -> 6713 | H22: ='Raw Data'!K57 -> 4422 | I22: =F22/E22 -> 0.34028114 | J22: =D22/E22 -> 0.10227824 | K22: =D22/G22 -> 0.062863101 | L22: =LN(G22) -> 8.8118012 | M22: =(B22-'Raw Data'!D56)/'Raw Data'!D56 -> -0.094233271 | N22: =H22/G22 -> 0.65872188 | O22: ='Raw Data'!L57 -> 0.83 | P22: ='Raw Data'!M57/'Raw Data'!N57 -> 1.9324324
A23: FY23-24 | B23: ='Raw Data'!D58 -> 6730 | C23: ='Raw Data'!E58 -> 935 | D23: ='Raw Data'!F58 -> 390 | E23: ='Raw Data'!G58+'Raw Data'!H58 -> 4310 | F23: ='Raw Data'!I58 -> 2094 | G23: ='Raw Data'!J58 -> 7522 | H23: ='Raw Data'!K58 -> 4663 | I23: =F23/E23 -> 0.48584687 | J23: =D23/E23 -> 0.090487239 | K23: =D23/G23 -> 0.051847913 | L23: =LN(G23) -> 8.9255873 | M23: =(B23-'Raw Data'!D57)/'Raw Data'!D57 -> 0.073879049 | N23: =H23/G23 -> 0.61991492 | O23: ='Raw Data'!L58 -> 0.76 | P23: ='Raw Data'!M58/'Raw Data'!N58 -> 2.5093834
A24: FY24-25 | B24: ='Raw Data'!D59 -> 6966 | C24: ='Raw Data'!E59 -> 886 | D24: ='Raw Data'!F59 -> 367 | E24: ='Raw Data'!G59+'Raw Data'!H59 -> 4611 | F24: ='Raw Data'!I59 -> 1606 | G24: ='Raw Data'!J59 -> 7129 | H24: ='Raw Data'!K59 -> 4478 | I24: =F24/E24 -> 0.34829755 | J24: =D24/E24 -> 0.079592279 | K24: =D24/G24 -> 0.051479871 | L24: =LN(G24) -> 8.8719263 | M24: =(B24-'Raw Data'!D58)/'Raw Data'!D58 -> 0.035066865 | N24: =H24/G24 -> 0.62813859 | O24: ='Raw Data'!L59 -> 0.72 | P24: ='Raw Data'!M59/'Raw Data'!N59 -> 2.8817087
A25: 10-YR AVERAGE | B25: =AVERAGE(B15:B24) -> 5416.8 | C25: =AVERAGE(C15:C24) -> 933.4 | D25: =AVERAGE(D15:D24) -> 389.8 | E25: =AVERAGE(E15:E24) -> 3389.5 | F25: =AVERAGE(F15:F24) -> 2183.9 | G25: =AVERAGE(G15:G24) -> 6415.5 | H25: =AVERAGE(H15:H24) -> 4218.7 | I25: =AVERAGE(I15:I24) -> 0.71020611 | ... P25: =AVERAGE(P15:P24) -> 2.6019052
A27: SD (10-yr) | I27: =STDEV(I15:I24) -> 0.37177203 | J27: =STDEV(J15:J24) -> 0.037618743 | K27: =STDEV(K15:K24) -> 0.024529454 | O27: =STDEV(O15:O24) -> 0.31149282 | P27: =STDEV(P15:P24) -> 0.36343344

Sheet Arvind
A1: Arvind
A3: Screener Ticker | B3: ARVIND
A4: Basis | B4: Standalone
A5: Primary Business | B5: Denim, Woven Fabrics, Garments
A6: Year Established | B6: 1931
A7: Headquarters | B7: Ahmedabad, Gujarat
A8: Promoter / Group | B8: Lalbhai Group — founder Kasturbhai Lalbhai (current Chairman: Sanjay Lalbhai)
A9: Manufacturing Locations | B9: Naroda & Santej (near Ahmedabad, Gujarat)
A10: Listed On | B10: NSE & BSE (BSE code: 500101)
A11: Note
A13: 10-Year Financials & Computed Ratios (FY2015-16 to FY2024-25)
A14: FY | B14: Sales | C14: EBIT | D14: Net Profit | E14: Total Equity | F14: Borrowings | G14: Total Assets | H14: Fixed Assets | I14: D/E Ratio | J14: ROE | K14: ROA | L14: Size (ln TA) | M14: Sales Growth % | N14: Tangibility | O14: EPS (Rs.) | P14: Liquidity (CR proxy)
A15: FY15-16 | B15: ='Raw Data'!D61 -> 5357 | C15: ='Raw Data'!E61 -> 808 | D15: ='Raw Data'!F61 -> 321 | E15: ='Raw Data'!G61+'Raw Data'!H61 -> 2986 | F15: ='Raw Data'!I61 -> 3123 | G15: ='Raw Data'!J61 -> 6990 | H15: ='Raw Data'!K61 -> 2928 | I15: =F15/E15 -> 1.0458808 | J15: =D15/E15 -> 0.10750167 | K15: =D15/G15 -> 0.045922747 | L15: =LN(G15) -> 8.8522358 | M15: =(B15-'Raw Data'!D60)/'Raw Data'!D60 -> 0.025263158 | N15: =H15/G15 -> 0.41888412 | O15: ='Raw Data'!L61 -> 12.42 | P15: ='Raw Data'!M61/'Raw Data'!N61 -> 3.1772727
A16: FY16-17 | B16: ='Raw Data'!D62 -> 5967 | C16: ='Raw Data'!E62 -> 732 | D16: ='Raw Data'!F62 -> 19 | E16: ='Raw Data'!G62+'Raw Data'!H62 -> 3011 | F16: ='Raw Data'!I62 -> 2428 | G16: ='Raw Data'!J62 -> 6458 | H16: ='Raw Data'!K62 -> 3177 | I16: =F16/E16 -> 0.80637662 | J16: =D16/E16 -> 0.0063101959 | K16: =D16/G16 -> 0.0029420873 | L16: =LN(G16) -> 8.773075 | M16: =(B16-'Raw Data'!D61)/'Raw Data'!D61 -> 0.1138697 | N16: =H16/G16 -> 0.49194797 | O16: ='Raw Data'!L62 -> 0.72 | P16: ='Raw Data'!M62/'Raw Data'!N62 -> 2.7102161
A17: FY17-18 | B17: ='Raw Data'!D63 -> 6332 | C17: ='Raw Data'!E63 -> 639 | D17: ='Raw Data'!F63 -> 250 | E17: ='Raw Data'!G63+'Raw Data'!H63 -> 3159 | F17: ='Raw Data'!I63 -> 2562 | G17: ='Raw Data'!J63 -> 7044 | H17: ='Raw Data'!K63 -> 3208 | I17: =F17/E17 -> 0.81101614 | J17: =D17/E17 -> 0.079138968 | K17: =D17/G17 -> 0.035491198 | L17: =LN(G17) -> 8.8599315 | M17: =(B17-'Raw Data'!D62)/'Raw Data'!D62 -> 0.061169767 | N17: =H17/G17 -> 0.45542306 | O17: ='Raw Data'!L63 -> 9.67 | P17: ='Raw Data'!M63/'Raw Data'!N63 -> 2.2303625
A18: FY18-19 | B18: ='Raw Data'!D64 -> 6436 | C18: ='Raw Data'!E64 -> 633 | D18: ='Raw Data'!F64 -> 199 | E18: ='Raw Data'!G64+'Raw Data'!H64 -> 2817 | F18: ='Raw Data'!I64 -> 2652 | G18: ='Raw Data'!J64 -> 7014 | H18: ='Raw Data'!K64 -> 3362 | I18: =F18/E18 -> 0.94142705 | J18: =D18/E18 -> 0.070642528 | K18: =D18/G18 -> 0.028371828 | L18: =LN(G18) -> 8.8556634 | M18: =(B18-'Raw Data'!D63)/'Raw Data'!D63 -> 0.01642451 | N18: =H18/G18 -> 0.47932706 | O18: ='Raw Data'!L64 -> 7.71 | P18: ='Raw Data'!M64/'Raw Data'!N64 -> 2.0278137
A19: FY19-20 | B19: ='Raw Data'!D65 -> 6705 | C19: ='Raw Data'!E65 -> 708 | D19: ='Raw Data'!F65 -> 171 | E19: ='Raw Data'!G65+'Raw Data'!H65 -> 2854 | F19: ='Raw Data'!I65 -> 2431 | G19: ='Raw Data'!J65 -> 6815 | H19: ='Raw Data'!K65 -> 3532 | I19: =F19/E19 -> 0.85178697 | J19: =D19/E19 -> 0.059915907 | K19: =D19/G19 -> 0.025091709 | L19: =LN(G19) -> 8.8268813 | M19: =(B19-'Raw Data'!D64)/'Raw Data'!D64 -> 0.041796147 | N19: =H19/G19 -> 0.51826853 | O19: ='Raw Data'!L65 -> 6.62 | P19: ='Raw Data'!M65/'Raw Data'!N65 -> 1.8026144
A20: FY20-21 | B20: ='Raw Data'!D66 -> 4529 | C20: ='Raw Data'!E66 -> 477 | D20: ='Raw Data'!F66 -> 93 | E20: ='Raw Data'!G66+'Raw Data'!H66 -> 2941 | F20: ='Raw Data'!I66 -> 1985 | G20: ='Raw Data'!J66 -> 6609 | H20: ='Raw Data'!K66 -> 3332 | I20: =F20/E20 -> 0.6749405 | J20: =D20/E20 -> 0.031621897 | K20: =D20/G20 -> 0.01407172 | L20: =LN(G20) -> 8.7961876 | M20: =(B20-'Raw Data'!D65)/'Raw Data'!D65 -> -0.32453393 | N20: =H20/G20 -> 0.50416099 | O20: ='Raw Data'!L66 -> 3.58 | P20: ='Raw Data'!M66/'Raw Data'!N66 -> 1.6319857
A21: FY21-22 | B21: ='Raw Data'!D67 -> 7436 | C21: ='Raw Data'!E67 -> 790 | D21: ='Raw Data'!F67 -> 59 | E21: ='Raw Data'!G67+'Raw Data'!H67 -> 3012 | F21: ='Raw Data'!I67 -> 1783 | G21: ='Raw Data'!J67 -> 7413 | H21: ='Raw Data'!K67 -> 3268 | I21: =F21/E21 -> 0.59196547 | J21: =D21/E21 -> 0.019588313 | K21: =D21/G21 -> 0.007958991 | L21: =LN(G21) -> 8.9109905 | M21: =(B21-'Raw Data'!D66)/'Raw Data'!D66 -> 0.64186355 | N21: =H21/G21 -> 0.44084716 | O21: ='Raw Data'!L67 -> 2.28 | P21: ='Raw Data'!M67/'Raw Data'!N67 -> 1.410462
A22: FY22-23 | B22: ='Raw Data'!D68 -> 7723 | C22: ='Raw Data'!E68 -> 720 | D22: ='Raw Data'!F68 -> 346 | E22: ='Raw Data'!G68+'Raw Data'!H68 -> 3297 | F22: ='Raw Data'!I68 -> 1420 | G22: ='Raw Data'!J68 -> 6398 | H22: ='Raw Data'!K68 -> 3255 | I22: =F22/E22 -> 0.43069457 | J22: =D22/E22 -> 0.10494389 | K22: =D22/G22 -> 0.0540794 | L22: =LN(G22) -> 8.7637407 | M22: =(B22-'Raw Data'!D67)/'Raw Data'!D67 -> 0.038596019 | N22: =H22/G22 -> 0.50875274 | O22: ='Raw Data'!L68 -> 13.23 | P22: ='Raw Data'!M68/'Raw Data'!N68 -> 1.6395003
A23: FY23-24 | B23: ='Raw Data'!D69 -> 7100 | C23: ='Raw Data'!E69 -> 767 | D23: ='Raw Data'!F69 -> 305 | E23: ='Raw Data'!G69+'Raw Data'!H69 -> 3477 | F23: ='Raw Data'!I69 -> 1320 | G23: ='Raw Data'!J69 -> 6729 | H23: ='Raw Data'!K69 -> 3288 | I23: =F23/E23 -> 0.37963762 | J23: =D23/E23 -> 0.087719298 | K23: =D23/G23 -> 0.0453262 | L23: =LN(G23) -> 8.8141818 | M23: =(B23-'Raw Data'!D68)/'Raw Data'!D68 -> -0.080668134 | N23: =H23/G23 -> 0.4886313 | O23: ='Raw Data'!L69 -> 11.65 | P23: ='Raw Data'!M69/'Raw Data'!N69 -> 1.6035197
A24: FY24-25 | B24: ='Raw Data'!D70 -> 6236 | C24: ='Raw Data'!E70 -> 581 | D24: ='Raw Data'!F70 -> 240 | E24: ='Raw Data'!G70+'Raw Data'!H70 -> 3587 | F24: ='Raw Data'!I70 -> 1496 | G24: ='Raw Data'!J70 -> 7324 | H24: ='Raw Data'!K70 -> 3504 | I24: =F24/E24 -> 0.41706161 | J24: =D24/E24 -> 0.06690828 | K24: =D24/G24 -> 0.032768979 | L24: =LN(G24) -> 8.8989119 | M24: =(B24-'Raw Data'!D69)/'Raw Data'!D69 -> -0.12169014 | N24: =H24/G24 -> 0.47842709 | O24: ='Raw Data'!L70 -> 9.18 | P24: ='Raw Data'!M70/'Raw Data'!N70 -> 1.5046854
A25: 10-YR AVERAGE | B25: =AVERAGE(B15:B24) -> 6382.1 | C25: =AVERAGE(C15:C24) -> 685.5 | D25: =AVERAGE(D15:D24) -> 200.3 | E25: =AVERAGE(E15:E24) -> 3114.1 | F25: =AVERAGE(F15:F24) -> 2120 | G25: =AVERAGE(G15:G24) -> 6879.4 | H25: =AVERAGE(H15:H24) -> 3285.4 | I25: =AVERAGE(I15:I24) -> 0.69507873 | ... P25: =AVERAGE(P15:P24) -> 1.9738433
A27: SD (10-yr) | I27: =STDEV(I15:I24) -> 0.23377797 | J27: =STDEV(J15:J24) -> 0.034601615 | K27: =STDEV(K15:K24) -> 0.016990498 | O27: =STDEV(O15:O24) -> 4.3559721 | P27: =STDEV(P15:P24) -> 0.57656267

Sheet Nitin Spinners
A1: Nitin Spinners
A3: Screener Ticker | B3: NITINSPIN
A4: Basis | B4: Standalone
A5: Primary Business | B5: Cotton Yarn, Knitted & Woven Fabric — spinning specialist
A6: Year Established | B6: 1992
A7: Headquarters | B7: Bhilwara, Rajasthan (the 'Textile City of India')
A8: Promoter / Group | B8: Nolkha family
A9: Manufacturing Locations | B9: Hamirgarh (Bhilwara) and Begun (Chittorgarh), Rajasthan
A10: Listed On | B10: NSE & BSE (BSE code: 532698)
A11: Note
A13: 10-Year Financials & Computed Ratios (FY2015-16 to FY2024-25)
A14: FY | B14: Sales | C14: EBIT | D14: Net Profit | E14: Total Equity | F14: Borrowings | G14: Total Assets | H14: Fixed Assets | I14: D/E Ratio | J14: ROE | K14: ROA | L14: Size (ln TA) | M14: Sales Growth % | N14: Tangibility | O14: EPS (Rs.) | P14: Liquidity (CR proxy)
A15: FY15-16 | B15: ='Raw Data'!D72 -> 766 | C15: ='Raw Data'!E72 -> 137 | D15: ='Raw Data'!F72 -> 44 | E15: ='Raw Data'!G72+'Raw Data'!H72 -> 206 | F15: ='Raw Data'!I72 -> 352 | G15: ='Raw Data'!J72 -> 635 | H15: ='Raw Data'!K72 -> 399 | I15: =F15/E15 -> 1.7087379 | J15: =D15/E15 -> 0.21359223 | K15: =D15/G15 -> 0.069291339 | L15: =LN(G15) -> 6.453625 | M15: =(B15-'Raw Data'!D71)/'Raw Data'!D71 -> 0.24350649 | N15: =H15/G15 -> 0.62834646 | O15: ='Raw Data'!L72 -> 9.63 | P15: ='Raw Data'!M72/'Raw Data'!N72 -> 3.0649351
A16: FY16-17 | B16: ='Raw Data'!D73 -> 933 | C16: ='Raw Data'!E73 -> 133 | D16: ='Raw Data'!F73 -> 57 | E16: ='Raw Data'!G73+'Raw Data'!H73 -> 264 | F16: ='Raw Data'!I73 -> 568 | G16: ='Raw Data'!J73 -> 885 | H16: ='Raw Data'!K73 -> 613 | I16: =F16/E16 -> 2.1515152 | J16: =D16/E16 -> 0.21590909 | K16: =D16/G16 -> 0.06440678 | L16: =LN(G16) -> 6.7855876 | M16: =(B16-'Raw Data'!D72)/'Raw Data'!D72 -> 0.21801567 | N16: =H16/G16 -> 0.69265537 | O16: ='Raw Data'!L73 -> 12.51 | P16: ='Raw Data'!M73/'Raw Data'!N73 -> 5.1320755
A17: FY17-18 | B17: ='Raw Data'!D74 -> 1145 | C17: ='Raw Data'!E74 -> 155 | D17: ='Raw Data'!F74 -> 52 | E17: ='Raw Data'!G74+'Raw Data'!H74 -> 417 | F17: ='Raw Data'!I74 -> 449 | G17: ='Raw Data'!J74 -> 929 | H17: ='Raw Data'!K74 -> 574 | I17: =F17/E17 -> 1.0767386 | J17: =D17/E17 -> 0.12470024 | K17: =D17/G17 -> 0.055974166 | L17: =LN(G17) -> 6.8341087 | M17: =(B17-'Raw Data'!D73)/'Raw Data'!D73 -> 0.22722401 | N17: =H17/G17 -> 0.61786868 | O17: ='Raw Data'!L74 -> 9.43 | P17: ='Raw Data'!M74/'Raw Data'!N74 -> 5.6349206
A18: FY18-19 | B18: ='Raw Data'!D75 -> 1241 | C18: ='Raw Data'!E75 -> 178 | D18: ='Raw Data'!F75 -> 64 | E18: ='Raw Data'!G75+'Raw Data'!H75 -> 482 | F18: ='Raw Data'!I75 -> 860 | G18: ='Raw Data'!J75 -> 1436 | H18: ='Raw Data'!K75 -> 992 | I18: =F18/E18 -> 1.7842324 | J18: =D18/E18 -> 0.13278008 | K18: =D18/G18 -> 0.044568245 | L18: =LN(G18) -> 7.2696167 | M18: =(B18-'Raw Data'!D74)/'Raw Data'!D74 -> 0.083842795 | N18: =H18/G18 -> 0.6908078 | O18: ='Raw Data'!L75 -> 11.4 | P18: ='Raw Data'!M75/'Raw Data'!N75 -> 4.7849462
A19: FY19-20 | B19: ='Raw Data'!D76 -> 1436 | C19: ='Raw Data'!E76 -> 170 | D19: ='Raw Data'!F76 -> 24 | E19: ='Raw Data'!G76+'Raw Data'!H76 -> 494 | F19: ='Raw Data'!I76 -> 1040 | G19: ='Raw Data'!J76 -> 1645 | H19: ='Raw Data'!K76 -> 1140 | I19: =F19/E19 -> 2.1052632 | J19: =D19/E19 -> 0.048582996 | K19: =D19/G19 -> 0.014589666 | L19: =LN(G19) -> 7.4054957 | M19: =(B19-'Raw Data'!D75)/'Raw Data'!D75 -> 0.15713135 | N19: =H19/G19 -> 0.69300912 | O19: ='Raw Data'!L76 -> 4.24 | P19: ='Raw Data'!M76/'Raw Data'!N76 -> 4.5585586
A20: FY20-21 | B20: ='Raw Data'!D77 -> 1622 | C20: ='Raw Data'!E77 -> 257 | D20: ='Raw Data'!F77 -> 69 | E20: ='Raw Data'!G77+'Raw Data'!H77 -> 563 | F20: ='Raw Data'!I77 -> 962 | G20: ='Raw Data'!J77 -> 1676 | H20: ='Raw Data'!K77 -> 1062 | I20: =F20/E20 -> 1.7087034 | J20: =D20/E20 -> 0.12255773 | K20: =D20/G20 -> 0.041169451 | L20: =LN(G20) -> 7.4241653 | M20: =(B20-'Raw Data'!D76)/'Raw Data'!D76 -> 0.12952646 | N20: =H20/G20 -> 0.63365155 | O20: ='Raw Data'!L77 -> 12.25 | P20: ='Raw Data'!M77/'Raw Data'!N77 -> 4.0728477
A21: FY21-22 | B21: ='Raw Data'!D78 -> 2690 | C21: ='Raw Data'!E78 -> 652 | D21: ='Raw Data'!F78 -> 326 | E21: ='Raw Data'!G78+'Raw Data'!H78 -> 876 | F21: ='Raw Data'!I78 -> 689 | G21: ='Raw Data'!J78 -> 1824 | H21: ='Raw Data'!K78 -> 1012 | I21: =F21/E21 -> 0.78652968 | J21: =D21/E21 -> 0.37214612 | K21: =D21/G21 -> 0.17872807 | L21: =LN(G21) -> 7.5087872 | M21: =(B21-'Raw Data'!D77)/'Raw Data'!D77 -> 0.65844636 | N21: =H21/G21 -> 0.55482456 | O21: ='Raw Data'!L78 -> 58.01 | P21: ='Raw Data'!M78/'Raw Data'!N78 -> 3.1230769
A22: FY22-23 | B22: ='Raw Data'!D79 -> 2404 | C22: ='Raw Data'!E79 -> 297 | D22: ='Raw Data'!F79 -> 165 | E22: ='Raw Data'!G79+'Raw Data'!H79 -> 1029 | F22: ='Raw Data'!I79 -> 980 | G22: ='Raw Data'!J79 -> 2218 | H22: ='Raw Data'!K79 -> 1351 | I22: =F22/E22 -> 0.95238095 | J22: =D22/E22 -> 0.16034985 | K22: =D22/G22 -> 0.074391344 | L22: =LN(G22) -> 7.7043612 | M22: =(B22-'Raw Data'!D78)/'Raw Data'!D78 -> -0.1063197 | N22: =H22/G22 -> 0.6091073 | O22: ='Raw Data'!L79 -> 29.32 | P22: ='Raw Data'!M79/'Raw Data'!N79 -> 4.1483254
A23: FY23-24 | B23: ='Raw Data'!D80 -> 2902 | C23: ='Raw Data'!E80 -> 377 | D23: ='Raw Data'!F80 -> 132 | E23: ='Raw Data'!G80+'Raw Data'!H80 -> 1146 | F23: ='Raw Data'!I80 -> 1339 | G23: ='Raw Data'!J80 -> 2717 | H23: ='Raw Data'!K80 -> 1711 | I23: =F23/E23 -> 1.1684119 | J23: =D23/E23 -> 0.11518325 | K23: =D23/G23 -> 0.048582996 | L23: =LN(G23) -> 7.9072836 | M23: =(B23-'Raw Data'!D79)/'Raw Data'!D79 -> 0.20715474 | N23: =H23/G23 -> 0.62973868 | O23: ='Raw Data'!L80 -> 23.39 | P23: ='Raw Data'!M80/'Raw Data'!N80 -> 4.3506494
A24: FY24-25 | B24: ='Raw Data'!D81 -> 3300 | C24: ='Raw Data'!E81 -> 471 | D24: ='Raw Data'!F81 -> 175 | E24: ='Raw Data'!G81+'Raw Data'!H81 -> 1311 | F24: ='Raw Data'!I81 -> 1165 | G24: ='Raw Data'!J81 -> 2732 | H24: ='Raw Data'!K81 -> 1584 | I24: =F24/E24 -> 0.88863463 | J24: =D24/E24 -> 0.13348589 | K24: =D24/G24 -> 0.064055637 | L24: =LN(G24) -> 7.9127892 | M24: =(B24-'Raw Data'!D80)/'Raw Data'!D80 -> 0.1371468 | N24: =H24/G24 -> 0.57979502 | O24: ='Raw Data'!L81 -> 31.2 | P24: ='Raw Data'!M81/'Raw Data'!N81 -> 4.484375
A25: 10-YR AVERAGE | B25: =AVERAGE(B15:B24) -> 1843.9 | C25: =AVERAGE(C15:C24) -> 282.7 | D25: =AVERAGE(D15:D24) -> 110.8 | E25: =AVERAGE(E15:E24) -> 678.8 | F25: =AVERAGE(F15:F24) -> 840.4 | G25: =AVERAGE(G15:G24) -> 1669.7 | H25: =AVERAGE(H15:H24) -> 1043.8 | I25: =AVERAGE(I15:I24) -> 1.4331148 | ... P25: =AVERAGE(P15:P24) -> 4.335471
A27: SD (10-yr) | I27: =STDEV(I15:I24) -> 0.51486684 | J27: =STDEV(J15:J24) -> 0.087790097 | K27: =STDEV(K15:K24) -> 0.043354037 | O27: =STDEV(O15:O24) -> 16.076643 | P27: =STDEV(P15:P24) -> 0.80176904

Sheet Sutlej Textiles
A1: Sutlej Textiles
A3: Screener Ticker | B3: SUTLEJTEX
A4: Basis | B4: Standalone
A5: Primary Business | B5: Yarn, Home Textiles — spinning specialist
A6: Year Established | B6: Current entity incorporated 2005 (demerger); heritage traces to Sutlej Cotton Mills, 1934
A7: Headquarters | B7: Registered office: Jaipur, Rajasthan
A8: Promoter / Group | B8: KK Birla Group — founder Dr. Krishna Kumar Birla
A9: Manufacturing Locations | B9: Bhawanimandi (Rajasthan), Baddi (Himachal Pradesh), Kathua (J&K), Bhillad (Gujarat)
A10: Listed On | B10: NSE & BSE
A11: Note
A13: 10-Year Financials & Computed Ratios (FY2015-16 to FY2024-25)
A14: FY | B14: Sales | C14: EBIT | D14: Net Profit | E14: Total Equity | F14: Borrowings | G14: Total Assets | H14: Fixed Assets | I14: D/E Ratio | J14: ROE | K14: ROA | L14: Size (ln TA) | M14: Sales Growth % | N14: Tangibility | O14: EPS (Rs.) | P14: Liquidity (CR proxy)
A15: FY15-16 | B15: ='Raw Data'!D83 -> 2074 | C15: ='Raw Data'!E83 -> 263 | D15: ='Raw Data'!F83 -> 143 | E15: ='Raw Data'!G83+'Raw Data'!H83 -> 683 | F15: ='Raw Data'!I83 -> 804 | G15: ='Raw Data'!J83 -> 1675 | H15: ='Raw Data'!K83 -> 877 | I15: =F15/E15 -> 1.1771596 | J15: =D15/E15 -> 0.20937042 | K15: =D15/G15 -> 0.085373134 | L15: =LN(G15) -> 7.4235684 | M15: =(B15-'Raw Data'!D82)/'Raw Data'!D82 -> 0.11087306 | N15: =H15/G15 -> 0.52358209 | O15: ='Raw Data'!L83 -> 8.76 | P15: ='Raw Data'!M83/'Raw Data'!N83 -> 4.106383
A16: FY16-17 | B16: ='Raw Data'!D84 -> 2249 | C16: ='Raw Data'!E84 -> 282 | D16: ='Raw Data'!F84 -> 158 | E16: ='Raw Data'!G84+'Raw Data'!H84 -> 816 | F16: ='Raw Data'!I84 -> 1036 | G16: ='Raw Data'!J84 -> 2045 | H16: ='Raw Data'!K84 -> 1139 | I16: =F16/E16 -> 1.2696078 | J16: =D16/E16 -> 0.19362745 | K16: =D16/G16 -> 0.077261614 | L16: =LN(G16) -> 7.6231531 | M16: =(B16-'Raw Data'!D83)/'Raw Data'!D83 -> 0.084378014 | N16: =H16/G16 -> 0.55696822 | O16: ='Raw Data'!L84 -> 9.64 | P16: ='Raw Data'!M84/'Raw Data'!N84 -> 4.5440415
A17: FY17-18 | B17: ='Raw Data'!D85 -> 2453 | C17: ='Raw Data'!E85 -> 247 | D17: ='Raw Data'!F85 -> 113 | E17: ='Raw Data'!G85+'Raw Data'!H85 -> 906 | F17: ='Raw Data'!I85 -> 1047 | G17: ='Raw Data'!J85 -> 2182 | H17: ='Raw Data'!K85 -> 1119 | I17: =F17/E17 -> 1.1556291 | J17: =D17/E17 -> 0.12472406 | K17: =D17/G17 -> 0.051787351 | L17: =LN(G17) -> 7.6879972 | M17: =(B17-'Raw Data'!D84)/'Raw Data'!D84 -> 0.090706981 | N17: =H17/G17 -> 0.51283226 | O17: ='Raw Data'!L85 -> 6.91 | P17: ='Raw Data'!M85/'Raw Data'!N85 -> 4.3026316
A18: FY18-19 | B18: ='Raw Data'!D86 -> 2562 | C18: ='Raw Data'!E86 -> 219 | D18: ='Raw Data'!F86 -> 66 | E18: ='Raw Data'!G86+'Raw Data'!H86 -> 946 | F18: ='Raw Data'!I86 -> 923 | G18: ='Raw Data'!J86 -> 2131 | H18: ='Raw Data'!K86 -> 1074 | I18: =F18/E18 -> 0.9756871 | J18: =D18/E18 -> 0.069767442 | K18: =D18/G18 -> 0.030971375 | L18: =LN(G18) -> 7.6643466 | M18: =(B18-'Raw Data'!D85)/'Raw Data'!D85 -> 0.044435385 | N18: =H18/G18 -> 0.50398874 | O18: ='Raw Data'!L86 -> 4.01 | P18: ='Raw Data'!M86/'Raw Data'!N86 -> 3.8275862
A19: FY19-20 | B19: ='Raw Data'!D87 -> 2379 | C19: ='Raw Data'!E87 -> 178 | D19: ='Raw Data'!F87 -> 36 | E19: ='Raw Data'!G87+'Raw Data'!H87 -> 971 | F19: ='Raw Data'!I87 -> 868 | G19: ='Raw Data'!J87 -> 2118 | H19: ='Raw Data'!K87 -> 1210 | I19: =F19/E19 -> 0.89392379 | J19: =D19/E19 -> 0.03707518 | K19: =D19/G19 -> 0.016997167 | L19: =LN(G19) -> 7.6582275 | M19: =(B19-'Raw Data'!D86)/'Raw Data'!D86 -> -0.071428571 | N19: =H19/G19 -> 0.57129367 | O19: ='Raw Data'!L87 -> 2.2 | P19: ='Raw Data'!M87/'Raw Data'!N87 -> 3.1362007
A20: FY20-21 | B20: ='Raw Data'!D88 -> 1861 | C20: ='Raw Data'!E88 -> 115 | D20: ='Raw Data'!F88 -> 10 | E20: ='Raw Data'!G88+'Raw Data'!H88 -> 980 | F20: ='Raw Data'!I88 -> 901 | G20: ='Raw Data'!J88 -> 2149 | H20: ='Raw Data'!K88 -> 1231 | I20: =F20/E20 -> 0.91938776 | J20: =D20/E20 -> 0.010204082 | K20: =D20/G20 -> 0.0046533271 | L20: =LN(G20) -> 7.6727579 | M20: =(B20-'Raw Data'!D87)/'Raw Data'!D87 -> -0.21773855 | N20: =H20/G20 -> 0.57282457 | O20: ='Raw Data'!L88 -> 0.58 | P20: ='Raw Data'!M88/'Raw Data'!N88 -> 3.2761194
A21: FY21-22 | B21: ='Raw Data'!D89 -> 3042 | C21: ='Raw Data'!E89 -> 387 | D21: ='Raw Data'!F89 -> 156 | E21: ='Raw Data'!G89+'Raw Data'!H89 -> 1130 | F21: ='Raw Data'!I89 -> 938 | G21: ='Raw Data'!J89 -> 2442 | H21: ='Raw Data'!K89 -> 1187 | I21: =F21/E21 -> 0.8300885 | J21: =D21/E21 -> 0.1380531 | K21: =D21/G21 -> 0.063882064 | L21: =LN(G21) -> 7.8005727 | M21: =(B21-'Raw Data'!D88)/'Raw Data'!D88 -> 0.63460505 | N21: =H21/G21 -> 0.48607699 | O21: ='Raw Data'!L89 -> 9.5 | P21: ='Raw Data'!M89/'Raw Data'!N89 -> 3.2112299
A22: FY22-23 | B22: ='Raw Data'!D90 -> 3039 | C22: ='Raw Data'!E90 -> 264 | D22: ='Raw Data'!F90 -> 23 | E22: ='Raw Data'!G90+'Raw Data'!H90 -> 1123 | F22: ='Raw Data'!I90 -> 933 | G22: ='Raw Data'!J90 -> 2421 | H22: ='Raw Data'!K90 -> 1121 | I22: =F22/E22 -> 0.83081033 | J22: =D22/E22 -> 0.020480855 | K22: =D22/G22 -> 0.0095002065 | L22: =LN(G22) -> 7.791936 | M22: =(B22-'Raw Data'!D89)/'Raw Data'!D89 -> -0.00098619329 | N22: =H22/G22 -> 0.46303181 | O22: ='Raw Data'!L90 -> 1.39 | P22: ='Raw Data'!M90/'Raw Data'!N90 -> 3.5
A23: FY23-24 | B23: ='Raw Data'!D91 -> 2672 | C23: ='Raw Data'!E91 -> -29 | D23: ='Raw Data'!F91 -> -135 | E23: ='Raw Data'!G91+'Raw Data'!H91 -> 976 | F23: ='Raw Data'!I91 -> 826 | G23: ='Raw Data'!J91 -> 2097 | H23: ='Raw Data'!K91 -> 1063 | I23: =F23/E23 -> 0.84631148 | J23: =D23/E23 -> -0.13831967 | K23: =D23/G23 -> -0.064377682 | L23: =LN(G23) -> 7.648263 | M23: =(B23-'Raw Data'!D90)/'Raw Data'!D90 -> -0.12076341 | N23: =H23/G23 -> 0.50691464 | O23: ='Raw Data'!L91 -> -8.22 | P23: ='Raw Data'!M91/'Raw Data'!N91 -> 3.4576271
A24: FY24-25 | B24: ='Raw Data'!D92 -> 2642 | C24: ='Raw Data'!E92 -> 46 | D24: ='Raw Data'!F92 -> -84 | E24: ='Raw Data'!G92+'Raw Data'!H92 -> 894 | F24: ='Raw Data'!I92 -> 877 | G24: ='Raw Data'!J92 -> 2043 | H24: ='Raw Data'!K92 -> 1010 | I24: =F24/E24 -> 0.98098434 | J24: =D24/E24 -> -0.093959732 | K24: =D24/G24 -> -0.041116006 | L24: =LN(G24) -> 7.6221746 | M24: =(B24-'Raw Data'!D91)/'Raw Data'!D91 -> -0.011227545 | N24: =H24/G24 -> 0.49437102 | O24: ='Raw Data'!L92 -> -5.14 | P24: ='Raw Data'!M92/'Raw Data'!N92 -> 3.7069597
A25: 10-YR AVERAGE | B25: =AVERAGE(B15:B24) -> 2497.3 | C25: =AVERAGE(C15:C24) -> 197.2 | D25: =AVERAGE(D15:D24) -> 48.6 | E25: =AVERAGE(E15:E24) -> 942.5 | F25: =AVERAGE(F15:F24) -> 915.3 | G25: =AVERAGE(G15:G24) -> 2130.3 | H25: =AVERAGE(H15:H24) -> 1103.1 | I25: =AVERAGE(I15:I24) -> 0.98795899 | ... P25: =AVERAGE(P15:P24) -> 3.7068779
A27: SD (10-yr) | I27: =STDEV(I15:I24) -> 0.1586971 | J27: =STDEV(J15:J24) -> 0.11453383 | K27: =STDEV(K15:K24) -> 0.049099101 | O27: =STDEV(O15:O24) -> 6.1196243 | P27: =STDEV(P15:P24) -> 0.48209689

Sheet Gokaldas Exports
A1: Gokaldas Exports
A3: Screener Ticker | B3: GOKEX
A4: Basis | B4: Standalone
A5: Primary Business | B5: Apparel / Garment Exports
A6: Year Established | B6: 1979
A7: Headquarters | B7: Bengaluru, Karnataka
A8: Promoter / Group | B8: Founded by Jhamandas Hinduja; Blackstone Group has held majority stake since 2007
A9: Manufacturing Locations | B9: Bengaluru region, Karnataka; also Kenya and Ethiopia
A10: Listed On | B10: NSE & BSE
A11: Note
A13: 10-Year Financials & Computed Ratios (FY2015-16 to FY2024-25)
A14: FY | B14: Sales | C14: EBIT | D14: Net Profit | E14: Total Equity | F14: Borrowings | G14: Total Assets | H14: Fixed Assets | I14: D/E Ratio | J14: ROE | K14: ROA | L14: Size (ln TA) | M14: Sales Growth % | N14: Tangibility | O14: EPS (Rs.) | P14: Liquidity (CR proxy)
A15: FY15-16 | B15: ='Raw Data'!D94 -> 1123 | C15: ='Raw Data'!E94 -> 37 | D15: ='Raw Data'!F94 -> 61 | E15: ='Raw Data'!G94+'Raw Data'!H94 -> 212 | F15: ='Raw Data'!I94 -> 343 | G15: ='Raw Data'!J94 -> 725 | H15: ='Raw Data'!K94 -> 94 | I15: =F15/E15 -> 1.6179245 | J15: =D15/E15 -> 0.28773585 | K15: =D15/G15 -> 0.084137931 | L15: =LN(G15) -> 6.5861717 | M15: =(B15-'Raw Data'!D93)/'Raw Data'!D93 -> 0.04953271 | N15: =H15/G15 -> 0.12965517 | O15: ='Raw Data'!L94 -> 17.44 | P15: ='Raw Data'!M94/'Raw Data'!N94 -> 3.5833333
A16: FY16-17 | B16: ='Raw Data'!D95 -> 915 | C16: ='Raw Data'!E95 -> -31 | D16: ='Raw Data'!F95 -> -46 | E16: ='Raw Data'!G95+'Raw Data'!H95 -> 165 | F16: ='Raw Data'!I95 -> 474 | G16: ='Raw Data'!J95 -> 794 | H16: ='Raw Data'!K95 -> 95 | I16: =F16/E16 -> 2.8727273 | J16: =D16/E16 -> -0.27878788 | K16: =D16/G16 -> -0.057934509 | L16: =LN(G16) -> 6.6770835 | M16: =(B16-'Raw Data'!D94)/'Raw Data'!D94 -> -0.18521817 | N16: =H16/G16 -> 0.11964736 | O16: ='Raw Data'!L95 -> -13.23 | P16: ='Raw Data'!M95/'Raw Data'!N95 -> 4.3571429
A17: FY17-18 | B17: ='Raw Data'!D96 -> 1031 | C17: ='Raw Data'!E96 -> -23 | D17: ='Raw Data'!F96 -> -31 | E17: ='Raw Data'!G96+'Raw Data'!H96 -> 130 | F17: ='Raw Data'!I96 -> 472 | G17: ='Raw Data'!J96 -> 794 | H17: ='Raw Data'!K96 -> 95 | I17: =F17/E17 -> 3.6307692 | J17: =D17/E17 -> -0.23846154 | K17: =D17/G17 -> -0.039042821 | L17: =LN(G17) -> 6.6770835 | M17: =(B17-'Raw Data'!D95)/'Raw Data'!D95 -> 0.12677596 | N17: =H17/G17 -> 0.11964736 | O17: ='Raw Data'!L96 -> -8.83 | P17: ='Raw Data'!M96/'Raw Data'!N96 -> 3.5364583
A18: FY18-19 | B18: ='Raw Data'!D97 -> 1173 | C18: ='Raw Data'!E97 -> 62 | D18: ='Raw Data'!F97 -> 26 | E18: ='Raw Data'!G97+'Raw Data'!H97 -> 239 | F18: ='Raw Data'!I97 -> 381 | G18: ='Raw Data'!J97 -> 823 | H18: ='Raw Data'!K97 -> 108 | I18: =F18/E18 -> 1.5941423 | J18: =D18/E18 -> 0.10878661 | K18: =D18/G18 -> 0.031591738 | L18: =LN(G18) -> 6.7129562 | M18: =(B18-'Raw Data'!D96)/'Raw Data'!D96 -> 0.13773036 | N18: =H18/G18 -> 0.13122722 | O18: ='Raw Data'!L97 -> 5.99 | P18: ='Raw Data'!M97/'Raw Data'!N97 -> 3.4356436
A19: FY19-20 | B19: ='Raw Data'!D98 -> 1368 | C19: ='Raw Data'!E98 -> 87 | D19: ='Raw Data'!F98 -> 32 | E19: ='Raw Data'!G98+'Raw Data'!H98 -> 228 | F19: ='Raw Data'!I98 -> 440 | G19: ='Raw Data'!J98 -> 939 | H19: ='Raw Data'!K98 -> 172 | I19: =F19/E19 -> 1.9298246 | J19: =D19/E19 -> 0.14035088 | K19: =D19/G19 -> 0.034078807 | L19: =LN(G19) -> 6.8448155 | M19: =(B19-'Raw Data'!D97)/'Raw Data'!D97 -> 0.16624041 | N19: =H19/G19 -> 0.18317359 | O19: ='Raw Data'!L98 -> 7.56 | P19: ='Raw Data'!M98/'Raw Data'!N98 -> 2.6273063
A20: FY20-21 | B20: ='Raw Data'!D99 -> 1209 | C20: ='Raw Data'!E99 -> 101 | D20: ='Raw Data'!F99 -> 26 | E20: ='Raw Data'!G99+'Raw Data'!H99 -> 291 | F20: ='Raw Data'!I99 -> 476 | G20: ='Raw Data'!J99 -> 1005 | H20: ='Raw Data'!K99 -> 235 | I20: =F20/E20 -> 1.6357388 | J20: =D20/E20 -> 0.089347079 | K20: =D20/G20 -> 0.025870647 | L20: =LN(G20) -> 6.9127428 | M20: =(B20-'Raw Data'!D98)/'Raw Data'!D98 -> -0.11622807 | N20: =H20/G20 -> 0.23383085 | O20: ='Raw Data'!L99 -> 6.12 | P20: ='Raw Data'!M99/'Raw Data'!N99 -> 3.0084388
A21: FY21-22 | B21: ='Raw Data'!D100 -> 1789 | C21: ='Raw Data'!E100 -> 204 | D21: ='Raw Data'!F100 -> 117 | E21: ='Raw Data'!G100+'Raw Data'!H100 -> 709 | F21: ='Raw Data'!I100 -> 191 | G21: ='Raw Data'!J100 -> 1226 | H21: ='Raw Data'!K100 -> 282 | I21: =F21/E21 -> 0.26939351 | J21: =D21/E21 -> 0.16502116 | K21: =D21/G21 -> 0.0954323 | L21: =LN(G21) -> 7.1115121 | M21: =(B21-'Raw Data'!D99)/'Raw Data'!D99 -> 0.47973532 | N21: =H21/G21 -> 0.23001631 | O21: ='Raw Data'!L100 -> 19.79 | P21: ='Raw Data'!M100/'Raw Data'!N100 -> 2.3692308
A22: FY22-23 | B22: ='Raw Data'!D101 -> 2221 | C22: ='Raw Data'!E101 -> 269 | D22: ='Raw Data'!F101 -> 178 | E22: ='Raw Data'!G101+'Raw Data'!H101 -> 893 | F22: ='Raw Data'!I101 -> 141 | G22: ='Raw Data'!J101 -> 1343 | H22: ='Raw Data'!K101 -> 261 | I22: =F22/E22 -> 0.15789474 | J22: =D22/E22 -> 0.19932811 | K22: =D22/G22 -> 0.13253909 | L22: =LN(G22) -> 7.2026612 | M22: =(B22-'Raw Data'!D100)/'Raw Data'!D100 -> 0.24147568 | N22: =H22/G22 -> 0.19434103 | O22: ='Raw Data'!L101 -> 29.45 | P22: ='Raw Data'!M101/'Raw Data'!N101 -> 2.3203883
A23: FY23-24 | B23: ='Raw Data'!D102 -> 2139 | C23: ='Raw Data'!E102 -> 255 | D23: ='Raw Data'!F102 -> 164 | E23: ='Raw Data'!G102+'Raw Data'!H102 -> 1342 | F23: ='Raw Data'!I102 -> 254 | G23: ='Raw Data'!J102 -> 1955 | H23: ='Raw Data'!K102 -> 254 | I23: =F23/E23 -> 0.18926975 | J23: =D23/E23 -> 0.12220566 | K23: =D23/G23 -> 0.083887468 | L23: =LN(G23) -> 7.5781455 | M23: =(B23-'Raw Data'!D101)/'Raw Data'!D101 -> -0.036920306 | N23: =H23/G23 -> 0.12992327 | O23: ='Raw Data'!L102 -> 25.9 | P23: ='Raw Data'!M102/'Raw Data'!N102 -> 3.3342618
A24: FY24-25 | B24: ='Raw Data'!D103 -> 2477 | C24: ='Raw Data'!E103 -> 244 | D24: ='Raw Data'!F103 -> 191 | E24: ='Raw Data'!G103+'Raw Data'!H103 -> 2145 | F24: ='Raw Data'!I103 -> 192 | G24: ='Raw Data'!J103 -> 2763 | H24: ='Raw Data'!K103 -> 272 | I24: =F24/E24 -> 0.08951049 | J24: =D24/E24 -> 0.089044289 | K24: =D24/G24 -> 0.06912776 | L24: =LN(G24) -> 7.9240723 | M24: =(B24-'Raw Data'!D102)/'Raw Data'!D102 -> 0.15801777 | N24: =H24/G24 -> 0.098443721 | O24: ='Raw Data'!L103 -> 26.77 | P24: ='Raw Data'!M103/'Raw Data'!N103 -> 3.870892
A25: 10-YR AVERAGE | B25: =AVERAGE(B15:B24) -> 1544.5 | C25: =AVERAGE(C15:C24) -> 120.5 | D25: =AVERAGE(D15:D24) -> 71.8 | E25: =AVERAGE(E15:E24) -> 635.4 | F25: =AVERAGE(F15:F24) -> 336.4 | G25: =AVERAGE(G15:G24) -> 1236.7 | H25: =AVERAGE(H15:H24) -> 186.8 | I25: =AVERAGE(I15:I24) -> 1.3987195 | ... P25: =AVERAGE(P15:P24) -> 3.2443096
A27: SD (10-yr) | I27: =STDEV(I15:I24) -> 1.2279638 | J27: =STDEV(J15:J24) -> 0.1825308 | K27: =STDEV(K15:K24) -> 0.059765263 | O27: =STDEV(O15:O24) -> 14.780125 | P27: =STDEV(P15:P24) -> 0.66095159

Sheet Siyaram Silk Mills
A1: Siyaram Silk Mills
A3: Screener Ticker | B3: SIYSIL
A4: Basis | B4: Standalone
A5: Primary Business | B5: Fabrics, Readymade Garments (Menswear) — branded player
A6: Year Established | B6: 1978
A7: Headquarters | B7: Mumbai, Maharashtra (registered plant: Tarapur, Maharashtra)
A8: Promoter / Group | B8: Poddar family (Chairman & MD: Ramesh Poddar)
A9: Manufacturing Locations | B9: Tarapur, Daman, Amravati, Silvassa
A10: Listed On | B10: NSE & BSE (BSE code: 503811)
A11: Note | B11: Substituted for Raymond Ltd (see Cover & Notes for rationale)
A13: 10-Year Financials & Computed Ratios (FY2015-16 to FY2024-25)
A14: FY | B14: Sales | C14: EBIT | D14: Net Profit | E14: Total Equity | F14: Borrowings | G14: Total Assets | H14: Fixed Assets | I14: D/E Ratio | J14: ROE | K14: ROA | L14: Size (ln TA) | M14: Sales Growth % | N14: Tangibility | O14: EPS (Rs.) | P14: Liquidity (CR proxy)
A15: FY15-16 | B15: ='Raw Data'!D105 -> 1609 | C15: ='Raw Data'!E105 -> 196 | D15: ='Raw Data'!F105 -> 84 | E15: ='Raw Data'!G105+'Raw Data'!H105 -> 506 | F15: ='Raw Data'!I105 -> 408 | G15: ='Raw Data'!J105 -> 1195 | H15: ='Raw Data'!K105 -> 403 | I15: =F15/E15 -> 0.80632411 | J15: =D15/E15 -> 0.16600791 | K15: =D15/G15 -> 0.070292887 | L15: =LN(G15) -> 7.0859015 | M15: =(B15-'Raw Data'!D104)/'Raw Data'!D104 -> 0.075534759 | N15: =H15/G15 -> 0.33723849 | O15: ='Raw Data'!L105 -> 17.93 | P15: ='Raw Data'!M105/'Raw Data'!N105 -> 2.7588652
A16: FY16-17 | B16: ='Raw Data'!D106 -> 1570 | C16: ='Raw Data'!E106 -> 197 | D16: ='Raw Data'!F106 -> 91 | E16: ='Raw Data'!G106+'Raw Data'!H106 -> 596 | F16: ='Raw Data'!I106 -> 305 | G16: ='Raw Data'!J106 -> 1159 | H16: ='Raw Data'!K106 -> 445 | I16: =F16/E16 -> 0.51174497 | J16: =D16/E16 -> 0.15268456 | K16: =D16/G16 -> 0.078515962 | L16: =LN(G16) -> 7.0553128 | M16: =(B16-'Raw Data'!D105)/'Raw Data'!D105 -> -0.024238658 | N16: =H16/G16 -> 0.38395168 | O16: ='Raw Data'!L106 -> 19.41 | P16: ='Raw Data'!M106/'Raw Data'!N106 -> 2.7674419
A17: FY17-18 | B17: ='Raw Data'!D107 -> 1733 | C17: ='Raw Data'!E107 -> 246 | D17: ='Raw Data'!F107 -> 112 | E17: ='Raw Data'!G107+'Raw Data'!H107 -> 678 | F17: ='Raw Data'!I107 -> 573 | G17: ='Raw Data'!J107 -> 1553 | H17: ='Raw Data'!K107 -> 532 | I17: =F17/E17 -> 0.84513274 | J17: =D17/E17 -> 0.16519174 | K17: =D17/G17 -> 0.07211848 | L17: =LN(G17) -> 7.3479438 | M17: =(B17-'Raw Data'!D106)/'Raw Data'!D106 -> 0.10382166 | N17: =H17/G17 -> 0.34256278 | O17: ='Raw Data'!L107 -> 23.81 | P17: ='Raw Data'!M107/'Raw Data'!N107 -> 3.2857143
A18: FY18-19 | B18: ='Raw Data'!D108 -> 1815 | C18: ='Raw Data'!E108 -> 241 | D18: ='Raw Data'!F108 -> 101 | E18: ='Raw Data'!G108+'Raw Data'!H108 -> 757 | F18: ='Raw Data'!I108 -> 444 | G18: ='Raw Data'!J108 -> 1505 | H18: ='Raw Data'!K108 -> 527 | I18: =F18/E18 -> 0.58652576 | J18: =D18/E18 -> 0.1334214 | K18: =D18/G18 -> 0.067109635 | L18: =LN(G18) -> 7.3165482 | M18: =(B18-'Raw Data'!D107)/'Raw Data'!D107 -> 0.047316792 | N18: =H18/G18 -> 0.35016611 | O18: ='Raw Data'!L108 -> 21.58 | P18: ='Raw Data'!M108/'Raw Data'!N108 -> 3.1452145
A19: FY19-20 | B19: ='Raw Data'!D109 -> 1698 | C19: ='Raw Data'!E109 -> 169 | D19: ='Raw Data'!F109 -> 72 | E19: ='Raw Data'!G109+'Raw Data'!H109 -> 767 | F19: ='Raw Data'!I109 -> 428 | G19: ='Raw Data'!J109 -> 1503 | H19: ='Raw Data'!K109 -> 552 | I19: =F19/E19 -> 0.55801825 | J19: =D19/E19 -> 0.093872229 | K19: =D19/G19 -> 0.047904192 | L19: =LN(G19) -> 7.3152184 | M19: =(B19-'Raw Data'!D108)/'Raw Data'!D108 -> -0.06446281 | N19: =H19/G19 -> 0.36726547 | O19: ='Raw Data'!L109 -> 15.3 | P19: ='Raw Data'!M109/'Raw Data'!N109 -> 3.0064935
A20: FY20-21 | B20: ='Raw Data'!D110 -> 1088 | C20: ='Raw Data'!E110 -> 55 | D20: ='Raw Data'!F110 -> 5 | E20: ='Raw Data'!G110+'Raw Data'!H110 -> 774 | F20: ='Raw Data'!I110 -> 139 | G20: ='Raw Data'!J110 -> 1217 | H20: ='Raw Data'!K110 -> 490 | I20: =F20/E20 -> 0.17958656 | J20: =D20/E20 -> 0.0064599483 | K20: =D20/G20 -> 0.0041084634 | L20: =LN(G20) -> 7.1041441 | M20: =(B20-'Raw Data'!D109)/'Raw Data'!D109 -> -0.35924617 | N20: =H20/G20 -> 0.40262942 | O20: ='Raw Data'!L110 -> 1.14 | P20: ='Raw Data'!M110/'Raw Data'!N110 -> 2.2236842
A21: FY21-22 | B21: ='Raw Data'!D111 -> 1903 | C21: ='Raw Data'!E111 -> 334 | D21: ='Raw Data'!F111 -> 213 | E21: ='Raw Data'!G111+'Raw Data'!H111 -> 937 | F21: ='Raw Data'!I111 -> 223 | G21: ='Raw Data'!J111 -> 1515 | H21: ='Raw Data'!K111 -> 500 | I21: =F21/E21 -> 0.2379936 | J21: =D21/E21 -> 0.22732124 | K21: =D21/G21 -> 0.14059406 | L21: =LN(G21) -> 7.3231707 | M21: =(B21-'Raw Data'!D110)/'Raw Data'!D110 -> 0.74908088 | N21: =H21/G21 -> 0.330033 | O21: ='Raw Data'!L111 -> 45.34 | P21: ='Raw Data'!M111/'Raw Data'!N111 -> 2.7239437
A22: FY22-23 | B22: ='Raw Data'!D112 -> 2229 | C22: ='Raw Data'!E112 -> 369 | D22: ='Raw Data'!F112 -> 252 | E22: ='Raw Data'!G112+'Raw Data'!H112 -> 1141 | F22: ='Raw Data'!I112 -> 163 | G22: ='Raw Data'!J112 -> 1640 | H22: ='Raw Data'!K112 -> 482 | I22: =F22/E22 -> 0.14285714 | J22: =D22/E22 -> 0.2208589 | K22: =D22/G22 -> 0.15365854 | L22: =LN(G22) -> 7.4024515 | M22: =(B22-'Raw Data'!D111)/'Raw Data'!D111 -> 0.17130846 | N22: =H22/G22 -> 0.29390244 | O22: ='Raw Data'!L112 -> 53.73 | P22: ='Raw Data'!M112/'Raw Data'!N112 -> 3.0416667
A23: FY23-24 | B23: ='Raw Data'!D113 -> 2087 | C23: ='Raw Data'!E113 -> 286 | D23: ='Raw Data'!F113 -> 185 | E23: ='Raw Data'!G113+'Raw Data'!H113 -> 1141 | F23: ='Raw Data'!I113 -> 175 | G23: ='Raw Data'!J113 -> 1606 | H23: ='Raw Data'!K113 -> 493 | I23: =F23/E23 -> 0.15337423 | J23: =D23/E23 -> 0.16213848 | K23: =D23/G23 -> 0.11519303 | L23: =LN(G23) -> 7.3815019 | M23: =(B23-'Raw Data'!D112)/'Raw Data'!D112 -> -0.063705698 | N23: =H23/G23 -> 0.30697385 | O23: ='Raw Data'!L113 -> 40.7 | P23: ='Raw Data'!M113/'Raw Data'!N113 -> 3.6965517
A24: FY24-25 | B24: ='Raw Data'!D114 -> 2220 | C24: ='Raw Data'!E114 -> 277 | D24: ='Raw Data'!F114 -> 199 | E24: ='Raw Data'!G114+'Raw Data'!H114 -> 1288 | F24: ='Raw Data'!I114 -> 262 | G24: ='Raw Data'!J114 -> 1893 | H24: ='Raw Data'!K114 -> 592 | I24: =F24/E24 -> 0.20341615 | J24: =D24/E24 -> 0.15450311 | K24: =D24/G24 -> 0.10512414 | L24: =LN(G24) -> 7.5459182 | M24: =(B24-'Raw Data'!D113)/'Raw Data'!D113 -> 0.063727839 | N24: =H24/G24 -> 0.31273111 | O24: ='Raw Data'!L114 -> 43.8 | P24: ='Raw Data'!M114/'Raw Data'!N114 -> 3.1666667
A25: 10-YR AVERAGE | B25: =AVERAGE(B15:B24) -> 1795.2 | C25: =AVERAGE(C15:C24) -> 237 | D25: =AVERAGE(D15:D24) -> 131.4 | E25: =AVERAGE(E15:E24) -> 858.5 | F25: =AVERAGE(F15:F24) -> 312 | G25: =AVERAGE(G15:G24) -> 1478.6 | H25: =AVERAGE(H15:H24) -> 501.6 | I25: =AVERAGE(I15:I24) -> 0.42249735 | ... P25: =AVERAGE(P15:P24) -> 2.9816242
A27: SD (10-yr) | I27: =STDEV(I15:I24) -> 0.27301807 | J27: =STDEV(J15:J24) -> 0.062945817 | K27: =STDEV(K15:K24) -> 0.044451022 | O27: =STDEV(O15:O24) -> 16.631973 | P27: =STDEV(P15:P24) -> 0.39513516

Sheet Ratios Panel
A1: Computed Capital Structure & Performance Ratios — FY2015-16 to FY2024-25 (Panel of 100 firm-years)
A2: Total Equity = Equity Capital + Reserves | D/E = Borrowings / Total Equity | ROE = Net Profit / Total Equity | ROA = Net Profit / Total Assets | EPS = Net Profit / Shares Outstanding (as reported by Screener.in, split-adjusted) | Size = LN(Total Assets) | Sales Growth = (Salest - Salest-1)/Salest-1 | Tangibility = Fixed Assets / Total Assets | Liquidity (Current Ratio proxy) = Other Assets / Other Liabilities | COVID dummy = 1 for FY19-20 and FY20-21, else 0
S3: Regression inputs — X variables placed side by side so LINEST can use them (Regression Output sheet)
A4: Company | B4: FY | C4: Sales | D4: EBIT | E4: Net Profit | F4: Total Equity | G4: Borrowings | H4: Total Assets | I4: Fixed Assets | J4: D/E Ratio | K4: ROE | L4: ROA | M4: Size (ln TA) | N4: Sales Growth % | O4: Tangibility | P4: EPS (Rs.) | Q4: Liquidity (Current Ratio proxy) | R4: COVID dummy (FY19-20, FY20-21 = 1) | S4: X1: D/E | T4: X2: Size | U4: X3: Sales Growth | V4: X4: Tangibility | W4: X5: COVID dummy
A5: KPR Mill | B5: FY15-16 | C5: ='Raw Data'!D6 -> 1961 | D5: ='Raw Data'!E6 -> 356 | E5: ='Raw Data'!F6 -> 156 | F5: ='Raw Data'!G6+'Raw Data'!H6 -> 981 | G5: ='Raw Data'!I6 -> 590 | H5: ='Raw Data'!J6 -> 1730 | I5: ='Raw Data'!K6 -> 894 | J5: =G5/F5 -> 0.60142712 | K5: =E5/F5 -> 0.15902141 | L5: =E5/H5 -> 0.09017341 | M5: =LN(H5) -> 7.4558767 | N5: =(C5-'Raw Data'!D5)/'Raw Data'!D5 -> -0.057211538 | O5: =I5/H5 -> 0.51676301 | P5: ='Raw Data'!L6 -> 4.14 | Q5: ='Raw Data'!M6/'Raw Data'!N6 -> 4.7375 | R5: =IF(OR(B5="FY19-20",B5="FY20-21"),1,0) -> 0 | S5: =J5 -> 0.60142712 | T5: =M5 -> 7.4558767 | U5: =N5 -> -0.057211538 | V5: =O5 -> 0.51676301 | W5: =R5 -> 0
A6: KPR Mill | B6: FY16-17 | C6: ='Raw Data'!D7 -> 2219 | D6: ='Raw Data'!E7 -> 446 | E6: ='Raw Data'!F7 -> 238 | F6: ='Raw Data'!G7+'Raw Data'!H7 -> 1118 | G6: ='Raw Data'!I7 -> 491 | H6: ='Raw Data'!J7 -> 1800 | I6: ='Raw Data'!K7 -> 918 | J6: =G6/F6 -> 0.4391771 | K6: =E6/F6 -> 0.21288014 | L6: =E6/H6 -> 0.13222222 | M6: =LN(H6) -> 7.4955419 | N6: =(C6-'Raw Data'!D6)/'Raw Data'!D6 -> 0.13156553 | O6: =I6/H6 -> 0.51 | P6: ='Raw Data'!L7 -> 6.45 | Q6: ='Raw Data'!M7/'Raw Data'!N7 -> 4.1570681 | R6: =IF(OR(B6="FY19-20",B6="FY20-21"),1,0) -> 0 | S6: =J6 -> 0.4391771 | T6: =M6 -> 7.4955419 | U6: =N6 -> 0.13156553 | V6: =O6 -> 0.51 | W6: =R6 -> 0
A7: KPR Mill | B7: FY17-18 | C7: ='Raw Data'!D8 -> 2512 | D7: ='Raw Data'!E8 -> 429 | E7: ='Raw Data'!F8 -> 225 | F7: ='Raw Data'!G8+'Raw Data'!H8 -> 1337 | G7: ='Raw Data'!I8 -> 346 | H7: ='Raw Data'!J8 -> 1930 | I7: ='Raw Data'!K8 -> 865 | J7: =G7/F7 -> 0.25878833 | K7: =E7/F7 -> 0.16828721 | L7: =E7/H7 -> 0.11658031 | M7: =LN(H7) -> 7.5652753 | N7: =(C7-'Raw Data'!D7)/'Raw Data'!D7 -> 0.13204146 | O7: =I7/H7 -> 0.44818653 | P7: ='Raw Data'!L8 -> 6.09 | Q7: ='Raw Data'!M8/'Raw Data'!N8 -> 3.9473684 | R7: =IF(OR(B7="FY19-20",B7="FY20-21"),1,0) -> 0 | S7: =J7 -> 0.25878833 | T7: =M7 -> 7.5652753 | U7: =N7 -> 0.13204146 | V7: =O7 -> 0.44818653 | W7: =R7 -> 0
A8: KPR Mill | B8: FY18-19 | C8: ='Raw Data'!D9 -> 2979 | D8: ='Raw Data'!E9 -> 507 | E8: ='Raw Data'!F9 -> 289 | F8: ='Raw Data'!G9+'Raw Data'!H9 -> 1511 | G8: ='Raw Data'!I9 -> 654 | H8: ='Raw Data'!J9 -> 2397 | I8: ='Raw Data'!K9 -> 798 | J8: =G8/F8 -> 0.43282594 | K8: =E8/F8 -> 0.19126406 | L8: =E8/H8 -> 0.12056738 | M8: =LN(H8) -> 7.7819732 | N8: =(C8-'Raw Data'!D8)/'Raw Data'!D8 -> 0.18590764 | O8: =I8/H8 -> 0.33291615 | P8: ='Raw Data'!L9 -> 7.97 | Q8: ='Raw Data'!M9/'Raw Data'!N9 -> 6.5474138 | R8: =IF(OR(B8="FY19-20",B8="FY20-21"),1,0) -> 0 | S8: =J8 -> 0.43282594 | T8: =M8 -> 7.7819732 | U8: =N8 -> 0.18590764 | V8: =O8 -> 0.33291615 | W8: =R8 -> 0
A9: KPR Mill | B9: FY19-20 | C9: ='Raw Data'!D10 -> 2898 | D9: ='Raw Data'!E10 -> 475 | E9: ='Raw Data'!F10 -> 295 | F9: ='Raw Data'!G10+'Raw Data'!H10 -> 1504 | G9: ='Raw Data'!I10 -> 472 | H9: ='Raw Data'!J10 -> 2187 | I9: ='Raw Data'!K10 -> 873 | J9: =G9/F9 -> 0.31382979 | K9: =E9/F9 -> 0.19614362 | L9: =E9/H9 -> 0.13488797 | M9: =LN(H9) -> 7.690286 | N9: =(C9-'Raw Data'!D9)/'Raw Data'!D9 -> -0.027190332 | O9: =I9/H9 -> 0.39917695 | P9: ='Raw Data'!L10 -> 8.56 | Q9: ='Raw Data'!M10/'Raw Data'!N10 -> 5.8056872 | R9: =IF(OR(B9="FY19-20",B9="FY20-21"),1,0) -> 1 | S9: =J9 -> 0.31382979 | T9: =M9 -> 7.690286 | U9: =N9 -> -0.027190332 | V9: =O9 -> 0.39917695 | W9: =R9 -> 1
A10: KPR Mill | B10: FY20-21 | C10: ='Raw Data'!D11 -> 2954 | D10: ='Raw Data'!E11 -> 664 | E10: ='Raw Data'!F11 -> 433 | F10: ='Raw Data'!G11+'Raw Data'!H11 -> 1906 | G10: ='Raw Data'!I11 -> 317 | H10: ='Raw Data'!J11 -> 2485 | I10: ='Raw Data'!K11 -> 815 | J10: =G10/F10 -> 0.16631689 | K10: =E10/F10 -> 0.22717733 | L10: =E10/H10 -> 0.17424547 | M10: =LN(H10) -> 7.8180279 | N10: =(C10-'Raw Data'!D10)/'Raw Data'!D10 -> 0.019323671 | O10: =I10/H10 -> 0.32796781 | P10: ='Raw Data'!L11 -> 12.57 | Q10: ='Raw Data'!M11/'Raw Data'!N11 -> 4.7709924 | R10: =IF(OR(B10="FY19-20",B10="FY20-21"),1,0) -> 1 | S10: =J10 -> 0.16631689 | T10: =M10 -> 7.8180279 | U10: =N10 -> 0.019323671 | V10: =O10 -> 0.32796781 | W10: =R10 -> 1
A11: KPR Mill | B11: FY21-22 | C11: ='Raw Data'!D12 -> 4074 | D11: ='Raw Data'!E12 -> 984 | E11: ='Raw Data'!F12 -> 731 | F11: ='Raw Data'!G12+'Raw Data'!H12 -> 2632 | G11: ='Raw Data'!I12 -> 418 | H11: ='Raw Data'!J12 -> 3359 | I11: ='Raw Data'!K12 -> 850 | J11: =G11/F11 -> 0.15881459 | K11: =E11/F11 -> 0.27773556 | L11: =E11/H11 -> 0.21762429 | M11: =LN(H11) -> 8.1193986 | N11: =(C11-'Raw Data'!D11)/'Raw Data'!D11 -> 0.37914692 | O11: =I11/H11 -> 0.2530515 | P11: ='Raw Data'!L12 -> 21.24 | Q11: ='Raw Data'!M12/'Raw Data'!N12 -> 5.3592233 | R11: =IF(OR(B11="FY19-20",B11="FY20-21"),1,0) -> 0 | S11: =J11 -> 0.15881459 | T11: =M11 -> 8.1193986 | U11: =N11 -> 0.37914692 | V11: =O11 -> 0.2530515 | W11: =R11 -> 0
A12: KPR Mill | B12: FY22-23 | C12: ='Raw Data'!D13 -> 4740 | D12: ='Raw Data'!E13 -> 799 | E12: ='Raw Data'!F13 -> 635 | F12: ='Raw Data'!G13+'Raw Data'!H13 -> 2973 | G12: ='Raw Data'!I13 -> 498 | H12: ='Raw Data'!J13 -> 3874 | I12: ='Raw Data'!K13 -> 971 | J12: =G12/F12 -> 0.16750757 | K12: =E12/F12 -> 0.21358897 | L12: =E12/H12 -> 0.16391327 | M12: =LN(H12) -> 8.2620428 | N12: =(C12-'Raw Data'!D12)/'Raw Data'!D12 -> 0.1634757 | O12: =I12/H12 -> 0.25064533 | P12: ='Raw Data'!L13 -> 18.58 | Q12: ='Raw Data'!M13/'Raw Data'!N13 -> 5.0074442 | R12: =IF(OR(B12="FY19-20",B12="FY20-21"),1,0) -> 0 | S12: =J12 -> 0.16750757 | T12: =M12 -> 8.2620428 | U12: =N12 -> 0.1634757 | V12: =O12 -> 0.25064533 | W12: =R12 -> 0
A13: KPR Mill | B13: FY23-24 | C13: ='Raw Data'!D14 -> 4054 | D13: ='Raw Data'!E14 -> 595 | E13: ='Raw Data'!F14 -> 555 | F13: ='Raw Data'!G14+'Raw Data'!H14 -> 3374 | G13: ='Raw Data'!I14 -> 287 | H13: ='Raw Data'!J14 -> 3919 | I13: ='Raw Data'!K14 -> 1070 | J13: =G13/F13 -> 0.085062241 | K13: =E13/F13 -> 0.16449318 | L13: =E13/H13 -> 0.14161776 | M13: =LN(H13) -> 8.2735918 | N13: =(C13-'Raw Data'!D13)/'Raw Data'!D13 -> -0.14472574 | O13: =I13/H13 -> 0.27302883 | P13: ='Raw Data'!L14 -> 16.23 | Q13: ='Raw Data'!M14/'Raw Data'!N14 -> 8.0930233 | R13: =IF(OR(B13="FY19-20",B13="FY20-21"),1,0) -> 0 | S13: =J13 -> 0.085062241 | T13: =M13 -> 8.2735918 | U13: =N13 -> -0.14472574 | V13: =O13 -> 0.27302883 | W13: =R13 -> 0
A14: KPR Mill | B14: FY24-25 | C14: ='Raw Data'!D15 -> 4216 | D14: ='Raw Data'!E15 -> 764 | E14: ='Raw Data'!F15 -> 653 | F14: ='Raw Data'!G15+'Raw Data'!H15 -> 3856 | G14: ='Raw Data'!I15 -> 241 | H14: ='Raw Data'!J15 -> 4403 | I14: ='Raw Data'!K15 -> 1122 | J14: =G14/F14 -> 0.0625 | K14: =E14/F14 -> 0.16934647 | L14: =E14/H14 -> 0.14830797 | M14: =LN(H14) -> 8.3900414 | N14: =(C14-'Raw Data'!D14)/'Raw Data'!D14 -> 0.039960533 | O14: =I14/H14 -> 0.25482625 | P14: ='Raw Data'!L15 -> 19.11 | Q14: ='Raw Data'!M15/'Raw Data'!N15 -> 7.6013072 | R14: =IF(OR(B14="FY19-20",B14="FY20-21"),1,0) -> 0 | S14: =J14 -> 0.0625 | T14: =M14 -> 8.3900414 | U14: =N14 -> 0.039960533 | V14: =O14 -> 0.25482625 | W14: =R14 -> 0
A15: Welspun Living | B15: FY15-16 | C15: ='Raw Data'!D17 -> 4885 | D15: ='Raw Data'!E17 -> 1275 | E15: ='Raw Data'!F17 -> 648 | F15: ='Raw Data'!G17+'Raw Data'!H17 -> 1899 | G15: ='Raw Data'!I17 -> 2566 | H15: ='Raw Data'!J17 -> 5362 | I15: ='Raw Data'!K17 -> 2830 | J15: =G15/F15 -> 1.3512375 | K15: =E15/F15 -> 0.34123223 | L15: =E15/H15 -> 0.12085043 | M15: =LN(H15) -> 8.5870923 | N15: =(C15-'Raw Data'!D16)/'Raw Data'!D16 -> 0.11275626 | O15: =I15/H15 -> 0.52778814 | P15: ='Raw Data'!L17 -> 6.45 | Q15: ='Raw Data'!M17/'Raw Data'!N17 -> 2.0546875 | R15: =IF(OR(B15="FY19-20",B15="FY20-21"),1,0) -> 0 | S15: =J15 -> 1.3512375 | T15: =M15 -> 8.5870923 | U15: =N15 -> 0.11275626 | V15: =O15 -> 0.52778814 | W15: =R15 -> 0
A16: Welspun Living | B16: FY16-17 | C16: ='Raw Data'!D18 -> 5639 | D16: ='Raw Data'!E18 -> 1370 | E16: ='Raw Data'!F18 -> 307 | F16: ='Raw Data'!G18+'Raw Data'!H18 -> 2201 | G16: ='Raw Data'!I18 -> 2738 | H16: ='Raw Data'!J18 -> 6248 | I16: ='Raw Data'!K18 -> 3057 | J16: =G16/F16 -> 1.24398 | K16: =E16/F16 -> 0.13948205 | L16: =E16/H16 -> 0.049135723 | M16: =LN(H16) -> 8.7400167 | N16: =(C16-'Raw Data'!D17)/'Raw Data'!D17 -> 0.15435005 | O16: =I16/H16 -> 0.48927657 | P16: ='Raw Data'!L18 -> 3.05 | Q16: ='Raw Data'!M18/'Raw Data'!N18 -> 1.808104 | R16: =IF(OR(B16="FY19-20",B16="FY20-21"),1,0) -> 0 | S16: =J16 -> 1.24398 | T16: =M16 -> 8.7400167 | U16: =N16 -> 0.15435005 | V16: =O16 -> 0.48927657 | W16: =R16 -> 0
A17: Welspun Living | B17: FY17-18 | C17: ='Raw Data'!D19 -> 4977 | D17: ='Raw Data'!E19 -> 894 | E17: ='Raw Data'!F19 -> 304 | F17: ='Raw Data'!G19+'Raw Data'!H19 -> 2429 | G17: ='Raw Data'!I19 -> 2721 | H17: ='Raw Data'!J19 -> 6248 | I17: ='Raw Data'!K19 -> 2846 | J17: =G17/F17 -> 1.1202141 | K17: =E17/F17 -> 0.12515438 | L17: =E17/H17 -> 0.04865557 | M17: =LN(H17) -> 8.7400167 | N17: =(C17-'Raw Data'!D18)/'Raw Data'!D18 -> -0.1173967 | O17: =I17/H17 -> 0.45550576 | P17: ='Raw Data'!L19 -> 3.03 | Q17: ='Raw Data'!M19/'Raw Data'!N19 -> 2.2747953 | R17: =IF(OR(B17="FY19-20",B17="FY20-21"),1,0) -> 0 | S17: =J17 -> 1.1202141 | T17: =M17 -> 8.7400167 | U17: =N17 -> -0.1173967 | V17: =O17 -> 0.45550576 | W17: =R17 -> 0
A18: Welspun Living | B18: FY18-19 | C18: ='Raw Data'!D20 -> 5395 | D18: ='Raw Data'!E20 -> 795 | E18: ='Raw Data'!F20 -> 142 | F18: ='Raw Data'!G20+'Raw Data'!H20 -> 2489 | G18: ='Raw Data'!I20 -> 2510 | H18: ='Raw Data'!J20 -> 6264 | I18: ='Raw Data'!K20 -> 2654 | J18: =G18/F18 -> 1.0084371 | K18: =E18/F18 -> 0.057051025 | L18: =E18/H18 -> 0.022669221 | M18: =LN(H18) -> 8.7425742 | N18: =(C18-'Raw Data'!D19)/'Raw Data'!D19 -> 0.083986337 | O18: =I18/H18 -> 0.42369093 | P18: ='Raw Data'!L20 -> 1.41 | Q18: ='Raw Data'!M20/'Raw Data'!N20 -> 2.0023734 | R18: =IF(OR(B18="FY19-20",B18="FY20-21"),1,0) -> 0 | S18: =J18 -> 1.0084371 | T18: =M18 -> 8.7425742 | U18: =N18 -> 0.083986337 | V18: =O18 -> 0.42369093 | W18: =R18 -> 0
A19: Welspun Living | B19: FY19-20 | C19: ='Raw Data'!D21 -> 5324 | D19: ='Raw Data'!E21 -> 1009 | E19: ='Raw Data'!F21 -> 475 | F19: ='Raw Data'!G21+'Raw Data'!H21 -> 2807 | G19: ='Raw Data'!I21 -> 2275 | H19: ='Raw Data'!J21 -> 6221 | I19: ='Raw Data'!K21 -> 2385 | J19: =G19/F19 -> 0.81047382 | K19: =E19/F19 -> 0.16921981 | L19: =E19/H19 -> 0.076354284 | M19: =LN(H19) -> 8.7356859 | N19: =(C19-'Raw Data'!D20)/'Raw Data'!D20 -> -0.013160334 | O19: =I19/H19 -> 0.38337888 | P19: ='Raw Data'!L21 -> 4.73 | Q19: ='Raw Data'!M21/'Raw Data'!N21 -> 2.1826163 | R19: =IF(OR(B19="FY19-20",B19="FY20-21"),1,0) -> 1 | S19: =J19 -> 0.81047382 | T19: =M19 -> 8.7356859 | U19: =N19 -> -0.013160334 | V19: =O19 -> 0.38337888 | W19: =R19 -> 1
A20: Welspun Living | B20: FY20-21 | C20: ='Raw Data'!D22 -> 5956 | D20: ='Raw Data'!E22 -> 1084 | E20: ='Raw Data'!F22 -> 527 | F20: ='Raw Data'!G22+'Raw Data'!H22 -> 3338 | G20: ='Raw Data'!I22 -> 1409 | H20: ='Raw Data'!J22 -> 6098 | I20: ='Raw Data'!K22 -> 2158 | J20: =G20/F20 -> 0.42210905 | K20: =E20/F20 -> 0.15787897 | L20: =E20/H20 -> 0.086421778 | M20: =LN(H20) -> 8.7157161 | N20: =(C20-'Raw Data'!D21)/'Raw Data'!D21 -> 0.11870774 | O20: =I20/H20 -> 0.35388652 | P20: ='Raw Data'!L22 -> 5.24 | Q20: ='Raw Data'!M22/'Raw Data'!N22 -> 1.8725926 | R20: =IF(OR(B20="FY19-20",B20="FY20-21"),1,0) -> 1 | S20: =J20 -> 0.42210905 | T20: =M20 -> 8.7157161 | U20: =N20 -> 0.11870774 | V20: =O20 -> 0.35388652 | W20: =R20 -> 1
A21: Welspun Living | B21: FY21-22 | C21: ='Raw Data'!D23 -> 6703 | D21: ='Raw Data'!E23 -> 893 | E21: ='Raw Data'!F23 -> 392 | F21: ='Raw Data'!G23+'Raw Data'!H23 -> 3475 | G21: ='Raw Data'!I23 -> 1318 | H21: ='Raw Data'!J23 -> 6191 | I21: ='Raw Data'!K23 -> 2025 | J21: =G21/F21 -> 0.37928058 | K21: =E21/F21 -> 0.11280576 | L21: =E21/H21 -> 0.063317719 | M21: =LN(H21) -> 8.7308519 | N21: =(C21-'Raw Data'!D22)/'Raw Data'!D22 -> 0.12541974 | O21: =I21/H21 -> 0.32708771 | P21: ='Raw Data'!L23 -> 3.9 | Q21: ='Raw Data'!M23/'Raw Data'!N23 -> 1.6237482 | R21: =IF(OR(B21="FY19-20",B21="FY20-21"),1,0) -> 0 | S21: =J21 -> 0.37928058 | T21: =M21 -> 8.7308519 | U21: =N21 -> 0.12541974 | V21: =O21 -> 0.32708771 | W21: =R21 -> 0
A22: Welspun Living | B22: FY22-23 | C22: ='Raw Data'!D24 -> 6298 | D22: ='Raw Data'!E24 -> 456 | E22: ='Raw Data'!F24 -> 123 | F22: ='Raw Data'!G24+'Raw Data'!H24 -> 3408 | G22: ='Raw Data'!I24 -> 1767 | H22: ='Raw Data'!J24 -> 6880 | I22: ='Raw Data'!K24 -> 2938 | J22: =G22/F22 -> 0.51848592 | K22: =E22/F22 -> 0.036091549 | L22: =E22/H22 -> 0.017877907 | M22: =LN(H22) -> 8.8363739 | N22: =(C22-'Raw Data'!D23)/'Raw Data'!D23 -> -0.060420707 | O22: =I22/H22 -> 0.42703488 | P22: ='Raw Data'!L24 -> 1.22 | Q22: ='Raw Data'!M24/'Raw Data'!N24 -> 1.5472141 | R22: =IF(OR(B22="FY19-20",B22="FY20-21"),1,0) -> 0 | S22: =J22 -> 0.51848592 | T22: =M22 -> 8.8363739 | U22: =N22 -> -0.060420707 | V22: =O22 -> 0.42703488 | W22: =R22 -> 0
A23: Welspun Living | B23: FY23-24 | C23: ='Raw Data'!D25 -> 8085 | D23: ='Raw Data'!E25 -> 1012 | E23: ='Raw Data'!F25 -> 596 | F23: ='Raw Data'!G25+'Raw Data'!H25 -> 3741 | G23: ='Raw Data'!I25 -> 1965 | H23: ='Raw Data'!J25 -> 7515 | I23: ='Raw Data'!K25 -> 2879 | J23: =G23/F23 -> 0.52526063 | K23: =E23/F23 -> 0.15931569 | L23: =E23/H23 -> 0.079308051 | M23: =LN(H23) -> 8.9246563 | N23: =(C23-'Raw Data'!D24)/'Raw Data'!D24 -> 0.28374087 | O23: =I23/H23 -> 0.38310047 | P23: ='Raw Data'!L25 -> 6.13 | Q23: ='Raw Data'!M25/'Raw Data'!N25 -> 1.6955801 | R23: =IF(OR(B23="FY19-20",B23="FY20-21"),1,0) -> 0 | S23: =J23 -> 0.52526063 | T23: =M23 -> 8.9246563 | U23: =N23 -> 0.28374087 | V23: =O23 -> 0.38310047 | W23: =R23 -> 0
A24: Welspun Living | B24: FY24-25 | C24: ='Raw Data'!D26 -> 8622 | D24: ='Raw Data'!E26 -> 907 | E24: ='Raw Data'!F26 -> 507 | F24: ='Raw Data'!G26+'Raw Data'!H26 -> 3905 | G24: ='Raw Data'!I26 -> 1678 | H24: ='Raw Data'!J26 -> 7508 | I24: ='Raw Data'!K26 -> 2933 | J24: =G24/F24 -> 0.42970551 | K24: =E24/F24 -> 0.12983355 | L24: =E24/H24 -> 0.06752797 | M24: =LN(H24) -> 8.9237244 | N24: =(C24-'Raw Data'!D25)/'Raw Data'!D25 -> 0.066419295 | O24: =I24/H24 -> 0.39064997 | P24: ='Raw Data'!L26 -> 5.28 | Q24: ='Raw Data'!M26/'Raw Data'!N26 -> 1.7038961 | R24: =IF(OR(B24="FY19-20",B24="FY20-21"),1,0) -> 0 | S24: =J24 -> 0.42970551 | T24: =M24 -> 8.9237244 | U24: =N24 -> 0.066419295 | V24: =O24 -> 0.39064997 | W24: =R24 -> 0
A25: Indo Count Industries | B25: FY15-16 | C25: ='Raw Data'!D28 -> 2001 | D25: ='Raw Data'!E28 -> 396 | E25: ='Raw Data'!F28 -> 238 | F25: ='Raw Data'!G28+'Raw Data'!H28 -> 613 | G25: ='Raw Data'!I28 -> 340 | H25: ='Raw Data'!J28 -> 1283 | I25: ='Raw Data'!K28 -> 466 | J25: =G25/F25 -> 0.55464927 | K25: =E25/F25 -> 0.38825449 | L25: =E25/H25 -> 0.18550273 | M25: =LN(H25) -> 7.1569564 | N25: =(C25-'Raw Data'!D27)/'Raw Data'!D27 -> 0.23824257 | O25: =I25/H25 -> 0.36321122 | P25: ='Raw Data'!L28 -> 12.04 | Q25: ='Raw Data'!M28/'Raw Data'!N28 -> 2.4255319 | R25: =IF(OR(B25="FY19-20",B25="FY20-21"),1,0) -> 0 | S25: =J25 -> 0.55464927 | T25: =M25 -> 7.1569564 | U25: =N25 -> 0.23824257 | V25: =O25 -> 0.36321122 | W25: =R25 -> 0
A26: Indo Count Industries | B26: FY16-17 | C26: ='Raw Data'!D29 -> 1990 | D26: ='Raw Data'!E29 -> 325 | E26: ='Raw Data'!F29 -> 228 | F26: ='Raw Data'!G29+'Raw Data'!H29 -> 826 | G26: ='Raw Data'!I29 -> 267 | H26: ='Raw Data'!J29 -> 1440 | I26: ='Raw Data'!K29 -> 511 | J26: =G26/F26 -> 0.32324455 | K26: =E26/F26 -> 0.27602906 | L26: =E26/H26 -> 0.15833333 | M26: =LN(H26) -> 7.2723984 | N26: =(C26-'Raw Data'!D28)/'Raw Data'!D28 -> -0.0054972514 | O26: =I26/H26 -> 0.35486111 | P26: ='Raw Data'!L29 -> 11.55 | Q26: ='Raw Data'!M29/'Raw Data'!N29 -> 2.6271676 | R26: =IF(OR(B26="FY19-20",B26="FY20-21"),1,0) -> 0 | S26: =J26 -> 0.32324455 | T26: =M26 -> 7.2723984 | U26: =N26 -> -0.0054972514 | V26: =O26 -> 0.35486111 | W26: =R26 -> 0
A27: Indo Count Industries | B27: FY17-18 | C27: ='Raw Data'!D30 -> 1709 | D27: ='Raw Data'!E30 -> 167 | E27: ='Raw Data'!F30 -> 131 | F27: ='Raw Data'!G30+'Raw Data'!H30 -> 938 | G27: ='Raw Data'!I30 -> 371 | H27: ='Raw Data'!J30 -> 1644 | I27: ='Raw Data'!K30 -> 535 | J27: =G27/F27 -> 0.39552239 | K27: =E27/F27 -> 0.13965885 | L27: =E27/H27 -> 0.079683698 | M27: =LN(H27) -> 7.4048876 | N27: =(C27-'Raw Data'!D29)/'Raw Data'!D29 -> -0.14120603 | O27: =I27/H27 -> 0.32542579 | P27: ='Raw Data'!L30 -> 6.64 | Q27: ='Raw Data'!M30/'Raw Data'!N30 -> 3.2537313 | R27: =IF(OR(B27="FY19-20",B27="FY20-21"),1,0) -> 0 | S27: =J27 -> 0.39552239 | T27: =M27 -> 7.4048876 | U27: =N27 -> -0.14120603 | V27: =O27 -> 0.32542579 | W27: =R27 -> 0
A28: Indo Count Industries | B28: FY18-19 | C28: ='Raw Data'!D31 -> 1813 | D28: ='Raw Data'!E31 -> 151 | E28: ='Raw Data'!F31 -> 59 | F28: ='Raw Data'!G31+'Raw Data'!H31 -> 960 | G28: ='Raw Data'!I31 -> 309 | H28: ='Raw Data'!J31 -> 1552 | I28: ='Raw Data'!K31 -> 560 | J28: =G28/F28 -> 0.321875 | K28: =E28/F28 -> 0.061458333 | L28: =E28/H28 -> 0.038015464 | M28: =LN(H28) -> 7.3472997 | N28: =(C28-'Raw Data'!D30)/'Raw Data'!D30 -> 0.060854301 | O28: =I28/H28 -> 0.36082474 | P28: ='Raw Data'!L31 -> 3 | Q28: ='Raw Data'!M31/'Raw Data'!N31 -> 3.2508834 | R28: =IF(OR(B28="FY19-20",B28="FY20-21"),1,0) -> 0 | S28: =J28 -> 0.321875 | T28: =M28 -> 7.3472997 | U28: =N28 -> 0.060854301 | V28: =O28 -> 0.36082474 | W28: =R28 -> 0
A29: Indo Count Industries | B29: FY19-20 | C29: ='Raw Data'!D32 -> 1965 | D29: ='Raw Data'!E32 -> 178 | E29: ='Raw Data'!F32 -> 74 | F29: ='Raw Data'!G32+'Raw Data'!H32 -> 972 | G29: ='Raw Data'!I32 -> 348 | H29: ='Raw Data'!J32 -> 1659 | I29: ='Raw Data'!K32 -> 553 | J29: =G29/F29 -> 0.35802469 | K29: =E29/F29 -> 0.076131687 | L29: =E29/H29 -> 0.044605184 | M29: =LN(H29) -> 7.4139703 | N29: =(C29-'Raw Data'!D31)/'Raw Data'!D31 -> 0.083838941 | O29: =I29/H29 -> 0.33333333 | P29: ='Raw Data'!L32 -> 3.74 | Q29: ='Raw Data'!M32/'Raw Data'!N32 -> 3.1982249 | R29: =IF(OR(B29="FY19-20",B29="FY20-21"),1,0) -> 1 | S29: =J29 -> 0.35802469 | T29: =M29 -> 7.4139703 | U29: =N29 -> 0.083838941 | V29: =O29 -> 0.33333333 | W29: =R29 -> 1
A30: Indo Count Industries | B30: FY20-21 | C30: ='Raw Data'!D33 -> 2515 | D30: ='Raw Data'!E33 -> 384 | E30: ='Raw Data'!F33 -> 260 | F30: ='Raw Data'!G33+'Raw Data'!H33 -> 1274 | G30: ='Raw Data'!I33 -> 546 | H30: ='Raw Data'!J33 -> 2247 | I30: ='Raw Data'!K33 -> 543 | J30: =G30/F30 -> 0.42857143 | K30: =E30/F30 -> 0.20408163 | L30: =E30/H30 -> 0.11570984 | M30: =LN(H30) -> 7.7173513 | N30: =(C30-'Raw Data'!D32)/'Raw Data'!D32 -> 0.27989822 | O30: =I30/H30 -> 0.24165554 | P30: ='Raw Data'!L33 -> 13.18 | Q30: ='Raw Data'!M33/'Raw Data'!N33 -> 3.5492958 | R30: =IF(OR(B30="FY19-20",B30="FY20-21"),1,0) -> 1 | S30: =J30 -> 0.42857143 | T30: =M30 -> 7.7173513 | U30: =N30 -> 0.27989822 | V30: =O30 -> 0.24165554 | W30: =R30 -> 1
A31: Indo Count Industries | B31: FY21-22 | C31: ='Raw Data'!D34 -> 2806 | D31: ='Raw Data'!E34 -> 402 | E31: ='Raw Data'!F34 -> 339 | F31: ='Raw Data'!G34+'Raw Data'!H34 -> 1576 | G31: ='Raw Data'!I34 -> 1214 | H31: ='Raw Data'!J34 -> 3090 | I31: ='Raw Data'!K34 -> 650 | J31: =G31/F31 -> 0.77030457 | K31: =E31/F31 -> 0.21510152 | L31: =E31/H31 -> 0.10970874 | M31: =LN(H31) -> 8.0359264 | N31: =(C31-'Raw Data'!D33)/'Raw Data'!D33 -> 0.11570577 | O31: =I31/H31 -> 0.21035599 | P31: ='Raw Data'!L34 -> 17.16 | Q31: ='Raw Data'!M34/'Raw Data'!N34 -> 8.0933333 | R31: =IF(OR(B31="FY19-20",B31="FY20-21"),1,0) -> 0 | S31: =J31 -> 0.77030457 | T31: =M31 -> 8.0359264 | U31: =N31 -> 0.11570577 | V31: =O31 -> 0.21035599 | W31: =R31 -> 0
A32: Indo Count Industries | B32: FY22-23 | C32: ='Raw Data'!D35 -> 2784 | D32: ='Raw Data'!E35 -> 411 | E32: ='Raw Data'!F35 -> 238 | F32: ='Raw Data'!G35+'Raw Data'!H35 -> 1765 | G32: ='Raw Data'!I35 -> 853 | H32: ='Raw Data'!J35 -> 2983 | I32: ='Raw Data'!K35 -> 1243 | J32: =G32/F32 -> 0.48328612 | K32: =E32/F32 -> 0.13484419 | L32: =E32/H32 -> 0.079785451 | M32: =LN(H32) -> 8.0006848 | N32: =(C32-'Raw Data'!D34)/'Raw Data'!D34 -> -0.0078403421 | O32: =I32/H32 -> 0.4166946 | P32: ='Raw Data'!L35 -> 12.03 | Q32: ='Raw Data'!M35/'Raw Data'!N35 -> 4.3424658 | R32: =IF(OR(B32="FY19-20",B32="FY20-21"),1,0) -> 0 | S32: =J32 -> 0.48328612 | T32: =M32 -> 8.0006848 | U32: =N32 -> -0.0078403421 | V32: =O32 -> 0.4166946 | W32: =R32 -> 0
A33: Indo Count Industries | B33: FY23-24 | C33: ='Raw Data'!D36 -> 3332 | D33: ='Raw Data'!E36 -> 526 | E33: ='Raw Data'!F36 -> 320 | F33: ='Raw Data'!G36+'Raw Data'!H36 -> 2048 | G33: ='Raw Data'!I36 -> 936 | H33: ='Raw Data'!J36 -> 3493 | I33: ='Raw Data'!K36 -> 1344 | J33: =G33/F33 -> 0.45703125 | K33: =E33/F33 -> 0.15625 | L33: =E33/H33 -> 0.091611795 | M33: =LN(H33) -> 8.1585162 | N33: =(C33-'Raw Data'!D35)/'Raw Data'!D35 -> 0.19683908 | O33: =I33/H33 -> 0.38476954 | P33: ='Raw Data'!L36 -> 16.17 | Q33: ='Raw Data'!M36/'Raw Data'!N36 -> 3.9352941 | R33: =IF(OR(B33="FY19-20",B33="FY20-21"),1,0) -> 0 | S33: =J33 -> 0.45703125 | T33: =M33 -> 8.1585162 | U33: =N33 -> 0.19683908 | V33: =O33 -> 0.38476954 | W33: =R33 -> 0
A34: Indo Count Industries | B34: FY24-25 | C34: ='Raw Data'!D37 -> 3772 | D34: ='Raw Data'!E37 -> 465 | E34: ='Raw Data'!F37 -> 237 | F34: ='Raw Data'!G37+'Raw Data'!H37 -> 2237 | G34: ='Raw Data'!I37 -> 1061 | H34: ='Raw Data'!J37 -> 3695 | I34: ='Raw Data'!K37 -> 1381 | J34: =G34/F34 -> 0.47429593 | K34: =E34/F34 -> 0.10594546 | L34: =E34/H34 -> 0.064140731 | M34: =LN(H34) -> 8.2147358 | N34: =(C34-'Raw Data'!D36)/'Raw Data'!D36 -> 0.13205282 | O34: =I34/H34 -> 0.37374831 | P34: ='Raw Data'!L37 -> 11.98 | Q34: ='Raw Data'!M37/'Raw Data'!N37 -> 5.3341709 | R34: =IF(OR(B34="FY19-20",B34="FY20-21"),1,0) -> 0 | S34: =J34 -> 0.47429593 | T34: =M34 -> 8.2147358 | U34: =N34 -> 0.13205282 | V34: =O34 -> 0.37374831 | W34: =R34 -> 0
A35: Vardhman Textiles | B35: FY15-16 | C35: ='Raw Data'!D39 -> 5602 | D35: ='Raw Data'!E39 -> 1108 | E35: ='Raw Data'!F39 -> 676 | F35: ='Raw Data'!G39+'Raw Data'!H39 -> 3690 | G35: ='Raw Data'!I39 -> 2596 | H35: ='Raw Data'!J39 -> 6985 | I35: ='Raw Data'!K39 -> 2585 | J35: =G35/F35 -> 0.70352304 | K35: =E35/F35 -> 0.18319783 | L35: =E35/H35 -> 0.096778812 | M35: =LN(H35) -> 8.8515203 | N35: =(C35-'Raw Data'!D38)/'Raw Data'!D38 -> -0.022338569 | O35: =I35/H35 -> 0.37007874 | P35: ='Raw Data'!L39 -> 21.25 | Q35: ='Raw Data'!M39/'Raw Data'!N39 -> 4.7571429 | R35: =IF(OR(B35="FY19-20",B35="FY20-21"),1,0) -> 0 | S35: =J35 -> 0.70352304 | T35: =M35 -> 8.8515203 | U35: =N35 -> -0.022338569 | V35: =O35 -> 0.37007874 | W35: =R35 -> 0
A36: Vardhman Textiles | B36: FY16-17 | C36: ='Raw Data'!D40 -> 5691 | D36: ='Raw Data'!E40 -> 1131 | E36: ='Raw Data'!F40 -> 1002 | F36: ='Raw Data'!G40+'Raw Data'!H40 -> 3986 | G36: ='Raw Data'!I40 -> 2198 | H36: ='Raw Data'!J40 -> 6959 | I36: ='Raw Data'!K40 -> 2507 | J36: =G36/F36 -> 0.55143001 | K36: =E36/F36 -> 0.25137983 | L36: =E36/H36 -> 0.1439862 | M36: =LN(H36) -> 8.8477911 | N36: =(C36-'Raw Data'!D39)/'Raw Data'!D39 -> 0.015887183 | O36: =I36/H36 -> 0.36025291 | P36: ='Raw Data'!L40 -> 34.87 | Q36: ='Raw Data'!M40/'Raw Data'!N40 -> 3.6245161 | R36: =IF(OR(B36="FY19-20",B36="FY20-21"),1,0) -> 0 | S36: =J36 -> 0.55143001 | T36: =M36 -> 8.8477911 | U36: =N36 -> 0.015887183 | V36: =O36 -> 0.36025291 | W36: =R36 -> 0
A37: Vardhman Textiles | B37: FY17-18 | C37: ='Raw Data'!D41 -> 5851 | D37: ='Raw Data'!E41 -> 859 | E37: ='Raw Data'!F41 -> 546 | F37: ='Raw Data'!G41+'Raw Data'!H41 -> 4632 | G37: ='Raw Data'!I41 -> 2282 | H37: ='Raw Data'!J41 -> 7696 | I37: ='Raw Data'!K41 -> 2612 | J37: =G37/F37 -> 0.49265976 | K37: =E37/F37 -> 0.11787565 | L37: =E37/H37 -> 0.070945946 | M37: =LN(H37) -> 8.948456 | N37: =(C37-'Raw Data'!D40)/'Raw Data'!D40 -> 0.028114567 | O37: =I37/H37 -> 0.33939709 | P37: ='Raw Data'!L41 -> 19 | Q37: ='Raw Data'!M41/'Raw Data'!N41 -> 4.4654731 | R37: =IF(OR(B37="FY19-20",B37="FY20-21"),1,0) -> 0 | S37: =J37 -> 0.49265976 | T37: =M37 -> 8.948456 | U37: =N37 -> 0.028114567 | V37: =O37 -> 0.33939709 | W37: =R37 -> 0
A38: Vardhman Textiles | B38: FY18-19 | C38: ='Raw Data'!D42 -> 6415 | D38: ='Raw Data'!E42 -> 1132 | E38: ='Raw Data'!F42 -> 696 | F38: ='Raw Data'!G42+'Raw Data'!H42 -> 5239 | G38: ='Raw Data'!I42 -> 2238 | H38: ='Raw Data'!J42 -> 8369 | I38: ='Raw Data'!K42 -> 3333 | J38: =G38/F38 -> 0.42718076 | K38: =E38/F38 -> 0.13284978 | L38: =E38/H38 -> 0.083164058 | M38: =LN(H38) -> 9.0322897 | N38: =(C38-'Raw Data'!D41)/'Raw Data'!D41 -> 0.096393779 | O38: =I38/H38 -> 0.39825547 | P38: ='Raw Data'!L42 -> 24.21 | Q38: ='Raw Data'!M42/'Raw Data'!N42 -> 4.4282511 | R38: =IF(OR(B38="FY19-20",B38="FY20-21"),1,0) -> 0 | S38: =J38 -> 0.42718076 | T38: =M38 -> 9.0322897 | U38: =N38 -> 0.096393779 | V38: =O38 -> 0.39825547 | W38: =R38 -> 0
A39: Vardhman Textiles | B39: FY19-20 | C39: ='Raw Data'!D43 -> 6325 | D39: ='Raw Data'!E43 -> 883 | E39: ='Raw Data'!F43 -> 545 | F39: ='Raw Data'!G43+'Raw Data'!H43 -> 5667 | G39: ='Raw Data'!I43 -> 2197 | H39: ='Raw Data'!J43 -> 8727 | I39: ='Raw Data'!K43 -> 3620 | J39: =G39/F39 -> 0.38768308 | K39: =E39/F39 -> 0.096170813 | L39: =E39/H39 -> 0.062449868 | M39: =LN(H39) -> 9.0741769 | N39: =(C39-'Raw Data'!D42)/'Raw Data'!D42 -> -0.014029618 | O39: =I39/H39 -> 0.41480463 | P39: ='Raw Data'!L43 -> 18.97 | Q39: ='Raw Data'!M43/'Raw Data'!N43 -> 4.7164352 | R39: =IF(OR(B39="FY19-20",B39="FY20-21"),1,0) -> 1 | S39: =J39 -> 0.38768308 | T39: =M39 -> 9.0741769 | U39: =N39 -> -0.014029618 | V39: =O39 -> 0.41480463 | W39: =R39 -> 1
A40: Vardhman Textiles | B40: FY20-21 | C40: ='Raw Data'!D44 -> 5926 | D40: ='Raw Data'!E44 -> 767 | E40: ='Raw Data'!F44 -> 367 | F40: ='Raw Data'!G44+'Raw Data'!H44 -> 6139 | G40: ='Raw Data'!I44 -> 2132 | H40: ='Raw Data'!J44 -> 9064 | I40: ='Raw Data'!K44 -> 3546 | J40: =G40/F40 -> 0.34728783 | K40: =E40/F40 -> 0.059781723 | L40: =E40/H40 -> 0.04048985 | M40: =LN(H40) -> 9.1120658 | N40: =(C40-'Raw Data'!D43)/'Raw Data'!D43 -> -0.063083004 | O40: =I40/H40 -> 0.39121801 | P40: ='Raw Data'!L44 -> 12.74 | Q40: ='Raw Data'!M44/'Raw Data'!N44 -> 5.9331652 | R40: =IF(OR(B40="FY19-20",B40="FY20-21"),1,0) -> 1 | S40: =J40 -> 0.34728783 | T40: =M40 -> 9.1120658 | U40: =N40 -> -0.063083004 | V40: =O40 -> 0.39121801 | W40: =R40 -> 1
A41: Vardhman Textiles | B41: FY21-22 | C41: ='Raw Data'!D45 -> 9386 | D41: ='Raw Data'!E45 -> 2262 | E41: ='Raw Data'!F45 -> 1677 | F41: ='Raw Data'!G45+'Raw Data'!H45 -> 7539 | G41: ='Raw Data'!I45 -> 1980 | H41: ='Raw Data'!J45 -> 10576 | I41: ='Raw Data'!K45 -> 3677 | J41: =G41/F41 -> 0.2626343 | K41: =E41/F41 -> 0.22244329 | L41: =E41/H41 -> 0.15856657 | M41: =LN(H41) -> 9.2663426 | N41: =(C41-'Raw Data'!D44)/'Raw Data'!D44 -> 0.5838677 | O41: =I41/H41 -> 0.34767398 | P41: ='Raw Data'!L45 -> 58.07 | Q41: ='Raw Data'!M45/'Raw Data'!N45 -> 5.1524621 | R41: =IF(OR(B41="FY19-20",B41="FY20-21"),1,0) -> 0 | S41: =J41 -> 0.2626343 | T41: =M41 -> 9.2663426 | U41: =N41 -> 0.5838677 | V41: =O41 -> 0.34767398 | W41: =R41 -> 0
A42: Vardhman Textiles | B42: FY22-23 | C42: ='Raw Data'!D46 -> 9841 | D42: ='Raw Data'!E46 -> 1285 | E42: ='Raw Data'!F46 -> 749 | F42: ='Raw Data'!G46+'Raw Data'!H46 -> 8294 | G42: ='Raw Data'!I46 -> 1677 | H42: ='Raw Data'!J46 -> 10861 | I42: ='Raw Data'!K46 -> 3927 | J42: =G42/F42 -> 0.20219436 | K42: =E42/F42 -> 0.090306245 | L42: =E42/H42 -> 0.068962342 | M42: =LN(H42) -> 9.2929337 | N42: =(C42-'Raw Data'!D45)/'Raw Data'!D45 -> 0.048476454 | O42: =I42/H42 -> 0.36156892 | P42: ='Raw Data'!L46 -> 25.91 | Q42: ='Raw Data'!M46/'Raw Data'!N46 -> 5.2662921 | R42: =IF(OR(B42="FY19-20",B42="FY20-21"),1,0) -> 0 | S42: =J42 -> 0.20219436 | T42: =M42 -> 9.2929337 | U42: =N42 -> 0.048476454 | V42: =O42 -> 0.36156892 | W42: =R42 -> 0
A43: Vardhman Textiles | B43: FY23-24 | C43: ='Raw Data'!D47 -> 9299 | D43: ='Raw Data'!E47 -> 958 | E43: ='Raw Data'!F47 -> 608 | F43: ='Raw Data'!G47+'Raw Data'!H47 -> 8805 | G43: ='Raw Data'!I47 -> 1790 | H43: ='Raw Data'!J47 -> 11487 | I43: ='Raw Data'!K47 -> 3772 | J43: =G43/F43 -> 0.20329358 | K43: =E43/F43 -> 0.069051675 | L43: =E43/H43 -> 0.052929398 | M43: =LN(H43) -> 9.3489712 | N43: =(C43-'Raw Data'!D46)/'Raw Data'!D46 -> -0.055075704 | O43: =I43/H43 -> 0.3283712 | P43: ='Raw Data'!L47 -> 21.01 | Q43: ='Raw Data'!M47/'Raw Data'!N47 -> 7.1301908 | R43: =IF(OR(B43="FY19-20",B43="FY20-21"),1,0) -> 0 | S43: =J43 -> 0.20329358 | T43: =M43 -> 9.3489712 | U43: =N43 -> -0.055075704 | V43: =O43 -> 0.3283712 | W43: =R43 -> 0
A44: Vardhman Textiles | B44: FY24-25 | C44: ='Raw Data'!D48 -> 9587 | D44: ='Raw Data'!E48 -> 1257 | E44: ='Raw Data'!F48 -> 879 | F44: ='Raw Data'!G48+'Raw Data'!H48 -> 9578 | G44: ='Raw Data'!I48 -> 1238 | H44: ='Raw Data'!J48 -> 11900 | I44: ='Raw Data'!K48 -> 4342 | J44: =G44/F44 -> 0.12925454 | K44: =E44/F44 -> 0.091772813 | L44: =E44/H44 -> 0.073865546 | M44: =LN(H44) -> 9.3842937 | N44: =(C44-'Raw Data'!D47)/'Raw Data'!D47 -> 0.030971072 | O44: =I44/H44 -> 0.36487395 | P44: ='Raw Data'!L48 -> 30.4 | Q44: ='Raw Data'!M48/'Raw Data'!N48 -> 5.6097786 | R44: =IF(OR(B44="FY19-20",B44="FY20-21"),1,0) -> 0 | S44: =J44 -> 0.12925454 | T44: =M44 -> 9.3842937 | U44: =N44 -> 0.030971072 | V44: =O44 -> 0.36487395 | W44: =R44 -> 0
A45: Trident | B45: FY15-16 | C45: ='Raw Data'!D50 -> 3665 | D45: ='Raw Data'!E50 -> 730 | E45: ='Raw Data'!F50 -> 242 | F45: ='Raw Data'!G50+'Raw Data'!H50 -> 2415 | G45: ='Raw Data'!I50 -> 3503 | H45: ='Raw Data'!J50 -> 6506 | I45: ='Raw Data'!K50 -> 4755 | J45: =G45/F45 -> 1.4505176 | K45: =E45/F45 -> 0.10020704 | L45: =E45/H45 -> 0.037196434 | M45: =LN(H45) -> 8.7804801 | N45: =(C45-'Raw Data'!D49)/'Raw Data'!D49 -> -0.018741633 | O45: =I45/H45 -> 0.73086382 | P45: ='Raw Data'!L50 -> 0.48 | Q45: ='Raw Data'!M50/'Raw Data'!N50 -> 2.8894558 | R45: =IF(OR(B45="FY19-20",B45="FY20-21"),1,0) -> 0 | S45: =J45 -> 1.4505176 | T45: =M45 -> 8.7804801 | U45: =N45 -> -0.018741633 | V45: =O45 -> 0.73086382 | W45: =R45 -> 0
A46: Trident | B46: FY16-17 | C46: ='Raw Data'!D51 -> 4617 | D46: ='Raw Data'!E51 -> 886 | E46: ='Raw Data'!F51 -> 337 | F46: ='Raw Data'!G51+'Raw Data'!H51 -> 2725 | G46: ='Raw Data'!I51 -> 2849 | H46: ='Raw Data'!J51 -> 6150 | I46: ='Raw Data'!K51 -> 4467 | J46: =G46/F46 -> 1.0455046 | K46: =E46/F46 -> 0.12366972 | L46: =E46/H46 -> 0.054796748 | M46: =LN(H46) -> 8.7242074 | N46: =(C46-'Raw Data'!D50)/'Raw Data'!D50 -> 0.25975443 | O46: =I46/H46 -> 0.72634146 | P46: ='Raw Data'!L51 -> 0.66 | Q46: ='Raw Data'!M51/'Raw Data'!N51 -> 2.7916667 | R46: =IF(OR(B46="FY19-20",B46="FY20-21"),1,0) -> 0 | S46: =J46 -> 1.0455046 | T46: =M46 -> 8.7242074 | U46: =N46 -> 0.25975443 | V46: =O46 -> 0.72634146 | W46: =R46 -> 0
A47: Trident | B47: FY17-18 | C47: ='Raw Data'!D52 -> 4566 | D47: ='Raw Data'!E52 -> 852 | E47: ='Raw Data'!F52 -> 266 | F47: ='Raw Data'!G52+'Raw Data'!H52 -> 2694 | G47: ='Raw Data'!I52 -> 2798 | H47: ='Raw Data'!J52 -> 6129 | I47: ='Raw Data'!K52 -> 4079 | J47: =G47/F47 -> 1.0386043 | K47: =E47/F47 -> 0.098737936 | L47: =E47/H47 -> 0.043400228 | M47: =LN(H47) -> 8.7207869 | N47: =(C47-'Raw Data'!D51)/'Raw Data'!D51 -> -0.011046134 | O47: =I47/H47 -> 0.66552456 | P47: ='Raw Data'!L52 -> 0.52 | Q47: ='Raw Data'!M52/'Raw Data'!N52 -> 3.0830721 | R47: =IF(OR(B47="FY19-20",B47="FY20-21"),1,0) -> 0 | S47: =J47 -> 1.0386043 | T47: =M47 -> 8.7207869 | U47: =N47 -> -0.011046134 | V47: =O47 -> 0.66552456 | W47: =R47 -> 0
A48: Trident | B48: FY18-19 | C48: ='Raw Data'!D53 -> 5220 | D48: ='Raw Data'!E53 -> 977 | E48: ='Raw Data'!F53 -> 371 | F48: ='Raw Data'!G53+'Raw Data'!H53 -> 2932 | G48: ='Raw Data'!I53 -> 2436 | H48: ='Raw Data'!J53 -> 6103 | I48: ='Raw Data'!K53 -> 3848 | J48: =G48/F48 -> 0.8308322 | K48: =E48/F48 -> 0.12653479 | L48: =E48/H48 -> 0.060789776 | M48: =LN(H48) -> 8.7165357 | N48: =(C48-'Raw Data'!D52)/'Raw Data'!D52 -> 0.14323259 | O48: =I48/H48 -> 0.63050959 | P48: ='Raw Data'!L53 -> 0.73 | Q48: ='Raw Data'!M53/'Raw Data'!N53 -> 2.8464674 | R48: =IF(OR(B48="FY19-20",B48="FY20-21"),1,0) -> 0 | S48: =J48 -> 0.8308322 | T48: =M48 -> 8.7165357 | U48: =N48 -> 0.14323259 | V48: =O48 -> 0.63050959 | W48: =R48 -> 0
A49: Trident | B49: FY19-20 | C49: ='Raw Data'!D54 -> 4699 | D49: ='Raw Data'!E54 -> 841 | E49: ='Raw Data'!F54 -> 342 | F49: ='Raw Data'!G54+'Raw Data'!H54 -> 2967 | G49: ='Raw Data'!I54 -> 1991 | H49: ='Raw Data'!J54 -> 5718 | I49: ='Raw Data'!K54 -> 3826 | J49: =G49/F49 -> 0.6710482 | K49: =E49/F49 -> 0.11526795 | L49: =E49/H49 -> 0.059811123 | M49: =LN(H49) -> 8.6513744 | N49: =(C49-'Raw Data'!D53)/'Raw Data'!D53 -> -0.099808429 | O49: =I49/H49 -> 0.66911508 | P49: ='Raw Data'!L54 -> 0.67 | Q49: ='Raw Data'!M54/'Raw Data'!N54 -> 2.3823916 | R49: =IF(OR(B49="FY19-20",B49="FY20-21"),1,0) -> 1 | S49: =J49 -> 0.6710482 | T49: =M49 -> 8.6513744 | U49: =N49 -> -0.099808429 | V49: =O49 -> 0.66911508 | W49: =R49 -> 1
A50: Trident | B50: FY20-21 | C50: ='Raw Data'!D55 -> 4519 | D50: ='Raw Data'!E55 -> 814 | E50: ='Raw Data'!F55 -> 346 | F50: ='Raw Data'!G55+'Raw Data'!H55 -> 3317 | G50: ='Raw Data'!I55 -> 1562 | H50: ='Raw Data'!J55 -> 5754 | I50: ='Raw Data'!K55 -> 3854 | J50: =G50/F50 -> 0.47090745 | K50: =E50/F50 -> 0.10431112 | L50: =E50/H50 -> 0.060132082 | M50: =LN(H50) -> 8.6576505 | N50: =(C50-'Raw Data'!D54)/'Raw Data'!D54 -> -0.038306023 | O50: =I50/H50 -> 0.66979493 | P50: ='Raw Data'!L55 -> 0.68 | Q50: ='Raw Data'!M55/'Raw Data'!N55 -> 2.1643836 | R50: =IF(OR(B50="FY19-20",B50="FY20-21"),1,0) -> 1 | S50: =J50 -> 0.47090745 | T50: =M50 -> 8.6576505 | U50: =N50 -> -0.038306023 | V50: =O50 -> 0.66979493 | W50: =R50 -> 1
A51: Trident | B51: FY21-22 | C51: ='Raw Data'!D56 -> 6919 | D51: ='Raw Data'!E56 -> 1495 | E51: ='Raw Data'!F56 -> 815 | F51: ='Raw Data'!G56+'Raw Data'!H56 -> 3798 | G51: ='Raw Data'!I56 -> 1596 | H51: ='Raw Data'!J56 -> 6431 | I51: ='Raw Data'!K56 -> 3795 | J51: =G51/F51 -> 0.42022117 | K51: =E51/F51 -> 0.21458662 | L51: =E51/H51 -> 0.1267299 | M51: =LN(H51) -> 8.7688853 | N51: =(C51-'Raw Data'!D55)/'Raw Data'!D55 -> 0.53109095 | O51: =I51/H51 -> 0.5901104 | P51: ='Raw Data'!L56 -> 1.6 | Q51: ='Raw Data'!M56/'Raw Data'!N56 -> 2.5380906 | R51: =IF(OR(B51="FY19-20",B51="FY20-21"),1,0) -> 0 | S51: =J51 -> 0.42022117 | T51: =M51 -> 8.7688853 | U51: =N51 -> 0.53109095 | V51: =O51 -> 0.5901104 | W51: =R51 -> 0
A52: Trident | B52: FY22-23 | C52: ='Raw Data'!D57 -> 6267 | D52: ='Raw Data'!E57 -> 918 | E52: ='Raw Data'!F57 -> 422 | F52: ='Raw Data'!G57+'Raw Data'!H57 -> 4126 | G52: ='Raw Data'!I57 -> 1404 | H52: ='Raw Data'!J57 -> 6713 | I52: ='Raw Data'!K57 -> 4422 | J52: =G52/F52 -> 0.34028114 | K52: =E52/F52 -> 0.10227824 | L52: =E52/H52 -> 0.062863101 | M52: =LN(H52) -> 8.8118012 | N52: =(C52-'Raw Data'!D56)/'Raw Data'!D56 -> -0.094233271 | O52: =I52/H52 -> 0.65872188 | P52: ='Raw Data'!L57 -> 0.83 | Q52: ='Raw Data'!M57/'Raw Data'!N57 -> 1.9324324 | R52: =IF(OR(B52="FY19-20",B52="FY20-21"),1,0) -> 0 | S52: =J52 -> 0.34028114 | T52: =M52 -> 8.8118012 | U52: =N52 -> -0.094233271 | V52: =O52 -> 0.65872188 | W52: =R52 -> 0
A53: Trident | B53: FY23-24 | C53: ='Raw Data'!D58 -> 6730 | D53: ='Raw Data'!E58 -> 935 | E53: ='Raw Data'!F58 -> 390 | F53: ='Raw Data'!G58+'Raw Data'!H58 -> 4310 | G53: ='Raw Data'!I58 -> 2094 | H53: ='Raw Data'!J58 -> 7522 | I53: ='Raw Data'!K58 -> 4663 | J53: =G53/F53 -> 0.48584687 | K53: =E53/F53 -> 0.090487239 | L53: =E53/H53 -> 0.051847913 | M53: =LN(H53) -> 8.9255873 | N53: =(C53-'Raw Data'!D57)/'Raw Data'!D57 -> 0.073879049 | O53: =I53/H53 -> 0.61991492 | P53: ='Raw Data'!L58 -> 0.76 | Q53: ='Raw Data'!M58/'Raw Data'!N58 -> 2.5093834 | R53: =IF(OR(B53="FY19-20",B53="FY20-21"),1,0) -> 0 | S53: =J53 -> 0.48584687 | T53: =M53 -> 8.9255873 | U53: =N53 -> 0.073879049 | V53: =O53 -> 0.61991492 | W53: =R53 -> 0
A54: Trident | B54: FY24-25 | C54: ='Raw Data'!D59 -> 6966 | D54: ='Raw Data'!E59 -> 886 | E54: ='Raw Data'!F59 -> 367 | F54: ='Raw Data'!G59+'Raw Data'!H59 -> 4611 | G54: ='Raw Data'!I59 -> 1606 | H54: ='Raw Data'!J59 -> 7129 | I54: ='Raw Data'!K59 -> 4478 | J54: =G54/F54 -> 0.34829755 | K54: =E54/F54 -> 0.079592279 | L54: =E54/H54 -> 0.051479871 | M54: =LN(H54) -> 8.8719263 | N54: =(C54-'Raw Data'!D58)/'Raw Data'!D58 -> 0.035066865 | O54: =I54/H54 -> 0.62813859 | P54: ='Raw Data'!L59 -> 0.72 | Q54: ='Raw Data'!M59/'Raw Data'!N59 -> 2.8817087 | R54: =IF(OR(B54="FY19-20",B54="FY20-21"),1,0) -> 0 | S54: =J54 -> 0.34829755 | T54: =M54 -> 8.8719263 | U54: =N54 -> 0.035066865 | V54: =O54 -> 0.62813859 | W54: =R54 -> 0
A55: Arvind | B55: FY15-16 | C55: ='Raw Data'!D61 -> 5357 | D55: ='Raw Data'!E61 -> 808 | E55: ='Raw Data'!F61 -> 321 | F55: ='Raw Data'!G61+'Raw Data'!H61 -> 2986 | G55: ='Raw Data'!I61 -> 3123 | H55: ='Raw Data'!J61 -> 6990 | I55: ='Raw Data'!K61 -> 2928 | J55: =G55/F55 -> 1.0458808 | K55: =E55/F55 -> 0.10750167 | L55: =E55/H55 -> 0.045922747 | M55: =LN(H55) -> 8.8522358 | N55: =(C55-'Raw Data'!D60)/'Raw Data'!D60 -> 0.025263158 | O55: =I55/H55 -> 0.41888412 | P55: ='Raw Data'!L61 -> 12.42 | Q55: ='Raw Data'!M61/'Raw Data'!N61 -> 3.1772727 | R55: =IF(OR(B55="FY19-20",B55="FY20-21"),1,0) -> 0 | S55: =J55 -> 1.0458808 | T55: =M55 -> 8.8522358 | U55: =N55 -> 0.025263158 | V55: =O55 -> 0.41888412 | W55: =R55 -> 0
A56: Arvind | B56: FY16-17 | C56: ='Raw Data'!D62 -> 5967 | D56: ='Raw Data'!E62 -> 732 | E56: ='Raw Data'!F62 -> 19 | F56: ='Raw Data'!G62+'Raw Data'!H62 -> 3011 | G56: ='Raw Data'!I62 -> 2428 | H56: ='Raw Data'!J62 -> 6458 | I56: ='Raw Data'!K62 -> 3177 | J56: =G56/F56 -> 0.80637662 | K56: =E56/F56 -> 0.0063101959 | L56: =E56/H56 -> 0.0029420873 | M56: =LN(H56) -> 8.773075 | N56: =(C56-'Raw Data'!D61)/'Raw Data'!D61 -> 0.1138697 | O56: =I56/H56 -> 0.49194797 | P56: ='Raw Data'!L62 -> 0.72 | Q56: ='Raw Data'!M62/'Raw Data'!N62 -> 2.7102161 | R56: =IF(OR(B56="FY19-20",B56="FY20-21"),1,0) -> 0 | S56: =J56 -> 0.80637662 | T56: =M56 -> 8.773075 | U56: =N56 -> 0.1138697 | V56: =O56 -> 0.49194797 | W56: =R56 -> 0
A57: Arvind | B57: FY17-18 | C57: ='Raw Data'!D63 -> 6332 | D57: ='Raw Data'!E63 -> 639 | E57: ='Raw Data'!F63 -> 250 | F57: ='Raw Data'!G63+'Raw Data'!H63 -> 3159 | G57: ='Raw Data'!I63 -> 2562 | H57: ='Raw Data'!J63 -> 7044 | I57: ='Raw Data'!K63 -> 3208 | J57: =G57/F57 -> 0.81101614 | K57: =E57/F57 -> 0.079138968 | L57: =E57/H57 -> 0.035491198 | M57: =LN(H57) -> 8.8599315 | N57: =(C57-'Raw Data'!D62)/'Raw Data'!D62 -> 0.061169767 | O57: =I57/H57 -> 0.45542306 | P57: ='Raw Data'!L63 -> 9.67 | Q57: ='Raw Data'!M63/'Raw Data'!N63 -> 2.2303625 | R57: =IF(OR(B57="FY19-20",B57="FY20-21"),1,0) -> 0 | S57: =J57 -> 0.81101614 | T57: =M57 -> 8.8599315 | U57: =N57 -> 0.061169767 | V57: =O57 -> 0.45542306 | W57: =R57 -> 0
A58: Arvind | B58: FY18-19 | C58: ='Raw Data'!D64 -> 6436 | D58: ='Raw Data'!E64 -> 633 | E58: ='Raw Data'!F64 -> 199 | F58: ='Raw Data'!G64+'Raw Data'!H64 -> 2817 | G58: ='Raw Data'!I64 -> 2652 | H58: ='Raw Data'!J64 -> 7014 | I58: ='Raw Data'!K64 -> 3362 | J58: =G58/F58 -> 0.94142705 | K58: =E58/F58 -> 0.070642528 | L58: =E58/H58 -> 0.028371828 | M58: =LN(H58) -> 8.8556634 | N58: =(C58-'Raw Data'!D63)/'Raw Data'!D63 -> 0.01642451 | O58: =I58/H58 -> 0.47932706 | P58: ='Raw Data'!L64 -> 7.71 | Q58: ='Raw Data'!M64/'Raw Data'!N64 -> 2.0278137 | R58: =IF(OR(B58="FY19-20",B58="FY20-21"),1,0) -> 0 | S58: =J58 -> 0.94142705 | T58: =M58 -> 8.8556634 | U58: =N58 -> 0.01642451 | V58: =O58 -> 0.47932706 | W58: =R58 -> 0
A59: Arvind | B59: FY19-20 | C59: ='Raw Data'!D65 -> 6705 | D59: ='Raw Data'!E65 -> 708 | E59: ='Raw Data'!F65 -> 171 | F59: ='Raw Data'!G65+'Raw Data'!H65 -> 2854 | G59: ='Raw Data'!I65 -> 2431 | H59: ='Raw Data'!J65 -> 6815 | I59: ='Raw Data'!K65 -> 3532 | J59: =G59/F59 -> 0.85178697 | K59: =E59/F59 -> 0.059915907 | L59: =E59/H59 -> 0.025091709 | M59: =LN(H59) -> 8.8268813 | N59: =(C59-'Raw Data'!D64)/'Raw Data'!D64 -> 0.041796147 | O59: =I59/H59 -> 0.51826853 | P59: ='Raw Data'!L65 -> 6.62 | Q59: ='Raw Data'!M65/'Raw Data'!N65 -> 1.8026144 | R59: =IF(OR(B59="FY19-20",B59="FY20-21"),1,0) -> 1 | S59: =J59 -> 0.85178697 | T59: =M59 -> 8.8268813 | U59: =N59 -> 0.041796147 | V59: =O59 -> 0.51826853 | W59: =R59 -> 1
A60: Arvind | B60: FY20-21 | C60: ='Raw Data'!D66 -> 4529 | D60: ='Raw Data'!E66 -> 477 | E60: ='Raw Data'!F66 -> 93 | F60: ='Raw Data'!G66+'Raw Data'!H66 -> 2941 | G60: ='Raw Data'!I66 -> 1985 | H60: ='Raw Data'!J66 -> 6609 | I60: ='Raw Data'!K66 -> 3332 | J60: =G60/F60 -> 0.6749405 | K60: =E60/F60 -> 0.031621897 | L60: =E60/H60 -> 0.01407172 | M60: =LN(H60) -> 8.7961876 | N60: =(C60-'Raw Data'!D65)/'Raw Data'!D65 -> -0.32453393 | O60: =I60/H60 -> 0.50416099 | P60: ='Raw Data'!L66 -> 3.58 | Q60: ='Raw Data'!M66/'Raw Data'!N66 -> 1.6319857 | R60: =IF(OR(B60="FY19-20",B60="FY20-21"),1,0) -> 1 | S60: =J60 -> 0.6749405 | T60: =M60 -> 8.7961876 | U60: =N60 -> -0.32453393 | V60: =O60 -> 0.50416099 | W60: =R60 -> 1
A61: Arvind | B61: FY21-22 | C61: ='Raw Data'!D67 -> 7436 | D61: ='Raw Data'!E67 -> 790 | E61: ='Raw Data'!F67 -> 59 | F61: ='Raw Data'!G67+'Raw Data'!H67 -> 3012 | G61: ='Raw Data'!I67 -> 1783 | H61: ='Raw Data'!J67 -> 7413 | I61: ='Raw Data'!K67 -> 3268 | J61: =G61/F61 -> 0.59196547 | K61: =E61/F61 -> 0.019588313 | L61: =E61/H61 -> 0.007958991 | M61: =LN(H61) -> 8.9109905 | N61: =(C61-'Raw Data'!D66)/'Raw Data'!D66 -> 0.64186355 | O61: =I61/H61 -> 0.44084716 | P61: ='Raw Data'!L67 -> 2.28 | Q61: ='Raw Data'!M67/'Raw Data'!N67 -> 1.410462 | R61: =IF(OR(B61="FY19-20",B61="FY20-21"),1,0) -> 0 | S61: =J61 -> 0.59196547 | T61: =M61 -> 8.9109905 | U61: =N61 -> 0.64186355 | V61: =O61 -> 0.44084716 | W61: =R61 -> 0
A62: Arvind | B62: FY22-23 | C62: ='Raw Data'!D68 -> 7723 | D62: ='Raw Data'!E68 -> 720 | E62: ='Raw Data'!F68 -> 346 | F62: ='Raw Data'!G68+'Raw Data'!H68 -> 3297 | G62: ='Raw Data'!I68 -> 1420 | H62: ='Raw Data'!J68 -> 6398 | I62: ='Raw Data'!K68 -> 3255 | J62: =G62/F62 -> 0.43069457 | K62: =E62/F62 -> 0.10494389 | L62: =E62/H62 -> 0.0540794 | M62: =LN(H62) -> 8.7637407 | N62: =(C62-'Raw Data'!D67)/'Raw Data'!D67 -> 0.038596019 | O62: =I62/H62 -> 0.50875274 | P62: ='Raw Data'!L68 -> 13.23 | Q62: ='Raw Data'!M68/'Raw Data'!N68 -> 1.6395003 | R62: =IF(OR(B62="FY19-20",B62="FY20-21"),1,0) -> 0 | S62: =J62 -> 0.43069457 | T62: =M62 -> 8.7637407 | U62: =N62 -> 0.038596019 | V62: =O62 -> 0.50875274 | W62: =R62 -> 0
A63: Arvind | B63: FY23-24 | C63: ='Raw Data'!D69 -> 7100 | D63: ='Raw Data'!E69 -> 767 | E63: ='Raw Data'!F69 -> 305 | F63: ='Raw Data'!G69+'Raw Data'!H69 -> 3477 | G63: ='Raw Data'!I69 -> 1320 | H63: ='Raw Data'!J69 -> 6729 | I63: ='Raw Data'!K69 -> 3288 | J63: =G63/F63 -> 0.37963762 | K63: =E63/F63 -> 0.087719298 | L63: =E63/H63 -> 0.0453262 | M63: =LN(H63) -> 8.8141818 | N63: =(C63-'Raw Data'!D68)/'Raw Data'!D68 -> -0.080668134 | O63: =I63/H63 -> 0.4886313 | P63: ='Raw Data'!L69 -> 11.65 | Q63: ='Raw Data'!M69/'Raw Data'!N69 -> 1.6035197 | R63: =IF(OR(B63="FY19-20",B63="FY20-21"),1,0) -> 0 | S63: =J63 -> 0.37963762 | T63: =M63 -> 8.8141818 | U63: =N63 -> -0.080668134 | V63: =O63 -> 0.4886313 | W63: =R63 -> 0
A64: Arvind | B64: FY24-25 | C64: ='Raw Data'!D70 -> 6236 | D64: ='Raw Data'!E70 -> 581 | E64: ='Raw Data'!F70 -> 240 | F64: ='Raw Data'!G70+'Raw Data'!H70 -> 3587 | G64: ='Raw Data'!I70 -> 1496 | H64: ='Raw Data'!J70 -> 7324 | I64: ='Raw Data'!K70 -> 3504 | J64: =G64/F64 -> 0.41706161 | K64: =E64/F64 -> 0.06690828 | L64: =E64/H64 -> 0.032768979 | M64: =LN(H64) -> 8.8989119 | N64: =(C64-'Raw Data'!D69)/'Raw Data'!D69 -> -0.12169014 | O64: =I64/H64 -> 0.47842709 | P64: ='Raw Data'!L70 -> 9.18 | Q64: ='Raw Data'!M70/'Raw Data'!N70 -> 1.5046854 | R64: =IF(OR(B64="FY19-20",B64="FY20-21"),1,0) -> 0 | S64: =J64 -> 0.41706161 | T64: =M64 -> 8.8989119 | U64: =N64 -> -0.12169014 | V64: =O64 -> 0.47842709 | W64: =R64 -> 0
A65: Nitin Spinners | B65: FY15-16 | C65: ='Raw Data'!D72 -> 766 | D65: ='Raw Data'!E72 -> 137 | E65: ='Raw Data'!F72 -> 44 | F65: ='Raw Data'!G72+'Raw Data'!H72 -> 206 | G65: ='Raw Data'!I72 -> 352 | H65: ='Raw Data'!J72 -> 635 | I65: ='Raw Data'!K72 -> 399 | J65: =G65/F65 -> 1.7087379 | K65: =E65/F65 -> 0.21359223 | L65: =E65/H65 -> 0.069291339 | M65: =LN(H65) -> 6.453625 | N65: =(C65-'Raw Data'!D71)/'Raw Data'!D71 -> 0.24350649 | O65: =I65/H65 -> 0.62834646 | P65: ='Raw Data'!L72 -> 9.63 | Q65: ='Raw Data'!M72/'Raw Data'!N72 -> 3.0649351 | R65: =IF(OR(B65="FY19-20",B65="FY20-21"),1,0) -> 0 | S65: =J65 -> 1.7087379 | T65: =M65 -> 6.453625 | U65: =N65 -> 0.24350649 | V65: =O65 -> 0.62834646 | W65: =R65 -> 0
A66: Nitin Spinners | B66: FY16-17 | C66: ='Raw Data'!D73 -> 933 | D66: ='Raw Data'!E73 -> 133 | E66: ='Raw Data'!F73 -> 57 | F66: ='Raw Data'!G73+'Raw Data'!H73 -> 264 | G66: ='Raw Data'!I73 -> 568 | H66: ='Raw Data'!J73 -> 885 | I66: ='Raw Data'!K73 -> 613 | J66: =G66/F66 -> 2.1515152 | K66: =E66/F66 -> 0.21590909 | L66: =E66/H66 -> 0.06440678 | M66: =LN(H66) -> 6.7855876 | N66: =(C66-'Raw Data'!D72)/'Raw Data'!D72 -> 0.21801567 | O66: =I66/H66 -> 0.69265537 | P66: ='Raw Data'!L73 -> 12.51 | Q66: ='Raw Data'!M73/'Raw Data'!N73 -> 5.1320755 | R66: =IF(OR(B66="FY19-20",B66="FY20-21"),1,0) -> 0 | S66: =J66 -> 2.1515152 | T66: =M66 -> 6.7855876 | U66: =N66 -> 0.21801567 | V66: =O66 -> 0.69265537 | W66: =R66 -> 0
A67: Nitin Spinners | B67: FY17-18 | C67: ='Raw Data'!D74 -> 1145 | D67: ='Raw Data'!E74 -> 155 | E67: ='Raw Data'!F74 -> 52 | F67: ='Raw Data'!G74+'Raw Data'!H74 -> 417 | G67: ='Raw Data'!I74 -> 449 | H67: ='Raw Data'!J74 -> 929 | I67: ='Raw Data'!K74 -> 574 | J67: =G67/F67 -> 1.0767386 | K67: =E67/F67 -> 0.12470024 | L67: =E67/H67 -> 0.055974166 | M67: =LN(H67) -> 6.8341087 | N67: =(C67-'Raw Data'!D73)/'Raw Data'!D73 -> 0.22722401 | O67: =I67/H67 -> 0.61786868 | P67: ='Raw Data'!L74 -> 9.43 | Q67: ='Raw Data'!M74/'Raw Data'!N74 -> 5.6349206 | R67: =IF(OR(B67="FY19-20",B67="FY20-21"),1,0) -> 0 | S67: =J67 -> 1.0767386 | T67: =M67 -> 6.8341087 | U67: =N67 -> 0.22722401 | V67: =O67 -> 0.61786868 | W67: =R67 -> 0
A68: Nitin Spinners | B68: FY18-19 | C68: ='Raw Data'!D75 -> 1241 | D68: ='Raw Data'!E75 -> 178 | E68: ='Raw Data'!F75 -> 64 | F68: ='Raw Data'!G75+'Raw Data'!H75 -> 482 | G68: ='Raw Data'!I75 -> 860 | H68: ='Raw Data'!J75 -> 1436 | I68: ='Raw Data'!K75 -> 992 | J68: =G68/F68 -> 1.7842324 | K68: =E68/F68 -> 0.13278008 | L68: =E68/H68 -> 0.044568245 | M68: =LN(H68) -> 7.2696167 | N68: =(C68-'Raw Data'!D74)/'Raw Data'!D74 -> 0.083842795 | O68: =I68/H68 -> 0.6908078 | P68: ='Raw Data'!L75 -> 11.4 | Q68: ='Raw Data'!M75/'Raw Data'!N75 -> 4.7849462 | R68: =IF(OR(B68="FY19-20",B68="FY20-21"),1,0) -> 0 | S68: =J68 -> 1.7842324 | T68: =M68 -> 7.2696167 | U68: =N68 -> 0.083842795 | V68: =O68 -> 0.6908078 | W68: =R68 -> 0
A69: Nitin Spinners | B69: FY19-20 | C69: ='Raw Data'!D76 -> 1436 | D69: ='Raw Data'!E76 -> 170 | E69: ='Raw Data'!F76 -> 24 | F69: ='Raw Data'!G76+'Raw Data'!H76 -> 494 | G69: ='Raw Data'!I76 -> 1040 | H69: ='Raw Data'!J76 -> 1645 | I69: ='Raw Data'!K76 -> 1140 | J69: =G69/F69 -> 2.1052632 | K69: =E69/F69 -> 0.048582996 | L69: =E69/H69 -> 0.014589666 | M69: =LN(H69) -> 7.4054957 | N69: =(C69-'Raw Data'!D75)/'Raw Data'!D75 -> 0.15713135 | O69: =I69/H69 -> 0.69300912 | P69: ='Raw Data'!L76 -> 4.24 | Q69: ='Raw Data'!M76/'Raw Data'!N76 -> 4.5585586 | R69: =IF(OR(B69="FY19-20",B69="FY20-21"),1,0) -> 1 | S69: =J69 -> 2.1052632 | T69: =M69 -> 7.4054957 | U69: =N69 -> 0.15713135 | V69: =O69 -> 0.69300912 | W69: =R69 -> 1
A70: Nitin Spinners | B70: FY20-21 | C70: ='Raw Data'!D77 -> 1622 | D70: ='Raw Data'!E77 -> 257 | E70: ='Raw Data'!F77 -> 69 | F70: ='Raw Data'!G77+'Raw Data'!H77 -> 563 | G70: ='Raw Data'!I77 -> 962 | H70: ='Raw Data'!J77 -> 1676 | I70: ='Raw Data'!K77 -> 1062 | J70: =G70/F70 -> 1.7087034 | K70: =E70/F70 -> 0.12255773 | L70: =E70/H70 -> 0.041169451 | M70: =LN(H70) -> 7.4241653 | N70: =(C70-'Raw Data'!D76)/'Raw Data'!D76 -> 0.12952646 | O70: =I70/H70 -> 0.63365155 | P70: ='Raw Data'!L77 -> 12.25 | Q70: ='Raw Data'!M77/'Raw Data'!N77 -> 4.0728477 | R70: =IF(OR(B70="FY19-20",B70="FY20-21"),1,0) -> 1 | S70: =J70 -> 1.7087034 | T70: =M70 -> 7.4241653 | U70: =N70 -> 0.12952646 | V70: =O70 -> 0.63365155 | W70: =R70 -> 1
A71: Nitin Spinners | B71: FY21-22 | C71: ='Raw Data'!D78 -> 2690 | D71: ='Raw Data'!E78 -> 652 | E71: ='Raw Data'!F78 -> 326 | F71: ='Raw Data'!G78+'Raw Data'!H78 -> 876 | G71: ='Raw Data'!I78 -> 689 | H71: ='Raw Data'!J78 -> 1824 | I71: ='Raw Data'!K78 -> 1012 | J71: =G71/F71 -> 0.78652968 | K71: =E71/F71 -> 0.37214612 | L71: =E71/H71 -> 0.17872807 | M71: =LN(H71) -> 7.5087872 | N71: =(C71-'Raw Data'!D77)/'Raw Data'!D77 -> 0.65844636 | O71: =I71/H71 -> 0.55482456 | P71: ='Raw Data'!L78 -> 58.01 | Q71: ='Raw Data'!M78/'Raw Data'!N78 -> 3.1230769 | R71: =IF(OR(B71="FY19-20",B71="FY20-21"),1,0) -> 0 | S71: =J71 -> 0.78652968 | T71: =M71 -> 7.5087872 | U71: =N71 -> 0.65844636 | V71: =O71 -> 0.55482456 | W71: =R71 -> 0
A72: Nitin Spinners | B72: FY22-23 | C72: ='Raw Data'!D79 -> 2404 | D72: ='Raw Data'!E79 -> 297 | E72: ='Raw Data'!F79 -> 165 | F72: ='Raw Data'!G79+'Raw Data'!H79 -> 1029 | G72: ='Raw Data'!I79 -> 980 | H72: ='Raw Data'!J79 -> 2218 | I72: ='Raw Data'!K79 -> 1351 | J72: =G72/F72 -> 0.95238095 | K72: =E72/F72 -> 0.16034985 | L72: =E72/H72 -> 0.074391344 | M72: =LN(H72) -> 7.7043612 | N72: =(C72-'Raw Data'!D78)/'Raw Data'!D78 -> -0.1063197 | O72: =I72/H72 -> 0.6091073 | P72: ='Raw Data'!L79 -> 29.32 | Q72: ='Raw Data'!M79/'Raw Data'!N79 -> 4.1483254 | R72: =IF(OR(B72="FY19-20",B72="FY20-21"),1,0) -> 0 | S72: =J72 -> 0.95238095 | T72: =M72 -> 7.7043612 | U72: =N72 -> -0.1063197 | V72: =O72 -> 0.6091073 | W72: =R72 -> 0
A73: Nitin Spinners | B73: FY23-24 | C73: ='Raw Data'!D80 -> 2902 | D73: ='Raw Data'!E80 -> 377 | E73: ='Raw Data'!F80 -> 132 | F73: ='Raw Data'!G80+'Raw Data'!H80 -> 1146 | G73: ='Raw Data'!I80 -> 1339 | H73: ='Raw Data'!J80 -> 2717 | I73: ='Raw Data'!K80 -> 1711 | J73: =G73/F73 -> 1.1684119 | K73: =E73/F73 -> 0.11518325 | L73: =E73/H73 -> 0.048582996 | M73: =LN(H73) -> 7.9072836 | N73: =(C73-'Raw Data'!D79)/'Raw Data'!D79 -> 0.20715474 | O73: =I73/H73 -> 0.62973868 | P73: ='Raw Data'!L80 -> 23.39 | Q73: ='Raw Data'!M80/'Raw Data'!N80 -> 4.3506494 | R73: =IF(OR(B73="FY19-20",B73="FY20-21"),1,0) -> 0 | S73: =J73 -> 1.1684119 | T73: =M73 -> 7.9072836 | U73: =N73 -> 0.20715474 | V73: =O73 -> 0.62973868 | W73: =R73 -> 0
A74: Nitin Spinners | B74: FY24-25 | C74: ='Raw Data'!D81 -> 3300 | D74: ='Raw Data'!E81 -> 471 | E74: ='Raw Data'!F81 -> 175 | F74: ='Raw Data'!G81+'Raw Data'!H81 -> 1311 | G74: ='Raw Data'!I81 -> 1165 | H74: ='Raw Data'!J81 -> 2732 | I74: ='Raw Data'!K81 -> 1584 | J74: =G74/F74 -> 0.88863463 | K74: =E74/F74 -> 0.13348589 | L74: =E74/H74 -> 0.064055637 | M74: =LN(H74) -> 7.9127892 | N74: =(C74-'Raw Data'!D80)/'Raw Data'!D80 -> 0.1371468 | O74: =I74/H74 -> 0.57979502 | P74: ='Raw Data'!L81 -> 31.2 | Q74: ='Raw Data'!M81/'Raw Data'!N81 -> 4.484375 | R74: =IF(OR(B74="FY19-20",B74="FY20-21"),1,0) -> 0 | S74: =J74 -> 0.88863463 | T74: =M74 -> 7.9127892 | U74: =N74 -> 0.1371468 | V74: =O74 -> 0.57979502 | W74: =R74 -> 0
A75: Sutlej Textiles | B75: FY15-16 | C75: ='Raw Data'!D83 -> 2074 | D75: ='Raw Data'!E83 -> 263 | E75: ='Raw Data'!F83 -> 143 | F75: ='Raw Data'!G83+'Raw Data'!H83 -> 683 | G75: ='Raw Data'!I83 -> 804 | H75: ='Raw Data'!J83 -> 1675 | I75: ='Raw Data'!K83 -> 877 | J75: =G75/F75 -> 1.1771596 | K75: =E75/F75 -> 0.20937042 | L75: =E75/H75 -> 0.085373134 | M75: =LN(H75) -> 7.4235684 | N75: =(C75-'Raw Data'!D82)/'Raw Data'!D82 -> 0.11087306 | O75: =I75/H75 -> 0.52358209 | P75: ='Raw Data'!L83 -> 8.76 | Q75: ='Raw Data'!M83/'Raw Data'!N83 -> 4.106383 | R75: =IF(OR(B75="FY19-20",B75="FY20-21"),1,0) -> 0 | S75: =J75 -> 1.1771596 | T75: =M75 -> 7.4235684 | U75: =N75 -> 0.11087306 | V75: =O75 -> 0.52358209 | W75: =R75 -> 0
A76: Sutlej Textiles | B76: FY16-17 | C76: ='Raw Data'!D84 -> 2249 | D76: ='Raw Data'!E84 -> 282 | E76: ='Raw Data'!F84 -> 158 | F76: ='Raw Data'!G84+'Raw Data'!H84 -> 816 | G76: ='Raw Data'!I84 -> 1036 | H76: ='Raw Data'!J84 -> 2045 | I76: ='Raw Data'!K84 -> 1139 | J76: =G76/F76 -> 1.2696078 | K76: =E76/F76 -> 0.19362745 | L76: =E76/H76 -> 0.077261614 | M76: =LN(H76) -> 7.6231531 | N76: =(C76-'Raw Data'!D83)/'Raw Data'!D83 -> 0.084378014 | O76: =I76/H76 -> 0.55696822 | P76: ='Raw Data'!L84 -> 9.64 | Q76: ='Raw Data'!M84/'Raw Data'!N84 -> 4.5440415 | R76: =IF(OR(B76="FY19-20",B76="FY20-21"),1,0) -> 0 | S76: =J76 -> 1.2696078 | T76: =M76 -> 7.6231531 | U76: =N76 -> 0.084378014 | V76: =O76 -> 0.55696822 | W76: =R76 -> 0
A77: Sutlej Textiles | B77: FY17-18 | C77: ='Raw Data'!D85 -> 2453 | D77: ='Raw Data'!E85 -> 247 | E77: ='Raw Data'!F85 -> 113 | F77: ='Raw Data'!G85+'Raw Data'!H85 -> 906 | G77: ='Raw Data'!I85 -> 1047 | H77: ='Raw Data'!J85 -> 2182 | I77: ='Raw Data'!K85 -> 1119 | J77: =G77/F77 -> 1.1556291 | K77: =E77/F77 -> 0.12472406 | L77: =E77/H77 -> 0.051787351 | M77: =LN(H77) -> 7.6879972 | N77: =(C77-'Raw Data'!D84)/'Raw Data'!D84 -> 0.090706981 | O77: =I77/H77 -> 0.51283226 | P77: ='Raw Data'!L85 -> 6.91 | Q77: ='Raw Data'!M85/'Raw Data'!N85 -> 4.3026316 | R77: =IF(OR(B77="FY19-20",B77="FY20-21"),1,0) -> 0 | S77: =J77 -> 1.1556291 | T77: =M77 -> 7.6879972 | U77: =N77 -> 0.090706981 | V77: =O77 -> 0.51283226 | W77: =R77 -> 0
A78: Sutlej Textiles | B78: FY18-19 | C78: ='Raw Data'!D86 -> 2562 | D78: ='Raw Data'!E86 -> 219 | E78: ='Raw Data'!F86 -> 66 | F78: ='Raw Data'!G86+'Raw Data'!H86 -> 946 | G78: ='Raw Data'!I86 -> 923 | H78: ='Raw Data'!J86 -> 2131 | I78: ='Raw Data'!K86 -> 1074 | J78: =G78/F78 -> 0.9756871 | K78: =E78/F78 -> 0.069767442 | L78: =E78/H78 -> 0.030971375 | M78: =LN(H78) -> 7.6643466 | N78: =(C78-'Raw Data'!D85)/'Raw Data'!D85 -> 0.044435385 | O78: =I78/H78 -> 0.50398874 | P78: ='Raw Data'!L86 -> 4.01 | Q78: ='Raw Data'!M86/'Raw Data'!N86 -> 3.8275862 | R78: =IF(OR(B78="FY19-20",B78="FY20-21"),1,0) -> 0 | S78: =J78 -> 0.9756871 | T78: =M78 -> 7.6643466 | U78: =N78 -> 0.044435385 | V78: =O78 -> 0.50398874 | W78: =R78 -> 0
A79: Sutlej Textiles | B79: FY19-20 | C79: ='Raw Data'!D87 -> 2379 | D79: ='Raw Data'!E87 -> 178 | E79: ='Raw Data'!F87 -> 36 | F79: ='Raw Data'!G87+'Raw Data'!H87 -> 971 | G79: ='Raw Data'!I87 -> 868 | H79: ='Raw Data'!J87 -> 2118 | I79: ='Raw Data'!K87 -> 1210 | J79: =G79/F79 -> 0.89392379 | K79: =E79/F79 -> 0.03707518 | L79: =E79/H79 -> 0.016997167 | M79: =LN(H79) -> 7.6582275 | N79: =(C79-'Raw Data'!D86)/'Raw Data'!D86 -> -0.071428571 | O79: =I79/H79 -> 0.57129367 | P79: ='Raw Data'!L87 -> 2.2 | Q79: ='Raw Data'!M87/'Raw Data'!N87 -> 3.1362007 | R79: =IF(OR(B79="FY19-20",B79="FY20-21"),1,0) -> 1 | S79: =J79 -> 0.89392379 | T79: =M79 -> 7.6582275 | U79: =N79 -> -0.071428571 | V79: =O79 -> 0.57129367 | W79: =R79 -> 1
A80: Sutlej Textiles | B80: FY20-21 | C80: ='Raw Data'!D88 -> 1861 | D80: ='Raw Data'!E88 -> 115 | E80: ='Raw Data'!F88 -> 10 | F80: ='Raw Data'!G88+'Raw Data'!H88 -> 980 | G80: ='Raw Data'!I88 -> 901 | H80: ='Raw Data'!J88 -> 2149 | I80: ='Raw Data'!K88 -> 1231 | J80: =G80/F80 -> 0.91938776 | K80: =E80/F80 -> 0.010204082 | L80: =E80/H80 -> 0.0046533271 | M80: =LN(H80) -> 7.6727579 | N80: =(C80-'Raw Data'!D87)/'Raw Data'!D87 -> -0.21773855 | O80: =I80/H80 -> 0.57282457 | P80: ='Raw Data'!L88 -> 0.58 | Q80: ='Raw Data'!M88/'Raw Data'!N88 -> 3.2761194 | R80: =IF(OR(B80="FY19-20",B80="FY20-21"),1,0) -> 1 | S80: =J80 -> 0.91938776 | T80: =M80 -> 7.6727579 | U80: =N80 -> -0.21773855 | V80: =O80 -> 0.57282457 | W80: =R80 -> 1
A81: Sutlej Textiles | B81: FY21-22 | C81: ='Raw Data'!D89 -> 3042 | D81: ='Raw Data'!E89 -> 387 | E81: ='Raw Data'!F89 -> 156 | F81: ='Raw Data'!G89+'Raw Data'!H89 -> 1130 | G81: ='Raw Data'!I89 -> 938 | H81: ='Raw Data'!J89 -> 2442 | I81: ='Raw Data'!K89 -> 1187 | J81: =G81/F81 -> 0.8300885 | K81: =E81/F81 -> 0.1380531 | L81: =E81/H81 -> 0.063882064 | M81: =LN(H81) -> 7.8005727 | N81: =(C81-'Raw Data'!D88)/'Raw Data'!D88 -> 0.63460505 | O81: =I81/H81 -> 0.48607699 | P81: ='Raw Data'!L89 -> 9.5 | Q81: ='Raw Data'!M89/'Raw Data'!N89 -> 3.2112299 | R81: =IF(OR(B81="FY19-20",B81="FY20-21"),1,0) -> 0 | S81: =J81 -> 0.8300885 | T81: =M81 -> 7.8005727 | U81: =N81 -> 0.63460505 | V81: =O81 -> 0.48607699 | W81: =R81 -> 0
A82: Sutlej Textiles | B82: FY22-23 | C82: ='Raw Data'!D90 -> 3039 | D82: ='Raw Data'!E90 -> 264 | E82: ='Raw Data'!F90 -> 23 | F82: ='Raw Data'!G90+'Raw Data'!H90 -> 1123 | G82: ='Raw Data'!I90 -> 933 | H82: ='Raw Data'!J90 -> 2421 | I82: ='Raw Data'!K90 -> 1121 | J82: =G82/F82 -> 0.83081033 | K82: =E82/F82 -> 0.020480855 | L82: =E82/H82 -> 0.0095002065 | M82: =LN(H82) -> 7.791936 | N82: =(C82-'Raw Data'!D89)/'Raw Data'!D89 -> -0.00098619329 | O82: =I82/H82 -> 0.46303181 | P82: ='Raw Data'!L90 -> 1.39 | Q82: ='Raw Data'!M90/'Raw Data'!N90 -> 3.5 | R82: =IF(OR(B82="FY19-20",B82="FY20-21"),1,0) -> 0 | S82: =J82 -> 0.83081033 | T82: =M82 -> 7.791936 | U82: =N82 -> -0.00098619329 | V82: =O82 -> 0.46303181 | W82: =R82 -> 0
A83: Sutlej Textiles | B83: FY23-24 | C83: ='Raw Data'!D91 -> 2672 | D83: ='Raw Data'!E91 -> -29 | E83: ='Raw Data'!F91 -> -135 | F83: ='Raw Data'!G91+'Raw Data'!H91 -> 976 | G83: ='Raw Data'!I91 -> 826 | H83: ='Raw Data'!J91 -> 2097 | I83: ='Raw Data'!K91 -> 1063 | J83: =G83/F83 -> 0.84631148 | K83: =E83/F83 -> -0.13831967 | L83: =E83/H83 -> -0.064377682 | M83: =LN(H83) -> 7.648263 | N83: =(C83-'Raw Data'!D90)/'Raw Data'!D90 -> -0.12076341 | O83: =I83/H83 -> 0.50691464 | P83: ='Raw Data'!L91 -> -8.22 | Q83: ='Raw Data'!M91/'Raw Data'!N91 -> 3.4576271 | R83: =IF(OR(B83="FY19-20",B83="FY20-21"),1,0) -> 0 | S83: =J83 -> 0.84631148 | T83: =M83 -> 7.648263 | U83: =N83 -> -0.12076341 | V83: =O83 -> 0.50691464 | W83: =R83 -> 0
A84: Sutlej Textiles | B84: FY24-25 | C84: ='Raw Data'!D92 -> 2642 | D84: ='Raw Data'!E92 -> 46 | E84: ='Raw Data'!F92 -> -84 | F84: ='Raw Data'!G92+'Raw Data'!H92 -> 894 | G84: ='Raw Data'!I92 -> 877 | H84: ='Raw Data'!J92 -> 2043 | I84: ='Raw Data'!K92 -> 1010 | J84: =G84/F84 -> 0.98098434 | K84: =E84/F84 -> -0.093959732 | L84: =E84/H84 -> -0.041116006 | M84: =LN(H84) -> 7.6221746 | N84: =(C84-'Raw Data'!D91)/'Raw Data'!D91 -> -0.011227545 | O84: =I84/H84 -> 0.49437102 | P84: ='Raw Data'!L92 -> -5.14 | Q84: ='Raw Data'!M92/'Raw Data'!N92 -> 3.7069597 | R84: =IF(OR(B84="FY19-20",B84="FY20-21"),1,0) -> 0 | S84: =J84 -> 0.98098434 | T84: =M84 -> 7.6221746 | U84: =N84 -> -0.011227545 | V84: =O84 -> 0.49437102 | W84: =R84 -> 0
A85: Gokaldas Exports | B85: FY15-16 | C85: ='Raw Data'!D94 -> 1123 | D85: ='Raw Data'!E94 -> 37 | E85: ='Raw Data'!F94 -> 61 | F85: ='Raw Data'!G94+'Raw Data'!H94 -> 212 | G85: ='Raw Data'!I94 -> 343 | H85: ='Raw Data'!J94 -> 725 | I85: ='Raw Data'!K94 -> 94 | J85: =G85/F85 -> 1.6179245 | K85: =E85/F85 -> 0.28773585 | L85: =E85/H85 -> 0.084137931 | M85: =LN(H85) -> 6.5861717 | N85: =(C85-'Raw Data'!D93)/'Raw Data'!D93 -> 0.04953271 | O85: =I85/H85 -> 0.12965517 | P85: ='Raw Data'!L94 -> 17.44 | Q85: ='Raw Data'!M94/'Raw Data'!N94 -> 3.5833333 | R85: =IF(OR(B85="FY19-20",B85="FY20-21"),1,0) -> 0 | S85: =J85 -> 1.6179245 | T85: =M85 -> 6.5861717 | U85: =N85 -> 0.04953271 | V85: =O85 -> 0.12965517 | W85: =R85 -> 0
A86: Gokaldas Exports | B86: FY16-17 | C86: ='Raw Data'!D95 -> 915 | D86: ='Raw Data'!E95 -> -31 | E86: ='Raw Data'!F95 -> -46 | F86: ='Raw Data'!G95+'Raw Data'!H95 -> 165 | G86: ='Raw Data'!I95 -> 474 | H86: ='Raw Data'!J95 -> 794 | I86: ='Raw Data'!K95 -> 95 | J86: =G86/F86 -> 2.8727273 | K86: =E86/F86 -> -0.27878788 | L86: =E86/H86 -> -0.057934509 | M86: =LN(H86) -> 6.6770835 | N86: =(C86-'Raw Data'!D94)/'Raw Data'!D94 -> -0.18521817 | O86: =I86/H86 -> 0.11964736 | P86: ='Raw Data'!L95 -> -13.23 | Q86: ='Raw Data'!M95/'Raw Data'!N95 -> 4.3571429 | R86: =IF(OR(B86="FY19-20",B86="FY20-21"),1,0) -> 0 | S86: =J86 -> 2.8727273 | T86: =M86 -> 6.6770835 | U86: =N86 -> -0.18521817 | V86: =O86 -> 0.11964736 | W86: =R86 -> 0
A87: Gokaldas Exports | B87: FY17-18 | C87: ='Raw Data'!D96 -> 1031 | D87: ='Raw Data'!E96 -> -23 | E87: ='Raw Data'!F96 -> -31 | F87: ='Raw Data'!G96+'Raw Data'!H96 -> 130 | G87: ='Raw Data'!I96 -> 472 | H87: ='Raw Data'!J96 -> 794 | I87: ='Raw Data'!K96 -> 95 | J87: =G87/F87 -> 3.6307692 | K87: =E87/F87 -> -0.23846154 | L87: =E87/H87 -> -0.039042821 | M87: =LN(H87) -> 6.6770835 | N87: =(C87-'Raw Data'!D95)/'Raw Data'!D95 -> 0.12677596 | O87: =I87/H87 -> 0.11964736 | P87: ='Raw Data'!L96 -> -8.83 | Q87: ='Raw Data'!M96/'Raw Data'!N96 -> 3.5364583 | R87: =IF(OR(B87="FY19-20",B87="FY20-21"),1,0) -> 0 | S87: =J87 -> 3.6307692 | T87: =M87 -> 6.6770835 | U87: =N87 -> 0.12677596 | V87: =O87 -> 0.11964736 | W87: =R87 -> 0
A88: Gokaldas Exports | B88: FY18-19 | C88: ='Raw Data'!D97 -> 1173 | D88: ='Raw Data'!E97 -> 62 | E88: ='Raw Data'!F97 -> 26 | F88: ='Raw Data'!G97+'Raw Data'!H97 -> 239 | G88: ='Raw Data'!I97 -> 381 | H88: ='Raw Data'!J97 -> 823 | I88: ='Raw Data'!K97 -> 108 | J88: =G88/F88 -> 1.5941423 | K88: =E88/F88 -> 0.10878661 | L88: =E88/H88 -> 0.031591738 | M88: =LN(H88) -> 6.7129562 | N88: =(C88-'Raw Data'!D96)/'Raw Data'!D96 -> 0.13773036 | O88: =I88/H88 -> 0.13122722 | P88: ='Raw Data'!L97 -> 5.99 | Q88: ='Raw Data'!M97/'Raw Data'!N97 -> 3.4356436 | R88: =IF(OR(B88="FY19-20",B88="FY20-21"),1,0) -> 0 | S88: =J88 -> 1.5941423 | T88: =M88 -> 6.7129562 | U88: =N88 -> 0.13773036 | V88: =O88 -> 0.13122722 | W88: =R88 -> 0
A89: Gokaldas Exports | B89: FY19-20 | C89: ='Raw Data'!D98 -> 1368 | D89: ='Raw Data'!E98 -> 87 | E89: ='Raw Data'!F98 -> 32 | F89: ='Raw Data'!G98+'Raw Data'!H98 -> 228 | G89: ='Raw Data'!I98 -> 440 | H89: ='Raw Data'!J98 -> 939 | I89: ='Raw Data'!K98 -> 172 | J89: =G89/F89 -> 1.9298246 | K89: =E89/F89 -> 0.14035088 | L89: =E89/H89 -> 0.034078807 | M89: =LN(H89) -> 6.8448155 | N89: =(C89-'Raw Data'!D97)/'Raw Data'!D97 -> 0.16624041 | O89: =I89/H89 -> 0.18317359 | P89: ='Raw Data'!L98 -> 7.56 | Q89: ='Raw Data'!M98/'Raw Data'!N98 -> 2.6273063 | R89: =IF(OR(B89="FY19-20",B89="FY20-21"),1,0) -> 1 | S89: =J89 -> 1.9298246 | T89: =M89 -> 6.8448155 | U89: =N89 -> 0.16624041 | V89: =O89 -> 0.18317359 | W89: =R89 -> 1
A90: Gokaldas Exports | B90: FY20-21 | C90: ='Raw Data'!D99 -> 1209 | D90: ='Raw Data'!E99 -> 101 | E90: ='Raw Data'!F99 -> 26 | F90: ='Raw Data'!G99+'Raw Data'!H99 -> 291 | G90: ='Raw Data'!I99 -> 476 | H90: ='Raw Data'!J99 -> 1005 | I90: ='Raw Data'!K99 -> 235 | J90: =G90/F90 -> 1.6357388 | K90: =E90/F90 -> 0.089347079 | L90: =E90/H90 -> 0.025870647 | M90: =LN(H90) -> 6.9127428 | N90: =(C90-'Raw Data'!D98)/'Raw Data'!D98 -> -0.11622807 | O90: =I90/H90 -> 0.23383085 | P90: ='Raw Data'!L99 -> 6.12 | Q90: ='Raw Data'!M99/'Raw Data'!N99 -> 3.0084388 | R90: =IF(OR(B90="FY19-20",B90="FY20-21"),1,0) -> 1 | S90: =J90 -> 1.6357388 | T90: =M90 -> 6.9127428 | U90: =N90 -> -0.11622807 | V90: =O90 -> 0.23383085 | W90: =R90 -> 1
A91: Gokaldas Exports | B91: FY21-22 | C91: ='Raw Data'!D100 -> 1789 | D91: ='Raw Data'!E100 -> 204 | E91: ='Raw Data'!F100 -> 117 | F91: ='Raw Data'!G100+'Raw Data'!H100 -> 709 | G91: ='Raw Data'!I100 -> 191 | H91: ='Raw Data'!J100 -> 1226 | I91: ='Raw Data'!K100 -> 282 | J91: =G91/F91 -> 0.26939351 | K91: =E91/F91 -> 0.16502116 | L91: =E91/H91 -> 0.0954323 | M91: =LN(H91) -> 7.1115121 | N91: =(C91-'Raw Data'!D99)/'Raw Data'!D99 -> 0.47973532 | O91: =I91/H91 -> 0.23001631 | P91: ='Raw Data'!L100 -> 19.79 | Q91: ='Raw Data'!M100/'Raw Data'!N100 -> 2.3692308 | R91: =IF(OR(B91="FY19-20",B91="FY20-21"),1,0) -> 0 | S91: =J91 -> 0.26939351 | T91: =M91 -> 7.1115121 | U91: =N91 -> 0.47973532 | V91: =O91 -> 0.23001631 | W91: =R91 -> 0
A92: Gokaldas Exports | B92: FY22-23 | C92: ='Raw Data'!D101 -> 2221 | D92: ='Raw Data'!E101 -> 269 | E92: ='Raw Data'!F101 -> 178 | F92: ='Raw Data'!G101+'Raw Data'!H101 -> 893 | G92: ='Raw Data'!I101 -> 141 | H92: ='Raw Data'!J101 -> 1343 | I92: ='Raw Data'!K101 -> 261 | J92: =G92/F92 -> 0.15789474 | K92: =E92/F92 -> 0.19932811 | L92: =E92/H92 -> 0.13253909 | M92: =LN(H92) -> 7.2026612 | N92: =(C92-'Raw Data'!D100)/'Raw Data'!D100 -> 0.24147568 | O92: =I92/H92 -> 0.19434103 | P92: ='Raw Data'!L101 -> 29.45 | Q92: ='Raw Data'!M101/'Raw Data'!N101 -> 2.3203883 | R92: =IF(OR(B92="FY19-20",B92="FY20-21"),1,0) -> 0 | S92: =J92 -> 0.15789474 | T92: =M92 -> 7.2026612 | U92: =N92 -> 0.24147568 | V92: =O92 -> 0.19434103 | W92: =R92 -> 0
A93: Gokaldas Exports | B93: FY23-24 | C93: ='Raw Data'!D102 -> 2139 | D93: ='Raw Data'!E102 -> 255 | E93: ='Raw Data'!F102 -> 164 | F93: ='Raw Data'!G102+'Raw Data'!H102 -> 1342 | G93: ='Raw Data'!I102 -> 254 | H93: ='Raw Data'!J102 -> 1955 | I93: ='Raw Data'!K102 -> 254 | J93: =G93/F93 -> 0.18926975 | K93: =E93/F93 -> 0.12220566 | L93: =E93/H93 -> 0.083887468 | M93: =LN(H93) -> 7.5781455 | N93: =(C93-'Raw Data'!D101)/'Raw Data'!D101 -> -0.036920306 | O93: =I93/H93 -> 0.12992327 | P93: ='Raw Data'!L102 -> 25.9 | Q93: ='Raw Data'!M102/'Raw Data'!N102 -> 3.3342618 | R93: =IF(OR(B93="FY19-20",B93="FY20-21"),1,0) -> 0 | S93: =J93 -> 0.18926975 | T93: =M93 -> 7.5781455 | U93: =N93 -> -0.036920306 | V93: =O93 -> 0.12992327 | W93: =R93 -> 0
A94: Gokaldas Exports | B94: FY24-25 | C94: ='Raw Data'!D103 -> 2477 | D94: ='Raw Data'!E103 -> 244 | E94: ='Raw Data'!F103 -> 191 | F94: ='Raw Data'!G103+'Raw Data'!H103 -> 2145 | G94: ='Raw Data'!I103 -> 192 | H94: ='Raw Data'!J103 -> 2763 | I94: ='Raw Data'!K103 -> 272 | J94: =G94/F94 -> 0.08951049 | K94: =E94/F94 -> 0.089044289 | L94: =E94/H94 -> 0.06912776 | M94: =LN(H94) -> 7.9240723 | N94: =(C94-'Raw Data'!D102)/'Raw Data'!D102 -> 0.15801777 | O94: =I94/H94 -> 0.098443721 | P94: ='Raw Data'!L103 -> 26.77 | Q94: ='Raw Data'!M103/'Raw Data'!N103 -> 3.870892 | R94: =IF(OR(B94="FY19-20",B94="FY20-21"),1,0) -> 0 | S94: =J94 -> 0.08951049 | T94: =M94 -> 7.9240723 | U94: =N94 -> 0.15801777 | V94: =O94 -> 0.098443721 | W94: =R94 -> 0
A95: Siyaram Silk Mills | B95: FY15-16 | C95: ='Raw Data'!D105 -> 1609 | D95: ='Raw Data'!E105 -> 196 | E95: ='Raw Data'!F105 -> 84 | F95: ='Raw Data'!G105+'Raw Data'!H105 -> 506 | G95: ='Raw Data'!I105 -> 408 | H95: ='Raw Data'!J105 -> 1195 | I95: ='Raw Data'!K105 -> 403 | J95: =G95/F95 -> 0.80632411 | K95: =E95/F95 -> 0.16600791 | L95: =E95/H95 -> 0.070292887 | M95: =LN(H95) -> 7.0859015 | N95: =(C95-'Raw Data'!D104)/'Raw Data'!D104 -> 0.075534759 | O95: =I95/H95 -> 0.33723849 | P95: ='Raw Data'!L105 -> 17.93 | Q95: ='Raw Data'!M105/'Raw Data'!N105 -> 2.7588652 | R95: =IF(OR(B95="FY19-20",B95="FY20-21"),1,0) -> 0 | S95: =J95 -> 0.80632411 | T95: =M95 -> 7.0859015 | U95: =N95 -> 0.075534759 | V95: =O95 -> 0.33723849 | W95: =R95 -> 0
A96: Siyaram Silk Mills | B96: FY16-17 | C96: ='Raw Data'!D106 -> 1570 | D96: ='Raw Data'!E106 -> 197 | E96: ='Raw Data'!F106 -> 91 | F96: ='Raw Data'!G106+'Raw Data'!H106 -> 596 | G96: ='Raw Data'!I106 -> 305 | H96: ='Raw Data'!J106 -> 1159 | I96: ='Raw Data'!K106 -> 445 | J96: =G96/F96 -> 0.51174497 | K96: =E96/F96 -> 0.15268456 | L96: =E96/H96 -> 0.078515962 | M96: =LN(H96) -> 7.0553128 | N96: =(C96-'Raw Data'!D105)/'Raw Data'!D105 -> -0.024238658 | O96: =I96/H96 -> 0.38395168 | P96: ='Raw Data'!L106 -> 19.41 | Q96: ='Raw Data'!M106/'Raw Data'!N106 -> 2.7674419 | R96: =IF(OR(B96="FY19-20",B96="FY20-21"),1,0) -> 0 | S96: =J96 -> 0.51174497 | T96: =M96 -> 7.0553128 | U96: =N96 -> -0.024238658 | V96: =O96 -> 0.38395168 | W96: =R96 -> 0
A97: Siyaram Silk Mills | B97: FY17-18 | C97: ='Raw Data'!D107 -> 1733 | D97: ='Raw Data'!E107 -> 246 | E97: ='Raw Data'!F107 -> 112 | F97: ='Raw Data'!G107+'Raw Data'!H107 -> 678 | G97: ='Raw Data'!I107 -> 573 | H97: ='Raw Data'!J107 -> 1553 | I97: ='Raw Data'!K107 -> 532 | J97: =G97/F97 -> 0.84513274 | K97: =E97/F97 -> 0.16519174 | L97: =E97/H97 -> 0.07211848 | M97: =LN(H97) -> 7.3479438 | N97: =(C97-'Raw Data'!D106)/'Raw Data'!D106 -> 0.10382166 | O97: =I97/H97 -> 0.34256278 | P97: ='Raw Data'!L107 -> 23.81 | Q97: ='Raw Data'!M107/'Raw Data'!N107 -> 3.2857143 | R97: =IF(OR(B97="FY19-20",B97="FY20-21"),1,0) -> 0 | S97: =J97 -> 0.84513274 | T97: =M97 -> 7.3479438 | U97: =N97 -> 0.10382166 | V97: =O97 -> 0.34256278 | W97: =R97 -> 0
A98: Siyaram Silk Mills | B98: FY18-19 | C98: ='Raw Data'!D108 -> 1815 | D98: ='Raw Data'!E108 -> 241 | E98: ='Raw Data'!F108 -> 101 | F98: ='Raw Data'!G108+'Raw Data'!H108 -> 757 | G98: ='Raw Data'!I108 -> 444 | H98: ='Raw Data'!J108 -> 1505 | I98: ='Raw Data'!K108 -> 527 | J98: =G98/F98 -> 0.58652576 | K98: =E98/F98 -> 0.1334214 | L98: =E98/H98 -> 0.067109635 | M98: =LN(H98) -> 7.3165482 | N98: =(C98-'Raw Data'!D107)/'Raw Data'!D107 -> 0.047316792 | O98: =I98/H98 -> 0.35016611 | P98: ='Raw Data'!L108 -> 21.58 | Q98: ='Raw Data'!M108/'Raw Data'!N108 -> 3.1452145 | R98: =IF(OR(B98="FY19-20",B98="FY20-21"),1,0) -> 0 | S98: =J98 -> 0.58652576 | T98: =M98 -> 7.3165482 | U98: =N98 -> 0.047316792 | V98: =O98 -> 0.35016611 | W98: =R98 -> 0
A99: Siyaram Silk Mills | B99: FY19-20 | C99: ='Raw Data'!D109 -> 1698 | D99: ='Raw Data'!E109 -> 169 | E99: ='Raw Data'!F109 -> 72 | F99: ='Raw Data'!G109+'Raw Data'!H109 -> 767 | G99: ='Raw Data'!I109 -> 428 | H99: ='Raw Data'!J109 -> 1503 | I99: ='Raw Data'!K109 -> 552 | J99: =G99/F99 -> 0.55801825 | K99: =E99/F99 -> 0.093872229 | L99: =E99/H99 -> 0.047904192 | M99: =LN(H99) -> 7.3152184 | N99: =(C99-'Raw Data'!D108)/'Raw Data'!D108 -> -0.06446281 | O99: =I99/H99 -> 0.36726547 | P99: ='Raw Data'!L109 -> 15.3 | Q99: ='Raw Data'!M109/'Raw Data'!N109 -> 3.0064935 | R99: =IF(OR(B99="FY19-20",B99="FY20-21"),1,0) -> 1 | S99: =J99 -> 0.55801825 | T99: =M99 -> 7.3152184 | U99: =N99 -> -0.06446281 | V99: =O99 -> 0.36726547 | W99: =R99 -> 1
A100: Siyaram Silk Mills | B100: FY20-21 | C100: ='Raw Data'!D110 -> 1088 | D100: ='Raw Data'!E110 -> 55 | E100: ='Raw Data'!F110 -> 5 | F100: ='Raw Data'!G110+'Raw Data'!H110 -> 774 | G100: ='Raw Data'!I110 -> 139 | H100: ='Raw Data'!J110 -> 1217 | I100: ='Raw Data'!K110 -> 490 | J100: =G100/F100 -> 0.17958656 | K100: =E100/F100 -> 0.0064599483 | L100: =E100/H100 -> 0.0041084634 | M100: =LN(H100) -> 7.1041441 | N100: =(C100-'Raw Data'!D109)/'Raw Data'!D109 -> -0.35924617 | O100: =I100/H100 -> 0.40262942 | P100: ='Raw Data'!L110 -> 1.14 | Q100: ='Raw Data'!M110/'Raw Data'!N110 -> 2.2236842 | R100: =IF(OR(B100="FY19-20",B100="FY20-21"),1,0) -> 1 | S100: =J100 -> 0.17958656 | T100: =M100 -> 7.1041441 | U100: =N100 -> -0.35924617 | V100: =O100 -> 0.40262942 | W100: =R100 -> 1
...

Sheet Descriptive Stats
A1: Descriptive Statistics — by Company (FY2015-16 to FY2024-25, N=10 years each)
A3: Company | B3: Mean D/E | C3: SD D/E | D3: Min D/E | E3: Max D/E | F3: Mean ROE | G3: Mean ROA | H3: Mean EPS (Rs.) | I3: Mean Sales Growth | J3: Mean Tangibility | K3: Mean Size (ln TA) | L3: Mean Liquidity (CR proxy)
A4: KPR Mill | B4: =AVERAGEIF('Ratios Panel'!$A$5:$A$104,A4,'Ratios Panel'!$J$5:$J$104) -> 0.26862496 | C4: =SQRT(SUMPRODUCT(('Ratios Panel'!$A$5:$A$104=A4)*('Ratios Panel'!$J$5:$J$104-B4)^2)/(COUNTIF('Ratios Panel'!$A$5:$A$104,A4)-1)) -> 0.1757145 | D4: =_xlfn.MINIFS('Ratios Panel'!$J$5:$J$104,'Ratios Panel'!$A$5:$A$104,A4) -> 0.0625 | E4: =_xlfn.MAXIFS('Ratios Panel'!$J$5:$J$104,'Ratios Panel'!$A$5:$A$104,A4) -> 0.60142712 | F4: =AVERAGEIF('Ratios Panel'!$A$5:$A$104,A4,'Ratios Panel'!$K$5:$K$104) -> 0.1979938 | G4: =AVERAGEIF('Ratios Panel'!$A$5:$A$104,A4,'Ratios Panel'!$L$5:$L$104) -> 0.14401401 | H4: =AVERAGEIF('Ratios Panel'!$A$5:$A$104,A4,'Ratios Panel'!$P$5:$P$104) -> 12.094 | I4: =AVERAGEIF('Ratios Panel'!$A$5:$A$104,A4,'Ratios Panel'!$N$5:$N$104) -> 0.082229385 | J4: =AVERAGEIF('Ratios Panel'!$A$5:$A$104,A4,'Ratios Panel'!$O$5:$O$104) -> 0.35665624 | K4: =AVERAGEIF('Ratios Panel'!$A$5:$A$104,A4,'Ratios Panel'!$M$5:$M$104) -> 7.8852056 | L4: =AVERAGEIF('Ratios Panel'!$A$5:$A$104,A4,'Ratios Panel'!$Q$5:$Q$104) -> 5.6027028
A5: Welspun Living | B5: =AVERAGEIF('Ratios Panel'!$A$5:$A$104,A5,'Ratios Panel'!$J$5:$J$104) -> 0.78091842 | C5: =SQRT(SUMPRODUCT(('Ratios Panel'!$A$5:$A$104=A5)*('Ratios Panel'!$J$5:$J$104-B5)^2)/(COUNTIF('Ratios Panel'!$A$5:$A$104,A5)-1)) -> 0.37343586 | D5: =_xlfn.MINIFS('Ratios Panel'!$J$5:$J$104,'Ratios Panel'!$A$5:$A$104,A5) -> 0.37928058 | E5: =_xlfn.MAXIFS('Ratios Panel'!$J$5:$J$104,'Ratios Panel'!$A$5:$A$104,A5) -> 1.3512375 | F5: =AVERAGEIF('Ratios Panel'!$A$5:$A$104,A5,'Ratios Panel'!$K$5:$K$104) -> 0.1428065 | G5: =AVERAGEIF('Ratios Panel'!$A$5:$A$104,A5,'Ratios Panel'!$L$5:$L$104) -> 0.063211865 | H5: =AVERAGEIF('Ratios Panel'!$A$5:$A$104,A5,'Ratios Panel'!$P$5:$P$104) -> 4.044 | I5: =AVERAGEIF('Ratios Panel'!$A$5:$A$104,A5,'Ratios Panel'!$N$5:$N$104) -> 0.075440256 | J5: =AVERAGEIF('Ratios Panel'!$A$5:$A$104,A5,'Ratios Panel'!$O$5:$O$104) -> 0.41613998 | K5: =AVERAGEIF('Ratios Panel'!$A$5:$A$104,A5,'Ratios Panel'!$M$5:$M$104) -> 8.7676709 | L5: =AVERAGEIF('Ratios Panel'!$A$5:$A$104,A5,'Ratios Panel'!$Q$5:$Q$104) -> 1.8765608
A6: Indo Count Industries | B6: =AVERAGEIF('Ratios Panel'!$A$5:$A$104,A6,'Ratios Panel'!$J$5:$J$104) -> 0.45668052 | C6: =SQRT(SUMPRODUCT(('Ratios Panel'!$A$5:$A$104=A6)*('Ratios Panel'!$J$5:$J$104-B6)^2)/(COUNTIF('Ratios Panel'!$A$5:$A$104,A6)-1)) -> 0.13300681 | D6: =_xlfn.MINIFS('Ratios Panel'!$J$5:$J$104,'Ratios Panel'!$A$5:$A$104,A6) -> 0.321875 | E6: =_xlfn.MAXIFS('Ratios Panel'!$J$5:$J$104,'Ratios Panel'!$A$5:$A$104,A6) -> 0.77030457 | F6: =AVERAGEIF('Ratios Panel'!$A$5:$A$104,A6,'Ratios Panel'!$K$5:$K$104) -> 0.17577552 | G6: =AVERAGEIF('Ratios Panel'!$A$5:$A$104,A6,'Ratios Panel'!$L$5:$L$104) -> 0.096709696 | H6: =AVERAGEIF('Ratios Panel'!$A$5:$A$104,A6,'Ratios Panel'!$P$5:$P$104) -> 10.749 | I6: =AVERAGEIF('Ratios Panel'!$A$5:$A$104,A6,'Ratios Panel'!$N$5:$N$104) -> 0.095288808 | J6: =AVERAGEIF('Ratios Panel'!$A$5:$A$104,A6,'Ratios Panel'!$O$5:$O$104) -> 0.33648802 | K6: =AVERAGEIF('Ratios Panel'!$A$5:$A$104,A6,'Ratios Panel'!$M$5:$M$104) -> 7.6722727 | L6: =AVERAGEIF('Ratios Panel'!$A$5:$A$104,A6,'Ratios Panel'!$Q$5:$Q$104) -> 4.0010099
A7: Vardhman Textiles | B7: =AVERAGEIF('Ratios Panel'!$A$5:$A$104,A7,'Ratios Panel'!$J$5:$J$104) -> 0.37071413 | C7: =SQRT(SUMPRODUCT(('Ratios Panel'!$A$5:$A$104=A7)*('Ratios Panel'!$J$5:$J$104-B7)^2)/(COUNTIF('Ratios Panel'!$A$5:$A$104,A7)-1)) -> 0.17911154 | D7: =_xlfn.MINIFS('Ratios Panel'!$J$5:$J$104,'Ratios Panel'!$A$5:$A$104,A7) -> 0.12925454 | E7: =_xlfn.MAXIFS('Ratios Panel'!$J$5:$J$104,'Ratios Panel'!$A$5:$A$104,A7) -> 0.70352304 | F7: =AVERAGEIF('Ratios Panel'!$A$5:$A$104,A7,'Ratios Panel'!$K$5:$K$104) -> 0.13148297 | G7: =AVERAGEIF('Ratios Panel'!$A$5:$A$104,A7,'Ratios Panel'!$L$5:$L$104) -> 0.085213859 | H7: =AVERAGEIF('Ratios Panel'!$A$5:$A$104,A7,'Ratios Panel'!$P$5:$P$104) -> 26.643 | I7: =AVERAGEIF('Ratios Panel'!$A$5:$A$104,A7,'Ratios Panel'!$N$5:$N$104) -> 0.064918386 | J7: =AVERAGEIF('Ratios Panel'!$A$5:$A$104,A7,'Ratios Panel'!$O$5:$O$104) -> 0.36764949 | K7: =AVERAGEIF('Ratios Panel'!$A$5:$A$104,A7,'Ratios Panel'!$M$5:$M$104) -> 9.1158841 | L7: =AVERAGEIF('Ratios Panel'!$A$5:$A$104,A7,'Ratios Panel'!$Q$5:$Q$104) -> 5.1083707
A8: Trident | B8: =AVERAGEIF('Ratios Panel'!$A$5:$A$104,A8,'Ratios Panel'!$J$5:$J$104) -> 0.71020611 | C8: =SQRT(SUMPRODUCT(('Ratios Panel'!$A$5:$A$104=A8)*('Ratios Panel'!$J$5:$J$104-B8)^2)/(COUNTIF('Ratios Panel'!$A$5:$A$104,A8)-1)) -> 0.37177203 | D8: =_xlfn.MINIFS('Ratios Panel'!$J$5:$J$104,'Ratios Panel'!$A$5:$A$104,A8) -> 0.34028114 | E8: =_xlfn.MAXIFS('Ratios Panel'!$J$5:$J$104,'Ratios Panel'!$A$5:$A$104,A8) -> 1.4505176 | F8: =AVERAGEIF('Ratios Panel'!$A$5:$A$104,A8,'Ratios Panel'!$K$5:$K$104) -> 0.11556729 | G8: =AVERAGEIF('Ratios Panel'!$A$5:$A$104,A8,'Ratios Panel'!$L$5:$L$104) -> 0.060904718 | H8: =AVERAGEIF('Ratios Panel'!$A$5:$A$104,A8,'Ratios Panel'!$P$5:$P$104) -> 0.765 | I8: =AVERAGEIF('Ratios Panel'!$A$5:$A$104,A8,'Ratios Panel'!$N$5:$N$104) -> 0.07808884 | J8: =AVERAGEIF('Ratios Panel'!$A$5:$A$104,A8,'Ratios Panel'!$O$5:$O$104) -> 0.65890352 | K8: =AVERAGEIF('Ratios Panel'!$A$5:$A$104,A8,'Ratios Panel'!$M$5:$M$104) -> 8.7629235 | L8: =AVERAGEIF('Ratios Panel'!$A$5:$A$104,A8,'Ratios Panel'!$Q$5:$Q$104) -> 2.6019052
A9: Arvind | B9: =AVERAGEIF('Ratios Panel'!$A$5:$A$104,A9,'Ratios Panel'!$J$5:$J$104) -> 0.69507873 | C9: =SQRT(SUMPRODUCT(('Ratios Panel'!$A$5:$A$104=A9)*('Ratios Panel'!$J$5:$J$104-B9)^2)/(COUNTIF('Ratios Panel'!$A$5:$A$104,A9)-1)) -> 0.23377797 | D9: =_xlfn.MINIFS('Ratios Panel'!$J$5:$J$104,'Ratios Panel'!$A$5:$A$104,A9) -> 0.37963762 | E9: =_xlfn.MAXIFS('Ratios Panel'!$J$5:$J$104,'Ratios Panel'!$A$5:$A$104,A9) -> 1.0458808 | F9: =AVERAGEIF('Ratios Panel'!$A$5:$A$104,A9,'Ratios Panel'!$K$5:$K$104) -> 0.063429095 | G9: =AVERAGEIF('Ratios Panel'!$A$5:$A$104,A9,'Ratios Panel'!$L$5:$L$104) -> 0.029202486 | H9: =AVERAGEIF('Ratios Panel'!$A$5:$A$104,A9,'Ratios Panel'!$P$5:$P$104) -> 7.706 | I9: =AVERAGEIF('Ratios Panel'!$A$5:$A$104,A9,'Ratios Panel'!$N$5:$N$104) -> 0.041209065 | J9: =AVERAGEIF('Ratios Panel'!$A$5:$A$104,A9,'Ratios Panel'!$O$5:$O$104) -> 0.478467 | K9: =AVERAGEIF('Ratios Panel'!$A$5:$A$104,A9,'Ratios Panel'!$M$5:$M$104) -> 8.83518 | L9: =AVERAGEIF('Ratios Panel'!$A$5:$A$104,A9,'Ratios Panel'!$Q$5:$Q$104) -> 1.9738433
A10: Nitin Spinners | B10: =AVERAGEIF('Ratios Panel'!$A$5:$A$104,A10,'Ratios Panel'!$J$5:$J$104) -> 1.4331148 | C10: =SQRT(SUMPRODUCT(('Ratios Panel'!$A$5:$A$104=A10)*('Ratios Panel'!$J$5:$J$104-B10)^2)/(COUNTIF('Ratios Panel'!$A$5:$A$104,A10)-1)) -> 0.51486684 | D10: =_xlfn.MINIFS('Ratios Panel'!$J$5:$J$104,'Ratios Panel'!$A$5:$A$104,A10) -> 0.78652968 | E10: =_xlfn.MAXIFS('Ratios Panel'!$J$5:$J$104,'Ratios Panel'!$A$5:$A$104,A10) -> 2.1515152 | F10: =AVERAGEIF('Ratios Panel'!$A$5:$A$104,A10,'Ratios Panel'!$K$5:$K$104) -> 0.16392875 | G10: =AVERAGEIF('Ratios Panel'!$A$5:$A$104,A10,'Ratios Panel'!$L$5:$L$104) -> 0.065575769 | H10: =AVERAGEIF('Ratios Panel'!$A$5:$A$104,A10,'Ratios Panel'!$P$5:$P$104) -> 20.138 | I10: =AVERAGEIF('Ratios Panel'!$A$5:$A$104,A10,'Ratios Panel'!$N$5:$N$104) -> 0.1955675 | J10: =AVERAGEIF('Ratios Panel'!$A$5:$A$104,A10,'Ratios Panel'!$O$5:$O$104) -> 0.63298045 | K10: =AVERAGEIF('Ratios Panel'!$A$5:$A$104,A10,'Ratios Panel'!$M$5:$M$104) -> 7.320582 | L10: =AVERAGEIF('Ratios Panel'!$A$5:$A$104,A10,'Ratios Panel'!$Q$5:$Q$104) -> 4.335471
A11: Sutlej Textiles | B11: =AVERAGEIF('Ratios Panel'!$A$5:$A$104,A11,'Ratios Panel'!$J$5:$J$104) -> 0.98795899 | C11: =SQRT(SUMPRODUCT(('Ratios Panel'!$A$5:$A$104=A11)*('Ratios Panel'!$J$5:$J$104-B11)^2)/(COUNTIF('Ratios Panel'!$A$5:$A$104,A11)-1)) -> 0.1586971 | D11: =_xlfn.MINIFS('Ratios Panel'!$J$5:$J$104,'Ratios Panel'!$A$5:$A$104,A11) -> 0.8300885 | E11: =_xlfn.MAXIFS('Ratios Panel'!$J$5:$J$104,'Ratios Panel'!$A$5:$A$104,A11) -> 1.2696078 | F11: =AVERAGEIF('Ratios Panel'!$A$5:$A$104,A11,'Ratios Panel'!$K$5:$K$104) -> 0.057102319 | G11: =AVERAGEIF('Ratios Panel'!$A$5:$A$104,A11,'Ratios Panel'!$L$5:$L$104) -> 0.023493255 | H11: =AVERAGEIF('Ratios Panel'!$A$5:$A$104,A11,'Ratios Panel'!$P$5:$P$104) -> 2.963 | I11: =AVERAGEIF('Ratios Panel'!$A$5:$A$104,A11,'Ratios Panel'!$N$5:$N$104) -> 0.054285422 | J11: =AVERAGEIF('Ratios Panel'!$A$5:$A$104,A11,'Ratios Panel'!$O$5:$O$104) -> 0.5191884 | K11: =AVERAGEIF('Ratios Panel'!$A$5:$A$104,A11,'Ratios Panel'!$M$5:$M$104) -> 7.6592997 | L11: =AVERAGEIF('Ratios Panel'!$A$5:$A$104,A11,'Ratios Panel'!$Q$5:$Q$104) -> 3.7068779
A12: Gokaldas Exports | B12: =AVERAGEIF('Ratios Panel'!$A$5:$A$104,A12,'Ratios Panel'!$J$5:$J$104) -> 1.3987195 | C12: =SQRT(SUMPRODUCT(('Ratios Panel'!$A$5:$A$104=A12)*('Ratios Panel'!$J$5:$J$104-B12)^2)/(COUNTIF('Ratios Panel'!$A$5:$A$104,A12)-1)) -> 1.2279638 | D12: =_xlfn.MINIFS('Ratios Panel'!$J$5:$J$104,'Ratios Panel'!$A$5:$A$104,A12) -> 0.08951049 | E12: =_xlfn.MAXIFS('Ratios Panel'!$J$5:$J$104,'Ratios Panel'!$A$5:$A$104,A12) -> 3.6307692 | F12: =AVERAGEIF('Ratios Panel'!$A$5:$A$104,A12,'Ratios Panel'!$K$5:$K$104) -> 0.068457022 | G12: =AVERAGEIF('Ratios Panel'!$A$5:$A$104,A12,'Ratios Panel'!$L$5:$L$104) -> 0.045968841 | H12: =AVERAGEIF('Ratios Panel'!$A$5:$A$104,A12,'Ratios Panel'!$P$5:$P$104) -> 11.696 | I12: =AVERAGEIF('Ratios Panel'!$A$5:$A$104,A12,'Ratios Panel'!$N$5:$N$104) -> 0.10211417 | J12: =AVERAGEIF('Ratios Panel'!$A$5:$A$104,A12,'Ratios Panel'!$O$5:$O$104) -> 0.15699059 | K12: =AVERAGEIF('Ratios Panel'!$A$5:$A$104,A12,'Ratios Panel'!$M$5:$M$104) -> 7.0227244 | L12: =AVERAGEIF('Ratios Panel'!$A$5:$A$104,A12,'Ratios Panel'!$Q$5:$Q$104) -> 3.2443096
A13: Siyaram Silk Mills | B13: =AVERAGEIF('Ratios Panel'!$A$5:$A$104,A13,'Ratios Panel'!$J$5:$J$104) -> 0.42249735 | C13: =SQRT(SUMPRODUCT(('Ratios Panel'!$A$5:$A$104=A13)*('Ratios Panel'!$J$5:$J$104-B13)^2)/(COUNTIF('Ratios Panel'!$A$5:$A$104,A13)-1)) -> 0.27301807 | D13: =_xlfn.MINIFS('Ratios Panel'!$J$5:$J$104,'Ratios Panel'!$A$5:$A$104,A13) -> 0.14285714 | E13: =_xlfn.MAXIFS('Ratios Panel'!$J$5:$J$104,'Ratios Panel'!$A$5:$A$104,A13) -> 0.84513274 | F13: =AVERAGEIF('Ratios Panel'!$A$5:$A$104,A13,'Ratios Panel'!$K$5:$K$104) -> 0.14824595 | G13: =AVERAGEIF('Ratios Panel'!$A$5:$A$104,A13,'Ratios Panel'!$L$5:$L$104) -> 0.085461938 | H13: =AVERAGEIF('Ratios Panel'!$A$5:$A$104,A13,'Ratios Panel'!$P$5:$P$104) -> 28.274 | I13: =AVERAGEIF('Ratios Panel'!$A$5:$A$104,A13,'Ratios Panel'!$N$5:$N$104) -> 0.069913705 | J13: =AVERAGEIF('Ratios Panel'!$A$5:$A$104,A13,'Ratios Panel'!$O$5:$O$104) -> 0.34274544 | K13: =AVERAGEIF('Ratios Panel'!$A$5:$A$104,A13,'Ratios Panel'!$M$5:$M$104) -> 7.2878111 | L13: =AVERAGEIF('Ratios Panel'!$A$5:$A$104,A13,'Ratios Panel'!$Q$5:$Q$104) -> 2.9816242
A14: POOLED (all 100 firm-years) | B14: =AVERAGE('Ratios Panel'!$J$5:$J$104) -> 0.75245135 | C14: =STDEV('Ratios Panel'!$J$5:$J$104) -> 0.60097434 | D14: =MIN('Ratios Panel'!$J$5:$J$104) -> 0.0625 | E14: =MAX('Ratios Panel'!$J$5:$J$104) -> 3.6307692 | F14: =AVERAGE('Ratios Panel'!$K$5:$K$104) -> 0.12647892 | G14: =AVERAGE('Ratios Panel'!$L$5:$L$104) -> 0.069975643 | H14: =AVERAGE('Ratios Panel'!$P$5:$P$104) -> 12.5072 | I14: =AVERAGE('Ratios Panel'!$N$5:$N$104) -> 0.085905553 | J14: =AVERAGE('Ratios Panel'!$O$5:$O$104) -> 0.42662091 | K14: =AVERAGE('Ratios Panel'!$M$5:$M$104) -> 8.0329554 | L14: =AVERAGE('Ratios Panel'!$Q$5:$Q$104) -> 3.5432675
A16: Year-wise Trend (pooled across 10 companies)
A17: FY | B17: Mean D/E | C17: SD D/E | D17: Mean ROE | E17: Mean ROA | F17: Mean EPS (Rs.)
A18: FY15-16 | B18: =AVERAGEIF('Ratios Panel'!$B$5:$B$104,A18,'Ratios Panel'!$J$5:$J$104) -> 1.1017381 | C18: =SQRT(SUMPRODUCT(('Ratios Panel'!$B$5:$B$104=A18)*('Ratios Panel'!$J$5:$J$104-B18)^2)/(COUNTIF('Ratios Panel'!$B$5:$B$104,A18)-1)) -> 0.42466518 | D18: =AVERAGEIF('Ratios Panel'!$B$5:$B$104,A18,'Ratios Panel'!$K$5:$K$104) -> 0.21561211 | E18: =AVERAGEIF('Ratios Panel'!$B$5:$B$104,A18,'Ratios Panel'!$L$5:$L$104) -> 0.088551985 | F18: =AVERAGEIF('Ratios Panel'!$B$5:$B$104,A18,'Ratios Panel'!$P$5:$P$104) -> 11.054
A19: FY16-17 | B19: =AVERAGEIF('Ratios Panel'!$B$5:$B$104,A19,'Ratios Panel'!$J$5:$J$104) -> 1.1215308 | C19: =SQRT(SUMPRODUCT(('Ratios Panel'!$B$5:$B$104=A19)*('Ratios Panel'!$J$5:$J$104-B19)^2)/(COUNTIF('Ratios Panel'!$B$5:$B$104,A19)-1)) -> 0.82119837 | D19: =AVERAGEIF('Ratios Panel'!$B$5:$B$104,A19,'Ratios Panel'!$K$5:$K$104) -> 0.12931842 | E19: =AVERAGEIF('Ratios Panel'!$B$5:$B$104,A19,'Ratios Panel'!$L$5:$L$104) -> 0.070366617 | F19: =AVERAGEIF('Ratios Panel'!$B$5:$B$104,A19,'Ratios Panel'!$P$5:$P$104) -> 8.563
A20: FY17-18 | B20: =AVERAGEIF('Ratios Panel'!$B$5:$B$104,A20,'Ratios Panel'!$J$5:$J$104) -> 1.0825075 | C20: =SQRT(SUMPRODUCT(('Ratios Panel'!$B$5:$B$104=A20)*('Ratios Panel'!$J$5:$J$104-B20)^2)/(COUNTIF('Ratios Panel'!$B$5:$B$104,A20)-1)) -> 0.95048547 | D20: =AVERAGEIF('Ratios Panel'!$B$5:$B$104,A20,'Ratios Panel'!$K$5:$K$104) -> 0.09050075 | E20: =AVERAGEIF('Ratios Panel'!$B$5:$B$104,A20,'Ratios Panel'!$L$5:$L$104) -> 0.053559413 | F20: =AVERAGEIF('Ratios Panel'!$B$5:$B$104,A20,'Ratios Panel'!$P$5:$P$104) -> 7.627
A21: FY18-19 | B21: =AVERAGEIF('Ratios Panel'!$B$5:$B$104,A21,'Ratios Panel'!$J$5:$J$104) -> 0.89031656 | C21: =SQRT(SUMPRODUCT(('Ratios Panel'!$B$5:$B$104=A21)*('Ratios Panel'!$J$5:$J$104-B21)^2)/(COUNTIF('Ratios Panel'!$B$5:$B$104,A21)-1)) -> 0.49001751 | D21: =AVERAGEIF('Ratios Panel'!$B$5:$B$104,A21,'Ratios Panel'!$K$5:$K$104) -> 0.10845561 | E21: =AVERAGEIF('Ratios Panel'!$B$5:$B$104,A21,'Ratios Panel'!$L$5:$L$104) -> 0.052781871 | F21: =AVERAGEIF('Ratios Panel'!$B$5:$B$104,A21,'Ratios Panel'!$P$5:$P$104) -> 8.801
A22: FY19-20 | B22: =AVERAGEIF('Ratios Panel'!$B$5:$B$104,A22,'Ratios Panel'!$J$5:$J$104) -> 0.88798763 | C22: =SQRT(SUMPRODUCT(('Ratios Panel'!$B$5:$B$104=A22)*('Ratios Panel'!$J$5:$J$104-B22)^2)/(COUNTIF('Ratios Panel'!$B$5:$B$104,A22)-1)) -> 0.63169113 | D22: =AVERAGEIF('Ratios Panel'!$B$5:$B$104,A22,'Ratios Panel'!$K$5:$K$104) -> 0.10327311 | E22: =AVERAGEIF('Ratios Panel'!$B$5:$B$104,A22,'Ratios Panel'!$L$5:$L$104) -> 0.051676997 | F22: =AVERAGEIF('Ratios Panel'!$B$5:$B$104,A22,'Ratios Panel'!$P$5:$P$104) -> 7.259
A23: FY20-21 | B23: =AVERAGEIF('Ratios Panel'!$B$5:$B$104,A23,'Ratios Panel'!$J$5:$J$104) -> 0.69535497 | C23: =SQRT(SUMPRODUCT(('Ratios Panel'!$B$5:$B$104=A23)*('Ratios Panel'!$J$5:$J$104-B23)^2)/(COUNTIF('Ratios Panel'!$B$5:$B$104,A23)-1)) -> 0.5602645 | D23: =AVERAGEIF('Ratios Panel'!$B$5:$B$104,A23,'Ratios Panel'!$K$5:$K$104) -> 0.10134215 | E23: =AVERAGEIF('Ratios Panel'!$B$5:$B$104,A23,'Ratios Panel'!$L$5:$L$104) -> 0.056687263 | F23: =AVERAGEIF('Ratios Panel'!$B$5:$B$104,A23,'Ratios Panel'!$P$5:$P$104) -> 6.808
A24: FY21-22 | B24: =AVERAGEIF('Ratios Panel'!$B$5:$B$104,A24,'Ratios Panel'!$J$5:$J$104) -> 0.4707226 | C24: =SQRT(SUMPRODUCT(('Ratios Panel'!$B$5:$B$104=A24)*('Ratios Panel'!$J$5:$J$104-B24)^2)/(COUNTIF('Ratios Panel'!$B$5:$B$104,A24)-1)) -> 0.25375463 | D24: =AVERAGEIF('Ratios Panel'!$B$5:$B$104,A24,'Ratios Panel'!$K$5:$K$104) -> 0.19648027 | E24: =AVERAGEIF('Ratios Panel'!$B$5:$B$104,A24,'Ratios Panel'!$L$5:$L$104) -> 0.11625427 | F24: =AVERAGEIF('Ratios Panel'!$B$5:$B$104,A24,'Ratios Panel'!$P$5:$P$104) -> 23.689
A25: FY22-23 | B25: =AVERAGEIF('Ratios Panel'!$B$5:$B$104,A25,'Ratios Panel'!$J$5:$J$104) -> 0.42263928 | C25: =SQRT(SUMPRODUCT(('Ratios Panel'!$B$5:$B$104=A25)*('Ratios Panel'!$J$5:$J$104-B25)^2)/(COUNTIF('Ratios Panel'!$B$5:$B$104,A25)-1)) -> 0.28460462 | D25: =AVERAGEIF('Ratios Panel'!$B$5:$B$104,A25,'Ratios Panel'!$K$5:$K$104) -> 0.12830708 | E25: =AVERAGEIF('Ratios Panel'!$B$5:$B$104,A25,'Ratios Panel'!$L$5:$L$104) -> 0.081757065 | F25: =AVERAGEIF('Ratios Panel'!$B$5:$B$104,A25,'Ratios Panel'!$P$5:$P$104) -> 18.569
A26: FY23-24 | B26: =AVERAGEIF('Ratios Panel'!$B$5:$B$104,A26,'Ratios Panel'!$J$5:$J$104) -> 0.44934995 | C26: =SQRT(SUMPRODUCT(('Ratios Panel'!$B$5:$B$104=A26)*('Ratios Panel'!$J$5:$J$104-B26)^2)/(COUNTIF('Ratios Panel'!$B$5:$B$104,A26)-1)) -> 0.33913851 | D26: =AVERAGEIF('Ratios Panel'!$B$5:$B$104,A26,'Ratios Panel'!$K$5:$K$104) -> 0.09885248 | E26: =AVERAGEIF('Ratios Panel'!$B$5:$B$104,A26,'Ratios Panel'!$L$5:$L$104) -> 0.064592692 | F26: =AVERAGEIF('Ratios Panel'!$B$5:$B$104,A26,'Ratios Panel'!$P$5:$P$104) -> 15.372
A27: FY24-25 | B27: =AVERAGEIF('Ratios Panel'!$B$5:$B$104,A27,'Ratios Panel'!$J$5:$J$104) -> 0.40236607 | C27: =SQRT(SUMPRODUCT(('Ratios Panel'!$B$5:$B$104=A27)*('Ratios Panel'!$J$5:$J$104-B27)^2)/(COUNTIF('Ratios Panel'!$B$5:$B$104,A27)-1)) -> 0.31760833 | D27: =AVERAGEIF('Ratios Panel'!$B$5:$B$104,A27,'Ratios Panel'!$K$5:$K$104) -> 0.092647241 | E27: =AVERAGEIF('Ratios Panel'!$B$5:$B$104,A27,'Ratios Panel'!$L$5:$L$104) -> 0.06352826 | F27: =AVERAGEIF('Ratios Panel'!$B$5:$B$104,A27,'Ratios Panel'!$P$5:$P$104) -> 17.33

Sheet Correlation Matrix
A1: Correlation Matrix — Pooled Panel (100 firm-years)
B3: D/E | C3: ROE | D3: ROA | E3: EPS | F3: Size (ln TA) | G3: Sales Growth | H3: Tangibility | I3: Liquidity
A4: D/E | B4: =CORREL('Ratios Panel'!$J$5:$J$104,'Ratios Panel'!$J$5:$J$104) -> 1 | C4: =CORREL('Ratios Panel'!$J$5:$J$104,'Ratios Panel'!$K$5:$K$104) -> -0.36134275 | D4: =CORREL('Ratios Panel'!$J$5:$J$104,'Ratios Panel'!$L$5:$L$104) -> -0.5105267 | E4: =CORREL('Ratios Panel'!$J$5:$J$104,'Ratios Panel'!$P$5:$P$104) -> -0.38517444 | F4: =CORREL('Ratios Panel'!$J$5:$J$104,'Ratios Panel'!$M$5:$M$104) -> -0.4036985 | G4: =CORREL('Ratios Panel'!$J$5:$J$104,'Ratios Panel'!$N$5:$N$104) -> -0.025696022 | H4: =CORREL('Ratios Panel'!$J$5:$J$104,'Ratios Panel'!$O$5:$O$104) -> 0.1477739 | I4: =CORREL('Ratios Panel'!$J$5:$J$104,'Ratios Panel'!$Q$5:$Q$104) -> -0.050189744
A5: ROE | B5: =CORREL('Ratios Panel'!$K$5:$K$104,'Ratios Panel'!$J$5:$J$104) -> -0.36134275 | C5: =CORREL('Ratios Panel'!$K$5:$K$104,'Ratios Panel'!$K$5:$K$104) -> 1 | D5: =CORREL('Ratios Panel'!$K$5:$K$104,'Ratios Panel'!$L$5:$L$104) -> 0.87685804 | E5: =CORREL('Ratios Panel'!$K$5:$K$104,'Ratios Panel'!$P$5:$P$104) -> 0.53325122 | F5: =CORREL('Ratios Panel'!$K$5:$K$104,'Ratios Panel'!$M$5:$M$104) -> -0.049009685 | G5: =CORREL('Ratios Panel'!$K$5:$K$104,'Ratios Panel'!$N$5:$N$104) -> 0.40629718 | H5: =CORREL('Ratios Panel'!$K$5:$K$104,'Ratios Panel'!$O$5:$O$104) -> -0.0093948253 | I5: =CORREL('Ratios Panel'!$K$5:$K$104,'Ratios Panel'!$Q$5:$Q$104) -> 0.10759195
A6: ROA | B6: =CORREL('Ratios Panel'!$L$5:$L$104,'Ratios Panel'!$J$5:$J$104) -> -0.5105267 | C6: =CORREL('Ratios Panel'!$L$5:$L$104,'Ratios Panel'!$K$5:$K$104) -> 0.87685804 | D6: =CORREL('Ratios Panel'!$L$5:$L$104,'Ratios Panel'!$L$5:$L$104) -> 1 | E6: =CORREL('Ratios Panel'!$L$5:$L$104,'Ratios Panel'!$P$5:$P$104) -> 0.61388946 | F6: =CORREL('Ratios Panel'!$L$5:$L$104,'Ratios Panel'!$M$5:$M$104) -> -0.003689579 | G6: =CORREL('Ratios Panel'!$L$5:$L$104,'Ratios Panel'!$N$5:$N$104) -> 0.4000793 | H6: =CORREL('Ratios Panel'!$L$5:$L$104,'Ratios Panel'!$O$5:$O$104) -> -0.22461519 | I6: =CORREL('Ratios Panel'!$L$5:$L$104,'Ratios Panel'!$Q$5:$Q$104) -> 0.28335849
A7: EPS | B7: =CORREL('Ratios Panel'!$P$5:$P$104,'Ratios Panel'!$J$5:$J$104) -> -0.38517444 | C7: =CORREL('Ratios Panel'!$P$5:$P$104,'Ratios Panel'!$K$5:$K$104) -> 0.53325122 | D7: =CORREL('Ratios Panel'!$P$5:$P$104,'Ratios Panel'!$L$5:$L$104) -> 0.61388946 | E7: =CORREL('Ratios Panel'!$P$5:$P$104,'Ratios Panel'!$P$5:$P$104) -> 1 | F7: =CORREL('Ratios Panel'!$P$5:$P$104,'Ratios Panel'!$M$5:$M$104) -> -0.025267278 | G7: =CORREL('Ratios Panel'!$P$5:$P$104,'Ratios Panel'!$N$5:$N$104) -> 0.36807829 | H7: =CORREL('Ratios Panel'!$P$5:$P$104,'Ratios Panel'!$O$5:$O$104) -> -0.27570381 | I7: =CORREL('Ratios Panel'!$P$5:$P$104,'Ratios Panel'!$Q$5:$Q$104) -> 0.25484342
A8: Size (ln TA) | B8: =CORREL('Ratios Panel'!$M$5:$M$104,'Ratios Panel'!$J$5:$J$104) -> -0.4036985 | C8: =CORREL('Ratios Panel'!$M$5:$M$104,'Ratios Panel'!$K$5:$K$104) -> -0.049009685 | D8: =CORREL('Ratios Panel'!$M$5:$M$104,'Ratios Panel'!$L$5:$L$104) -> -0.003689579 | E8: =CORREL('Ratios Panel'!$M$5:$M$104,'Ratios Panel'!$P$5:$P$104) -> -0.025267278 | F8: =CORREL('Ratios Panel'!$M$5:$M$104,'Ratios Panel'!$M$5:$M$104) -> 1 | G8: =CORREL('Ratios Panel'!$M$5:$M$104,'Ratios Panel'!$N$5:$N$104) -> -0.065802334 | H8: =CORREL('Ratios Panel'!$M$5:$M$104,'Ratios Panel'!$O$5:$O$104) -> 0.24106651 | I8: =CORREL('Ratios Panel'!$M$5:$M$104,'Ratios Panel'!$Q$5:$Q$104) -> -0.090852057
A9: Sales Growth | B9: =CORREL('Ratios Panel'!$N$5:$N$104,'Ratios Panel'!$J$5:$J$104) -> -0.025696022 | C9: =CORREL('Ratios Panel'!$N$5:$N$104,'Ratios Panel'!$K$5:$K$104) -> 0.40629718 | D9: =CORREL('Ratios Panel'!$N$5:$N$104,'Ratios Panel'!$L$5:$L$104) -> 0.4000793 | E9: =CORREL('Ratios Panel'!$N$5:$N$104,'Ratios Panel'!$P$5:$P$104) -> 0.36807829 | F9: =CORREL('Ratios Panel'!$N$5:$N$104,'Ratios Panel'!$M$5:$M$104) -> -0.065802334 | G9: =CORREL('Ratios Panel'!$N$5:$N$104,'Ratios Panel'!$N$5:$N$104) -> 1 | H9: =CORREL('Ratios Panel'!$N$5:$N$104,'Ratios Panel'!$O$5:$O$104) -> -0.026878496 | I9: =CORREL('Ratios Panel'!$N$5:$N$104,'Ratios Panel'!$Q$5:$Q$104) -> -0.018685899
A10: Tangibility | B10: =CORREL('Ratios Panel'!$O$5:$O$104,'Ratios Panel'!$J$5:$J$104) -> 0.1477739 | C10: =CORREL('Ratios Panel'!$O$5:$O$104,'Ratios Panel'!$K$5:$K$104) -> -0.0093948253 | D10: =CORREL('Ratios Panel'!$O$5:$O$104,'Ratios Panel'!$L$5:$L$104) -> -0.22461519 | E10: =CORREL('Ratios Panel'!$O$5:$O$104,'Ratios Panel'!$P$5:$P$104) -> -0.27570381 | F10: =CORREL('Ratios Panel'!$O$5:$O$104,'Ratios Panel'!$M$5:$M$104) -> 0.24106651 | G10: =CORREL('Ratios Panel'!$O$5:$O$104,'Ratios Panel'!$N$5:$N$104) -> -0.026878496 | H10: =CORREL('Ratios Panel'!$O$5:$O$104,'Ratios Panel'!$O$5:$O$104) -> 1 | I10: =CORREL('Ratios Panel'!$O$5:$O$104,'Ratios Panel'!$Q$5:$Q$104) -> -0.18452977
A11: Liquidity | B11: =CORREL('Ratios Panel'!$Q$5:$Q$104,'Ratios Panel'!$J$5:$J$104) -> -0.050189744 | C11: =CORREL('Ratios Panel'!$Q$5:$Q$104,'Ratios Panel'!$K$5:$K$104) -> 0.10759195 | D11: =CORREL('Ratios Panel'!$Q$5:$Q$104,'Ratios Panel'!$L$5:$L$104) -> 0.28335849 | E11: =CORREL('Ratios Panel'!$Q$5:$Q$104,'Ratios Panel'!$P$5:$P$104) -> 0.25484342 | F11: =CORREL('Ratios Panel'!$Q$5:$Q$104,'Ratios Panel'!$M$5:$M$104) -> -0.090852057 | G11: =CORREL('Ratios Panel'!$Q$5:$Q$104,'Ratios Panel'!$N$5:$N$104) -> -0.018685899 | H11: =CORREL('Ratios Panel'!$Q$5:$Q$104,'Ratios Panel'!$O$5:$O$104) -> -0.18452977 | I11: =CORREL('Ratios Panel'!$Q$5:$Q$104,'Ratios Panel'!$Q$5:$Q$104) -> 1
A13: Interpretation: Negative correlation between D/E and ROE/ROA/EPS indicates that more highly levered textile firms in the sample tend to report lower profitability — consistent with Pecking Order Theory (profitable firms rely first on internal accruals, borrowing only when internal funds are insufficient).
A18: Significance: with n = 100, |r| > 0.197 is significant at the 5% level (two-tailed).

Sheet Regression Output
A1: Regression Analysis — Pooled OLS, 100 firm-years (live Excel LINEST formulas)
A2: Model specified in the assignment: ROE = β0 + β1(D/E) + β2(Size) + β3(Growth) + β4(Tangibility) + ε. Every figure below is a live formula: LINEST fits the model on the Ratios Panel (Y = ROE or ROA; X = columns S–V, plus W for the COVID dummy). t = coefficient ÷ standard error; p-value = TDIST(|t|, residual df, 2). ** = significant at 1%, * = at 5%.
A4: Model 1: ROE as dependent variable (assignment model)
A5: Variable | B5: Coefficient | C5: Std. Error | D5: t-Statistic | E5: p-value | F5: Significant at 5%?
A6: Intercept (β0) | B6: =INDEX(LINEST('Ratios Panel'!$K$5:$K$104,'Ratios Panel'!$S$5:$V$104,TRUE(),TRUE()),1,5) -> 0.38149215 | C6: =INDEX(LINEST('Ratios Panel'!$K$5:$K$104,'Ratios Panel'!$S$5:$V$104,TRUE(),TRUE()),2,5) -> 0.10012818 | D6: =B6/C6 -> 3.810038 | E6: =TDIST(ABS(D6),$B$15,2) -> 0.00024648936 | F6: =IF(E6<0.01,"Yes**",IF(E6<0.05,"Yes*","No")) -> Yes**
A7: D/E Ratio (β1) | B7: =INDEX(LINEST('Ratios Panel'!$K$5:$K$104,'Ratios Panel'!$S$5:$V$104,TRUE(),TRUE()),1,4) -> -0.077179508 | C7: =INDEX(LINEST('Ratios Panel'!$K$5:$K$104,'Ratios Panel'!$S$5:$V$104,TRUE(),TRUE()),2,4) -> 0.015666456 | D7: =B7/C7 -> -4.9264177 | E7: =TDIST(ABS(D7),$B$15,2) -> 3.5344039e-06 | F7: =IF(E7<0.01,"Yes**",IF(E7<0.05,"Yes*","No")) -> Yes**
A8: Size — ln(Total Assets) (β2) | B8: =INDEX(LINEST('Ratios Panel'!$K$5:$K$104,'Ratios Panel'!$S$5:$V$104,TRUE(),TRUE()),1,3) -> -0.031053655 | C8: =INDEX(LINEST('Ratios Panel'!$K$5:$K$104,'Ratios Panel'!$S$5:$V$104,TRUE(),TRUE()),2,3) -> 0.01235072 | D8: =B8/C8 -> -2.5143194 | E8: =TDIST(ABS(D8),$B$15,2) -> 0.013607271 | F8: =IF(E8<0.01,"Yes**",IF(E8<0.05,"Yes*","No")) -> Yes*
A9: Sales Growth (β3) | B9: =INDEX(LINEST('Ratios Panel'!$K$5:$K$104,'Ratios Panel'!$S$5:$V$104,TRUE(),TRUE()),1,2) -> 0.19638454 | C9: =INDEX(LINEST('Ratios Panel'!$K$5:$K$104,'Ratios Panel'!$S$5:$V$104,TRUE(),TRUE()),2,2) -> 0.043206705 | D9: =B9/C9 -> 4.5452329 | E9: =TDIST(ABS(D9),$B$15,2) -> 1.615008e-05 | F9: =IF(E9<0.01,"Yes**",IF(E9<0.05,"Yes*","No")) -> Yes**
A10: Tangibility (β4) | B10: =INDEX(LINEST('Ratios Panel'!$K$5:$K$104,'Ratios Panel'!$S$5:$V$104,TRUE(),TRUE()),1,1) -> 0.083546539 | C10: =INDEX(LINEST('Ratios Panel'!$K$5:$K$104,'Ratios Panel'!$S$5:$V$104,TRUE(),TRUE()),2,1) -> 0.058001378 | D10: =B10/C10 -> 1.4404233 | E10: =TDIST(ABS(D10),$B$15,2) -> 0.15303529 | F10: =IF(E10<0.01,"Yes**",IF(E10<0.05,"Yes*","No")) -> No
A12: R-squared | B12: =INDEX(LINEST('Ratios Panel'!$K$5:$K$104,'Ratios Panel'!$S$5:$V$104,TRUE(),TRUE()),3,1) -> 0.33540869
A13: Adjusted R-squared | B13: =1-(1-B12)*(B16-1)/(B16-4-1) -> 0.30742589
A14: F-statistic | B14: =INDEX(LINEST('Ratios Panel'!$K$5:$K$104,'Ratios Panel'!$S$5:$V$104,TRUE(),TRUE()),4,1) -> 11.986248
A15: Residual degrees of freedom | B15: =INDEX(LINEST('Ratios Panel'!$K$5:$K$104,'Ratios Panel'!$S$5:$V$104,TRUE(),TRUE()),4,2) -> 95
A16: Number of observations (n) | B16: =COUNT('Ratios Panel'!$K$5:$K$104) -> 100
A17: Prob (F-statistic) | B17: =FDIST(B14,4,B15) -> 6.310335e-08
A20: Model 2 (robustness): ROA as dependent variable
A21: Variable | B21: Coefficient | C21: Std. Error | D21: t-Statistic | E21: p-value | F21: Significant at 5%?
A22: Intercept (β0) | B22: =INDEX(LINEST('Ratios Panel'!$L$5:$L$104,'Ratios Panel'!$S$5:$V$104,TRUE(),TRUE()),1,5) -> 0.20865747 | C22: =INDEX(LINEST('Ratios Panel'!$L$5:$L$104,'Ratios Panel'!$S$5:$V$104,TRUE(),TRUE()),2,5) -> 0.047102469 | D22: =B22/C22 -> 4.4298628 | E22: =TDIST(ABS(D22),$B$31,2) -> 2.5235533e-05 | F22: =IF(E22<0.01,"Yes**",IF(E22<0.05,"Yes*","No")) -> Yes**
A23: D/E Ratio (β1) | B23: =INDEX(LINEST('Ratios Panel'!$L$5:$L$104,'Ratios Panel'!$S$5:$V$104,TRUE(),TRUE()),1,4) -> -0.048158813 | C23: =INDEX(LINEST('Ratios Panel'!$L$5:$L$104,'Ratios Panel'!$S$5:$V$104,TRUE(),TRUE()),2,4) -> 0.0073698414 | D23: =B23/C23 -> -6.5345793 | E23: =TDIST(ABS(D23),$B$31,2) -> 3.1559495e-09 | F23: =IF(E23<0.01,"Yes**",IF(E23<0.05,"Yes*","No")) -> Yes**
A24: Size — ln(Total Assets) (β2) | B24: =INDEX(LINEST('Ratios Panel'!$L$5:$L$104,'Ratios Panel'!$S$5:$V$104,TRUE(),TRUE()),1,3) -> -0.012267073 | C24: =INDEX(LINEST('Ratios Panel'!$L$5:$L$104,'Ratios Panel'!$S$5:$V$104,TRUE(),TRUE()),2,3) -> 0.0058100471 | D24: =B24/C24 -> -2.1113552 | E24: =TDIST(ABS(D24),$B$31,2) -> 0.037366888 | F24: =IF(E24<0.01,"Yes**",IF(E24<0.05,"Yes*","No")) -> Yes*
A25: Sales Growth (β3) | B25: =INDEX(LINEST('Ratios Panel'!$L$5:$L$104,'Ratios Panel'!$S$5:$V$104,TRUE(),TRUE()),1,2) -> 0.099294937 | C25: =INDEX(LINEST('Ratios Panel'!$L$5:$L$104,'Ratios Panel'!$S$5:$V$104,TRUE(),TRUE()),2,2) -> 0.020325373 | D25: =B25/C25 -> 4.8852702 | E25: =TDIST(ABS(D25),$B$31,2) -> 4.1775326e-06 | F25: =IF(E25<0.01,"Yes**",IF(E25<0.05,"Yes*","No")) -> Yes**
A26: Tangibility (β4) | B26: =INDEX(LINEST('Ratios Panel'!$L$5:$L$104,'Ratios Panel'!$S$5:$V$104,TRUE(),TRUE()),1,1) -> -0.029144851 | C26: =INDEX(LINEST('Ratios Panel'!$L$5:$L$104,'Ratios Panel'!$S$5:$V$104,TRUE(),TRUE()),2,1) -> 0.027285108 | D26: =B26/C26 -> -1.0681596 | E26: =TDIST(ABS(D26),$B$31,2) -> 0.28815528 | F26: =IF(E26<0.01,"Yes**",IF(E26<0.05,"Yes*","No")) -> No
A28: R-squared | B28: =INDEX(LINEST('Ratios Panel'!$L$5:$L$104,'Ratios Panel'!$S$5:$V$104,TRUE(),TRUE()),3,1) -> 0.45611262
A29: Adjusted R-squared | B29: =1-(1-B28)*(B32-1)/(B32-4-1) -> 0.4332121
A30: F-statistic | B30: =INDEX(LINEST('Ratios Panel'!$L$5:$L$104,'Ratios Panel'!$S$5:$V$104,TRUE(),TRUE()),4,1) -> 19.917128
A31: Residual degrees of freedom | B31: =INDEX(LINEST('Ratios Panel'!$L$5:$L$104,'Ratios Panel'!$S$5:$V$104,TRUE(),TRUE()),4,2) -> 95
A32: Number of observations (n) | B32: =COUNT('Ratios Panel'!$L$5:$L$104) -> 100
A33: Prob (F-statistic) | B33: =FDIST(B30,4,B31) -> 6.1949666e-12
A36: Model 3 (COVID control): ROE with a COVID-19 dummy (FY19-20, FY20-21 = 1)
A37: Variable | B37: Coefficient | C37: Std. Error | D37: t-Statistic | E37: p-value | F37: Significant at 5%?
A38: Intercept (β0) | B38: =INDEX(LINEST('Ratios Panel'!$K$5:$K$104,'Ratios Panel'!$S$5:$W$104,TRUE(),TRUE()),1,6) -> 0.38378201 | C38: =INDEX(LINEST('Ratios Panel'!$K$5:$K$104,'Ratios Panel'!$S$5:$W$104,TRUE(),TRUE()),2,6) -> 0.10121997 | D38: =B38/C38 -> 3.7915642 | E38: =TDIST(ABS(D38),$B$48,2) -> 0.00026439464 | F38: =IF(E38<0.01,"Yes**",IF(E38<0.05,"Yes*","No")) -> Yes**
A39: D/E Ratio (β1) | B39: =INDEX(LINEST('Ratios Panel'!$K$5:$K$104,'Ratios Panel'!$S$5:$W$104,TRUE(),TRUE()),1,5) -> -0.077227239 | C39: =INDEX(LINEST('Ratios Panel'!$K$5:$K$104,'Ratios Panel'!$S$5:$W$104,TRUE(),TRUE()),2,5) -> 0.015747473 | D39: =B39/C39 -> -4.9041036 | E39: =TDIST(ABS(D39),$B$48,2) -> 3.9207445e-06 | F39: =IF(E39<0.01,"Yes**",IF(E39<0.05,"Yes*","No")) -> Yes**
A40: Size — ln(Total Assets) (β2) | B40: =INDEX(LINEST('Ratios Panel'!$K$5:$K$104,'Ratios Panel'!$S$5:$W$104,TRUE(),TRUE()),1,4) -> -0.031235297 | C40: =INDEX(LINEST('Ratios Panel'!$K$5:$K$104,'Ratios Panel'!$S$5:$W$104,TRUE(),TRUE()),2,4) -> 0.012443169 | D40: =B40/C40 -> -2.5102364 | E40: =TDIST(ABS(D40),$B$48,2) -> 0.013773911 | F40: =IF(E40<0.01,"Yes**",IF(E40<0.05,"Yes*","No")) -> Yes*
A41: Sales Growth (β3) | B41: =INDEX(LINEST('Ratios Panel'!$K$5:$K$104,'Ratios Panel'!$S$5:$W$104,TRUE(),TRUE()),1,3) -> 0.19369193 | C41: =INDEX(LINEST('Ratios Panel'!$K$5:$K$104,'Ratios Panel'!$S$5:$W$104,TRUE(),TRUE()),2,3) -> 0.045264731 | D41: =B41/C41 -> 4.2790917 | E41: =TDIST(ABS(D41),$B$48,2) -> 4.5137975e-05 | F41: =IF(E41<0.01,"Yes**",IF(E41<0.05,"Yes*","No")) -> Yes**
A42: Tangibility (β4) | B42: =INDEX(LINEST('Ratios Panel'!$K$5:$K$104,'Ratios Panel'!$S$5:$W$104,TRUE(),TRUE()),1,2) -> 0.084360639 | C42: =INDEX(LINEST('Ratios Panel'!$K$5:$K$104,'Ratios Panel'!$S$5:$W$104,TRUE(),TRUE()),2,2) -> 0.058423045 | D42: =B42/C42 -> 1.4439617 | E42: =TDIST(ABS(D42),$B$48,2) -> 0.15207452 | F42: =IF(E42<0.01,"Yes**",IF(E42<0.05,"Yes*","No")) -> No
A43: COVID dummy (β5) | B43: =INDEX(LINEST('Ratios Panel'!$K$5:$K$104,'Ratios Panel'!$S$5:$W$104,TRUE(),TRUE()),1,1) -> -0.00455413 | C43: =INDEX(LINEST('Ratios Panel'!$K$5:$K$104,'Ratios Panel'!$S$5:$W$104,TRUE(),TRUE()),2,1) -> 0.021600859 | D43: =B43/C43 -> -0.21083096 | E43: =TDIST(ABS(D43),$B$48,2) -> 0.83347555 | F43: =IF(E43<0.01,"Yes**",IF(E43<0.05,"Yes*","No")) -> No
A45: R-squared | B45: =INDEX(LINEST('Ratios Panel'!$K$5:$K$104,'Ratios Panel'!$S$5:$W$104,TRUE(),TRUE()),3,1) -> 0.3357228
A46: Adjusted R-squared | B46: =1-(1-B45)*(B49-1)/(B49-5-1) -> 0.30038891
A47: F-statistic | B47: =INDEX(LINEST('Ratios Panel'!$K$5:$K$104,'Ratios Panel'!$S$5:$W$104,TRUE(),TRUE()),4,1) -> 9.5014381
A48: Residual degrees of freedom | B48: =INDEX(LINEST('Ratios Panel'!$K$5:$K$104,'Ratios Panel'!$S$5:$W$104,TRUE(),TRUE()),4,2) -> 94
A49: Number of observations (n) | B49: =COUNT('Ratios Panel'!$K$5:$K$104) -> 100
A50: Prob (F-statistic) | B50: =FDIST(B47,5,B48) -> 2.3310015e-07
A52: Reading: the D/E coefficient is negative and significant in all three models. The COVID dummy is not significant, and adding it leaves the D/E coefficient virtually unchanged, so the COVID years do not drive the result. Results match the R cross-check to four decimal places.

Sheet ET Wealth Link
A1: ET Wealth Article Link — 'Textile stocks weave a comeback' (Bhardwaj, 2026)
A2: Source: Sameer Bhardwaj, 'Textile stocks weave a comeback: Trade deals and sourcing shift from China are reviving the sector that investors had written off', The Economic Times Wealth, August 2026. BLUE figures are typed in from the article (taken as reported, not independently verified). GREEN figures link to other sheets; BLACK figures are formulas on this sheet. Stocks mentioned in the article are not investment recommendations. Used in report Sections 1.2 and 5.5.
A4: A. Sector context reported in the article
A5: Item | B5: Value | C5: Unit | D5: Source cited in the article
A6: Indian textile & apparel market, 2025-26 | B6: 190 | C6: US$ billion | D6: Press Information Bureau release, June 2026
A7: Projected market size, 2030 | B7: 350 | C7: US$ billion | D7: Press Information Bureau release, June 2026
A8: Projected growth multiple, 2025-26 to 2030 | B8: =B7/B6 -> 1.8421053 | C8: times | D8: Formula: 2030 size ÷ 2025-26 size
A9: Equal-weighted return, 65 listed textile stocks (mkt cap > ₹500 cr), 2026 to 10 Aug | B9: 0.215 | C9: % | D9: Article's own analysis
A10: Nifty 500 Equal Weight Index return, same period | B10: 0.065 | C10: % | D10: Article's own analysis
A11: Textile stocks' outperformance | B11: =B9-B10 -> 0.15 | C11: % points | D11: Formula: textile return − index return
A12: Textile stocks that outperformed the benchmark | B12: 39 | C12: of 65 | D12: Article's own analysis
A13: Share of textile stocks outperforming | B13: =B12/65 -> 0.6 | C13: % | D13: Formula: 39 ÷ 65
A14: India's cotton output, 2025-26 (world's 2nd largest producer) | B14: 5 | C14: million tonnes (approx.) | D14: Article
A15: India's spinning capacity (world's 2nd largest) | B15: 43 | C15: million spindles (approx.) | D15: Motilal Oswal
A17: B. Share of Indian textile & apparel exports by destination, 2025-26 (Source: 360 One Capital, as cited in the article)
A18: Destination | B18: Share of exports
A19: USA | B19: 0.305
A20: European Union | B20: 0.295
A21: UK | B21: 0.095
A22: UAE | B22: 0.082
A23: Others | B23: 0.224
A24: Total (check) | B24: =SUM(B19:B23) -> 1.001 | C24: Sums to 100.1% because the article's shares are rounded.
A25: USA + EU combined | B25: =B19+B20 -> 0.6
A27: C. Analyst recommendations on the article's three picks (Source: Bloomberg, as on 10 August 2026)
A28: Company | B28: Buy | C28: Hold | D28: Sell | E28: Total ratings | F28: % Buy | G28: Share price (₹) | H28: Revenue growth, June 2026 qtr (YoY) | I28: Article highlight
A29: KPR Mill | B29: 12 | C29: 2 | D29: 0 | E29: =SUM(B29:D29) -> 14 | F29: =B29/E29 -> 0.85714286 | G29: 1086 | H29: 0.096 | I29: Branded apparel expansion; upcoming Odisha garmenting facility
A30: Welspun Living | B30: 11 | C30: 2 | D30: 0 | E30: =SUM(B30:D30) -> 13 | F30: =B30/E30 -> 0.84615385 | G30: 164 | H30: 0.24 | I30: Ties with major US retailers; gains from UK/EU FTAs (growth is consolidated)
A31: Indo Count Industries | B31: 8 | C31: 2 | D31: 0 | E31: =SUM(B31:D31) -> 10 | F31: =B31/E31 -> 0.8 | G31: 425 | H31: 0.26 | I31: Leader in bed-linen exports to USA; capacity allows growth without big capex
A32: Quarterly revenue growth is partly consolidated and is NOT comparable with this study's annual standalone data.
A34: D. Capital structure evidence for the three picks (live formulas from Descriptive Stats and Ratios Panel)
A35: Company | B35: Mean D/E | C35: D/E rank (1 = lowest of 10) | D35: D/E FY15-16 | E35: D/E FY24-25 | F35: Change in D/E | G35: Mean ROE | H35: ROE rank (1 = highest of 10) | I35: Mean ROA | J35: SD of D/E
A36: =A29 -> KPR Mill | B36: =INDEX('Descriptive Stats'!$B$4:$B$13,MATCH($A36,'Descriptive Stats'!$A$4:$A$13,0)) -> 0.26862496 | C36: =RANK(B36,'Descriptive Stats'!$B$4:$B$13,1) -> 1 | D36: =AVERAGEIFS('Ratios Panel'!$J$5:$J$104,'Ratios Panel'!$A$5:$A$104,$A36,'Ratios Panel'!$B$5:$B$104,"FY15-16") -> 0.60142712 | E36: =AVERAGEIFS('Ratios Panel'!$J$5:$J$104,'Ratios Panel'!$A$5:$A$104,$A36,'Ratios Panel'!$B$5:$B$104,"FY24-25") -> 0.0625 | F36: =E36-D36 -> -0.53892712 | G36: =INDEX('Descriptive Stats'!$F$4:$F$13,MATCH($A36,'Descriptive Stats'!$A$4:$A$13,0)) -> 0.1979938 | H36: =RANK(G36,'Descriptive Stats'!$F$4:$F$13,0) -> 1 | I36: =INDEX('Descriptive Stats'!$G$4:$G$13,MATCH($A36,'Descriptive Stats'!$A$4:$A$13,0)) -> 0.14401401 | J36: =INDEX('Descriptive Stats'!$C$4:$C$13,MATCH($A36,'Descriptive Stats'!$A$4:$A$13,0)) -> 0.1757145
A37: =A30 -> Welspun Living | B37: =INDEX('Descriptive Stats'!$B$4:$B$13,MATCH($A37,'Descriptive Stats'!$A$4:$A$13,0)) -> 0.78091842 | C37: =RANK(B37,'Descriptive Stats'!$B$4:$B$13,1) -> 7 | D37: =AVERAGEIFS('Ratios Panel'!$J$5:$J$104,'Ratios Panel'!$A$5:$A$104,$A37,'Ratios Panel'!$B$5:$B$104,"FY15-16") -> 1.3512375 | E37: =AVERAGEIFS('Ratios Panel'!$J$5:$J$104,'Ratios Panel'!$A$5:$A$104,$A37,'Ratios Panel'!$B$5:$B$104,"FY24-25") -> 0.42970551 | F37: =E37-D37 -> -0.92153199 | G37: =INDEX('Descriptive Stats'!$F$4:$F$13,MATCH($A37,'Descriptive Stats'!$A$4:$A$13,0)) -> 0.1428065 | H37: =RANK(G37,'Descriptive Stats'!$F$4:$F$13,0) -> 5 | I37: =INDEX('Descriptive Stats'!$G$4:$G$13,MATCH($A37,'Descriptive Stats'!$A$4:$A$13,0)) -> 0.063211865 | J37: =INDEX('Descriptive Stats'!$C$4:$C$13,MATCH($A37,'Descriptive Stats'!$A$4:$A$13,0)) -> 0.37343586
A38: =A31 -> Indo Count Industries | B38: =INDEX('Descriptive Stats'!$B$4:$B$13,MATCH($A38,'Descriptive Stats'!$A$4:$A$13,0)) -> 0.45668052 | C38: =RANK(B38,'Descriptive Stats'!$B$4:$B$13,1) -> 4 | D38: =AVERAGEIFS('Ratios Panel'!$J$5:$J$104,'Ratios Panel'!$A$5:$A$104,$A38,'Ratios Panel'!$B$5:$B$104,"FY15-16") -> 0.55464927 | E38: =AVERAGEIFS('Ratios Panel'!$J$5:$J$104,'Ratios Panel'!$A$5:$A$104,$A38,'Ratios Panel'!$B$5:$B$104,"FY24-25") -> 0.47429593 | F38: =E38-D38 -> -0.080353334 | G38: =INDEX('Descriptive Stats'!$F$4:$F$13,MATCH($A38,'Descriptive Stats'!$A$4:$A$13,0)) -> 0.17577552 | H38: =RANK(G38,'Descriptive Stats'!$F$4:$F$13,0) -> 2 | I38: =INDEX('Descriptive Stats'!$G$4:$G$13,MATCH($A38,'Descriptive Stats'!$A$4:$A$13,0)) -> 0.096709696 | J38: =INDEX('Descriptive Stats'!$C$4:$C$13,MATCH($A38,'Descriptive Stats'!$A$4:$A$13,0)) -> 0.13300681
A40: E. ET Wealth picks vs. the other seven sample companies (pooled firm-years)
A41: Group | B41: Firm-years (n) | C41: Mean D/E | D41: Mean ROE | E41: Mean ROA
A42: ET Wealth picks (3 companies) | B42: =SUMPRODUCT(--ISNUMBER(MATCH('Ratios Panel'!$A$5:$A$104,$A$29:$A$31,0))) -> 30 | C42: =SUMPRODUCT(ISNUMBER(MATCH('Ratios Panel'!$A$5:$A$104,$A$29:$A$31,0))*'Ratios Panel'!$J$5:$J$104)/$B$42 -> 0.50207463 | D42: =SUMPRODUCT(ISNUMBER(MATCH('Ratios Panel'!$A$5:$A$104,$A$29:$A$31,0))*'Ratios Panel'!$K$5:$K$104)/$B$42 -> 0.17219194 | E42: =SUMPRODUCT(ISNUMBER(MATCH('Ratios Panel'!$A$5:$A$104,$A$29:$A$31,0))*'Ratios Panel'!$L$5:$L$104)/$B$42 -> 0.10131186
A43: Other seven companies | B43: =COUNTA('Ratios Panel'!$A$5:$A$104)-B42 -> 70 | C43: =(SUM('Ratios Panel'!$J$5:$J$104)-C42*$B$42)/$B$43 -> 0.85975565 | D43: =(SUM('Ratios Panel'!$K$5:$K$104)-D42*$B$42)/$B$43 -> 0.10688763 | E43: =(SUM('Ratios Panel'!$L$5:$L$104)-E42*$B$42)/$B$43 -> 0.056545838
A44: Pooled sample (10 companies) | B44: =COUNTA('Ratios Panel'!$A$5:$A$104) -> 100 | C44: =AVERAGE('Ratios Panel'!$J$5:$J$104) -> 0.75245135 | D44: =AVERAGE('Ratios Panel'!$K$5:$K$104) -> 0.12647892 | E44: =AVERAGE('Ratios Panel'!$L$5:$L$104) -> 0.069975643
A45: Difference (picks − others) | C45: =C42-C43 -> -0.35768102 | D45: =D42-D43 -> 0.065304312 | E45: =E42-E43 -> 0.044766017
A47: F. Welch two-sample t-test: is the difference statistically significant?
A48: Variable | B48: Mean — picks | C48: Mean — others | D48: Variance — picks | E48: Variance — others | F48: t-statistic (picks − others) | G48: Welch df | H48: p-value (two-tailed) | I48: Significant at 5%?
A49: D/E ratio | B49: =C42 -> 0.50207463 | C49: =C43 -> 0.85975565 | D49: =SUMPRODUCT(ISNUMBER(MATCH('Ratios Panel'!$A$5:$A$104,$A$29:$A$31,0))*('Ratios Panel'!$J$5:$J$104-B49)^2)/($B$42-1) -> 0.10466617 | E49: =SUMPRODUCT((1-ISNUMBER(MATCH('Ratios Panel'!$A$5:$A$104,$A$29:$A$31,0)))*('Ratios Panel'!$J$5:$J$104-C49)^2)/($B$43-1) -> 0.43527357 | F49: =(B49-C49)/SQRT(D49/$B$42+E49/$B$43) -> -3.6303785 | G49: =(D49/$B$42+E49/$B$43)^2/((D49/$B$42)^2/($B$42-1)+(E49/$B$43)^2/($B$43-1)) -> 96.139547 | H49: =TDIST(ABS(F49),G49,2) -> 0.00045622294 | I49: =IF(H49<0.05,"Yes","No") -> Yes
A50: ROE | B50: =D42 -> 0.17219194 | C50: =D43 -> 0.10688763 | D50: =SUMPRODUCT(ISNUMBER(MATCH('Ratios Panel'!$A$5:$A$104,$A$29:$A$31,0))*('Ratios Panel'!$K$5:$K$104-B50)^2)/($B$42-1) -> 0.0061025081 | E50: =SUMPRODUCT((1-ISNUMBER(MATCH('Ratios Panel'!$A$5:$A$104,$A$29:$A$31,0)))*('Ratios Panel'!$K$5:$K$104-C50)^2)/($B$43-1) -> 0.010150862 | F50: =(B50-C50)/SQRT(D50/$B$42+E50/$B$43) -> 3.4985216 | G50: =(D50/$B$42+E50/$B$43)^2/((D50/$B$42)^2/($B$42-1)+(E50/$B$43)^2/($B$43-1)) -> 70.110068 | H50: =TDIST(ABS(F50),G50,2) -> 0.00081763662 | I50: =IF(H50<0.05,"Yes","No") -> Yes
A51: ROA | B51: =E42 -> 0.10131186 | C51: =E43 -> 0.056545838 | D51: =SUMPRODUCT(ISNUMBER(MATCH('Ratios Panel'!$A$5:$A$104,$A$29:$A$31,0))*('Ratios Panel'!$L$5:$L$104-B51)^2)/($B$42-1) -> 0.0025032255 | E51: =SUMPRODUCT((1-ISNUMBER(MATCH('Ratios Panel'!$A$5:$A$104,$A$29:$A$31,0)))*('Ratios Panel'!$L$5:$L$104-C51)^2)/($B$43-1) -> 0.0021274111 | F51: =(B51-C51)/SQRT(D51/$B$42+E51/$B$43) -> 4.1958064 | G51: =(D51/$B$42+E51/$B$43)^2/((D51/$B$42)^2/($B$42-1)+(E51/$B$43)^2/($B$43-1)) -> 51.122104 | H51: =TDIST(ABS(F51),G51,2) -> 0.00010868555 | I51: =IF(H51<0.05,"Yes","No") -> Yes
A52: Welch's test does not assume equal variances. TDIST rounds the degrees of freedom down to a whole number, so p-values can differ very slightly from statistical software. Caution: the picks are only 3 companies and firm-years from the same company are not independent, so treat these tests as supporting evidence rather than proof.
A55: G. Interpretation (see report Section 5.5)
A56: KPR Mill | B56: Lowest mean D/E and highest mean ROE in the sample; D/E cut to near zero by FY24-25. Classic Pecking Order behaviour: growth funded from retained earnings, leaving debt capacity for the Odisha facility and branded-apparel expansion.
A57: Indo Count Industries | B57: Second-highest ROE with below-average, very stable leverage (lowest SD of D/E in the sample). Spare capacity means little need for new debt.
A58: Welspun Living | B58: Mean D/E slightly above the pooled average and ROE only modestly above average, but the largest deleveraging of the three (D/E down about two-thirds). The optimism rests on its improved balance sheet and FTA-exposed US/UK/EU retail ties.
A59: Overall | B59: As a group the picks are less levered and more profitable than the other seven firms (Sections E–F), consistent with the report's regression finding that higher D/E goes with lower ROE — balance-sheet support for the article's optimism.

Sheet Theory Formulas
A1: Capital Structure Theories — Key Formulas
A2: Symbols: EBIT = earnings before interest & tax; I = interest (= Kd × D); t = tax rate; D = value of debt; S (or E) = value of equity; V = S + D; Ke = cost of equity; Kd = cost of debt; Ko = overall cost of capital (WACC); Vu / VL = value of unlevered / levered firm.
A4: Theory | B4: Key formula(s) | C4: What it says about debt | D4: Relevance?
A5: Net Income (NI) Approach | B5: S = (EBIT − I) ÷ Ke V = S + D Ko = EBIT ÷ V | C5: Ke and Kd stay constant, so more (cheaper) debt lowers Ko and raises V. | D5: Relevant
A6: Net Operating Income (NOI) Approach | B6: V = EBIT ÷ Ko S = V − D Ke = (EBIT − I) ÷ S | C6: Ko stays constant; Ke rises with debt, so V does not change. | D6: Irrelevant
A7: Traditional Approach | B7: Ko = Ke × (S ÷ V) + Kd × (D ÷ V) | C7: Moderate debt first lowers Ko; beyond a point Ke and Kd rise. Optimal structure = where Ko is minimum. | D7: Relevant (optimum exists)
A8: MM Approach — without taxes | B8: Prop. I: VL = Vu = EBIT ÷ Ko Prop. II: Ke = Ko + (Ko − Kd) × D ÷ S | C8: Value is independent of debt; arbitrage keeps VL = Vu. | D8: Irrelevant
A9: MM Approach — with taxes | B9: Vu = EBIT × (1 − t) ÷ Ke(u) VL = Vu + D × t Ke(L) = Ke(u) + (Ke(u) − Kd) × (1 − t) × D ÷ S Ko = Ke × S ÷ V + Kd × (1 − t) × D ÷ V | C9: Interest is tax-deductible, so each rupee of debt adds a tax shield (D × t) to firm value. | D9: Relevant (favours debt)
A10: Trade-off Theory | B10: VL = Vu + PV of tax shield − PV of financial distress costs | C10: Borrow until the extra tax saving equals the extra expected cost of distress. | D10: Relevant (optimum exists)
A11: Pecking Order Theory | B11: No formula (conceptual) | C11: Order of financing: retained earnings → debt → new equity. Profitable firms need less debt. | D11: Behavioural
A12: Agency Theory | B12: No formula (conceptual) | C12: Debt disciplines managers by committing free cash flow to interest; too much debt creates shareholder–lender conflict. | D12: Behavioural
A15: Worked example — Welspun Living, FY2024-25 (EBIT and debt from Raw Data; rates are ASSUMED for illustration, in blue)
A16: EBIT (Operating Profit), Rs cr | B16: ='Raw Data'!E26 -> 907
A17: Debt (Borrowings), D, Rs cr | B17: ='Raw Data'!I26 -> 1678
A18: Cost of debt, Kd (assumed) | B18: 0.09
A19: Cost of equity for NI approach, Ke (assumed) | B19: 0.14
A20: Overall cost of capital / Ke of unlevered firm, Ko (assumed) | B20: 0.12
A21: Corporate tax rate, t (Sec. 115BAA effective rate) | B21: 0.2517
A22: PV of financial distress costs, Rs cr (assumed) | B22: 150
A24: Approach | B24: Calculation | C24: Result | D24: Formula used
A25: Common | B25: Interest, I = Kd × D | C25: =$B$18*$B$17 -> 151.02 | D25: I = Kd × D
A26: NI Approach | B26: Value of equity, S | C26: =($B$16-C25)/$B$19 -> 5399.8571 | D26: S = (EBIT − I) ÷ Ke
A27: NI Approach | B27: Value of firm, V | C27: =C26+$B$17 -> 7077.8571 | D27: V = S + D
A28: NI Approach | B28: Overall cost of capital, Ko | C28: =$B$16/C27 -> 0.12814613 | D28: Ko = EBIT ÷ V
A29: NOI Approach | B29: Value of firm, V | C29: =$B$16/$B$20 -> 7558.3333 | D29: V = EBIT ÷ Ko
A30: NOI Approach | B30: Value of equity, S | C30: =C29-$B$17 -> 5880.3333 | D30: S = V − D
A31: NOI Approach | B31: Cost of equity, Ke | C31: =($B$16-C25)/C30 -> 0.12856074 | D31: Ke = (EBIT − I) ÷ S
A32: MM (no tax), Prop. II | B32: Ke check | C32: =$B$20+($B$20-$B$18)*$B$17/C30 -> 0.12856074 | D32: Ke = Ko + (Ko − Kd) × D ÷ S (= NOI result)
A33: MM (with tax) | B33: Value of unlevered firm, Vu | C33: =$B$16*(1-$B$21)/$B$20 -> 5655.9008 | D33: Vu = EBIT(1 − t) ÷ Ke(u)
A34: MM (with tax) | B34: Tax shield, D × t | C34: =$B$17*$B$21 -> 422.3526 | D34: D × t
A35: MM (with tax) | B35: Value of levered firm, VL | C35: =C33+C34 -> 6078.2534 | D35: VL = Vu + D × t
A36: MM (with tax) | B36: Value of equity, S | C36: =C35-$B$17 -> 4400.2534 | D36: S = VL − D
A37: MM (with tax) | B37: Cost of equity, Ke(L) | C37: =$B$20+($B$20-$B$18)*(1-$B$21)*$B$17/C36 -> 0.12856074 | D37: Ke(L) = Ke(u) + (Ke(u) − Kd)(1 − t) × D ÷ S
A38: MM (with tax) | B38: WACC, Ko | C38: =C37*C36/C35+$B$18*(1-$B$21)*$B$17/C35 -> 0.1116617 | D38: Ko = Ke × S ÷ V + Kd(1 − t) × D ÷ V
A39: Trade-off | B39: Value of levered firm, VL | C39: =C33+C34-$B$22 -> 5928.2534 | D39: VL = Vu + PV tax shield − PV distress costs
A41: Checks: the NOI cost of equity equals MM Proposition II (no tax); with taxes, WACC = EBIT(1 − t) ÷ VL, and it is lower than Ko because of the tax shield. Pecking Order and Agency Theory are conceptual and have no formula; they are tested against the data in the report instead (Section 7).

Sheet Formulas Used
A1: Formulas Used in This Workbook
A2: Every ratio and statistic below is a live Excel formula, not a typed-in number — open any cell in Ratios Panel, Descriptive Stats, Correlation Matrix or a company sheet and the formula bar will show exactly this. Cell references below are illustrative (row 5 of Ratios Panel); the same formula pattern repeats down all 100 rows.
A4: 1. Core Ratios — Ratios Panel sheet (row 5 = KPR Mill, FY2015-16)
A5: Item | B5: Definition | C5: Excel Formula (as used in this workbook) | D5: Where to find it
A6: Total Equity | B6: Equity Capital + Reserves & Surplus | C6: ='Raw Data'!G5+'Raw Data'!H5 | D6: Ratios Panel, column F
A7: D/E Ratio | B7: Borrowings ÷ Total Equity | C7: =G5/F5 | D7: Ratios Panel, column J
A8: ROE | B8: Net Profit ÷ Total Equity | C8: =E5/F5 | D8: Ratios Panel, column K
A9: ROA | B9: Net Profit ÷ Total Assets | C9: =E5/H5 | D9: Ratios Panel, column L
A10: Size | B10: LN(Total Assets) | C10: =LN(H5) | D10: Ratios Panel, column M
A11: Sales Growth % | B11: (Sales this year − Sales last year) ÷ Sales last year | C11: =(C5-'Raw Data'!D4)/'Raw Data'!D4 | D11: Ratios Panel, column N
A12: Tangibility | B12: Fixed Assets ÷ Total Assets | C12: =I5/H5 | D12: Ratios Panel, column O
A13: EPS | B13: As reported by Screener.in (split-adjusted); not derived within the workbook | C13: ='Raw Data'!L5 | D13: Ratios Panel, column P
A15: 2. Descriptive Statistics — by company (Descriptive Stats sheet)
A16: Item | B16: Definition | C16: Excel Formula (as used in this workbook) | D16: Where to find it
A17: Mean D/E (per company) | B17: Average D/E across that company's 10 years | C17: =AVERAGEIF('Ratios Panel'!$A$5:$A$104,A5,'Ratios Panel'!$J$5:$J$104) | D17: Descriptive Stats, column B
A18: SD D/E (per company) | B18: Standard deviation of D/E across that company's 10 years | C18: =SQRT(SUMPRODUCT(('Ratios Panel'!$A$5:$A$104=A5)*('Ratios Panel'!$J$5:$J$104-B5)^2)/(COUNTIF('Ratios Panel'!$A$5:$A$104,A5)-1)) | D18: Descriptive Stats, column C
A19: Min / Max D/E | B19: Lowest / highest D/E for that company across its 10 years | C19: =MINIFS('Ratios Panel'!$J$5:$J$104,'Ratios Panel'!$A$5:$A$104,A5) | D19: Descriptive Stats, columns D & E
A20: Pooled Mean / SD / Min / Max | B20: Same statistic across all 100 firm-years at once | C20: =AVERAGE('Ratios Panel'!$J$5:$J$104) (and STDEV / MIN / MAX) | D20: Descriptive Stats, POOLED row
A22: 3. Correlation Matrix
A23: Item | B23: Definition | C23: Excel Formula (as used in this workbook) | D23: Where to find it
A24: Pearson correlation | B24: Correlation between any two variables across all 100 firm-years, e.g. D/E and ROE | C24: =CORREL('Ratios Panel'!$J$5:$J$104,'Ratios Panel'!$K$5:$K$104) | D24: Correlation Matrix, each cell
A26: 4. Company Sheets (e.g. 'KPR Mill' sheet) — same pattern as Ratios Panel, self-contained
A27: Item | B27: Definition | C27: Excel Formula (as used in this workbook) | D27: Where to find it
A28: D/E, ROE, ROA, Size, Growth, Tangibility | B28: Identical formulas to Section 1 above, but referencing only that company's own 10 rows on its own sheet | C28: e.g. =F10/E10 (Total Equity in col F, Borrowings in col G on that sheet) | D28: Each company sheet, its own ratio table
A29: 10-Yr Average row | B29: Mean of each ratio across that company's own 10 years | C29: =AVERAGE(J5:J14) | D29: Bottom of each company sheet
A30: SD (10-yr) row | B30: Standard deviation of D/E, ROE, ROA and EPS for that one company | C30: =STDEV(J5:J14) | D30: Bottom of each company sheet
A32: 5. Regression Analysis — Excel LINEST (Regression Output sheet)
A33: Multiple regression | B33: LINEST fits all four X variables at once. It returns coefficients in REVERSE order of the X columns; row 2 holds standard errors. | C33: =INDEX(LINEST('Ratios Panel'!$K$5:$K$104,'Ratios Panel'!$S$5:$V$104,TRUE,TRUE),1,4) ← D/E coefficient | D33: Regression Output, Model 1
A34: t-statistic and p-value | B34: t = coefficient ÷ standard error; two-tailed p-value from the t-distribution | C34: =B6/C6 and =TDIST(ABS(D6),residual df,2) | D34: Regression Output, columns D–E
A35: R-squared, F | B35: Taken from rows 3 and 4 of the LINEST output | C35: =INDEX(LINEST(...),3,1) and =INDEX(LINEST(...),4,1) | D35: Regression Output, model summary
A36: Liquidity (CR proxy) | B36: Other Assets ÷ Other Liabilities | C36: ='Raw Data'!M6/'Raw Data'!N6 | D36: Ratios Panel, column Q
A37: COVID dummy | B37: 1 for FY19-20 and FY20-21, otherwise 0 | C37: =IF(OR(B5="FY19-20",B5="FY20-21"),1,0) | D37: Ratios Panel, column R
A39: 6. ET Wealth Link sheet — comparing the article's three picks with the rest of the sample
A40: Item | B40: Definition | C40: Excel Formula (as used in this workbook) | D40: Where to find it
A41: Company lookup | B41: Pulls a company's 10-year mean from Descriptive Stats | C41: =INDEX('Descriptive Stats'!$B$4:$B$13,MATCH($A36,'Descriptive Stats'!$A$4:$A$13,0)) | D41: ET Wealth Link, section D
A42: Rank of D/E | B42: Position among the 10 firms (1 = least debt) | C42: =RANK(B36,'Descriptive Stats'!$B$4:$B$13,1) | D42: ET Wealth Link, column C
A43: Group mean (picks) | B43: Average over the 30 firm-years of the 3 picks | C43: =SUMPRODUCT(ISNUMBER(MATCH('Ratios Panel'!$A$5:$A$104,$A$29:$A$31,0))*'Ratios Panel'!$J$5:$J$104)/$B$42 | D43: ET Wealth Link, section E
A44: Welch t-statistic | B44: Difference in means ÷ its standard error (unequal variances) | C44: =(B49-C49)/SQRT(D49/$B$42+E49/$B$43) | D44: ET Wealth Link, section F
A45: p-value | B45: Two-tailed probability from the t-distribution | C45: =TDIST(ABS(F49),G49,2) | D45: ET Wealth Link, section F
