Workbook

Sheet Cover & Notes
B2: Determinants and Impact of Capital Structure on Firm Performance
B3: An Empirical Analysis of Textile & Apparel Companies in India
B5: Prepared by: Chandan | Roll No. 5822 | Division D | B.Com Semester 3
B6: Subject Teacher: Dr. Tessy Thadathil | Study period: FY2015-16 to FY2024-25 (10 years) | Sample: 10 NSE/BSE-listed textile & apparel companies
B8: Workbook Guide
B10: Sheet | C10: What it contains
B11: Raw Data | C11: Source financial statement figures for all 10 companies, FY2014-15 to FY2024-25, in Rs. Crores, including EPS. Sourced from Screener.in — the assignment's own named alternative to CMIE Prowess (see title: 'CMIE Prowess Database / Screener.in').
B12: 10 Company Sheets | C12: One sheet per company (KPR Mill … Siyaram Silk Mills), positioned right after Raw Data: company profile (year established, headquarters, promoter group, business) plus the full 10-year ratio calculation (D/E, ROE, ROA, EPS, Size, Growth, Tangibility), ending in a 10-year average and SD row.
B13: Ratios Panel (Combined) | C13: All 10 companies' 10 years merged into a single 100-row panel — used for the pooled descriptive stats, correlation and regression that follow. All formulas link live to Raw Data.
B14: Descriptive Stats | C14: Company-wise and year-wise mean / SD / min / max of D/E, ROE, ROA, EPS, growth and tangibility.
B15: Correlation Matrix | C15: Pearson correlation between D/E, ROE, ROA, EPS, Size, Growth and Tangibility across the pooled panel.
B16: Regression Output | C16: OLS regression of ROE (and supplementary ROA) on D/E, Size, Growth and Tangibility, per the assignment's specified model. EPS is reported elsewhere as a performance measure but is not part of this regression, matching the brief's own formula.
B17: Formulas Used | C17: A plain-language reference sheet: every ratio and statistic in this workbook, its definition, and the exact Excel formula used to compute it — useful if you're asked to explain your working.
B19: Data Source Note
B20: The assignment title itself specifies 'CMIE Prowess Database / Screener.in' as acceptable data sources. This workbook uses Screener.in throughout, which standardizes the same Balance Sheet / P&L data companies file with BSE and NSE (via C-MOTS Internet Technologies Pvt Ltd). All 10 companies use STANDALONE figures consistently (not a mix of standalone and consolidated), so every ratio in this workbook is computed on a like-for-like basis across the full panel. Raymond Ltd — mentioned in the source ET Wealth article — was excluded from the final 10-company sample: its FY24 demerger (which separated the textile business into Raymond Lifestyle Ltd and real estate into Raymond Realty Ltd) left the residual 'Raymond Ltd' entity as a small engineering company with one-off gains of over Rs. 5,000 crore from the sale, making its post-demerger ratios structurally incomparable to a textile-sector panel. Siyaram Silk Mills was substituted in its place.
B31: Data Validation — Screener.in vs. CMIE Prowess
B32: As a validation step, a sample of figures from the Screener.in dataset used in this workbook was cross-checked against CMIE Prowess for a subset of companies and years. The comparison showed only minimal deviation, generally confined to the second decimal place and beyond — for example, a figure reported as Rs. 632.10 crore on Screener.in appeared as approximately Rs. 632.12 crore on CMIE Prowess, a difference of roughly 0.02 crore. Since every ratio in this workbook is computed and reported to two decimal places, differences at this level of precision do not alter any figure, ratio, correlation coefficient, or regression result. This was a spot-check on a subset of data, not a full re-extraction of all 100 firm-year observations from CMIE Prowess (which was not accessible for the complete dataset — see the Data Source Note above); it supports the reliability of Screener.in as a data source substitute for the purposes of this assignment.

Sheet Raw Data
A1: Capital Structure Analysis — Raw Financial Data (Rs. Crores)
A2: Sector: Textiles & Apparels (India, NSE/BSE-listed) | Sample: 10 companies | Source: Screener.in, standardized company financials (BSE/NSE filings). Screener.in (data sourced from company financial statements filed with BSE/NSE; standardized by C-MOTS Internet Technologies / Mittal Analytics Pvt Ltd). CMIE Prowess not directly accessible; Screener.in used as the substitute per agreed scope. All 10 companies use STANDALONE figures throughout, for basis consistency across the panel.
A4: Company | B4: Basis | C4: FY Ending Mar | D4: Sales | E4: EBIT (Op. Profit) | F4: Net Profit | G4: Equity Capital | H4: Reserves & Surplus | I4: Borrowings | J4: Total Assets | K4: Fixed Assets (+CWIP) | L4: EPS (Rs.)
A5: KPR Mill | B5: Standalone | C5: 2015 | D5: 2080 | E5: 357 | F5: 146 | G5: 38 | H5: 826 | I5: 672 | J5: 1731 | K5: 924 | L5: 3.87
A6: KPR Mill | B6: Standalone | C6: 2016 | D6: 1961 | E6: 356 | F6: 156 | G6: 38 | H6: 943 | I6: 590 | J6: 1730 | K6: 894 | L6: 4.14
A7: KPR Mill | B7: Standalone | C7: 2017 | D7: 2219 | E7: 446 | F7: 238 | G7: 37 | H7: 1081 | I7: 491 | J7: 1800 | K7: 918 | L7: 6.45
A8: KPR Mill | B8: Standalone | C8: 2018 | D8: 2512 | E8: 429 | F8: 225 | G8: 37 | H8: 1300 | I8: 346 | J8: 1930 | K8: 865 | L8: 6.09
A9: KPR Mill | B9: Standalone | C9: 2019 | D9: 2979 | E9: 507 | F9: 289 | G9: 36 | H9: 1475 | I9: 654 | J9: 2397 | K9: 798 | L9: 7.97
A10: KPR Mill | B10: Standalone | C10: 2020 | D10: 2898 | E10: 475 | F10: 295 | G10: 34 | H10: 1470 | I10: 472 | J10: 2187 | K10: 873 | L10: 8.56
A11: KPR Mill | B11: Standalone | C11: 2021 | D11: 2954 | E11: 664 | F11: 433 | G11: 34 | H11: 1872 | I11: 317 | J11: 2485 | K11: 815 | L11: 12.57
A12: KPR Mill | B12: Standalone | C12: 2022 | D12: 4074 | E12: 984 | F12: 731 | G12: 34 | H12: 2598 | I12: 418 | J12: 3359 | K12: 850 | L12: 21.24
A13: KPR Mill | B13: Standalone | C13: 2023 | D13: 4740 | E13: 799 | F13: 635 | G13: 34 | H13: 2939 | I13: 498 | J13: 3874 | K13: 971 | L13: 18.58
A14: KPR Mill | B14: Standalone | C14: 2024 | D14: 4054 | E14: 595 | F14: 555 | G14: 34 | H14: 3340 | I14: 287 | J14: 3919 | K14: 1070 | L14: 16.23
A15: KPR Mill | B15: Standalone | C15: 2025 | D15: 4216 | E15: 764 | F15: 653 | G15: 34 | H15: 3822 | I15: 241 | J15: 4403 | K15: 1122 | L15: 19.11
A16: Welspun Living | B16: Standalone | C16: 2015 | D16: 4390 | E16: 1042 | F16: 510 | G16: 100 | H16: 1332 | I16: 2467 | J16: 4827 | K16: 2052 | L16: 5.08
... A114: Siyaram Silk Mills | B114: Standalone | C114: 2025 | D114: 2220 | E114: 277 | F114: 199 | G114: 9 | H114: 1279 | I114: 262 | J114: 1893 | K114: 592 | L114: 43.8

Sheet KPR Mill
A1: KPR Mill
A3: Screener Ticker | B3: KPRMILL
A4: Basis | B4: Standalone
A5: Primary Business | B5: Yarn, Fabric, Garments, Apparel — vertically integrated composite mill
A6: Year Established | B6: 1984 (garment exports since 1989); incorporated as KPR Mill Ltd in 2003
A7: Headquarters | B7: Coimbatore, Tamil Nadu
A8: Promoter / Group | B8: K.P.R. Group — founder P. Nataraj and family
A9: Manufacturing Locations | B9: Sathyamangalam, Tirupur, Perundurai, Coimbatore (Tamil Nadu)
A10: Listed On | B10: NSE & BSE (BSE code: 532889)
A11: Note | B11: Anchor company — featured in the source ET Wealth article
A13: 10-Year Financials & Computed Ratios (FY2015-16 to FY2024-25)
A14: FY | B14: Sales | C14: EBIT | D14: Net Profit | E14: Total Equity | F14: Borrowings | G14: Total Assets | H14: Fixed Assets | I14: D/E Ratio | J14: ROE | K14: ROA | L14: Size (ln TA) | M14: Sales Growth % | N14: Tangibility | O14: EPS (Rs.)
A15: FY15-16 | B15: ='Raw Data'!D6 -> 1961 | C15: ='Raw Data'!E6 -> 356 | D15: ='Raw Data'!F6 -> 156 | E15: ='Raw Data'!G6+'Raw Data'!H6 -> 981 | F15: ='Raw Data'!I6 -> 590 | G15: ='Raw Data'!J6 -> 1730 | H15: ='Raw Data'!K6 -> 894 | I15: =F15/E15 -> 0.60142712 | J15: =D15/E15 -> 0.15902141 | K15: =D15/G15 -> 0.09017341 | L15: =LN(G15) -> 7.4558767 | M15: =(B15-'Raw Data'!D5)/'Raw Data'!D5 -> -0.057211538 | N15: =H15/G15 -> 0.51676301 | O15: ='Raw Data'!L6 -> 4.14
A16: FY16-17 | B16: ='Raw Data'!D7 -> 2219 | C16: ='Raw Data'!E7 -> 446 | D16: ='Raw Data'!F7 -> 238 | E16: ='Raw Data'!G7+'Raw Data'!H7 -> 1118 | F16: ='Raw Data'!I7 -> 491 | G16: ='Raw Data'!J7 -> 1800 | H16: ='Raw Data'!K7 -> 918 | I16: =F16/E16 -> 0.4391771 | J16: =D16/E16 -> 0.21288014 | K16: =D16/G16 -> 0.13222222 | L16: =LN(G16) -> 7.4955419 | M16: =(B16-'Raw Data'!D6)/'Raw Data'!D6 -> 0.13156553 | N16: =H16/G16 -> 0.51 | O16: ='Raw Data'!L7 -> 6.45
A17: FY17-18 | B17: ='Raw Data'!D8 -> 2512 | C17: ='Raw Data'!E8 -> 429 | D17: ='Raw Data'!F8 -> 225 | E17: ='Raw Data'!G8+'Raw Data'!H8 -> 1337 | F17: ='Raw Data'!I8 -> 346 | G17: ='Raw Data'!J8 -> 1930 | H17: ='Raw Data'!K8 -> 865 | I17: =F17/E17 -> 0.25878833 | J17: =D17/E17 -> 0.16828721 | K17: =D17/G17 -> 0.11658031 | L17: =LN(G17) -> 7.5652753 | M17: =(B17-'Raw Data'!D7)/'Raw Data'!D7 -> 0.13204146 | N17: =H17/G17 -> 0.44818653 | O17: ='Raw Data'!L8 -> 6.09
A18: FY18-19 | B18: ='Raw Data'!D9 -> 2979 | C18: ='Raw Data'!E9 -> 507 | D18: ='Raw Data'!F9 -> 289 | E18: ='Raw Data'!G9+'Raw Data'!H9 -> 1511 | F18: ='Raw Data'!I9 -> 654 | G18: ='Raw Data'!J9 -> 2397 | H18: ='Raw Data'!K9 -> 798 | I18: =F18/E18 -> 0.43282594 | J18: =D18/E18 -> 0.19126406 | K18: =D18/G18 -> 0.12056738 | L18: =LN(G18) -> 7.7819732 | M18: =(B18-'Raw Data'!D8)/'Raw Data'!D8 -> 0.18590764 | N18: =H18/G18 -> 0.33291615 | O18: ='Raw Data'!L9 -> 7.97
A19: FY19-20 | B19: ='Raw Data'!D10 -> 2898 | C19: ='Raw Data'!E10 -> 475 | D19: ='Raw Data'!F10 -> 295 | E19: ='Raw Data'!G10+'Raw Data'!H10 -> 1504 | F19: ='Raw Data'!I10 -> 472 | G19: ='Raw Data'!J10 -> 2187 | H19: ='Raw Data'!K10 -> 873 | I19: =F19/E19 -> 0.31382979 | J19: =D19/E19 -> 0.19614362 | K19: =D19/G19 -> 0.13488797 | L19: =LN(G19) -> 7.690286 | M19: =(B19-'Raw Data'!D9)/'Raw Data'!D9 -> -0.027190332 | N19: =H19/G19 -> 0.39917695 | O19: ='Raw Data'!L10 -> 8.56
A20: FY20-21 | B20: ='Raw Data'!D11 -> 2954 | C20: ='Raw Data'!E11 -> 664 | D20: ='Raw Data'!F11 -> 433 | E20: ='Raw Data'!G11+'Raw Data'!H11 -> 1906 | F20: ='Raw Data'!I11 -> 317 | G20: ='Raw Data'!J11 -> 2485 | H20: ='Raw Data'!K11 -> 815 | I20: =F20/E20 -> 0.16631689 | J20: =D20/E20 -> 0.22717733 | K20: =D20/G20 -> 0.17424547 | L20: =LN(G20) -> 7.8180279 | M20: =(B20-'Raw Data'!D10)/'Raw Data'!D10 -> 0.019323671 | N20: =H20/G20 -> 0.32796781 | O20: ='Raw Data'!L11 -> 12.57
A21: FY21-22 | B21: ='Raw Data'!D12 -> 4074 | C21: ='Raw Data'!E12 -> 984 | D21: ='Raw Data'!F12 -> 731 | E21: ='Raw Data'!G12+'Raw Data'!H12 -> 2632 | F21: ='Raw Data'!I12 -> 418 | G21: ='Raw Data'!J12 -> 3359 | H21: ='Raw Data'!K12 -> 850 | I21: =F21/E21 -> 0.15881459 | J21: =D21/E21 -> 0.27773556 | K21: =D21/G21 -> 0.21762429 | L21: =LN(G21) -> 8.1193986 | M21: =(B21-'Raw Data'!D11)/'Raw Data'!D11 -> 0.37914692 | N21: =H21/G21 -> 0.2530515 | O21: ='Raw Data'!L12 -> 21.24
A22: FY22-23 | B22: ='Raw Data'!D13 -> 4740 | C22: ='Raw Data'!E13 -> 799 | D22: ='Raw Data'!F13 -> 635 | E22: ='Raw Data'!G13+'Raw Data'!H13 -> 2973 | F22: ='Raw Data'!I13 -> 498 | G22: ='Raw Data'!J13 -> 3874 | H22: ='Raw Data'!K13 -> 971 | I22: =F22/E22 -> 0.16750757 | J22: =D22/E22 -> 0.21358897 | K22: =D22/G22 -> 0.16391327 | L22: =LN(G22) -> 8.2620428 | M22: =(B22-'Raw Data'!D12)/'Raw Data'!D12 -> 0.1634757 | N22: =H22/G22 -> 0.25064533 | O22: ='Raw Data'!L13 -> 18.58
A23: FY23-24 | B23: ='Raw Data'!D14 -> 4054 | C23: ='Raw Data'!E14 -> 595 | D23: ='Raw Data'!F14 -> 555 | E23: ='Raw Data'!G14+'Raw Data'!H14 -> 3374 | F23: ='Raw Data'!I14 -> 287 | G23: ='Raw Data'!J14 -> 3919 | H23: ='Raw Data'!K14 -> 1070 | I23: =F23/E23 -> 0.085062241 | J23: =D23/E23 -> 0.16449318 | K23: =D23/G23 -> 0.14161776 | L23: =LN(G23) -> 8.2735918 | M23: =(B23-'Raw Data'!D13)/'Raw Data'!D13 -> -0.14472574 | N23: =H23/G23 -> 0.27302883 | O23: ='Raw Data'!L14 -> 16.23
A24: FY24-25 | B24: ='Raw Data'!D15 -> 4216 | C24: ='Raw Data'!E15 -> 764 | D24: ='Raw Data'!F15 -> 653 | E24: ='Raw Data'!G15+'Raw Data'!H15 -> 3856 | F24: ='Raw Data'!I15 -> 241 | G24: ='Raw Data'!J15 -> 4403 | H24: ='Raw Data'!K15 -> 1122 | I24: =F24/E24 -> 0.0625 | J24: =D24/E24 -> 0.16934647 | K24: =D24/G24 -> 0.14830797 | L24: =LN(G24) -> 8.3900414 | M24: =(B24-'Raw Data'!D14)/'Raw Data'!D14 -> 0.039960533 | N24: =H24/G24 -> 0.25482625 | O24: ='Raw Data'!L15 -> 19.11
A25: 10-YR AVERAGE | B25: =AVERAGE(B15:B24) -> 3260.7 | C25: =AVERAGE(C15:C24) -> 601.9 | D25: =AVERAGE(D15:D24) -> 421 | E25: =AVERAGE(E15:E24) -> 2119.2 | F25: =AVERAGE(F15:F24) -> 431.4 | G25: =AVERAGE(G15:G24) -> 2808.4 | H25: =AVERAGE(H15:H24) -> 917.6 | I25: =AVERAGE(I15:I24) -> 0.26862496 | ... O25: =AVERAGE(O15:O24) -> 12.094
A27: SD (10-yr) | I27: =STDEV(I15:I24) -> 0.1757145 | J27: =STDEV(J15:J24) -> 0.036618517 | K27: =STDEV(K15:K24) -> 0.035238976 | O27: =STDEV(O15:O24) -> 6.2622346

Sheet Welspun Living
A1: Welspun Living
A3: Screener Ticker | B3: WELSPUNLIV
A4: Basis | B4: Standalone
A5: Primary Business | B5: Home Textiles (Towels, Bed Linen), Flooring
A6: Year Established | B6: 1985 (as Welspun Winilon Silk Mills, Palghar)
A7: Headquarters | B7: Mumbai, Maharashtra
A8: Promoter / Group | B8: Welspun Group — founder Balkrishan Goenka
A9: Manufacturing Locations | B9: Vapi & Anjar (Gujarat)
A10: Listed On | B10: NSE & BSE (BSE code: 514162)
A11: Note | B11: Anchor company — featured in the source ET Wealth article
A13: 10-Year Financials & Computed Ratios (FY2015-16 to FY2024-25)
A14: FY | B14: Sales | C14: EBIT | D14: Net Profit | E14: Total Equity | F14: Borrowings | G14: Total Assets | H14: Fixed Assets | I14: D/E Ratio | J14: ROE | K14: ROA | L14: Size (ln TA) | M14: Sales Growth % | N14: Tangibility | O14: EPS (Rs.)
A15: FY15-16 | B15: ='Raw Data'!D17 -> 4885 | C15: ='Raw Data'!E17 -> 1275 | D15: ='Raw Data'!F17 -> 648 | E15: ='Raw Data'!G17+'Raw Data'!H17 -> 1899 | F15: ='Raw Data'!I17 -> 2566 | G15: ='Raw Data'!J17 -> 5362 | H15: ='Raw Data'!K17 -> 2830 | I15: =F15/E15 -> 1.3512375 | J15: =D15/E15 -> 0.34123223 | K15: =D15/G15 -> 0.12085043 | L15: =LN(G15) -> 8.5870923 | M15: =(B15-'Raw Data'!D16)/'Raw Data'!D16 -> 0.11275626 | N15: =H15/G15 -> 0.52778814 | O15: ='Raw Data'!L17 -> 6.45
A16: FY16-17 | B16: ='Raw Data'!D18 -> 5639 | C16: ='Raw Data'!E18 -> 1370 | D16: ='Raw Data'!F18 -> 307 | E16: ='Raw Data'!G18+'Raw Data'!H18 -> 2201 | F16: ='Raw Data'!I18 -> 2738 | G16: ='Raw Data'!J18 -> 6248 | H16: ='Raw Data'!K18 -> 3057 | I16: =F16/E16 -> 1.24398 | J16: =D16/E16 -> 0.13948205 | K16: =D16/G16 -> 0.049135723 | L16: =LN(G16) -> 8.7400167 | M16: =(B16-'Raw Data'!D17)/'Raw Data'!D17 -> 0.15435005 | N16: =H16/G16 -> 0.48927657 | O16: ='Raw Data'!L18 -> 3.05
A17: FY17-18 | B17: ='Raw Data'!D19 -> 4977 | C17: ='Raw Data'!E19 -> 894 | D17: ='Raw Data'!F19 -> 304 | E17: ='Raw Data'!G19+'Raw Data'!H19 -> 2429 | F17: ='Raw Data'!I19 -> 2721 | G17: ='Raw Data'!J19 -> 6248 | H17: ='Raw Data'!K19 -> 2846 | I17: =F17/E17 -> 1.1202141 | J17: =D17/E17 -> 0.12515438 | K17: =D17/G17 -> 0.04865557 | L17: =LN(G17) -> 8.7400167 | M17: =(B17-'Raw Data'!D18)/'Raw Data'!D18 -> -0.1173967 | N17: =H17/G17 -> 0.45550576 | O17: ='Raw Data'!L19 -> 3.03
A18: FY18-19 | B18: ='Raw Data'!D20 -> 5395 | C18: ='Raw Data'!E20 -> 795 | D18: ='Raw Data'!F20 -> 142 | E18: ='Raw Data'!G20+'Raw Data'!H20 -> 2489 | F18: ='Raw Data'!I20 -> 2510 | G18: ='Raw Data'!J20 -> 6264 | H18: ='Raw Data'!K20 -> 2654 | I18: =F18/E18 -> 1.0084371 | J18: =D18/E18 -> 0.057051025 | K18: =D18/G18 -> 0.022669221 | L18: =LN(G18) -> 8.7425742 | M18: =(B18-'Raw Data'!D19)/'Raw Data'!D19 -> 0.083986337 | N18: =H18/G18 -> 0.42369093 | O18: ='Raw Data'!L20 -> 1.41
A19: FY19-20 | B19: ='Raw Data'!D21 -> 5324 | C19: ='Raw Data'!E21 -> 1009 | D19: ='Raw Data'!F21 -> 475 | E19: ='Raw Data'!G21+'Raw Data'!H21 -> 2807 | F19: ='Raw Data'!I21 -> 2275 | G19: ='Raw Data'!J21 -> 6221 | H19: ='Raw Data'!K21 -> 2385 | I19: =F19/E19 -> 0.81047382 | J19: =D19/E19 -> 0.16921981 | K19: =D19/G19 -> 0.076354284 | L19: =LN(G19) -> 8.7356859 | M19: =(B19-'Raw Data'!D20)/'Raw Data'!D20 -> -0.013160334 | N19: =H19/G19 -> 0.38337888 | O19: ='Raw Data'!L21 -> 4.73
A20: FY20-21 | B20: ='Raw Data'!D22 -> 5956 | C20: ='Raw Data'!E22 -> 1084 | D20: ='Raw Data'!F22 -> 527 | E20: ='Raw Data'!G22+'Raw Data'!H22 -> 3338 | F20: ='Raw Data'!I22 -> 1409 | G20: ='Raw Data'!J22 -> 6098 | H20: ='Raw Data'!K22 -> 2158 | I20: =F20/E20 -> 0.42210905 | J20: =D20/E20 -> 0.15787897 | K20: =D20/G20 -> 0.086421778 | L20: =LN(G20) -> 8.7157161 | M20: =(B20-'Raw Data'!D21)/'Raw Data'!D21 -> 0.11870774 | N20: =H20/G20 -> 0.35388652 | O20: ='Raw Data'!L22 -> 5.24
A21: FY21-22 | B21: ='Raw Data'!D23 -> 6703 | C21: ='Raw Data'!E23 -> 893 | D21: ='Raw Data'!F23 -> 392 | E21: ='Raw Data'!G23+'Raw Data'!H23 -> 3475 | F21: ='Raw Data'!I23 -> 1318 | G21: ='Raw Data'!J23 -> 6191 | H21: ='Raw Data'!K23 -> 2025 | I21: =F21/E21 -> 0.37928058 | J21: =D21/E21 -> 0.11280576 | K21: =D21/G21 -> 0.063317719 | L21: =LN(G21) -> 8.7308519 | M21: =(B21-'Raw Data'!D22)/'Raw Data'!D22 -> 0.12541974 | N21: =H21/G21 -> 0.32708771 | O21: ='Raw Data'!L23 -> 3.9
A22: FY22-23 | B22: ='Raw Data'!D24 -> 6298 | C22: ='Raw Data'!E24 -> 456 | D22: ='Raw Data'!F24 -> 123 | E22: ='Raw Data'!G24+'Raw Data'!H24 -> 3408 | F22: ='Raw Data'!I24 -> 1767 | G22: ='Raw Data'!J24 -> 6880 | H22: ='Raw Data'!K24 -> 2938 | I22: =F22/E22 -> 0.51848592 | J22: =D22/E22 -> 0.036091549 | K22: =D22/G22 -> 0.017877907 | L22: =LN(G22) -> 8.8363739 | M22: =(B22-'Raw Data'!D23)/'Raw Data'!D23 -> -0.060420707 | N22: =H22/G22 -> 0.42703488 | O22: ='Raw Data'!L24 -> 1.22
A23: FY23-24 | B23: ='Raw Data'!D25 -> 8085 | C23: ='Raw Data'!E25 -> 1012 | D23: ='Raw Data'!F25 -> 596 | E23: ='Raw Data'!G25+'Raw Data'!H25 -> 3741 | F23: ='Raw Data'!I25 -> 1965 | G23: ='Raw Data'!J25 -> 7515 | H23: ='Raw Data'!K25 -> 2879 | I23: =F23/E23 -> 0.52526063 | J23: =D23/E23 -> 0.15931569 | K23: =D23/G23 -> 0.079308051 | L23: =LN(G23) -> 8.9246563 | M23: =(B23-'Raw Data'!D24)/'Raw Data'!D24 -> 0.28374087 | N23: =H23/G23 -> 0.38310047 | O23: ='Raw Data'!L25 -> 6.13
A24: FY24-25 | B24: ='Raw Data'!D26 -> 8622 | C24: ='Raw Data'!E26 -> 907 | D24: ='Raw Data'!F26 -> 507 | E24: ='Raw Data'!G26+'Raw Data'!H26 -> 3905 | F24: ='Raw Data'!I26 -> 1678 | G24: ='Raw Data'!J26 -> 7508 | H24: ='Raw Data'!K26 -> 2933 | I24: =F24/E24 -> 0.42970551 | J24: =D24/E24 -> 0.12983355 | K24: =D24/G24 -> 0.06752797 | L24: =LN(G24) -> 8.9237244 | M24: =(B24-'Raw Data'!D25)/'Raw Data'!D25 -> 0.066419295 | N24: =H24/G24 -> 0.39064997 | O24: ='Raw Data'!L26 -> 5.28
A25: 10-YR AVERAGE | B25: =AVERAGE(B15:B24) -> 6188.4 | C25: =AVERAGE(C15:C24) -> 969.5 | D25: =AVERAGE(D15:D24) -> 402.1 | E25: =AVERAGE(E15:E24) -> 2969.2 | F25: =AVERAGE(F15:F24) -> 2094.7 | G25: =AVERAGE(G15:G24) -> 6453.5 | H25: =AVERAGE(H15:H24) -> 2670.5 | I25: =AVERAGE(I15:I24) -> 0.78091842 | ... O25: =AVERAGE(O15:O24) -> 4.044
A27: SD (10-yr) | I27: =STDEV(I15:I24) -> 0.37343586 | J27: =STDEV(J15:J24) -> 0.082126757 | K27: =STDEV(K15:K24) -> 0.03058731 | O27: =STDEV(O15:O24) -> 1.841462

Sheet Indo Count Industries
A1: Indo Count Industries
A3: Screener Ticker | B3: ICIL
A4: Basis | B4: Standalone
A5: Primary Business | B5: Home Textiles — Bed Linen (export-focused)
A6: Year Established | B6: 1988
A7: Headquarters | B7: Mumbai, Maharashtra
A8: Promoter / Group | B8: Lohia family
A9: Manufacturing Locations | B9: Kolhapur, Maharashtra
A10: Listed On | B10: NSE & BSE
A11: Note | B11: Anchor company — featured in the source ET Wealth article
A13: 10-Year Financials & Computed Ratios (FY2015-16 to FY2024-25)
A14: FY | B14: Sales | C14: EBIT | D14: Net Profit | E14: Total Equity | F14: Borrowings | G14: Total Assets | H14: Fixed Assets | I14: D/E Ratio | J14: ROE | K14: ROA | L14: Size (ln TA) | M14: Sales Growth % | N14: Tangibility | O14: EPS (Rs.)
A15: FY15-16 | B15: ='Raw Data'!D28 -> 2001 | C15: ='Raw Data'!E28 -> 396 | D15: ='Raw Data'!F28 -> 238 | E15: ='Raw Data'!G28+'Raw Data'!H28 -> 613 | F15: ='Raw Data'!I28 -> 340 | G15: ='Raw Data'!J28 -> 1283 | H15: ='Raw Data'!K28 -> 466 | I15: =F15/E15 -> 0.55464927 | J15: =D15/E15 -> 0.38825449 | K15: =D15/G15 -> 0.18550273 | L15: =LN(G15) -> 7.1569564 | M15: =(B15-'Raw Data'!D27)/'Raw Data'!D27 -> 0.23824257 | N15: =H15/G15 -> 0.36321122 | O15: ='Raw Data'!L28 -> 12.04
A16: FY16-17 | B16: ='Raw Data'!D29 -> 1990 | C16: ='Raw Data'!E29 -> 325 | D16: ='Raw Data'!F29 -> 228 | E16: ='Raw Data'!G29+'Raw Data'!H29 -> 826 | F16: ='Raw Data'!I29 -> 267 | G16: ='Raw Data'!J29 -> 1440 | H16: ='Raw Data'!K29 -> 511 | I16: =F16/E16 -> 0.32324455 | J16: =D16/E16 -> 0.27602906 | K16: =D16/G16 -> 0.15833333 | L16: =LN(G16) -> 7.2723984 | M16: =(B16-'Raw Data'!D28)/'Raw Data'!D28 -> -0.0054972514 | N16: =H16/G16 -> 0.35486111 | O16: ='Raw Data'!L29 -> 11.55
A17: FY17-18 | B17: ='Raw Data'!D30 -> 1709 | C17: ='Raw Data'!E30 -> 167 | D17: ='Raw Data'!F30 -> 131 | E17: ='Raw Data'!G30+'Raw Data'!H30 -> 938 | F17: ='Raw Data'!I30 -> 371 | G17: ='Raw Data'!J30 -> 1644 | H17: ='Raw Data'!K30 -> 535 | I17: =F17/E17 -> 0.39552239 | J17: =D17/E17 -> 0.13965885 | K17: =D17/G17 -> 0.079683698 | L17: =LN(G17) -> 7.4048876 | M17: =(B17-'Raw Data'!D29)/'Raw Data'!D29 -> -0.14120603 | N17: =H17/G17 -> 0.32542579 | O17: ='Raw Data'!L30 -> 6.64
A18: FY18-19 | B18: ='Raw Data'!D31 -> 1813 | C18: ='Raw Data'!E31 -> 151 | D18: ='Raw Data'!F31 -> 59 | E18: ='Raw Data'!G31+'Raw Data'!H31 -> 960 | F18: ='Raw Data'!I31 -> 309 | G18: ='Raw Data'!J31 -> 1552 | H18: ='Raw Data'!K31 -> 560 | I18: =F18/E18 -> 0.321875 | J18: =D18/E18 -> 0.061458333 | K18: =D18/G18 -> 0.038015464 | L18: =LN(G18) -> 7.3472997 | M18: =(B18-'Raw Data'!D30)/'Raw Data'!D30 -> 0.060854301 | N18: =H18/G18 -> 0.36082474 | O18: ='Raw Data'!L31 -> 3
A19: FY19-20 | B19: ='Raw Data'!D32 -> 1965 | C19: ='Raw Data'!E32 -> 178 | D19: ='Raw Data'!F32 -> 74 | E19: ='Raw Data'!G32+'Raw Data'!H32 -> 972 | F19: ='Raw Data'!I32 -> 348 | G19: ='Raw Data'!J32 -> 1659 | H19: ='Raw Data'!K32 -> 553 | I19: =F19/E19 -> 0.35802469 | J19: =D19/E19 -> 0.076131687 | K19: =D19/G19 -> 0.044605184 | L19: =LN(G19) -> 7.4139703 | M19: =(B19-'Raw Data'!D31)/'Raw Data'!D31 -> 0.083838941 | N19: =H19/G19 -> 0.33333333 | O19: ='Raw Data'!L32 -> 3.74
A20: FY20-21 | B20: ='Raw Data'!D33 -> 2515 | C20: ='Raw Data'!E33 -> 384 | D20: ='Raw Data'!F33 -> 260 | E20: ='Raw Data'!G33+'Raw Data'!H33 -> 1274 | F20: ='Raw Data'!I33 -> 546 | G20: ='Raw Data'!J33 -> 2247 | H20: ='Raw Data'!K33 -> 543 | I20: =F20/E20 -> 0.42857143 | J20: =D20/E20 -> 0.20408163 | K20: =D20/G20 -> 0.11570984 | L20: =LN(G20) -> 7.7173513 | M20: =(B20-'Raw Data'!D32)/'Raw Data'!D32 -> 0.27989822 | N20: =H20/G20 -> 0.24165554 | O20: ='Raw Data'!L33 -> 13.18
A21: FY21-22 | B21: ='Raw Data'!D34 -> 2806 | C21: ='Raw Data'!E34 -> 402 | D21: ='Raw Data'!F34 -> 339 | E21: ='Raw Data'!G34+'Raw Data'!H34 -> 1576 | F21: ='Raw Data'!I34 -> 1214 | G21: ='Raw Data'!J34 -> 3090 | H21: ='Raw Data'!K34 -> 650 | I21: =F21/E21 -> 0.77030457 | J21: =D21/E21 -> 0.21510152 | K21: =D21/G21 -> 0.10970874 | L21: =LN(G21) -> 8.0359264 | M21: =(B21-'Raw Data'!D33)/'Raw Data'!D33 -> 0.11570577 | N21: =H21/G21 -> 0.21035599 | O21: ='Raw Data'!L34 -> 17.16
A22: FY22-23 | B22: ='Raw Data'!D35 -> 2784 | C22: ='Raw Data'!E35 -> 411 | D22: ='Raw Data'!F35 -> 238 | E22: ='Raw Data'!G35+'Raw Data'!H35 -> 1765 | F22: ='Raw Data'!I35 -> 853 | G22: ='Raw Data'!J35 -> 2983 | H22: ='Raw Data'!K35 -> 1243 | I22: =F22/E22 -> 0.48328612 | J22: =D22/E22 -> 0.13484419 | K22: =D22/G22 -> 0.079785451 | L22: =LN(G22) -> 8.0006848 | M22: =(B22-'Raw Data'!D34)/'Raw Data'!D34 -> -0.0078403421 | N22: =H22/G22 -> 0.4166946 | O22: ='Raw Data'!L35 -> 12.03
A23: FY23-24 | B23: ='Raw Data'!D36 -> 3332 | C23: ='Raw Data'!E36 -> 526 | D23: ='Raw Data'!F36 -> 320 | E23: ='Raw Data'!G36+'Raw Data'!H36 -> 2048 | F23: ='Raw Data'!I36 -> 936 | G23: ='Raw Data'!J36 -> 3493 | H23: ='Raw Data'!K36 -> 1344 | I23: =F23/E23 -> 0.45703125 | J23: =D23/E23 -> 0.15625 | K23: =D23/G23 -> 0.091611795 | L23: =LN(G23) -> 8.1585162 | M23: =(B23-'Raw Data'!D35)/'Raw Data'!D35 -> 0.19683908 | N23: =H23/G23 -> 0.38476954 | O23: ='Raw Data'!L36 -> 16.17
A24: FY24-25 | B24: ='Raw Data'!D37 -> 3772 | C24: ='Raw Data'!E37 -> 465 | D24: ='Raw Data'!F37 -> 237 | E24: ='Raw Data'!G37+'Raw Data'!H37 -> 2237 | F24: ='Raw Data'!I37 -> 1061 | G24: ='Raw Data'!J37 -> 3695 | H24: ='Raw Data'!K37 -> 1381 | I24: =F24/E24 -> 0.47429593 | J24: =D24/E24 -> 0.10594546 | K24: =D24/G24 -> 0.064140731 | L24: =LN(G24) -> 8.2147358 | M24: =(B24-'Raw Data'!D36)/'Raw Data'!D36 -> 0.13205282 | N24: =H24/G24 -> 0.37374831 | O24: ='Raw Data'!L37 -> 11.98
A25: 10-YR AVERAGE | B25: =AVERAGE(B15:B24) -> 2468.7 | C25: =AVERAGE(C15:C24) -> 340.5 | D25: =AVERAGE(D15:D24) -> 212.4 | E25: =AVERAGE(E15:E24) -> 1320.9 | F25: =AVERAGE(F15:F24) -> 624.5 | G25: =AVERAGE(G15:G24) -> 2308.6 | H25: =AVERAGE(H15:H24) -> 778.6 | I25: =AVERAGE(I15:I24) -> 0.45668052 | ... O25: =AVERAGE(O15:O24) -> 10.749
A27: SD (10-yr) | I27: =STDEV(I15:I24) -> 0.13300681 | J27: =STDEV(J15:J24) -> 0.099320153 | K27: =STDEV(K15:K24) -> 0.047181198 | O27: =STDEV(O15:O24) -> 4.8064712

Sheet Vardhman Textiles
A1: Vardhman Textiles
A3: Screener Ticker | B3: VTL
A4: Basis | B4: Standalone
A5: Primary Business | B5: Yarn, Fabric, Acrylic Fibre, Garments — vertically integrated composite mill
A6: Year Established | B6: 1962 (incorporated as Vardhman Spinning & General Mills); yarn production commenced 1965
A7: Headquarters | B7: Ludhiana, Punjab
A8: Promoter / Group | B8: Vardhman Group — Oswal family (founder Lala Rattan Chand Oswal; current Chairman S.P. Oswal)
A9: Manufacturing Locations | B9: 22 units across 6 states, incl. Punjab, Himachal Pradesh, Madhya Pradesh
A10: Listed On | B10: NSE & BSE
A11: Note
A13: 10-Year Financials & Computed Ratios (FY2015-16 to FY2024-25)
A14: FY | B14: Sales | C14: EBIT | D14: Net Profit | E14: Total Equity | F14: Borrowings | G14: Total Assets | H14: Fixed Assets | I14: D/E Ratio | J14: ROE | K14: ROA | L14: Size (ln TA) | M14: Sales Growth % | N14: Tangibility | O14: EPS (Rs.)
A15: FY15-16 | B15: ='Raw Data'!D39 -> 5602 | C15: ='Raw Data'!E39 -> 1108 | D15: ='Raw Data'!F39 -> 676 | E15: ='Raw Data'!G39+'Raw Data'!H39 -> 3690 | F15: ='Raw Data'!I39 -> 2596 | G15: ='Raw Data'!J39 -> 6985 | H15: ='Raw Data'!K39 -> 2585 | I15: =F15/E15 -> 0.70352304 | J15: =D15/E15 -> 0.18319783 | K15: =D15/G15 -> 0.096778812 | L15: =LN(G15) -> 8.8515203 | M15: =(B15-'Raw Data'!D38)/'Raw Data'!D38 -> -0.022338569 | N15: =H15/G15 -> 0.37007874 | O15: ='Raw Data'!L39 -> 21.25
A16: FY16-17 | B16: ='Raw Data'!D40 -> 5691 | C16: ='Raw Data'!E40 -> 1131 | D16: ='Raw Data'!F40 -> 1002 | E16: ='Raw Data'!G40+'Raw Data'!H40 -> 3986 | F16: ='Raw Data'!I40 -> 2198 | G16: ='Raw Data'!J40 -> 6959 | H16: ='Raw Data'!K40 -> 2507 | I16: =F16/E16 -> 0.55143001 | J16: =D16/E16 -> 0.25137983 | K16: =D16/G16 -> 0.1439862 | L16: =LN(G16) -> 8.8477911 | M16: =(B16-'Raw Data'!D39)/'Raw Data'!D39 -> 0.015887183 | N16: =H16/G16 -> 0.36025291 | O16: ='Raw Data'!L40 -> 34.87
A17: FY17-18 | B17: ='Raw Data'!D41 -> 5851 | C17: ='Raw Data'!E41 -> 859 | D17: ='Raw Data'!F41 -> 546 | E17: ='Raw Data'!G41+'Raw Data'!H41 -> 4632 | F17: ='Raw Data'!I41 -> 2282 | G17: ='Raw Data'!J41 -> 7696 | H17: ='Raw Data'!K41 -> 2612 | I17: =F17/E17 -> 0.49265976 | J17: =D17/E17 -> 0.11787565 | K17: =D17/G17 -> 0.070945946 | L17: =LN(G17) -> 8.948456 | M17: =(B17-'Raw Data'!D40)/'Raw Data'!D40 -> 0.028114567 | N17: =H17/G17 -> 0.33939709 | O17: ='Raw Data'!L41 -> 19
A18: FY18-19 | B18: ='Raw Data'!D42 -> 6415 | C18: ='Raw Data'!E42 -> 1132 | D18: ='Raw Data'!F42 -> 696 | E18: ='Raw Data'!G42+'Raw Data'!H42 -> 5239 | F18: ='Raw Data'!I42 -> 2238 | G18: ='Raw Data'!J42 -> 8369 | H18: ='Raw Data'!K42 -> 3333 | I18: =F18/E18 -> 0.42718076 | J18: =D18/E18 -> 0.13284978 | K18: =D18/G18 -> 0.083164058 | L18: =LN(G18) -> 9.0322897 | M18: =(B18-'Raw Data'!D41)/'Raw Data'!D41 -> 0.096393779 | N18: =H18/G18 -> 0.39825547 | O18: ='Raw Data'!L42 -> 24.21
A19: FY19-20 | B19: ='Raw Data'!D43 -> 6325 | C19: ='Raw Data'!E43 -> 883 | D19: ='Raw Data'!F43 -> 545 | E19: ='Raw Data'!G43+'Raw Data'!H43 -> 5667 | F19: ='Raw Data'!I43 -> 2197 | G19: ='Raw Data'!J43 -> 8727 | H19: ='Raw Data'!K43 -> 3620 | I19: =F19/E19 -> 0.38768308 | J19: =D19/E19 -> 0.096170813 | K19: =D19/G19 -> 0.062449868 | L19: =LN(G19) -> 9.0741769 | M19: =(B19-'Raw Data'!D42)/'Raw Data'!D42 -> -0.014029618 | N19: =H19/G19 -> 0.41480463 | O19: ='Raw Data'!L43 -> 18.97
A20: FY20-21 | B20: ='Raw Data'!D44 -> 5926 | C20: ='Raw Data'!E44 -> 767 | D20: ='Raw Data'!F44 -> 367 | E20: ='Raw Data'!G44+'Raw Data'!H44 -> 6139 | F20: ='Raw Data'!I44 -> 2132 | G20: ='Raw Data'!J44 -> 9064 | H20: ='Raw Data'!K44 -> 3546 | I20: =F20/E20 -> 0.34728783 | J20: =D20/E20 -> 0.059781723 | K20: =D20/G20 -> 0.04048985 | L20: =LN(G20) -> 9.1120658 | M20: =(B20-'Raw Data'!D43)/'Raw Data'!D43 -> -0.063083004 | N20: =H20/G20 -> 0.39121801 | O20: ='Raw Data'!L44 -> 12.74
A21: FY21-22 | B21: ='Raw Data'!D45 -> 9386 | C21: ='Raw Data'!E45 -> 2262 | D21: ='Raw Data'!F45 -> 1677 | E21: ='Raw Data'!G45+'Raw Data'!H45 -> 7539 | F21: ='Raw Data'!I45 -> 1980 | G21: ='Raw Data'!J45 -> 10576 | H21: ='Raw Data'!K45 -> 3677 | I21: =F21/E21 -> 0.2626343 | J21: =D21/E21 -> 0.22244329 | K21: =D21/G21 -> 0.15856657 | L21: =LN(G21) -> 9.2663426 | M21: =(B21-'Raw Data'!D44)/'Raw Data'!D44 -> 0.5838677 | N21: =H21/G21 -> 0.34767398 | O21: ='Raw Data'!L45 -> 58.07
A22: FY22-23 | B22: ='Raw Data'!D46 -> 9841 | C22: ='Raw Data'!E46 -> 1285 | D22: ='Raw Data'!F46 -> 749 | E22: ='Raw Data'!G46+'Raw Data'!H46 -> 8294 | F22: ='Raw Data'!I46 -> 1677 | G22: ='Raw Data'!J46 -> 10861 | H22: ='Raw Data'!K46 -> 3927 | I22: =F22/E22 -> 0.20219436 | J22: =D22/E22 -> 0.090306245 | K22: =D22/G22 -> 0.068962342 | L22: =LN(G22) -> 9.2929337 | M22: =(B22-'Raw Data'!D45)/'Raw Data'!D45 -> 0.048476454 | N22: =H22/G22 -> 0.36156892 | O22: ='Raw Data'!L46 -> 25.91
A23: FY23-24 | B23: ='Raw Data'!D47 -> 9299 | C23: ='Raw Data'!E47 -> 958 | D23: ='Raw Data'!F47 -> 608 | E23: ='Raw Data'!G47+'Raw Data'!H47 -> 8805 | F23: ='Raw Data'!I47 -> 1790 | G23: ='Raw Data'!J47 -> 11487 | H23: ='Raw Data'!K47 -> 3772 | I23: =F23/E23 -> 0.20329358 | J23: =D23/E23 -> 0.069051675 | K23: =D23/G23 -> 0.052929398 | L23: =LN(G23) -> 9.3489712 | M23: =(B23-'Raw Data'!D46)/'Raw Data'!D46 -> -0.055075704 | N23: =H23/G23 -> 0.3283712 | O23: ='Raw Data'!L47 -> 21.01
A24: FY24-25 | B24: ='Raw Data'!D48 -> 9587 | C24: ='Raw Data'!E48 -> 1257 | D24: ='Raw Data'!F48 -> 879 | E24: ='Raw Data'!G48+'Raw Data'!H48 -> 9578 | F24: ='Raw Data'!I48 -> 1238 | G24: ='Raw Data'!J48 -> 11900 | H24: ='Raw Data'!K48 -> 4342 | I24: =F24/E24 -> 0.12925454 | J24: =D24/E24 -> 0.091772813 | K24: =D24/G24 -> 0.073865546 | L24: =LN(G24) -> 9.3842937 | M24: =(B24-'Raw Data'!D47)/'Raw Data'!D47 -> 0.030971072 | N24: =H24/G24 -> 0.36487395 | O24: ='Raw Data'!L48 -> 30.4
A25: 10-YR AVERAGE | B25: =AVERAGE(B15:B24) -> 7392.3 | C25: =AVERAGE(C15:C24) -> 1164.2 | D25: =AVERAGE(D15:D24) -> 774.5 | E25: =AVERAGE(E15:E24) -> 6356.9 | F25: =AVERAGE(F15:F24) -> 2032.8 | G25: =AVERAGE(G15:G24) -> 9262.4 | H25: =AVERAGE(H15:H24) -> 3392.1 | I25: =AVERAGE(I15:I24) -> 0.37071413 | ... O25: =AVERAGE(O15:O24) -> 26.643
A27: SD (10-yr) | I27: =STDEV(I15:I24) -> 0.17911154 | J27: =STDEV(J15:J24) -> 0.065885924 | K27: =STDEV(K15:K24) -> 0.038195331 | O27: =STDEV(O15:O24) -> 12.681179

Sheet Trident
A1: Trident
A3: Screener Ticker | B3: TRIDENT
A4: Basis | B4: Standalone
A5: Primary Business | B5: Yarn, Terry Towels, Bed Sheets — vertically integrated composite mill
A6: Year Established | B6: 1990 (as Abhishek Industries Ltd; renamed Trident Ltd in 2011)
A7: Headquarters | B7: Ludhiana, Punjab (registered office)
A8: Promoter / Group | B8: Trident Group — founder Rajinder Gupta
A9: Manufacturing Locations | B9: Barnala (Punjab) and Budhni (Madhya Pradesh)
A10: Listed On | B10: NSE & BSE
A11: Note
A13: 10-Year Financials & Computed Ratios (FY2015-16 to FY2024-25)
A14: FY | B14: Sales | C14: EBIT | D14: Net Profit | E14: Total Equity | F14: Borrowings | G14: Total Assets | H14: Fixed Assets | I14: D/E Ratio | J14: ROE | K14: ROA | L14: Size (ln TA) | M14: Sales Growth % | N14: Tangibility | O14: EPS (Rs.)
A15: FY15-16 | B15: ='Raw Data'!D50 -> 3665 | C15: ='Raw Data'!E50 -> 730 | D15: ='Raw Data'!F50 -> 242 | E15: ='Raw Data'!G50+'Raw Data'!H50 -> 2415 | F15: ='Raw Data'!I50 -> 3503 | G15: ='Raw Data'!J50 -> 6506 | H15: ='Raw Data'!K50 -> 4755 | I15: =F15/E15 -> 1.4505176 | J15: =D15/E15 -> 0.10020704 | K15: =D15/G15 -> 0.037196434 | L15: =LN(G15) -> 8.7804801 | M15: =(B15-'Raw Data'!D49)/'Raw Data'!D49 -> -0.018741633 | N15: =H15/G15 -> 0.73086382 | O15: ='Raw Data'!L50 -> 0.48
A16: FY16-17 | B16: ='Raw Data'!D51 -> 4617 | C16: ='Raw Data'!E51 -> 886 | D16: ='Raw Data'!F51 -> 337 | E16: ='Raw Data'!G51+'Raw Data'!H51 -> 2725 | F16: ='Raw Data'!I51 -> 2849 | G16: ='Raw Data'!J51 -> 6150 | H16: ='Raw Data'!K51 -> 4467 | I16: =F16/E16 -> 1.0455046 | J16: =D16/E16 -> 0.12366972 | K16: =D16/G16 -> 0.054796748 | L16: =LN(G16) -> 8.7242074 | M16: =(B16-'Raw Data'!D50)/'Raw Data'!D50 -> 0.25975443 | N16: =H16/G16 -> 0.72634146 | O16: ='Raw Data'!L51 -> 0.66
A17: FY17-18 | B17: ='Raw Data'!D52 -> 4566 | C17: ='Raw Data'!E52 -> 852 | D17: ='Raw Data'!F52 -> 266 | E17: ='Raw Data'!G52+'Raw Data'!H52 -> 2694 | F17: ='Raw Data'!I52 -> 2798 | G17: ='Raw Data'!J52 -> 6129 | H17: ='Raw Data'!K52 -> 4079 | I17: =F17/E17 -> 1.0386043 | J17: =D17/E17 -> 0.098737936 | K17: =D17/G17 -> 0.043400228 | L17: =LN(G17) -> 8.7207869 | M17: =(B17-'Raw Data'!D51)/'Raw Data'!D51 -> -0.011046134 | N17: =H17/G17 -> 0.66552456 | O17: ='Raw Data'!L52 -> 0.52
A18: FY18-19 | B18: ='Raw Data'!D53 -> 5220 | C18: ='Raw Data'!E53 -> 977 | D18: ='Raw Data'!F53 -> 371 | E18: ='Raw Data'!G53+'Raw Data'!H53 -> 2932 | F18: ='Raw Data'!I53 -> 2436 | G18: ='Raw Data'!J53 -> 6103 | H18: ='Raw Data'!K53 -> 3848 | I18: =F18/E18 -> 0.8308322 | J18: =D18/E18 -> 0.12653479 | K18: =D18/G18 -> 0.060789776 | L18: =LN(G18) -> 8.7165357 | M18: =(B18-'Raw Data'!D52)/'Raw Data'!D52 -> 0.14323259 | N18: =H18/G18 -> 0.63050959 | O18: ='Raw Data'!L53 -> 0.73
A19: FY19-20 | B19: ='Raw Data'!D54 -> 4699 | C19: ='Raw Data'!E54 -> 841 | D19: ='Raw Data'!F54 -> 342 | E19: ='Raw Data'!G54+'Raw Data'!H54 -> 2967 | F19: ='Raw Data'!I54 -> 1991 | G19: ='Raw Data'!J54 -> 5718 | H19: ='Raw Data'!K54 -> 3826 | I19: =F19/E19 -> 0.6710482 | J19: =D19/E19 -> 0.11526795 | K19: =D19/G19 -> 0.059811123 | L19: =LN(G19) -> 8.6513744 | M19: =(B19-'Raw Data'!D53)/'Raw Data'!D53 -> -0.099808429 | N19: =H19/G19 -> 0.66911508 | O19: ='Raw Data'!L54 -> 0.67
A20: FY20-21 | B20: ='Raw Data'!D55 -> 4519 | C20: ='Raw Data'!E55 -> 814 | D20: ='Raw Data'!F55 -> 346 | E20: ='Raw Data'!G55+'Raw Data'!H55 -> 3317 | F20: ='Raw Data'!I55 -> 1562 | G20: ='Raw Data'!J55 -> 5754 | H20: ='Raw Data'!K55 -> 3854 | I20: =F20/E20 -> 0.47090745 | J20: =D20/E20 -> 0.10431112 | K20: =D20/G20 -> 0.060132082 | L20: =LN(G20) -> 8.6576505 | M20: =(B20-'Raw Data'!D54)/'Raw Data'!D54 -> -0.038306023 | N20: =H20/G20 -> 0.66979493 | O20: ='Raw Data'!L55 -> 0.68
A21: FY21-22 | B21: ='Raw Data'!D56 -> 6919 | C21: ='Raw Data'!E56 -> 1495 | D21: ='Raw Data'!F56 -> 815 | E21: ='Raw Data'!G56+'Raw Data'!H56 -> 3798 | F21: ='Raw Data'!I56 -> 1596 | G21: ='Raw Data'!J56 -> 6431 | H21: ='Raw Data'!K56 -> 3795 | I21: =F21/E21 -> 0.42022117 | J21: =D21/E21 -> 0.21458662 | K21: =D21/G21 -> 0.1267299 | L21: =LN(G21) -> 8.7688853 | M21: =(B21-'Raw Data'!D55)/'Raw Data'!D55 -> 0.53109095 | N21: =H21/G21 -> 0.5901104 | O21: ='Raw Data'!L56 -> 1.6
A22: FY22-23 | B22: ='Raw Data'!D57 -> 6267 | C22: ='Raw Data'!E57 -> 918 | D22: ='Raw Data'!F57 -> 422 | E22: ='Raw Data'!G57+'Raw Data'!H57 -> 4126 | F22: ='Raw Data'!I57 -> 1404 | G22: ='Raw Data'!J57 -> 6713 | H22: ='Raw Data'!K57 -> 4422 | I22: =F22/E22 -> 0.34028114 | J22: =D22/E22 -> 0.10227824 | K22: =D22/G22 -> 0.062863101 | L22: =LN(G22) -> 8.8118012 | M22: =(B22-'Raw Data'!D56)/'Raw Data'!D56 -> -0.094233271 | N22: =H22/G22 -> 0.65872188 | O22: ='Raw Data'!L57 -> 0.83
A23: FY23-24 | B23: ='Raw Data'!D58 -> 6730 | C23: ='Raw Data'!E58 -> 935 | D23: ='Raw Data'!F58 -> 390 | E23: ='Raw Data'!G58+'Raw Data'!H58 -> 4310 | F23: ='Raw Data'!I58 -> 2094 | G23: ='Raw Data'!J58 -> 7522 | H23: ='Raw Data'!K58 -> 4663 | I23: =F23/E23 -> 0.48584687 | J23: =D23/E23 -> 0.090487239 | K23: =D23/G23 -> 0.051847913 | L23: =LN(G23) -> 8.9255873 | M23: =(B23-'Raw Data'!D57)/'Raw Data'!D57 -> 0.073879049 | N23: =H23/G23 -> 0.61991492 | O23: ='Raw Data'!L58 -> 0.76
A24: FY24-25 | B24: ='Raw Data'!D59 -> 6966 | C24: ='Raw Data'!E59 -> 886 | D24: ='Raw Data'!F59 -> 367 | E24: ='Raw Data'!G59+'Raw Data'!H59 -> 4611 | F24: ='Raw Data'!I59 -> 1606 | G24: ='Raw Data'!J59 -> 7129 | H24: ='Raw Data'!K59 -> 4478 | I24: =F24/E24 -> 0.34829755 | J24: =D24/E24 -> 0.079592279 | K24: =D24/G24 -> 0.051479871 | L24: =LN(G24) -> 8.8719263 | M24: =(B24-'Raw Data'!D58)/'Raw Data'!D58 -> 0.035066865 | N24: =H24/G24 -> 0.62813859 | O24: ='Raw Data'!L59 -> 0.72
A25: 10-YR AVERAGE | B25: =AVERAGE(B15:B24) -> 5416.8 | C25: =AVERAGE(C15:C24) -> 933.4 | D25: =AVERAGE(D15:D24) -> 389.8 | E25: =AVERAGE(E15:E24) -> 3389.5 | F25: =AVERAGE(F15:F24) -> 2183.9 | G25: =AVERAGE(G15:G24) -> 6415.5 | H25: =AVERAGE(H15:H24) -> 4218.7 | I25: =AVERAGE(I15:I24) -> 0.71020611 | ... O25: =AVERAGE(O15:O24) -> 0.765
A27: SD (10-yr) | I27: =STDEV(I15:I24) -> 0.37177203 | J27: =STDEV(J15:J24) -> 0.037618743 | K27: =STDEV(K15:K24) -> 0.024529454 | O27: =STDEV(O15:O24) -> 0.31149282

Sheet Arvind
A1: Arvind
A3: Screener Ticker | B3: ARVIND
A4: Basis | B4: Standalone
A5: Primary Business | B5: Denim, Woven Fabrics, Garments
A6: Year Established | B6: 1931
A7: Headquarters | B7: Ahmedabad, Gujarat
A8: Promoter / Group | B8: Lalbhai Group — founder Kasturbhai Lalbhai (current Chairman: Sanjay Lalbhai)
A9: Manufacturing Locations | B9: Naroda & Santej (near Ahmedabad, Gujarat)
A10: Listed On | B10: NSE & BSE (BSE code: 500101)
A11: Note
A13: 10-Year Financials & Computed Ratios (FY2015-16 to FY2024-25)
A14: FY | B14: Sales | C14: EBIT | D14: Net Profit | E14: Total Equity | F14: Borrowings | G14: Total Assets | H14: Fixed Assets | I14: D/E Ratio | J14: ROE | K14: ROA | L14: Size (ln TA) | M14: Sales Growth % | N14: Tangibility | O14: EPS (Rs.)
A15: FY15-16 | B15: ='Raw Data'!D61 -> 5357 | C15: ='Raw Data'!E61 -> 808 | D15: ='Raw Data'!F61 -> 321 | E15: ='Raw Data'!G61+'Raw Data'!H61 -> 2986 | F15: ='Raw Data'!I61 -> 3123 | G15: ='Raw Data'!J61 -> 6990 | H15: ='Raw Data'!K61 -> 2928 | I15: =F15/E15 -> 1.0458808 | J15: =D15/E15 -> 0.10750167 | K15: =D15/G15 -> 0.045922747 | L15: =LN(G15) -> 8.8522358 | M15: =(B15-'Raw Data'!D60)/'Raw Data'!D60 -> 0.025263158 | N15: =H15/G15 -> 0.41888412 | O15: ='Raw Data'!L61 -> 12.42
A16: FY16-17 | B16: ='Raw Data'!D62 -> 5967 | C16: ='Raw Data'!E62 -> 732 | D16: ='Raw Data'!F62 -> 19 | E16: ='Raw Data'!G62+'Raw Data'!H62 -> 3011 | F16: ='Raw Data'!I62 -> 2428 | G16: ='Raw Data'!J62 -> 6458 | H16: ='Raw Data'!K62 -> 3177 | I16: =F16/E16 -> 0.80637662 | J16: =D16/E16 -> 0.0063101959 | K16: =D16/G16 -> 0.0029420873 | L16: =LN(G16) -> 8.773075 | M16: =(B16-'Raw Data'!D61)/'Raw Data'!D61 -> 0.1138697 | N16: =H16/G16 -> 0.49194797 | O16: ='Raw Data'!L62 -> 0.72
A17: FY17-18 | B17: ='Raw Data'!D63 -> 6332 | C17: ='Raw Data'!E63 -> 639 | D17: ='Raw Data'!F63 -> 250 | E17: ='Raw Data'!G63+'Raw Data'!H63 -> 3159 | F17: ='Raw Data'!I63 -> 2562 | G17: ='Raw Data'!J63 -> 7044 | H17: ='Raw Data'!K63 -> 3208 | I17: =F17/E17 -> 0.81101614 | J17: =D17/E17 -> 0.079138968 | K17: =D17/G17 -> 0.035491198 | L17: =LN(G17) -> 8.8599315 | M17: =(B17-'Raw Data'!D62)/'Raw Data'!D62 -> 0.061169767 | N17: =H17/G17 -> 0.45542306 | O17: ='Raw Data'!L63 -> 9.67
A18: FY18-19 | B18: ='Raw Data'!D64 -> 6436 | C18: ='Raw Data'!E64 -> 633 | D18: ='Raw Data'!F64 -> 199 | E18: ='Raw Data'!G64+'Raw Data'!H64 -> 2817 | F18: ='Raw Data'!I64 -> 2652 | G18: ='Raw Data'!J64 -> 7014 | H18: ='Raw Data'!K64 -> 3362 | I18: =F18/E18 -> 0.94142705 | J18: =D18/E18 -> 0.070642528 | K18: =D18/G18 -> 0.028371828 | L18: =LN(G18) -> 8.8556634 | M18: =(B18-'Raw Data'!D63)/'Raw Data'!D63 -> 0.01642451 | N18: =H18/G18 -> 0.47932706 | O18: ='Raw Data'!L64 -> 7.71
A19: FY19-20 | B19: ='Raw Data'!D65 -> 6705 | C19: ='Raw Data'!E65 -> 708 | D19: ='Raw Data'!F65 -> 171 | E19: ='Raw Data'!G65+'Raw Data'!H65 -> 2854 | F19: ='Raw Data'!I65 -> 2431 | G19: ='Raw Data'!J65 -> 6815 | H19: ='Raw Data'!K65 -> 3532 | I19: =F19/E19 -> 0.85178697 | J19: =D19/E19 -> 0.059915907 | K19: =D19/G19 -> 0.025091709 | L19: =LN(G19) -> 8.8268813 | M19: =(B19-'Raw Data'!D64)/'Raw Data'!D64 -> 0.041796147 | N19: =H19/G19 -> 0.51826853 | O19: ='Raw Data'!L65 -> 6.62
A20: FY20-21 | B20: ='Raw Data'!D66 -> 4529 | C20: ='Raw Data'!E66 -> 477 | D20: ='Raw Data'!F66 -> 93 | E20: ='Raw Data'!G66+'Raw Data'!H66 -> 2941 | F20: ='Raw Data'!I66 -> 1985 | G20: ='Raw Data'!J66 -> 6609 | H20: ='Raw Data'!K66 -> 3332 | I20: =F20/E20 -> 0.6749405 | J20: =D20/E20 -> 0.031621897 | K20: =D20/G20 -> 0.01407172 | L20: =LN(G20) -> 8.7961876 | M20: =(B20-'Raw Data'!D65)/'Raw Data'!D65 -> -0.32453393 | N20: =H20/G20 -> 0.50416099 | O20: ='Raw Data'!L66 -> 3.58
A21: FY21-22 | B21: ='Raw Data'!D67 -> 7436 | C21: ='Raw Data'!E67 -> 790 | D21: ='Raw Data'!F67 -> 59 | E21: ='Raw Data'!G67+'Raw Data'!H67 -> 3012 | F21: ='Raw Data'!I67 -> 1783 | G21: ='Raw Data'!J67 -> 7413 | H21: ='Raw Data'!K67 -> 3268 | I21: =F21/E21 -> 0.59196547 | J21: =D21/E21 -> 0.019588313 | K21: =D21/G21 -> 0.007958991 | L21: =LN(G21) -> 8.9109905 | M21: =(B21-'Raw Data'!D66)/'Raw Data'!D66 -> 0.64186355 | N21: =H21/G21 -> 0.44084716 | O21: ='Raw Data'!L67 -> 2.28
A22: FY22-23 | B22: ='Raw Data'!D68 -> 7723 | C22: ='Raw Data'!E68 -> 720 | D22: ='Raw Data'!F68 -> 346 | E22: ='Raw Data'!G68+'Raw Data'!H68 -> 3297 | F22: ='Raw Data'!I68 -> 1420 | G22: ='Raw Data'!J68 -> 6398 | H22: ='Raw Data'!K68 -> 3255 | I22: =F22/E22 -> 0.43069457 | J22: =D22/E22 -> 0.10494389 | K22: =D22/G22 -> 0.0540794 | L22: =LN(G22) -> 8.7637407 | M22: =(B22-'Raw Data'!D67)/'Raw Data'!D67 -> 0.038596019 | N22: =H22/G22 -> 0.50875274 | O22: ='Raw Data'!L68 -> 13.23
A23: FY23-24 | B23: ='Raw Data'!D69 -> 7100 | C23: ='Raw Data'!E69 -> 767 | D23: ='Raw Data'!F69 -> 305 | E23: ='Raw Data'!G69+'Raw Data'!H69 -> 3477 | F23: ='Raw Data'!I69 -> 1320 | G23: ='Raw Data'!J69 -> 6729 | H23: ='Raw Data'!K69 -> 3288 | I23: =F23/E23 -> 0.37963762 | J23: =D23/E23 -> 0.087719298 | K23: =D23/G23 -> 0.0453262 | L23: =LN(G23) -> 8.8141818 | M23: =(B23-'Raw Data'!D68)/'Raw Data'!D68 -> -0.080668134 | N23: =H23/G23 -> 0.4886313 | O23: ='Raw Data'!L69 -> 11.65
A24: FY24-25 | B24: ='Raw Data'!D70 -> 6236 | C24: ='Raw Data'!E70 -> 581 | D24: ='Raw Data'!F70 -> 240 | E24: ='Raw Data'!G70+'Raw Data'!H70 -> 3587 | F24: ='Raw Data'!I70 -> 1496 | G24: ='Raw Data'!J70 -> 7324 | H24: ='Raw Data'!K70 -> 3504 | I24: =F24/E24 -> 0.41706161 | J24: =D24/E24 -> 0.06690828 | K24: =D24/G24 -> 0.032768979 | L24: =LN(G24) -> 8.8989119 | M24: =(B24-'Raw Data'!D69)/'Raw Data'!D69 -> -0.12169014 | N24: =H24/G24 -> 0.47842709 | O24: ='Raw Data'!L70 -> 9.18
A25: 10-YR AVERAGE | B25: =AVERAGE(B15:B24) -> 6382.1 | C25: =AVERAGE(C15:C24) -> 685.5 | D25: =AVERAGE(D15:D24) -> 200.3 | E25: =AVERAGE(E15:E24) -> 3114.1 | F25: =AVERAGE(F15:F24) -> 2120 | G25: =AVERAGE(G15:G24) -> 6879.4 | H25: =AVERAGE(H15:H24) -> 3285.4 | I25: =AVERAGE(I15:I24) -> 0.69507873 | ... O25: =AVERAGE(O15:O24) -> 7.706
A27: SD (10-yr) | I27: =STDEV(I15:I24) -> 0.23377797 | J27: =STDEV(J15:J24) -> 0.034601615 | K27: =STDEV(K15:K24) -> 0.016990498 | O27: =STDEV(O15:O24) -> 4.3559721

Sheet Nitin Spinners
A1: Nitin Spinners
A3: Screener Ticker | B3: NITINSPIN
A4: Basis | B4: Standalone
A5: Primary Business | B5: Cotton Yarn, Knitted & Woven Fabric — spinning specialist
A6: Year Established | B6: 1992
A7: Headquarters | B7: Bhilwara, Rajasthan (the 'Textile City of India')
A8: Promoter / Group | B8: Nolkha family
A9: Manufacturing Locations | B9: Hamirgarh (Bhilwara) and Begun (Chittorgarh), Rajasthan
A10: Listed On | B10: NSE & BSE (BSE code: 532698)
A11: Note
A13: 10-Year Financials & Computed Ratios (FY2015-16 to FY2024-25)
A14: FY | B14: Sales | C14: EBIT | D14: Net Profit | E14: Total Equity | F14: Borrowings | G14: Total Assets | H14: Fixed Assets | I14: D/E Ratio | J14: ROE | K14: ROA | L14: Size (ln TA) | M14: Sales Growth % | N14: Tangibility | O14: EPS (Rs.)
A15: FY15-16 | B15: ='Raw Data'!D72 -> 766 | C15: ='Raw Data'!E72 -> 137 | D15: ='Raw Data'!F72 -> 44 | E15: ='Raw Data'!G72+'Raw Data'!H72 -> 206 | F15: ='Raw Data'!I72 -> 352 | G15: ='Raw Data'!J72 -> 635 | H15: ='Raw Data'!K72 -> 399 | I15: =F15/E15 -> 1.7087379 | J15: =D15/E15 -> 0.21359223 | K15: =D15/G15 -> 0.069291339 | L15: =LN(G15) -> 6.453625 | M15: =(B15-'Raw Data'!D71)/'Raw Data'!D71 -> 0.24350649 | N15: =H15/G15 -> 0.62834646 | O15: ='Raw Data'!L72 -> 9.63
A16: FY16-17 | B16: ='Raw Data'!D73 -> 933 | C16: ='Raw Data'!E73 -> 133 | D16: ='Raw Data'!F73 -> 57 | E16: ='Raw Data'!G73+'Raw Data'!H73 -> 264 | F16: ='Raw Data'!I73 -> 568 | G16: ='Raw Data'!J73 -> 885 | H16: ='Raw Data'!K73 -> 613 | I16: =F16/E16 -> 2.1515152 | J16: =D16/E16 -> 0.21590909 | K16: =D16/G16 -> 0.06440678 | L16: =LN(G16) -> 6.7855876 | M16: =(B16-'Raw Data'!D72)/'Raw Data'!D72 -> 0.21801567 | N16: =H16/G16 -> 0.69265537 | O16: ='Raw Data'!L73 -> 12.51
A17: FY17-18 | B17: ='Raw Data'!D74 -> 1145 | C17: ='Raw Data'!E74 -> 155 | D17: ='Raw Data'!F74 -> 52 | E17: ='Raw Data'!G74+'Raw Data'!H74 -> 417 | F17: ='Raw Data'!I74 -> 449 | G17: ='Raw Data'!J74 -> 929 | H17: ='Raw Data'!K74 -> 574 | I17: =F17/E17 -> 1.0767386 | J17: =D17/E17 -> 0.12470024 | K17: =D17/G17 -> 0.055974166 | L17: =LN(G17) -> 6.8341087 | M17: =(B17-'Raw Data'!D73)/'Raw Data'!D73 -> 0.22722401 | N17: =H17/G17 -> 0.61786868 | O17: ='Raw Data'!L74 -> 9.43
A18: FY18-19 | B18: ='Raw Data'!D75 -> 1241 | C18: ='Raw Data'!E75 -> 178 | D18: ='Raw Data'!F75 -> 64 | E18: ='Raw Data'!G75+'Raw Data'!H75 -> 482 | F18: ='Raw Data'!I75 -> 860 | G18: ='Raw Data'!J75 -> 1436 | H18: ='Raw Data'!K75 -> 992 | I18: =F18/E18 -> 1.7842324 | J18: =D18/E18 -> 0.13278008 | K18: =D18/G18 -> 0.044568245 | L18: =LN(G18) -> 7.2696167 | M18: =(B18-'Raw Data'!D74)/'Raw Data'!D74 -> 0.083842795 | N18: =H18/G18 -> 0.6908078 | O18: ='Raw Data'!L75 -> 11.4
A19: FY19-20 | B19: ='Raw Data'!D76 -> 1436 | C19: ='Raw Data'!E76 -> 170 | D19: ='Raw Data'!F76 -> 24 | E19: ='Raw Data'!G76+'Raw Data'!H76 -> 494 | F19: ='Raw Data'!I76 -> 1040 | G19: ='Raw Data'!J76 -> 1645 | H19: ='Raw Data'!K76 -> 1140 | I19: =F19/E19 -> 2.1052632 | J19: =D19/E19 -> 0.048582996 | K19: =D19/G19 -> 0.014589666 | L19: =LN(G19) -> 7.4054957 | M19: =(B19-'Raw Data'!D75)/'Raw Data'!D75 -> 0.15713135 | N19: =H19/G19 -> 0.69300912 | O19: ='Raw Data'!L76 -> 4.24
A20: FY20-21 | B20: ='Raw Data'!D77 -> 1622 | C20: ='Raw Data'!E77 -> 257 | D20: ='Raw Data'!F77 -> 69 | E20: ='Raw Data'!G77+'Raw Data'!H77 -> 563 | F20: ='Raw Data'!I77 -> 962 | G20: ='Raw Data'!J77 -> 1676 | H20: ='Raw Data'!K77 -> 1062 | I20: =F20/E20 -> 1.7087034 | J20: =D20/E20 -> 0.12255773 | K20: =D20/G20 -> 0.041169451 | L20: =LN(G20) -> 7.4241653 | M20: =(B20-'Raw Data'!D76)/'Raw Data'!D76 -> 0.12952646 | N20: =H20/G20 -> 0.63365155 | O20: ='Raw Data'!L77 -> 12.25
A21: FY21-22 | B21: ='Raw Data'!D78 -> 2690 | C21: ='Raw Data'!E78 -> 652 | D21: ='Raw Data'!F78 -> 326 | E21: ='Raw Data'!G78+'Raw Data'!H78 -> 876 | F21: ='Raw Data'!I78 -> 689 | G21: ='Raw Data'!J78 -> 1824 | H21: ='Raw Data'!K78 -> 1012 | I21: =F21/E21 -> 0.78652968 | J21: =D21/E21 -> 0.37214612 | K21: =D21/G21 -> 0.17872807 | L21: =LN(G21) -> 7.5087872 | M21: =(B21-'Raw Data'!D77)/'Raw Data'!D77 -> 0.65844636 | N21: =H21/G21 -> 0.55482456 | O21: ='Raw Data'!L78 -> 58.01
A22: FY22-23 | B22: ='Raw Data'!D79 -> 2404 | C22: ='Raw Data'!E79 -> 297 | D22: ='Raw Data'!F79 -> 165 | E22: ='Raw Data'!G79+'Raw Data'!H79 -> 1029 | F22: ='Raw Data'!I79 -> 980 | G22: ='Raw Data'!J79 -> 2218 | H22: ='Raw Data'!K79 -> 1351 | I22: =F22/E22 -> 0.95238095 | J22: =D22/E22 -> 0.16034985 | K22: =D22/G22 -> 0.074391344 | L22: =LN(G22) -> 7.7043612 | M22: =(B22-'Raw Data'!D78)/'Raw Data'!D78 -> -0.1063197 | N22: =H22/G22 -> 0.6091073 | O22: ='Raw Data'!L79 -> 29.32
A23: FY23-24 | B23: ='Raw Data'!D80 -> 2902 | C23: ='Raw Data'!E80 -> 377 | D23: ='Raw Data'!F80 -> 132 | E23: ='Raw Data'!G80+'Raw Data'!H80 -> 1146 | F23: ='Raw Data'!I80 -> 1339 | G23: ='Raw Data'!J80 -> 2717 | H23: ='Raw Data'!K80 -> 1711 | I23: =F23/E23 -> 1.1684119 | J23: =D23/E23 -> 0.11518325 | K23: =D23/G23 -> 0.048582996 | L23: =LN(G23) -> 7.9072836 | M23: =(B23-'Raw Data'!D79)/'Raw Data'!D79 -> 0.20715474 | N23: =H23/G23 -> 0.62973868 | O23: ='Raw Data'!L80 -> 23.39
A24: FY24-25 | B24: ='Raw Data'!D81 -> 3300 | C24: ='Raw Data'!E81 -> 471 | D24: ='Raw Data'!F81 -> 175 | E24: ='Raw Data'!G81+'Raw Data'!H81 -> 1311 | F24: ='Raw Data'!I81 -> 1165 | G24: ='Raw Data'!J81 -> 2732 | H24: ='Raw Data'!K81 -> 1584 | I24: =F24/E24 -> 0.88863463 | J24: =D24/E24 -> 0.13348589 | K24: =D24/G24 -> 0.064055637 | L24: =LN(G24) -> 7.9127892 | M24: =(B24-'Raw Data'!D80)/'Raw Data'!D80 -> 0.1371468 | N24: =H24/G24 -> 0.57979502 | O24: ='Raw Data'!L81 -> 31.2
A25: 10-YR AVERAGE | B25: =AVERAGE(B15:B24) -> 1843.9 | C25: =AVERAGE(C15:C24) -> 282.7 | D25: =AVERAGE(D15:D24) -> 110.8 | E25: =AVERAGE(E15:E24) -> 678.8 | F25: =AVERAGE(F15:F24) -> 840.4 | G25: =AVERAGE(G15:G24) -> 1669.7 | H25: =AVERAGE(H15:H24) -> 1043.8 | I25: =AVERAGE(I15:I24) -> 1.4331148 | ... O25: =AVERAGE(O15:O24) -> 20.138
A27: SD (10-yr) | I27: =STDEV(I15:I24) -> 0.51486684 | J27: =STDEV(J15:J24) -> 0.087790097 | K27: =STDEV(K15:K24) -> 0.043354037 | O27: =STDEV(O15:O24) -> 16.076643

Sheet Sutlej Textiles
A1: Sutlej Textiles
A3: Screener Ticker | B3: SUTLEJTEX
A4: Basis | B4: Standalone
A5: Primary Business | B5: Yarn, Home Textiles — spinning specialist
A6: Year Established | B6: Current entity incorporated 2005 (demerger); heritage traces to Sutlej Cotton Mills, 1934
A7: Headquarters | B7: Registered office: Jaipur, Rajasthan
A8: Promoter / Group | B8: KK Birla Group — founder Dr. Krishna Kumar Birla
A9: Manufacturing Locations | B9: Bhawanimandi (Rajasthan), Baddi (Himachal Pradesh), Kathua (J&K), Bhillad (Gujarat)
A10: Listed On | B10: NSE & BSE
A11: Note
A13: 10-Year Financials & Computed Ratios (FY2015-16 to FY2024-25)
A14: FY | B14: Sales | C14: EBIT | D14: Net Profit | E14: Total Equity | F14: Borrowings | G14: Total Assets | H14: Fixed Assets | I14: D/E Ratio | J14: ROE | K14: ROA | L14: Size (ln TA) | M14: Sales Growth % | N14: Tangibility | O14: EPS (Rs.)
A15: FY15-16 | B15: ='Raw Data'!D83 -> 2074 | C15: ='Raw Data'!E83 -> 263 | D15: ='Raw Data'!F83 -> 143 | E15: ='Raw Data'!G83+'Raw Data'!H83 -> 683 | F15: ='Raw Data'!I83 -> 804 | G15: ='Raw Data'!J83 -> 1675 | H15: ='Raw Data'!K83 -> 877 | I15: =F15/E15 -> 1.1771596 | J15: =D15/E15 -> 0.20937042 | K15: =D15/G15 -> 0.085373134 | L15: =LN(G15) -> 7.4235684 | M15: =(B15-'Raw Data'!D82)/'Raw Data'!D82 -> 0.11087306 | N15: =H15/G15 -> 0.52358209 | O15: ='Raw Data'!L83 -> 8.76
A16: FY16-17 | B16: ='Raw Data'!D84 -> 2249 | C16: ='Raw Data'!E84 -> 282 | D16: ='Raw Data'!F84 -> 158 | E16: ='Raw Data'!G84+'Raw Data'!H84 -> 816 | F16: ='Raw Data'!I84 -> 1036 | G16: ='Raw Data'!J84 -> 2045 | H16: ='Raw Data'!K84 -> 1139 | I16: =F16/E16 -> 1.2696078 | J16: =D16/E16 -> 0.19362745 | K16: =D16/G16 -> 0.077261614 | L16: =LN(G16) -> 7.6231531 | M16: =(B16-'Raw Data'!D83)/'Raw Data'!D83 -> 0.084378014 | N16: =H16/G16 -> 0.55696822 | O16: ='Raw Data'!L84 -> 9.64
A17: FY17-18 | B17: ='Raw Data'!D85 -> 2453 | C17: ='Raw Data'!E85 -> 247 | D17: ='Raw Data'!F85 -> 113 | E17: ='Raw Data'!G85+'Raw Data'!H85 -> 906 | F17: ='Raw Data'!I85 -> 1047 | G17: ='Raw Data'!J85 -> 2182 | H17: ='Raw Data'!K85 -> 1119 | I17: =F17/E17 -> 1.1556291 | J17: =D17/E17 -> 0.12472406 | K17: =D17/G17 -> 0.051787351 | L17: =LN(G17) -> 7.6879972 | M17: =(B17-'Raw Data'!D84)/'Raw Data'!D84 -> 0.090706981 | N17: =H17/G17 -> 0.51283226 | O17: ='Raw Data'!L85 -> 6.91
A18: FY18-19 | B18: ='Raw Data'!D86 -> 2562 | C18: ='Raw Data'!E86 -> 219 | D18: ='Raw Data'!F86 -> 66 | E18: ='Raw Data'!G86+'Raw Data'!H86 -> 946 | F18: ='Raw Data'!I86 -> 923 | G18: ='Raw Data'!J86 -> 2131 | H18: ='Raw Data'!K86 -> 1074 | I18: =F18/E18 -> 0.9756871 | J18: =D18/E18 -> 0.069767442 | K18: =D18/G18 -> 0.030971375 | L18: =LN(G18) -> 7.6643466 | M18: =(B18-'Raw Data'!D85)/'Raw Data'!D85 -> 0.044435385 | N18: =H18/G18 -> 0.50398874 | O18: ='Raw Data'!L86 -> 4.01
A19: FY19-20 | B19: ='Raw Data'!D87 -> 2379 | C19: ='Raw Data'!E87 -> 178 | D19: ='Raw Data'!F87 -> 36 | E19: ='Raw Data'!G87+'Raw Data'!H87 -> 971 | F19: ='Raw Data'!I87 -> 868 | G19: ='Raw Data'!J87 -> 2118 | H19: ='Raw Data'!K87 -> 1210 | I19: =F19/E19 -> 0.89392379 | J19: =D19/E19 -> 0.03707518 | K19: =D19/G19 -> 0.016997167 | L19: =LN(G19) -> 7.6582275 | M19: =(B19-'Raw Data'!D86)/'Raw Data'!D86 -> -0.071428571 | N19: =H19/G19 -> 0.57129367 | O19: ='Raw Data'!L87 -> 2.2
A20: FY20-21 | B20: ='Raw Data'!D88 -> 1861 | C20: ='Raw Data'!E88 -> 115 | D20: ='Raw Data'!F88 -> 10 | E20: ='Raw Data'!G88+'Raw Data'!H88 -> 980 | F20: ='Raw Data'!I88 -> 901 | G20: ='Raw Data'!J88 -> 2149 | H20: ='Raw Data'!K88 -> 1231 | I20: =F20/E20 -> 0.91938776 | J20: =D20/E20 -> 0.010204082 | K20: =D20/G20 -> 0.0046533271 | L20: =LN(G20) -> 7.6727579 | M20: =(B20-'Raw Data'!D87)/'Raw Data'!D87 -> -0.21773855 | N20: =H20/G20 -> 0.57282457 | O20: ='Raw Data'!L88 -> 0.58
A21: FY21-22 | B21: ='Raw Data'!D89 -> 3042 | C21: ='Raw Data'!E89 -> 387 | D21: ='Raw Data'!F89 -> 156 | E21: ='Raw Data'!G89+'Raw Data'!H89 -> 1130 | F21: ='Raw Data'!I89 -> 938 | G21: ='Raw Data'!J89 -> 2442 | H21: ='Raw Data'!K89 -> 1187 | I21: =F21/E21 -> 0.8300885 | J21: =D21/E21 -> 0.1380531 | K21: =D21/G21 -> 0.063882064 | L21: =LN(G21) -> 7.8005727 | M21: =(B21-'Raw Data'!D88)/'Raw Data'!D88 -> 0.63460505 | N21: =H21/G21 -> 0.48607699 | O21: ='Raw Data'!L89 -> 9.5
A22: FY22-23 | B22: ='Raw Data'!D90 -> 3039 | C22: ='Raw Data'!E90 -> 264 | D22: ='Raw Data'!F90 -> 23 | E22: ='Raw Data'!G90+'Raw Data'!H90 -> 1123 | F22: ='Raw Data'!I90 -> 933 | G22: ='Raw Data'!J90 -> 2421 | H22: ='Raw Data'!K90 -> 1121 | I22: =F22/E22 -> 0.83081033 | J22: =D22/E22 -> 0.020480855 | K22: =D22/G22 -> 0.0095002065 | L22: =LN(G22) -> 7.791936 | M22: =(B22-'Raw Data'!D89)/'Raw Data'!D89 -> -0.00098619329 | N22: =H22/G22 -> 0.46303181 | O22: ='Raw Data'!L90 -> 1.39
A23: FY23-24 | B23: ='Raw Data'!D91 -> 2672 | C23: ='Raw Data'!E91 -> -29 | D23: ='Raw Data'!F91 -> -135 | E23: ='Raw Data'!G91+'Raw Data'!H91 -> 976 | F23: ='Raw Data'!I91 -> 826 | G23: ='Raw Data'!J91 -> 2097 | H23: ='Raw Data'!K91 -> 1063 | I23: =F23/E23 -> 0.84631148 | J23: =D23/E23 -> -0.13831967 | K23: =D23/G23 -> -0.064377682 | L23: =LN(G23) -> 7.648263 | M23: =(B23-'Raw Data'!D90)/'Raw Data'!D90 -> -0.12076341 | N23: =H23/G23 -> 0.50691464 | O23: ='Raw Data'!L91 -> -8.22
A24: FY24-25 | B24: ='Raw Data'!D92 -> 2642 | C24: ='Raw Data'!E92 -> 46 | D24: ='Raw Data'!F92 -> -84 | E24: ='Raw Data'!G92+'Raw Data'!H92 -> 894 | F24: ='Raw Data'!I92 -> 877 | G24: ='Raw Data'!J92 -> 2043 | H24: ='Raw Data'!K92 -> 1010 | I24: =F24/E24 -> 0.98098434 | J24: =D24/E24 -> -0.093959732 | K24: =D24/G24 -> -0.041116006 | L24: =LN(G24) -> 7.6221746 | M24: =(B24-'Raw Data'!D91)/'Raw Data'!D91 -> -0.011227545 | N24: =H24/G24 -> 0.49437102 | O24: ='Raw Data'!L92 -> -5.14
A25: 10-YR AVERAGE | B25: =AVERAGE(B15:B24) -> 2497.3 | C25: =AVERAGE(C15:C24) -> 197.2 | D25: =AVERAGE(D15:D24) -> 48.6 | E25: =AVERAGE(E15:E24) -> 942.5 | F25: =AVERAGE(F15:F24) -> 915.3 | G25: =AVERAGE(G15:G24) -> 2130.3 | H25: =AVERAGE(H15:H24) -> 1103.1 | I25: =AVERAGE(I15:I24) -> 0.98795899 | ... O25: =AVERAGE(O15:O24) -> 2.963
A27: SD (10-yr) | I27: =STDEV(I15:I24) -> 0.1586971 | J27: =STDEV(J15:J24) -> 0.11453383 | K27: =STDEV(K15:K24) -> 0.049099101 | O27: =STDEV(O15:O24) -> 6.1196243

Sheet Gokaldas Exports
A1: Gokaldas Exports
A3: Screener Ticker | B3: GOKEX
A4: Basis | B4: Standalone
A5: Primary Business | B5: Apparel / Garment Exports
A6: Year Established | B6: 1979
A7: Headquarters | B7: Bengaluru, Karnataka
A8: Promoter / Group | B8: Founded by Jhamandas Hinduja; Blackstone Group has held majority stake since 2007
A9: Manufacturing Locations | B9: Bengaluru region, Karnataka; also Kenya and Ethiopia
A10: Listed On | B10: NSE & BSE
A11: Note
A13: 10-Year Financials & Computed Ratios (FY2015-16 to FY2024-25)
A14: FY | B14: Sales | C14: EBIT | D14: Net Profit | E14: Total Equity | F14: Borrowings | G14: Total Assets | H14: Fixed Assets | I14: D/E Ratio | J14: ROE | K14: ROA | L14: Size (ln TA) | M14: Sales Growth % | N14: Tangibility | O14: EPS (Rs.)
A15: FY15-16 | B15: ='Raw Data'!D94 -> 1123 | C15: ='Raw Data'!E94 -> 37 | D15: ='Raw Data'!F94 -> 61 | E15: ='Raw Data'!G94+'Raw Data'!H94 -> 212 | F15: ='Raw Data'!I94 -> 343 | G15: ='Raw Data'!J94 -> 725 | H15: ='Raw Data'!K94 -> 94 | I15: =F15/E15 -> 1.6179245 | J15: =D15/E15 -> 0.28773585 | K15: =D15/G15 -> 0.084137931 | L15: =LN(G15) -> 6.5861717 | M15: =(B15-'Raw Data'!D93)/'Raw Data'!D93 -> 0.04953271 | N15: =H15/G15 -> 0.12965517 | O15: ='Raw Data'!L94 -> 17.44
A16: FY16-17 | B16: ='Raw Data'!D95 -> 915 | C16: ='Raw Data'!E95 -> -31 | D16: ='Raw Data'!F95 -> -46 | E16: ='Raw Data'!G95+'Raw Data'!H95 -> 165 | F16: ='Raw Data'!I95 -> 474 | G16: ='Raw Data'!J95 -> 794 | H16: ='Raw Data'!K95 -> 95 | I16: =F16/E16 -> 2.8727273 | J16: =D16/E16 -> -0.27878788 | K16: =D16/G16 -> -0.057934509 | L16: =LN(G16) -> 6.6770835 | M16: =(B16-'Raw Data'!D94)/'Raw Data'!D94 -> -0.18521817 | N16: =H16/G16 -> 0.11964736 | O16: ='Raw Data'!L95 -> -13.23
A17: FY17-18 | B17: ='Raw Data'!D96 -> 1031 | C17: ='Raw Data'!E96 -> -23 | D17: ='Raw Data'!F96 -> -31 | E17: ='Raw Data'!G96+'Raw Data'!H96 -> 130 | F17: ='Raw Data'!I96 -> 472 | G17: ='Raw Data'!J96 -> 794 | H17: ='Raw Data'!K96 -> 95 | I17: =F17/E17 -> 3.6307692 | J17: =D17/E17 -> -0.23846154 | K17: =D17/G17 -> -0.039042821 | L17: =LN(G17) -> 6.6770835 | M17: =(B17-'Raw Data'!D95)/'Raw Data'!D95 -> 0.12677596 | N17: =H17/G17 -> 0.11964736 | O17: ='Raw Data'!L96 -> -8.83
A18: FY18-19 | B18: ='Raw Data'!D97 -> 1173 | C18: ='Raw Data'!E97 -> 62 | D18: ='Raw Data'!F97 -> 26 | E18: ='Raw Data'!G97+'Raw Data'!H97 -> 239 | F18: ='Raw Data'!I97 -> 381 | G18: ='Raw Data'!J97 -> 823 | H18: ='Raw Data'!K97 -> 108 | I18: =F18/E18 -> 1.5941423 | J18: =D18/E18 -> 0.10878661 | K18: =D18/G18 -> 0.031591738 | L18: =LN(G18) -> 6.7129562 | M18: =(B18-'Raw Data'!D96)/'Raw Data'!D96 -> 0.13773036 | N18: =H18/G18 -> 0.13122722 | O18: ='Raw Data'!L97 -> 5.99
A19: FY19-20 | B19: ='Raw Data'!D98 -> 1368 | C19: ='Raw Data'!E98 -> 87 | D19: ='Raw Data'!F98 -> 32 | E19: ='Raw Data'!G98+'Raw Data'!H98 -> 228 | F19: ='Raw Data'!I98 -> 440 | G19: ='Raw Data'!J98 -> 939 | H19: ='Raw Data'!K98 -> 172 | I19: =F19/E19 -> 1.9298246 | J19: =D19/E19 -> 0.14035088 | K19: =D19/G19 -> 0.034078807 | L19: =LN(G19) -> 6.8448155 | M19: =(B19-'Raw Data'!D97)/'Raw Data'!D97 -> 0.16624041 | N19: =H19/G19 -> 0.18317359 | O19: ='Raw Data'!L98 -> 7.56
A20: FY20-21 | B20: ='Raw Data'!D99 -> 1209 | C20: ='Raw Data'!E99 -> 101 | D20: ='Raw Data'!F99 -> 26 | E20: ='Raw Data'!G99+'Raw Data'!H99 -> 291 | F20: ='Raw Data'!I99 -> 476 | G20: ='Raw Data'!J99 -> 1005 | H20: ='Raw Data'!K99 -> 235 | I20: =F20/E20 -> 1.6357388 | J20: =D20/E20 -> 0.089347079 | K20: =D20/G20 -> 0.025870647 | L20: =LN(G20) -> 6.9127428 | M20: =(B20-'Raw Data'!D98)/'Raw Data'!D98 -> -0.11622807 | N20: =H20/G20 -> 0.23383085 | O20: ='Raw Data'!L99 -> 6.12
A21: FY21-22 | B21: ='Raw Data'!D100 -> 1789 | C21: ='Raw Data'!E100 -> 204 | D21: ='Raw Data'!F100 -> 117 | E21: ='Raw Data'!G100+'Raw Data'!H100 -> 709 | F21: ='Raw Data'!I100 -> 191 | G21: ='Raw Data'!J100 -> 1226 | H21: ='Raw Data'!K100 -> 282 | I21: =F21/E21 -> 0.26939351 | J21: =D21/E21 -> 0.16502116 | K21: =D21/G21 -> 0.0954323 | L21: =LN(G21) -> 7.1115121 | M21: =(B21-'Raw Data'!D99)/'Raw Data'!D99 -> 0.47973532 | N21: =H21/G21 -> 0.23001631 | O21: ='Raw Data'!L100 -> 19.79
A22: FY22-23 | B22: ='Raw Data'!D101 -> 2221 | C22: ='Raw Data'!E101 -> 269 | D22: ='Raw Data'!F101 -> 178 | E22: ='Raw Data'!G101+'Raw Data'!H101 -> 893 | F22: ='Raw Data'!I101 -> 141 | G22: ='Raw Data'!J101 -> 1343 | H22: ='Raw Data'!K101 -> 261 | I22: =F22/E22 -> 0.15789474 | J22: =D22/E22 -> 0.19932811 | K22: =D22/G22 -> 0.13253909 | L22: =LN(G22) -> 7.2026612 | M22: =(B22-'Raw Data'!D100)/'Raw Data'!D100 -> 0.24147568 | N22: =H22/G22 -> 0.19434103 | O22: ='Raw Data'!L101 -> 29.45
A23: FY23-24 | B23: ='Raw Data'!D102 -> 2139 | C23: ='Raw Data'!E102 -> 255 | D23: ='Raw Data'!F102 -> 164 | E23: ='Raw Data'!G102+'Raw Data'!H102 -> 1342 | F23: ='Raw Data'!I102 -> 254 | G23: ='Raw Data'!J102 -> 1955 | H23: ='Raw Data'!K102 -> 254 | I23: =F23/E23 -> 0.18926975 | J23: =D23/E23 -> 0.12220566 | K23: =D23/G23 -> 0.083887468 | L23: =LN(G23) -> 7.5781455 | M23: =(B23-'Raw Data'!D101)/'Raw Data'!D101 -> -0.036920306 | N23: =H23/G23 -> 0.12992327 | O23: ='Raw Data'!L102 -> 25.9
A24: FY24-25 | B24: ='Raw Data'!D103 -> 2477 | C24: ='Raw Data'!E103 -> 244 | D24: ='Raw Data'!F103 -> 191 | E24: ='Raw Data'!G103+'Raw Data'!H103 -> 2145 | F24: ='Raw Data'!I103 -> 192 | G24: ='Raw Data'!J103 -> 2763 | H24: ='Raw Data'!K103 -> 272 | I24: =F24/E24 -> 0.08951049 | J24: =D24/E24 -> 0.089044289 | K24: =D24/G24 -> 0.06912776 | L24: =LN(G24) -> 7.9240723 | M24: =(B24-'Raw Data'!D102)/'Raw Data'!D102 -> 0.15801777 | N24: =H24/G24 -> 0.098443721 | O24: ='Raw Data'!L103 -> 26.77
A25: 10-YR AVERAGE | B25: =AVERAGE(B15:B24) -> 1544.5 | C25: =AVERAGE(C15:C24) -> 120.5 | D25: =AVERAGE(D15:D24) -> 71.8 | E25: =AVERAGE(E15:E24) -> 635.4 | F25: =AVERAGE(F15:F24) -> 336.4 | G25: =AVERAGE(G15:G24) -> 1236.7 | H25: =AVERAGE(H15:H24) -> 186.8 | I25: =AVERAGE(I15:I24) -> 1.3987195 | ... O25: =AVERAGE(O15:O24) -> 11.696
A27: SD (10-yr) | I27: =STDEV(I15:I24) -> 1.2279638 | J27: =STDEV(J15:J24) -> 0.1825308 | K27: =STDEV(K15:K24) -> 0.059765263 | O27: =STDEV(O15:O24) -> 14.780125

Sheet Siyaram Silk Mills
A1: Siyaram Silk Mills
A3: Screener Ticker | B3: SIYSIL
A4: Basis | B4: Standalone
A5: Primary Business | B5: Fabrics, Readymade Garments (Menswear) — branded player
A6: Year Established | B6: 1978
A7: Headquarters | B7: Mumbai, Maharashtra (registered plant: Tarapur, Maharashtra)
A8: Promoter / Group | B8: Poddar family (Chairman & MD: Ramesh Poddar)
A9: Manufacturing Locations | B9: Tarapur, Daman, Amravati, Silvassa
A10: Listed On | B10: NSE & BSE (BSE code: 503811)
A11: Note | B11: Substituted for Raymond Ltd (see Cover & Notes for rationale)
A13: 10-Year Financials & Computed Ratios (FY2015-16 to FY2024-25)
A14: FY | B14: Sales | C14: EBIT | D14: Net Profit | E14: Total Equity | F14: Borrowings | G14: Total Assets | H14: Fixed Assets | I14: D/E Ratio | J14: ROE | K14: ROA | L14: Size (ln TA) | M14: Sales Growth % | N14: Tangibility | O14: EPS (Rs.)
A15: FY15-16 | B15: ='Raw Data'!D105 -> 1609 | C15: ='Raw Data'!E105 -> 196 | D15: ='Raw Data'!F105 -> 84 | E15: ='Raw Data'!G105+'Raw Data'!H105 -> 506 | F15: ='Raw Data'!I105 -> 408 | G15: ='Raw Data'!J105 -> 1195 | H15: ='Raw Data'!K105 -> 403 | I15: =F15/E15 -> 0.80632411 | J15: =D15/E15 -> 0.16600791 | K15: =D15/G15 -> 0.070292887 | L15: =LN(G15) -> 7.0859015 | M15: =(B15-'Raw Data'!D104)/'Raw Data'!D104 -> 0.075534759 | N15: =H15/G15 -> 0.33723849 | O15: ='Raw Data'!L105 -> 17.93
A16: FY16-17 | B16: ='Raw Data'!D106 -> 1570 | C16: ='Raw Data'!E106 -> 197 | D16: ='Raw Data'!F106 -> 91 | E16: ='Raw Data'!G106+'Raw Data'!H106 -> 596 | F16: ='Raw Data'!I106 -> 305 | G16: ='Raw Data'!J106 -> 1159 | H16: ='Raw Data'!K106 -> 445 | I16: =F16/E16 -> 0.51174497 | J16: =D16/E16 -> 0.15268456 | K16: =D16/G16 -> 0.078515962 | L16: =LN(G16) -> 7.0553128 | M16: =(B16-'Raw Data'!D105)/'Raw Data'!D105 -> -0.024238658 | N16: =H16/G16 -> 0.38395168 | O16: ='Raw Data'!L106 -> 19.41
A17: FY17-18 | B17: ='Raw Data'!D107 -> 1733 | C17: ='Raw Data'!E107 -> 246 | D17: ='Raw Data'!F107 -> 112 | E17: ='Raw Data'!G107+'Raw Data'!H107 -> 678 | F17: ='Raw Data'!I107 -> 573 | G17: ='Raw Data'!J107 -> 1553 | H17: ='Raw Data'!K107 -> 532 | I17: =F17/E17 -> 0.84513274 | J17: =D17/E17 -> 0.16519174 | K17: =D17/G17 -> 0.07211848 | L17: =LN(G17) -> 7.3479438 | M17: =(B17-'Raw Data'!D106)/'Raw Data'!D106 -> 0.10382166 | N17: =H17/G17 -> 0.34256278 | O17: ='Raw Data'!L107 -> 23.81
A18: FY18-19 | B18: ='Raw Data'!D108 -> 1815 | C18: ='Raw Data'!E108 -> 241 | D18: ='Raw Data'!F108 -> 101 | E18: ='Raw Data'!G108+'Raw Data'!H108 -> 757 | F18: ='Raw Data'!I108 -> 444 | G18: ='Raw Data'!J108 -> 1505 | H18: ='Raw Data'!K108 -> 527 | I18: =F18/E18 -> 0.58652576 | J18: =D18/E18 -> 0.1334214 | K18: =D18/G18 -> 0.067109635 | L18: =LN(G18) -> 7.3165482 | M18: =(B18-'Raw Data'!D107)/'Raw Data'!D107 -> 0.047316792 | N18: =H18/G18 -> 0.35016611 | O18: ='Raw Data'!L108 -> 21.58
A19: FY19-20 | B19: ='Raw Data'!D109 -> 1698 | C19: ='Raw Data'!E109 -> 169 | D19: ='Raw Data'!F109 -> 72 | E19: ='Raw Data'!G109+'Raw Data'!H109 -> 767 | F19: ='Raw Data'!I109 -> 428 | G19: ='Raw Data'!J109 -> 1503 | H19: ='Raw Data'!K109 -> 552 | I19: =F19/E19 -> 0.55801825 | J19: =D19/E19 -> 0.093872229 | K19: =D19/G19 -> 0.047904192 | L19: =LN(G19) -> 7.3152184 | M19: =(B19-'Raw Data'!D108)/'Raw Data'!D108 -> -0.06446281 | N19: =H19/G19 -> 0.36726547 | O19: ='Raw Data'!L109 -> 15.3
A20: FY20-21 | B20: ='Raw Data'!D110 -> 1088 | C20: ='Raw Data'!E110 -> 55 | D20: ='Raw Data'!F110 -> 5 | E20: ='Raw Data'!G110+'Raw Data'!H110 -> 774 | F20: ='Raw Data'!I110 -> 139 | G20: ='Raw Data'!J110 -> 1217 | H20: ='Raw Data'!K110 -> 490 | I20: =F20/E20 -> 0.17958656 | J20: =D20/E20 -> 0.0064599483 | K20: =D20/G20 -> 0.0041084634 | L20: =LN(G20) -> 7.1041441 | M20: =(B20-'Raw Data'!D109)/'Raw Data'!D109 -> -0.35924617 | N20: =H20/G20 -> 0.40262942 | O20: ='Raw Data'!L110 -> 1.14
A21: FY21-22 | B21: ='Raw Data'!D111 -> 1903 | C21: ='Raw Data'!E111 -> 334 | D21: ='Raw Data'!F111 -> 213 | E21: ='Raw Data'!G111+'Raw Data'!H111 -> 937 | F21: ='Raw Data'!I111 -> 223 | G21: ='Raw Data'!J111 -> 1515 | H21: ='Raw Data'!K111 -> 500 | I21: =F21/E21 -> 0.2379936 | J21: =D21/E21 -> 0.22732124 | K21: =D21/G21 -> 0.14059406 | L21: =LN(G21) -> 7.3231707 | M21: =(B21-'Raw Data'!D110)/'Raw Data'!D110 -> 0.74908088 | N21: =H21/G21 -> 0.330033 | O21: ='Raw Data'!L111 -> 45.34
A22: FY22-23 | B22: ='Raw Data'!D112 -> 2229 | C22: ='Raw Data'!E112 -> 369 | D22: ='Raw Data'!F112 -> 252 | E22: ='Raw Data'!G112+'Raw Data'!H112 -> 1141 | F22: ='Raw Data'!I112 -> 163 | G22: ='Raw Data'!J112 -> 1640 | H22: ='Raw Data'!K112 -> 482 | I22: =F22/E22 -> 0.14285714 | J22: =D22/E22 -> 0.2208589 | K22: =D22/G22 -> 0.15365854 | L22: =LN(G22) -> 7.4024515 | M22: =(B22-'Raw Data'!D111)/'Raw Data'!D111 -> 0.17130846 | N22: =H22/G22 -> 0.29390244 | O22: ='Raw Data'!L112 -> 53.73
A23: FY23-24 | B23: ='Raw Data'!D113 -> 2087 | C23: ='Raw Data'!E113 -> 286 | D23: ='Raw Data'!F113 -> 185 | E23: ='Raw Data'!G113+'Raw Data'!H113 -> 1141 | F23: ='Raw Data'!I113 -> 175 | G23: ='Raw Data'!J113 -> 1606 | H23: ='Raw Data'!K113 -> 493 | I23: =F23/E23 -> 0.15337423 | J23: =D23/E23 -> 0.16213848 | K23: =D23/G23 -> 0.11519303 | L23: =LN(G23) -> 7.3815019 | M23: =(B23-'Raw Data'!D112)/'Raw Data'!D112 -> -0.063705698 | N23: =H23/G23 -> 0.30697385 | O23: ='Raw Data'!L113 -> 40.7
A24: FY24-25 | B24: ='Raw Data'!D114 -> 2220 | C24: ='Raw Data'!E114 -> 277 | D24: ='Raw Data'!F114 -> 199 | E24: ='Raw Data'!G114+'Raw Data'!H114 -> 1288 | F24: ='Raw Data'!I114 -> 262 | G24: ='Raw Data'!J114 -> 1893 | H24: ='Raw Data'!K114 -> 592 | I24: =F24/E24 -> 0.20341615 | J24: =D24/E24 -> 0.15450311 | K24: =D24/G24 -> 0.10512414 | L24: =LN(G24) -> 7.5459182 | M24: =(B24-'Raw Data'!D113)/'Raw Data'!D113 -> 0.063727839 | N24: =H24/G24 -> 0.31273111 | O24: ='Raw Data'!L114 -> 43.8
A25: 10-YR AVERAGE | B25: =AVERAGE(B15:B24) -> 1795.2 | C25: =AVERAGE(C15:C24) -> 237 | D25: =AVERAGE(D15:D24) -> 131.4 | E25: =AVERAGE(E15:E24) -> 858.5 | F25: =AVERAGE(F15:F24) -> 312 | G25: =AVERAGE(G15:G24) -> 1478.6 | H25: =AVERAGE(H15:H24) -> 501.6 | I25: =AVERAGE(I15:I24) -> 0.42249735 | ... O25: =AVERAGE(O15:O24) -> 28.274
A27: SD (10-yr) | I27: =STDEV(I15:I24) -> 0.27301807 | J27: =STDEV(J15:J24) -> 0.062945817 | K27: =STDEV(K15:K24) -> 0.044451022 | O27: =STDEV(O15:O24) -> 16.631973

Sheet Ratios Panel
A1: Computed Capital Structure & Performance Ratios — FY2015-16 to FY2024-25 (Panel of 100 firm-years)
A2: Total Equity = Equity Capital + Reserves | D/E = Borrowings / Total Equity | ROE = Net Profit / Total Equity | ROA = Net Profit / Total Assets | EPS = Net Profit / Shares Outstanding (as reported by Screener.in, split-adjusted) | Size = LN(Total Assets) | Sales Growth = (Salest - Salest-1)/Salest-1 | Tangibility = Fixed Assets / Total Assets
A4: Company | B4: FY | C4: Sales | D4: EBIT | E4: Net Profit | F4: Total Equity | G4: Borrowings | H4: Total Assets | I4: Fixed Assets | J4: D/E Ratio | K4: ROE | L4: ROA | M4: Size (ln TA) | N4: Sales Growth % | O4: Tangibility | P4: EPS (Rs.)
A5: KPR Mill | B5: FY15-16 | C5: ='Raw Data'!D6 -> 1961 | D5: ='Raw Data'!E6 -> 356 | E5: ='Raw Data'!F6 -> 156 | F5: ='Raw Data'!G6+'Raw Data'!H6 -> 981 | G5: ='Raw Data'!I6 -> 590 | H5: ='Raw Data'!J6 -> 1730 | I5: ='Raw Data'!K6 -> 894 | J5: =G5/F5 -> 0.60142712 | K5: =E5/F5 -> 0.15902141 | L5: =E5/H5 -> 0.09017341 | M5: =LN(H5) -> 7.4558767 | N5: =(C5-'Raw Data'!D5)/'Raw Data'!D5 -> -0.057211538 | O5: =I5/H5 -> 0.51676301 | P5: ='Raw Data'!L6 -> 4.14
A6: KPR Mill | B6: FY16-17 | C6: ='Raw Data'!D7 -> 2219 | D6: ='Raw Data'!E7 -> 446 | E6: ='Raw Data'!F7 -> 238 | F6: ='Raw Data'!G7+'Raw Data'!H7 -> 1118 | G6: ='Raw Data'!I7 -> 491 | H6: ='Raw Data'!J7 -> 1800 | I6: ='Raw Data'!K7 -> 918 | J6: =G6/F6 -> 0.4391771 | K6: =E6/F6 -> 0.21288014 | L6: =E6/H6 -> 0.13222222 | M6: =LN(H6) -> 7.4955419 | N6: =(C6-'Raw Data'!D6)/'Raw Data'!D6 -> 0.13156553 | O6: =I6/H6 -> 0.51 | P6: ='Raw Data'!L7 -> 6.45
A7: KPR Mill | B7: FY17-18 | C7: ='Raw Data'!D8 -> 2512 | D7: ='Raw Data'!E8 -> 429 | E7: ='Raw Data'!F8 -> 225 | F7: ='Raw Data'!G8+'Raw Data'!H8 -> 1337 | G7: ='Raw Data'!I8 -> 346 | H7: ='Raw Data'!J8 -> 1930 | I7: ='Raw Data'!K8 -> 865 | J7: =G7/F7 -> 0.25878833 | K7: =E7/F7 -> 0.16828721 | L7: =E7/H7 -> 0.11658031 | M7: =LN(H7) -> 7.5652753 | N7: =(C7-'Raw Data'!D7)/'Raw Data'!D7 -> 0.13204146 | O7: =I7/H7 -> 0.44818653 | P7: ='Raw Data'!L8 -> 6.09
A8: KPR Mill | B8: FY18-19 | C8: ='Raw Data'!D9 -> 2979 | D8: ='Raw Data'!E9 -> 507 | E8: ='Raw Data'!F9 -> 289 | F8: ='Raw Data'!G9+'Raw Data'!H9 -> 1511 | G8: ='Raw Data'!I9 -> 654 | H8: ='Raw Data'!J9 -> 2397 | I8: ='Raw Data'!K9 -> 798 | J8: =G8/F8 -> 0.43282594 | K8: =E8/F8 -> 0.19126406 | L8: =E8/H8 -> 0.12056738 | M8: =LN(H8) -> 7.7819732 | N8: =(C8-'Raw Data'!D8)/'Raw Data'!D8 -> 0.18590764 | O8: =I8/H8 -> 0.33291615 | P8: ='Raw Data'!L9 -> 7.97
A9: KPR Mill | B9: FY19-20 | C9: ='Raw Data'!D10 -> 2898 | D9: ='Raw Data'!E10 -> 475 | E9: ='Raw Data'!F10 -> 295 | F9: ='Raw Data'!G10+'Raw Data'!H10 -> 1504 | G9: ='Raw Data'!I10 -> 472 | H9: ='Raw Data'!J10 -> 2187 | I9: ='Raw Data'!K10 -> 873 | J9: =G9/F9 -> 0.31382979 | K9: =E9/F9 -> 0.19614362 | L9: =E9/H9 -> 0.13488797 | M9: =LN(H9) -> 7.690286 | N9: =(C9-'Raw Data'!D9)/'Raw Data'!D9 -> -0.027190332 | O9: =I9/H9 -> 0.39917695 | P9: ='Raw Data'!L10 -> 8.56
A10: KPR Mill | B10: FY20-21 | C10: ='Raw Data'!D11 -> 2954 | D10: ='Raw Data'!E11 -> 664 | E10: ='Raw Data'!F11 -> 433 | F10: ='Raw Data'!G11+'Raw Data'!H11 -> 1906 | G10: ='Raw Data'!I11 -> 317 | H10: ='Raw Data'!J11 -> 2485 | I10: ='Raw Data'!K11 -> 815 | J10: =G10/F10 -> 0.16631689 | K10: =E10/F10 -> 0.22717733 | L10: =E10/H10 -> 0.17424547 | M10: =LN(H10) -> 7.8180279 | N10: =(C10-'Raw Data'!D10)/'Raw Data'!D10 -> 0.019323671 | O10: =I10/H10 -> 0.32796781 | P10: ='Raw Data'!L11 -> 12.57
A11: KPR Mill | B11: FY21-22 | C11: ='Raw Data'!D12 -> 4074 | D11: ='Raw Data'!E12 -> 984 | E11: ='Raw Data'!F12 -> 731 | F11: ='Raw Data'!G12+'Raw Data'!H12 -> 2632 | G11: ='Raw Data'!I12 -> 418 | H11: ='Raw Data'!J12 -> 3359 | I11: ='Raw Data'!K12 -> 850 | J11: =G11/F11 -> 0.15881459 | K11: =E11/F11 -> 0.27773556 | L11: =E11/H11 -> 0.21762429 | M11: =LN(H11) -> 8.1193986 | N11: =(C11-'Raw Data'!D11)/'Raw Data'!D11 -> 0.37914692 | O11: =I11/H11 -> 0.2530515 | P11: ='Raw Data'!L12 -> 21.24
A12: KPR Mill | B12: FY22-23 | C12: ='Raw Data'!D13 -> 4740 | D12: ='Raw Data'!E13 -> 799 | E12: ='Raw Data'!F13 -> 635 | F12: ='Raw Data'!G13+'Raw Data'!H13 -> 2973 | G12: ='Raw Data'!I13 -> 498 | H12: ='Raw Data'!J13 -> 3874 | I12: ='Raw Data'!K13 -> 971 | J12: =G12/F12 -> 0.16750757 | K12: =E12/F12 -> 0.21358897 | L12: =E12/H12 -> 0.16391327 | M12: =LN(H12) -> 8.2620428 | N12: =(C12-'Raw Data'!D12)/'Raw Data'!D12 -> 0.1634757 | O12: =I12/H12 -> 0.25064533 | P12: ='Raw Data'!L13 -> 18.58
A13: KPR Mill | B13: FY23-24 | C13: ='Raw Data'!D14 -> 4054 | D13: ='Raw Data'!E14 -> 595 | E13: ='Raw Data'!F14 -> 555 | F13: ='Raw Data'!G14+'Raw Data'!H14 -> 3374 | G13: ='Raw Data'!I14 -> 287 | H13: ='Raw Data'!J14 -> 3919 | I13: ='Raw Data'!K14 -> 1070 | J13: =G13/F13 -> 0.085062241 | K13: =E13/F13 -> 0.16449318 | L13: =E13/H13 -> 0.14161776 | M13: =LN(H13) -> 8.2735918 | N13: =(C13-'Raw Data'!D13)/'Raw Data'!D13 -> -0.14472574 | O13: =I13/H13 -> 0.27302883 | P13: ='Raw Data'!L14 -> 16.23
A14: KPR Mill | B14: FY24-25 | C14: ='Raw Data'!D15 -> 4216 | D14: ='Raw Data'!E15 -> 764 | E14: ='Raw Data'!F15 -> 653 | F14: ='Raw Data'!G15+'Raw Data'!H15 -> 3856 | G14: ='Raw Data'!I15 -> 241 | H14: ='Raw Data'!J15 -> 4403 | I14: ='Raw Data'!K15 -> 1122 | J14: =G14/F14 -> 0.0625 | K14: =E14/F14 -> 0.16934647 | L14: =E14/H14 -> 0.14830797 | M14: =LN(H14) -> 8.3900414 | N14: =(C14-'Raw Data'!D14)/'Raw Data'!D14 -> 0.039960533 | O14: =I14/H14 -> 0.25482625 | P14: ='Raw Data'!L15 -> 19.11
A15: Welspun Living | B15: FY15-16 | C15: ='Raw Data'!D17 -> 4885 | D15: ='Raw Data'!E17 -> 1275 | E15: ='Raw Data'!F17 -> 648 | F15: ='Raw Data'!G17+'Raw Data'!H17 -> 1899 | G15: ='Raw Data'!I17 -> 2566 | H15: ='Raw Data'!J17 -> 5362 | I15: ='Raw Data'!K17 -> 2830 | J15: =G15/F15 -> 1.3512375 | K15: =E15/F15 -> 0.34123223 | L15: =E15/H15 -> 0.12085043 | M15: =LN(H15) -> 8.5870923 | N15: =(C15-'Raw Data'!D16)/'Raw Data'!D16 -> 0.11275626 | O15: =I15/H15 -> 0.52778814 | P15: ='Raw Data'!L17 -> 6.45
A16: Welspun Living | B16: FY16-17 | C16: ='Raw Data'!D18 -> 5639 | D16: ='Raw Data'!E18 -> 1370 | E16: ='Raw Data'!F18 -> 307 | F16: ='Raw Data'!G18+'Raw Data'!H18 -> 2201 | G16: ='Raw Data'!I18 -> 2738 | H16: ='Raw Data'!J18 -> 6248 | I16: ='Raw Data'!K18 -> 3057 | J16: =G16/F16 -> 1.24398 | K16: =E16/F16 -> 0.13948205 | L16: =E16/H16 -> 0.049135723 | M16: =LN(H16) -> 8.7400167 | N16: =(C16-'Raw Data'!D17)/'Raw Data'!D17 -> 0.15435005 | O16: =I16/H16 -> 0.48927657 | P16: ='Raw Data'!L18 -> 3.05
A17: Welspun Living | B17: FY17-18 | C17: ='Raw Data'!D19 -> 4977 | D17: ='Raw Data'!E19 -> 894 | E17: ='Raw Data'!F19 -> 304 | F17: ='Raw Data'!G19+'Raw Data'!H19 -> 2429 | G17: ='Raw Data'!I19 -> 2721 | H17: ='Raw Data'!J19 -> 6248 | I17: ='Raw Data'!K19 -> 2846 | J17: =G17/F17 -> 1.1202141 | K17: =E17/F17 -> 0.12515438 | L17: =E17/H17 -> 0.04865557 | M17: =LN(H17) -> 8.7400167 | N17: =(C17-'Raw Data'!D18)/'Raw Data'!D18 -> -0.1173967 | O17: =I17/H17 -> 0.45550576 | P17: ='Raw Data'!L19 -> 3.03
A18: Welspun Living | B18: FY18-19 | C18: ='Raw Data'!D20 -> 5395 | D18: ='Raw Data'!E20 -> 795 | E18: ='Raw Data'!F20 -> 142 | F18: ='Raw Data'!G20+'Raw Data'!H20 -> 2489 | G18: ='Raw Data'!I20 -> 2510 | H18: ='Raw Data'!J20 -> 6264 | I18: ='Raw Data'!K20 -> 2654 | J18: =G18/F18 -> 1.0084371 | K18: =E18/F18 -> 0.057051025 | L18: =E18/H18 -> 0.022669221 | M18: =LN(H18) -> 8.7425742 | N18: =(C18-'Raw Data'!D19)/'Raw Data'!D19 -> 0.083986337 | O18: =I18/H18 -> 0.42369093 | P18: ='Raw Data'!L20 -> 1.41
A19: Welspun Living | B19: FY19-20 | C19: ='Raw Data'!D21 -> 5324 | D19: ='Raw Data'!E21 -> 1009 | E19: ='Raw Data'!F21 -> 475 | F19: ='Raw Data'!G21+'Raw Data'!H21 -> 2807 | G19: ='Raw Data'!I21 -> 2275 | H19: ='Raw Data'!J21 -> 6221 | I19: ='Raw Data'!K21 -> 2385 | J19: =G19/F19 -> 0.81047382 | K19: =E19/F19 -> 0.16921981 | L19: =E19/H19 -> 0.076354284 | M19: =LN(H19) -> 8.7356859 | N19: =(C19-'Raw Data'!D20)/'Raw Data'!D20 -> -0.013160334 | O19: =I19/H19 -> 0.38337888 | P19: ='Raw Data'!L21 -> 4.73
A20: Welspun Living | B20: FY20-21 | C20: ='Raw Data'!D22 -> 5956 | D20: ='Raw Data'!E22 -> 1084 | E20: ='Raw Data'!F22 -> 527 | F20: ='Raw Data'!G22+'Raw Data'!H22 -> 3338 | G20: ='Raw Data'!I22 -> 1409 | H20: ='Raw Data'!J22 -> 6098 | I20: ='Raw Data'!K22 -> 2158 | J20: =G20/F20 -> 0.42210905 | K20: =E20/F20 -> 0.15787897 | L20: =E20/H20 -> 0.086421778 | M20: =LN(H20) -> 8.7157161 | N20: =(C20-'Raw Data'!D21)/'Raw Data'!D21 -> 0.11870774 | O20: =I20/H20 -> 0.35388652 | P20: ='Raw Data'!L22 -> 5.24
A21: Welspun Living | B21: FY21-22 | C21: ='Raw Data'!D23 -> 6703 | D21: ='Raw Data'!E23 -> 893 | E21: ='Raw Data'!F23 -> 392 | F21: ='Raw Data'!G23+'Raw Data'!H23 -> 3475 | G21: ='Raw Data'!I23 -> 1318 | H21: ='Raw Data'!J23 -> 6191 | I21: ='Raw Data'!K23 -> 2025 | J21: =G21/F21 -> 0.37928058 | K21: =E21/F21 -> 0.11280576 | L21: =E21/H21 -> 0.063317719 | M21: =LN(H21) -> 8.7308519 | N21: =(C21-'Raw Data'!D22)/'Raw Data'!D22 -> 0.12541974 | O21: =I21/H21 -> 0.32708771 | P21: ='Raw Data'!L23 -> 3.9
A22: Welspun Living | B22: FY22-23 | C22: ='Raw Data'!D24 -> 6298 | D22: ='Raw Data'!E24 -> 456 | E22: ='Raw Data'!F24 -> 123 | F22: ='Raw Data'!G24+'Raw Data'!H24 -> 3408 | G22: ='Raw Data'!I24 -> 1767 | H22: ='Raw Data'!J24 -> 6880 | I22: ='Raw Data'!K24 -> 2938 | J22: =G22/F22 -> 0.51848592 | K22: =E22/F22 -> 0.036091549 | L22: =E22/H22 -> 0.017877907 | M22: =LN(H22) -> 8.8363739 | N22: =(C22-'Raw Data'!D23)/'Raw Data'!D23 -> -0.060420707 | O22: =I22/H22 -> 0.42703488 | P22: ='Raw Data'!L24 -> 1.22
A23: Welspun Living | B23: FY23-24 | C23: ='Raw Data'!D25 -> 8085 | D23: ='Raw Data'!E25 -> 1012 | E23: ='Raw Data'!F25 -> 596 | F23: ='Raw Data'!G25+'Raw Data'!H25 -> 3741 | G23: ='Raw Data'!I25 -> 1965 | H23: ='Raw Data'!J25 -> 7515 | I23: ='Raw Data'!K25 -> 2879 | J23: =G23/F23 -> 0.52526063 | K23: =E23/F23 -> 0.15931569 | L23: =E23/H23 -> 0.079308051 | M23: =LN(H23) -> 8.9246563 | N23: =(C23-'Raw Data'!D24)/'Raw Data'!D24 -> 0.28374087 | O23: =I23/H23 -> 0.38310047 | P23: ='Raw Data'!L25 -> 6.13
A24: Welspun Living | B24: FY24-25 | C24: ='Raw Data'!D26 -> 8622 | D24: ='Raw Data'!E26 -> 907 | E24: ='Raw Data'!F26 -> 507 | F24: ='Raw Data'!G26+'Raw Data'!H26 -> 3905 | G24: ='Raw Data'!I26 -> 1678 | H24: ='Raw Data'!J26 -> 7508 | I24: ='Raw Data'!K26 -> 2933 | J24: =G24/F24 -> 0.42970551 | K24: =E24/F24 -> 0.12983355 | L24: =E24/H24 -> 0.06752797 | M24: =LN(H24) -> 8.9237244 | N24: =(C24-'Raw Data'!D25)/'Raw Data'!D25 -> 0.066419295 | O24: =I24/H24 -> 0.39064997 | P24: ='Raw Data'!L26 -> 5.28
A25: Indo Count Industries | B25: FY15-16 | C25: ='Raw Data'!D28 -> 2001 | D25: ='Raw Data'!E28 -> 396 | E25: ='Raw Data'!F28 -> 238 | F25: ='Raw Data'!G28+'Raw Data'!H28 -> 613 | G25: ='Raw Data'!I28 -> 340 | H25: ='Raw Data'!J28 -> 1283 | I25: ='Raw Data'!K28 -> 466 | J25: =G25/F25 -> 0.55464927 | K25: =E25/F25 -> 0.38825449 | L25: =E25/H25 -> 0.18550273 | M25: =LN(H25) -> 7.1569564 | N25: =(C25-'Raw Data'!D27)/'Raw Data'!D27 -> 0.23824257 | O25: =I25/H25 -> 0.36321122 | P25: ='Raw Data'!L28 -> 12.04
A26: Indo Count Industries | B26: FY16-17 | C26: ='Raw Data'!D29 -> 1990 | D26: ='Raw Data'!E29 -> 325 | E26: ='Raw Data'!F29 -> 228 | F26: ='Raw Data'!G29+'Raw Data'!H29 -> 826 | G26: ='Raw Data'!I29 -> 267 | H26: ='Raw Data'!J29 -> 1440 | I26: ='Raw Data'!K29 -> 511 | J26: =G26/F26 -> 0.32324455 | K26: =E26/F26 -> 0.27602906 | L26: =E26/H26 -> 0.15833333 | M26: =LN(H26) -> 7.2723984 | N26: =(C26-'Raw Data'!D28)/'Raw Data'!D28 -> -0.0054972514 | O26: =I26/H26 -> 0.35486111 | P26: ='Raw Data'!L29 -> 11.55
A27: Indo Count Industries | B27: FY17-18 | C27: ='Raw Data'!D30 -> 1709 | D27: ='Raw Data'!E30 -> 167 | E27: ='Raw Data'!F30 -> 131 | F27: ='Raw Data'!G30+'Raw Data'!H30 -> 938 | G27: ='Raw Data'!I30 -> 371 | H27: ='Raw Data'!J30 -> 1644 | I27: ='Raw Data'!K30 -> 535 | J27: =G27/F27 -> 0.39552239 | K27: =E27/F27 -> 0.13965885 | L27: =E27/H27 -> 0.079683698 | M27: =LN(H27) -> 7.4048876 | N27: =(C27-'Raw Data'!D29)/'Raw Data'!D29 -> -0.14120603 | O27: =I27/H27 -> 0.32542579 | P27: ='Raw Data'!L30 -> 6.64
A28: Indo Count Industries | B28: FY18-19 | C28: ='Raw Data'!D31 -> 1813 | D28: ='Raw Data'!E31 -> 151 | E28: ='Raw Data'!F31 -> 59 | F28: ='Raw Data'!G31+'Raw Data'!H31 -> 960 | G28: ='Raw Data'!I31 -> 309 | H28: ='Raw Data'!J31 -> 1552 | I28: ='Raw Data'!K31 -> 560 | J28: =G28/F28 -> 0.321875 | K28: =E28/F28 -> 0.061458333 | L28: =E28/H28 -> 0.038015464 | M28: =LN(H28) -> 7.3472997 | N28: =(C28-'Raw Data'!D30)/'Raw Data'!D30 -> 0.060854301 | O28: =I28/H28 -> 0.36082474 | P28: ='Raw Data'!L31 -> 3
A29: Indo Count Industries | B29: FY19-20 | C29: ='Raw Data'!D32 -> 1965 | D29: ='Raw Data'!E32 -> 178 | E29: ='Raw Data'!F32 -> 74 | F29: ='Raw Data'!G32+'Raw Data'!H32 -> 972 | G29: ='Raw Data'!I32 -> 348 | H29: ='Raw Data'!J32 -> 1659 | I29: ='Raw Data'!K32 -> 553 | J29: =G29/F29 -> 0.35802469 | K29: =E29/F29 -> 0.076131687 | L29: =E29/H29 -> 0.044605184 | M29: =LN(H29) -> 7.4139703 | N29: =(C29-'Raw Data'!D31)/'Raw Data'!D31 -> 0.083838941 | O29: =I29/H29 -> 0.33333333 | P29: ='Raw Data'!L32 -> 3.74
A30: Indo Count Industries | B30: FY20-21 | C30: ='Raw Data'!D33 -> 2515 | D30: ='Raw Data'!E33 -> 384 | E30: ='Raw Data'!F33 -> 260 | F30: ='Raw Data'!G33+'Raw Data'!H33 -> 1274 | G30: ='Raw Data'!I33 -> 546 | H30: ='Raw Data'!J33 -> 2247 | I30: ='Raw Data'!K33 -> 543 | J30: =G30/F30 -> 0.42857143 | K30: =E30/F30 -> 0.20408163 | L30: =E30/H30 -> 0.11570984 | M30: =LN(H30) -> 7.7173513 | N30: =(C30-'Raw Data'!D32)/'Raw Data'!D32 -> 0.27989822 | O30: =I30/H30 -> 0.24165554 | P30: ='Raw Data'!L33 -> 13.18
A31: Indo Count Industries | B31: FY21-22 | C31: ='Raw Data'!D34 -> 2806 | D31: ='Raw Data'!E34 -> 402 | E31: ='Raw Data'!F34 -> 339 | F31: ='Raw Data'!G34+'Raw Data'!H34 -> 1576 | G31: ='Raw Data'!I34 -> 1214 | H31: ='Raw Data'!J34 -> 3090 | I31: ='Raw Data'!K34 -> 650 | J31: =G31/F31 -> 0.77030457 | K31: =E31/F31 -> 0.21510152 | L31: =E31/H31 -> 0.10970874 | M31: =LN(H31) -> 8.0359264 | N31: =(C31-'Raw Data'!D33)/'Raw Data'!D33 -> 0.11570577 | O31: =I31/H31 -> 0.21035599 | P31: ='Raw Data'!L34 -> 17.16
A32: Indo Count Industries | B32: FY22-23 | C32: ='Raw Data'!D35 -> 2784 | D32: ='Raw Data'!E35 -> 411 | E32: ='Raw Data'!F35 -> 238 | F32: ='Raw Data'!G35+'Raw Data'!H35 -> 1765 | G32: ='Raw Data'!I35 -> 853 | H32: ='Raw Data'!J35 -> 2983 | I32: ='Raw Data'!K35 -> 1243 | J32: =G32/F32 -> 0.48328612 | K32: =E32/F32 -> 0.13484419 | L32: =E32/H32 -> 0.079785451 | M32: =LN(H32) -> 8.0006848 | N32: =(C32-'Raw Data'!D34)/'Raw Data'!D34 -> -0.0078403421 | O32: =I32/H32 -> 0.4166946 | P32: ='Raw Data'!L35 -> 12.03
A33: Indo Count Industries | B33: FY23-24 | C33: ='Raw Data'!D36 -> 3332 | D33: ='Raw Data'!E36 -> 526 | E33: ='Raw Data'!F36 -> 320 | F33: ='Raw Data'!G36+'Raw Data'!H36 -> 2048 | G33: ='Raw Data'!I36 -> 936 | H33: ='Raw Data'!J36 -> 3493 | I33: ='Raw Data'!K36 -> 1344 | J33: =G33/F33 -> 0.45703125 | K33: =E33/F33 -> 0.15625 | L33: =E33/H33 -> 0.091611795 | M33: =LN(H33) -> 8.1585162 | N33: =(C33-'Raw Data'!D35)/'Raw Data'!D35 -> 0.19683908 | O33: =I33/H33 -> 0.38476954 | P33: ='Raw Data'!L36 -> 16.17
A34: Indo Count Industries | B34: FY24-25 | C34: ='Raw Data'!D37 -> 3772 | D34: ='Raw Data'!E37 -> 465 | E34: ='Raw Data'!F37 -> 237 | F34: ='Raw Data'!G37+'Raw Data'!H37 -> 2237 | G34: ='Raw Data'!I37 -> 1061 | H34: ='Raw Data'!J37 -> 3695 | I34: ='Raw Data'!K37 -> 1381 | J34: =G34/F34 -> 0.47429593 | K34: =E34/F34 -> 0.10594546 | L34: =E34/H34 -> 0.064140731 | M34: =LN(H34) -> 8.2147358 | N34: =(C34-'Raw Data'!D36)/'Raw Data'!D36 -> 0.13205282 | O34: =I34/H34 -> 0.37374831 | P34: ='Raw Data'!L37 -> 11.98
A35: Vardhman Textiles | B35: FY15-16 | C35: ='Raw Data'!D39 -> 5602 | D35: ='Raw Data'!E39 -> 1108 | E35: ='Raw Data'!F39 -> 676 | F35: ='Raw Data'!G39+'Raw Data'!H39 -> 3690 | G35: ='Raw Data'!I39 -> 2596 | H35: ='Raw Data'!J39 -> 6985 | I35: ='Raw Data'!K39 -> 2585 | J35: =G35/F35 -> 0.70352304 | K35: =E35/F35 -> 0.18319783 | L35: =E35/H35 -> 0.096778812 | M35: =LN(H35) -> 8.8515203 | N35: =(C35-'Raw Data'!D38)/'Raw Data'!D38 -> -0.022338569 | O35: =I35/H35 -> 0.37007874 | P35: ='Raw Data'!L39 -> 21.25
A36: Vardhman Textiles | B36: FY16-17 | C36: ='Raw Data'!D40 -> 5691 | D36: ='Raw Data'!E40 -> 1131 | E36: ='Raw Data'!F40 -> 1002 | F36: ='Raw Data'!G40+'Raw Data'!H40 -> 3986 | G36: ='Raw Data'!I40 -> 2198 | H36: ='Raw Data'!J40 -> 6959 | I36: ='Raw Data'!K40 -> 2507 | J36: =G36/F36 -> 0.55143001 | K36: =E36/F36 -> 0.25137983 | L36: =E36/H36 -> 0.1439862 | M36: =LN(H36) -> 8.8477911 | N36: =(C36-'Raw Data'!D39)/'Raw Data'!D39 -> 0.015887183 | O36: =I36/H36 -> 0.36025291 | P36: ='Raw Data'!L40 -> 34.87
A37: Vardhman Textiles | B37: FY17-18 | C37: ='Raw Data'!D41 -> 5851 | D37: ='Raw Data'!E41 -> 859 | E37: ='Raw Data'!F41 -> 546 | F37: ='Raw Data'!G41+'Raw Data'!H41 -> 4632 | G37: ='Raw Data'!I41 -> 2282 | H37: ='Raw Data'!J41 -> 7696 | I37: ='Raw Data'!K41 -> 2612 | J37: =G37/F37 -> 0.49265976 | K37: =E37/F37 -> 0.11787565 | L37: =E37/H37 -> 0.070945946 | M37: =LN(H37) -> 8.948456 | N37: =(C37-'Raw Data'!D40)/'Raw Data'!D40 -> 0.028114567 | O37: =I37/H37 -> 0.33939709 | P37: ='Raw Data'!L41 -> 19
A38: Vardhman Textiles | B38: FY18-19 | C38: ='Raw Data'!D42 -> 6415 | D38: ='Raw Data'!E42 -> 1132 | E38: ='Raw Data'!F42 -> 696 | F38: ='Raw Data'!G42+'Raw Data'!H42 -> 5239 | G38: ='Raw Data'!I42 -> 2238 | H38: ='Raw Data'!J42 -> 8369 | I38: ='Raw Data'!K42 -> 3333 | J38: =G38/F38 -> 0.42718076 | K38: =E38/F38 -> 0.13284978 | L38: =E38/H38 -> 0.083164058 | M38: =LN(H38) -> 9.0322897 | N38: =(C38-'Raw Data'!D41)/'Raw Data'!D41 -> 0.096393779 | O38: =I38/H38 -> 0.39825547 | P38: ='Raw Data'!L42 -> 24.21
A39: Vardhman Textiles | B39: FY19-20 | C39: ='Raw Data'!D43 -> 6325 | D39: ='Raw Data'!E43 -> 883 | E39: ='Raw Data'!F43 -> 545 | F39: ='Raw Data'!G43+'Raw Data'!H43 -> 5667 | G39: ='Raw Data'!I43 -> 2197 | H39: ='Raw Data'!J43 -> 8727 | I39: ='Raw Data'!K43 -> 3620 | J39: =G39/F39 -> 0.38768308 | K39: =E39/F39 -> 0.096170813 | L39: =E39/H39 -> 0.062449868 | M39: =LN(H39) -> 9.0741769 | N39: =(C39-'Raw Data'!D42)/'Raw Data'!D42 -> -0.014029618 | O39: =I39/H39 -> 0.41480463 | P39: ='Raw Data'!L43 -> 18.97
A40: Vardhman Textiles | B40: FY20-21 | C40: ='Raw Data'!D44 -> 5926 | D40: ='Raw Data'!E44 -> 767 | E40: ='Raw Data'!F44 -> 367 | F40: ='Raw Data'!G44+'Raw Data'!H44 -> 6139 | G40: ='Raw Data'!I44 -> 2132 | H40: ='Raw Data'!J44 -> 9064 | I40: ='Raw Data'!K44 -> 3546 | J40: =G40/F40 -> 0.34728783 | K40: =E40/F40 -> 0.059781723 | L40: =E40/H40 -> 0.04048985 | M40: =LN(H40) -> 9.1120658 | N40: =(C40-'Raw Data'!D43)/'Raw Data'!D43 -> -0.063083004 | O40: =I40/H40 -> 0.39121801 | P40: ='Raw Data'!L44 -> 12.74
A41: Vardhman Textiles | B41: FY21-22 | C41: ='Raw Data'!D45 -> 9386 | D41: ='Raw Data'!E45 -> 2262 | E41: ='Raw Data'!F45 -> 1677 | F41: ='Raw Data'!G45+'Raw Data'!H45 -> 7539 | G41: ='Raw Data'!I45 -> 1980 | H41: ='Raw Data'!J45 -> 10576 | I41: ='Raw Data'!K45 -> 3677 | J41: =G41/F41 -> 0.2626343 | K41: =E41/F41 -> 0.22244329 | L41: =E41/H41 -> 0.15856657 | M41: =LN(H41) -> 9.2663426 | N41: =(C41-'Raw Data'!D44)/'Raw Data'!D44 -> 0.5838677 | O41: =I41/H41 -> 0.34767398 | P41: ='Raw Data'!L45 -> 58.07
A42: Vardhman Textiles | B42: FY22-23 | C42: ='Raw Data'!D46 -> 9841 | D42: ='Raw Data'!E46 -> 1285 | E42: ='Raw Data'!F46 -> 749 | F42: ='Raw Data'!G46+'Raw Data'!H46 -> 8294 | G42: ='Raw Data'!I46 -> 1677 | H42: ='Raw Data'!J46 -> 10861 | I42: ='Raw Data'!K46 -> 3927 | J42: =G42/F42 -> 0.20219436 | K42: =E42/F42 -> 0.090306245 | L42: =E42/H42 -> 0.068962342 | M42: =LN(H42) -> 9.2929337 | N42: =(C42-'Raw Data'!D45)/'Raw Data'!D45 -> 0.048476454 | O42: =I42/H42 -> 0.36156892 | P42: ='Raw Data'!L46 -> 25.91
A43: Vardhman Textiles | B43: FY23-24 | C43: ='Raw Data'!D47 -> 9299 | D43: ='Raw Data'!E47 -> 958 | E43: ='Raw Data'!F47 -> 608 | F43: ='Raw Data'!G47+'Raw Data'!H47 -> 8805 | G43: ='Raw Data'!I47 -> 1790 | H43: ='Raw Data'!J47 -> 11487 | I43: ='Raw Data'!K47 -> 3772 | J43: =G43/F43 -> 0.20329358 | K43: =E43/F43 -> 0.069051675 | L43: =E43/H43 -> 0.052929398 | M43: =LN(H43) -> 9.3489712 | N43: =(C43-'Raw Data'!D46)/'Raw Data'!D46 -> -0.055075704 | O43: =I43/H43 -> 0.3283712 | P43: ='Raw Data'!L47 -> 21.01
A44: Vardhman Textiles | B44: FY24-25 | C44: ='Raw Data'!D48 -> 9587 | D44: ='Raw Data'!E48 -> 1257 | E44: ='Raw Data'!F48 -> 879 | F44: ='Raw Data'!G48+'Raw Data'!H48 -> 9578 | G44: ='Raw Data'!I48 -> 1238 | H44: ='Raw Data'!J48 -> 11900 | I44: ='Raw Data'!K48 -> 4342 | J44: =G44/F44 -> 0.12925454 | K44: =E44/F44 -> 0.091772813 | L44: =E44/H44 -> 0.073865546 | M44: =LN(H44) -> 9.3842937 | N44: =(C44-'Raw Data'!D47)/'Raw Data'!D47 -> 0.030971072 | O44: =I44/H44 -> 0.36487395 | P44: ='Raw Data'!L48 -> 30.4
A45: Trident | B45: FY15-16 | C45: ='Raw Data'!D50 -> 3665 | D45: ='Raw Data'!E50 -> 730 | E45: ='Raw Data'!F50 -> 242 | F45: ='Raw Data'!G50+'Raw Data'!H50 -> 2415 | G45: ='Raw Data'!I50 -> 3503 | H45: ='Raw Data'!J50 -> 6506 | I45: ='Raw Data'!K50 -> 4755 | J45: =G45/F45 -> 1.4505176 | K45: =E45/F45 -> 0.10020704 | L45: =E45/H45 -> 0.037196434 | M45: =LN(H45) -> 8.7804801 | N45: =(C45-'Raw Data'!D49)/'Raw Data'!D49 -> -0.018741633 | O45: =I45/H45 -> 0.73086382 | P45: ='Raw Data'!L50 -> 0.48
A46: Trident | B46: FY16-17 | C46: ='Raw Data'!D51 -> 4617 | D46: ='Raw Data'!E51 -> 886 | E46: ='Raw Data'!F51 -> 337 | F46: ='Raw Data'!G51+'Raw Data'!H51 -> 2725 | G46: ='Raw Data'!I51 -> 2849 | H46: ='Raw Data'!J51 -> 6150 | I46: ='Raw Data'!K51 -> 4467 | J46: =G46/F46 -> 1.0455046 | K46: =E46/F46 -> 0.12366972 | L46: =E46/H46 -> 0.054796748 | M46: =LN(H46) -> 8.7242074 | N46: =(C46-'Raw Data'!D50)/'Raw Data'!D50 -> 0.25975443 | O46: =I46/H46 -> 0.72634146 | P46: ='Raw Data'!L51 -> 0.66
A47: Trident | B47: FY17-18 | C47: ='Raw Data'!D52 -> 4566 | D47: ='Raw Data'!E52 -> 852 | E47: ='Raw Data'!F52 -> 266 | F47: ='Raw Data'!G52+'Raw Data'!H52 -> 2694 | G47: ='Raw Data'!I52 -> 2798 | H47: ='Raw Data'!J52 -> 6129 | I47: ='Raw Data'!K52 -> 4079 | J47: =G47/F47 -> 1.0386043 | K47: =E47/F47 -> 0.098737936 | L47: =E47/H47 -> 0.043400228 | M47: =LN(H47) -> 8.7207869 | N47: =(C47-'Raw Data'!D51)/'Raw Data'!D51 -> -0.011046134 | O47: =I47/H47 -> 0.66552456 | P47: ='Raw Data'!L52 -> 0.52
A48: Trident | B48: FY18-19 | C48: ='Raw Data'!D53 -> 5220 | D48: ='Raw Data'!E53 -> 977 | E48: ='Raw Data'!F53 -> 371 | F48: ='Raw Data'!G53+'Raw Data'!H53 -> 2932 | G48: ='Raw Data'!I53 -> 2436 | H48: ='Raw Data'!J53 -> 6103 | I48: ='Raw Data'!K53 -> 3848 | J48: =G48/F48 -> 0.8308322 | K48: =E48/F48 -> 0.12653479 | L48: =E48/H48 -> 0.060789776 | M48: =LN(H48) -> 8.7165357 | N48: =(C48-'Raw Data'!D52)/'Raw Data'!D52 -> 0.14323259 | O48: =I48/H48 -> 0.63050959 | P48: ='Raw Data'!L53 -> 0.73
A49: Trident | B49: FY19-20 | C49: ='Raw Data'!D54 -> 4699 | D49: ='Raw Data'!E54 -> 841 | E49: ='Raw Data'!F54 -> 342 | F49: ='Raw Data'!G54+'Raw Data'!H54 -> 2967 | G49: ='Raw Data'!I54 -> 1991 | H49: ='Raw Data'!J54 -> 5718 | I49: ='Raw Data'!K54 -> 3826 | J49: =G49/F49 -> 0.6710482 | K49: =E49/F49 -> 0.11526795 | L49: =E49/H49 -> 0.059811123 | M49: =LN(H49) -> 8.6513744 | N49: =(C49-'Raw Data'!D53)/'Raw Data'!D53 -> -0.099808429 | O49: =I49/H49 -> 0.66911508 | P49: ='Raw Data'!L54 -> 0.67
A50: Trident | B50: FY20-21 | C50: ='Raw Data'!D55 -> 4519 | D50: ='Raw Data'!E55 -> 814 | E50: ='Raw Data'!F55 -> 346 | F50: ='Raw Data'!G55+'Raw Data'!H55 -> 3317 | G50: ='Raw Data'!I55 -> 1562 | H50: ='Raw Data'!J55 -> 5754 | I50: ='Raw Data'!K55 -> 3854 | J50: =G50/F50 -> 0.47090745 | K50: =E50/F50 -> 0.10431112 | L50: =E50/H50 -> 0.060132082 | M50: =LN(H50) -> 8.6576505 | N50: =(C50-'Raw Data'!D54)/'Raw Data'!D54 -> -0.038306023 | O50: =I50/H50 -> 0.66979493 | P50: ='Raw Data'!L55 -> 0.68
A51: Trident | B51: FY21-22 | C51: ='Raw Data'!D56 -> 6919 | D51: ='Raw Data'!E56 -> 1495 | E51: ='Raw Data'!F56 -> 815 | F51: ='Raw Data'!G56+'Raw Data'!H56 -> 3798 | G51: ='Raw Data'!I56 -> 1596 | H51: ='Raw Data'!J56 -> 6431 | I51: ='Raw Data'!K56 -> 3795 | J51: =G51/F51 -> 0.42022117 | K51: =E51/F51 -> 0.21458662 | L51: =E51/H51 -> 0.1267299 | M51: =LN(H51) -> 8.7688853 | N51: =(C51-'Raw Data'!D55)/'Raw Data'!D55 -> 0.53109095 | O51: =I51/H51 -> 0.5901104 | P51: ='Raw Data'!L56 -> 1.6
A52: Trident | B52: FY22-23 | C52: ='Raw Data'!D57 -> 6267 | D52: ='Raw Data'!E57 -> 918 | E52: ='Raw Data'!F57 -> 422 | F52: ='Raw Data'!G57+'Raw Data'!H57 -> 4126 | G52: ='Raw Data'!I57 -> 1404 | H52: ='Raw Data'!J57 -> 6713 | I52: ='Raw Data'!K57 -> 4422 | J52: =G52/F52 -> 0.34028114 | K52: =E52/F52 -> 0.10227824 | L52: =E52/H52 -> 0.062863101 | M52: =LN(H52) -> 8.8118012 | N52: =(C52-'Raw Data'!D56)/'Raw Data'!D56 -> -0.094233271 | O52: =I52/H52 -> 0.65872188 | P52: ='Raw Data'!L57 -> 0.83
A53: Trident | B53: FY23-24 | C53: ='Raw Data'!D58 -> 6730 | D53: ='Raw Data'!E58 -> 935 | E53: ='Raw Data'!F58 -> 390 | F53: ='Raw Data'!G58+'Raw Data'!H58 -> 4310 | G53: ='Raw Data'!I58 -> 2094 | H53: ='Raw Data'!J58 -> 7522 | I53: ='Raw Data'!K58 -> 4663 | J53: =G53/F53 -> 0.48584687 | K53: =E53/F53 -> 0.090487239 | L53: =E53/H53 -> 0.051847913 | M53: =LN(H53) -> 8.9255873 | N53: =(C53-'Raw Data'!D57)/'Raw Data'!D57 -> 0.073879049 | O53: =I53/H53 -> 0.61991492 | P53: ='Raw Data'!L58 -> 0.76
A54: Trident | B54: FY24-25 | C54: ='Raw Data'!D59 -> 6966 | D54: ='Raw Data'!E59 -> 886 | E54: ='Raw Data'!F59 -> 367 | F54: ='Raw Data'!G59+'Raw Data'!H59 -> 4611 | G54: ='Raw Data'!I59 -> 1606 | H54: ='Raw Data'!J59 -> 7129 | I54: ='Raw Data'!K59 -> 4478 | J54: =G54/F54 -> 0.34829755 | K54: =E54/F54 -> 0.079592279 | L54: =E54/H54 -> 0.051479871 | M54: =LN(H54) -> 8.8719263 | N54: =(C54-'Raw Data'!D58)/'Raw Data'!D58 -> 0.035066865 | O54: =I54/H54 -> 0.62813859 | P54: ='Raw Data'!L59 -> 0.72
A55: Arvind | B55: FY15-16 | C55: ='Raw Data'!D61 -> 5357 | D55: ='Raw Data'!E61 -> 808 | E55: ='Raw Data'!F61 -> 321 | F55: ='Raw Data'!G61+'Raw Data'!H61 -> 2986 | G55: ='Raw Data'!I61 -> 3123 | H55: ='Raw Data'!J61 -> 6990 | I55: ='Raw Data'!K61 -> 2928 | J55: =G55/F55 -> 1.0458808 | K55: =E55/F55 -> 0.10750167 | L55: =E55/H55 -> 0.045922747 | M55: =LN(H55) -> 8.8522358 | N55: =(C55-'Raw Data'!D60)/'Raw Data'!D60 -> 0.025263158 | O55: =I55/H55 -> 0.41888412 | P55: ='Raw Data'!L61 -> 12.42
A56: Arvind | B56: FY16-17 | C56: ='Raw Data'!D62 -> 5967 | D56: ='Raw Data'!E62 -> 732 | E56: ='Raw Data'!F62 -> 19 | F56: ='Raw Data'!G62+'Raw Data'!H62 -> 3011 | G56: ='Raw Data'!I62 -> 2428 | H56: ='Raw Data'!J62 -> 6458 | I56: ='Raw Data'!K62 -> 3177 | J56: =G56/F56 -> 0.80637662 | K56: =E56/F56 -> 0.0063101959 | L56: =E56/H56 -> 0.0029420873 | M56: =LN(H56) -> 8.773075 | N56: =(C56-'Raw Data'!D61)/'Raw Data'!D61 -> 0.1138697 | O56: =I56/H56 -> 0.49194797 | P56: ='Raw Data'!L62 -> 0.72
A57: Arvind | B57: FY17-18 | C57: ='Raw Data'!D63 -> 6332 | D57: ='Raw Data'!E63 -> 639 | E57: ='Raw Data'!F63 -> 250 | F57: ='Raw Data'!G63+'Raw Data'!H63 -> 3159 | G57: ='Raw Data'!I63 -> 2562 | H57: ='Raw Data'!J63 -> 7044 | I57: ='Raw Data'!K63 -> 3208 | J57: =G57/F57 -> 0.81101614 | K57: =E57/F57 -> 0.079138968 | L57: =E57/H57 -> 0.035491198 | M57: =LN(H57) -> 8.8599315 | N57: =(C57-'Raw Data'!D62)/'Raw Data'!D62 -> 0.061169767 | O57: =I57/H57 -> 0.45542306 | P57: ='Raw Data'!L63 -> 9.67
A58: Arvind | B58: FY18-19 | C58: ='Raw Data'!D64 -> 6436 | D58: ='Raw Data'!E64 -> 633 | E58: ='Raw Data'!F64 -> 199 | F58: ='Raw Data'!G64+'Raw Data'!H64 -> 2817 | G58: ='Raw Data'!I64 -> 2652 | H58: ='Raw Data'!J64 -> 7014 | I58: ='Raw Data'!K64 -> 3362 | J58: =G58/F58 -> 0.94142705 | K58: =E58/F58 -> 0.070642528 | L58: =E58/H58 -> 0.028371828 | M58: =LN(H58) -> 8.8556634 | N58: =(C58-'Raw Data'!D63)/'Raw Data'!D63 -> 0.01642451 | O58: =I58/H58 -> 0.47932706 | P58: ='Raw Data'!L64 -> 7.71
A59: Arvind | B59: FY19-20 | C59: ='Raw Data'!D65 -> 6705 | D59: ='Raw Data'!E65 -> 708 | E59: ='Raw Data'!F65 -> 171 | F59: ='Raw Data'!G65+'Raw Data'!H65 -> 2854 | G59: ='Raw Data'!I65 -> 2431 | H59: ='Raw Data'!J65 -> 6815 | I59: ='Raw Data'!K65 -> 3532 | J59: =G59/F59 -> 0.85178697 | K59: =E59/F59 -> 0.059915907 | L59: =E59/H59 -> 0.025091709 | M59: =LN(H59) -> 8.8268813 | N59: =(C59-'Raw Data'!D64)/'Raw Data'!D64 -> 0.041796147 | O59: =I59/H59 -> 0.51826853 | P59: ='Raw Data'!L65 -> 6.62
A60: Arvind | B60: FY20-21 | C60: ='Raw Data'!D66 -> 4529 | D60: ='Raw Data'!E66 -> 477 | E60: ='Raw Data'!F66 -> 93 | F60: ='Raw Data'!G66+'Raw Data'!H66 -> 2941 | G60: ='Raw Data'!I66 -> 1985 | H60: ='Raw Data'!J66 -> 6609 | I60: ='Raw Data'!K66 -> 3332 | J60: =G60/F60 -> 0.6749405 | K60: =E60/F60 -> 0.031621897 | L60: =E60/H60 -> 0.01407172 | M60: =LN(H60) -> 8.7961876 | N60: =(C60-'Raw Data'!D65)/'Raw Data'!D65 -> -0.32453393 | O60: =I60/H60 -> 0.50416099 | P60: ='Raw Data'!L66 -> 3.58
A61: Arvind | B61: FY21-22 | C61: ='Raw Data'!D67 -> 7436 | D61: ='Raw Data'!E67 -> 790 | E61: ='Raw Data'!F67 -> 59 | F61: ='Raw Data'!G67+'Raw Data'!H67 -> 3012 | G61: ='Raw Data'!I67 -> 1783 | H61: ='Raw Data'!J67 -> 7413 | I61: ='Raw Data'!K67 -> 3268 | J61: =G61/F61 -> 0.59196547 | K61: =E61/F61 -> 0.019588313 | L61: =E61/H61 -> 0.007958991 | M61: =LN(H61) -> 8.9109905 | N61: =(C61-'Raw Data'!D66)/'Raw Data'!D66 -> 0.64186355 | O61: =I61/H61 -> 0.44084716 | P61: ='Raw Data'!L67 -> 2.28
A62: Arvind | B62: FY22-23 | C62: ='Raw Data'!D68 -> 7723 | D62: ='Raw Data'!E68 -> 720 | E62: ='Raw Data'!F68 -> 346 | F62: ='Raw Data'!G68+'Raw Data'!H68 -> 3297 | G62: ='Raw Data'!I68 -> 1420 | H62: ='Raw Data'!J68 -> 6398 | I62: ='Raw Data'!K68 -> 3255 | J62: =G62/F62 -> 0.43069457 | K62: =E62/F62 -> 0.10494389 | L62: =E62/H62 -> 0.0540794 | M62: =LN(H62) -> 8.7637407 | N62: =(C62-'Raw Data'!D67)/'Raw Data'!D67 -> 0.038596019 | O62: =I62/H62 -> 0.50875274 | P62: ='Raw Data'!L68 -> 13.23
A63: Arvind | B63: FY23-24 | C63: ='Raw Data'!D69 -> 7100 | D63: ='Raw Data'!E69 -> 767 | E63: ='Raw Data'!F69 -> 305 | F63: ='Raw Data'!G69+'Raw Data'!H69 -> 3477 | G63: ='Raw Data'!I69 -> 1320 | H63: ='Raw Data'!J69 -> 6729 | I63: ='Raw Data'!K69 -> 3288 | J63: =G63/F63 -> 0.37963762 | K63: =E63/F63 -> 0.087719298 | L63: =E63/H63 -> 0.0453262 | M63: =LN(H63) -> 8.8141818 | N63: =(C63-'Raw Data'!D68)/'Raw Data'!D68 -> -0.080668134 | O63: =I63/H63 -> 0.4886313 | P63: ='Raw Data'!L69 -> 11.65
A64: Arvind | B64: FY24-25 | C64: ='Raw Data'!D70 -> 6236 | D64: ='Raw Data'!E70 -> 581 | E64: ='Raw Data'!F70 -> 240 | F64: ='Raw Data'!G70+'Raw Data'!H70 -> 3587 | G64: ='Raw Data'!I70 -> 1496 | H64: ='Raw Data'!J70 -> 7324 | I64: ='Raw Data'!K70 -> 3504 | J64: =G64/F64 -> 0.41706161 | K64: =E64/F64 -> 0.06690828 | L64: =E64/H64 -> 0.032768979 | M64: =LN(H64) -> 8.8989119 | N64: =(C64-'Raw Data'!D69)/'Raw Data'!D69 -> -0.12169014 | O64: =I64/H64 -> 0.47842709 | P64: ='Raw Data'!L70 -> 9.18
A65: Nitin Spinners | B65: FY15-16 | C65: ='Raw Data'!D72 -> 766 | D65: ='Raw Data'!E72 -> 137 | E65: ='Raw Data'!F72 -> 44 | F65: ='Raw Data'!G72+'Raw Data'!H72 -> 206 | G65: ='Raw Data'!I72 -> 352 | H65: ='Raw Data'!J72 -> 635 | I65: ='Raw Data'!K72 -> 399 | J65: =G65/F65 -> 1.7087379 | K65: =E65/F65 -> 0.21359223 | L65: =E65/H65 -> 0.069291339 | M65: =LN(H65) -> 6.453625 | N65: =(C65-'Raw Data'!D71)/'Raw Data'!D71 -> 0.24350649 | O65: =I65/H65 -> 0.62834646 | P65: ='Raw Data'!L72 -> 9.63
A66: Nitin Spinners | B66: FY16-17 | C66: ='Raw Data'!D73 -> 933 | D66: ='Raw Data'!E73 -> 133 | E66: ='Raw Data'!F73 -> 57 | F66: ='Raw Data'!G73+'Raw Data'!H73 -> 264 | G66: ='Raw Data'!I73 -> 568 | H66: ='Raw Data'!J73 -> 885 | I66: ='Raw Data'!K73 -> 613 | J66: =G66/F66 -> 2.1515152 | K66: =E66/F66 -> 0.21590909 | L66: =E66/H66 -> 0.06440678 | M66: =LN(H66) -> 6.7855876 | N66: =(C66-'Raw Data'!D72)/'Raw Data'!D72 -> 0.21801567 | O66: =I66/H66 -> 0.69265537 | P66: ='Raw Data'!L73 -> 12.51
A67: Nitin Spinners | B67: FY17-18 | C67: ='Raw Data'!D74 -> 1145 | D67: ='Raw Data'!E74 -> 155 | E67: ='Raw Data'!F74 -> 52 | F67: ='Raw Data'!G74+'Raw Data'!H74 -> 417 | G67: ='Raw Data'!I74 -> 449 | H67: ='Raw Data'!J74 -> 929 | I67: ='Raw Data'!K74 -> 574 | J67: =G67/F67 -> 1.0767386 | K67: =E67/F67 -> 0.12470024 | L67: =E67/H67 -> 0.055974166 | M67: =LN(H67) -> 6.8341087 | N67: =(C67-'Raw Data'!D73)/'Raw Data'!D73 -> 0.22722401 | O67: =I67/H67 -> 0.61786868 | P67: ='Raw Data'!L74 -> 9.43
A68: Nitin Spinners | B68: FY18-19 | C68: ='Raw Data'!D75 -> 1241 | D68: ='Raw Data'!E75 -> 178 | E68: ='Raw Data'!F75 -> 64 | F68: ='Raw Data'!G75+'Raw Data'!H75 -> 482 | G68: ='Raw Data'!I75 -> 860 | H68: ='Raw Data'!J75 -> 1436 | I68: ='Raw Data'!K75 -> 992 | J68: =G68/F68 -> 1.7842324 | K68: =E68/F68 -> 0.13278008 | L68: =E68/H68 -> 0.044568245 | M68: =LN(H68) -> 7.2696167 | N68: =(C68-'Raw Data'!D74)/'Raw Data'!D74 -> 0.083842795 | O68: =I68/H68 -> 0.6908078 | P68: ='Raw Data'!L75 -> 11.4
A69: Nitin Spinners | B69: FY19-20 | C69: ='Raw Data'!D76 -> 1436 | D69: ='Raw Data'!E76 -> 170 | E69: ='Raw Data'!F76 -> 24 | F69: ='Raw Data'!G76+'Raw Data'!H76 -> 494 | G69: ='Raw Data'!I76 -> 1040 | H69: ='Raw Data'!J76 -> 1645 | I69: ='Raw Data'!K76 -> 1140 | J69: =G69/F69 -> 2.1052632 | K69: =E69/F69 -> 0.048582996 | L69: =E69/H69 -> 0.014589666 | M69: =LN(H69) -> 7.4054957 | N69: =(C69-'Raw Data'!D75)/'Raw Data'!D75 -> 0.15713135 | O69: =I69/H69 -> 0.69300912 | P69: ='Raw Data'!L76 -> 4.24
A70: Nitin Spinners | B70: FY20-21 | C70: ='Raw Data'!D77 -> 1622 | D70: ='Raw Data'!E77 -> 257 | E70: ='Raw Data'!F77 -> 69 | F70: ='Raw Data'!G77+'Raw Data'!H77 -> 563 | G70: ='Raw Data'!I77 -> 962 | H70: ='Raw Data'!J77 -> 1676 | I70: ='Raw Data'!K77 -> 1062 | J70: =G70/F70 -> 1.7087034 | K70: =E70/F70 -> 0.12255773 | L70: =E70/H70 -> 0.041169451 | M70: =LN(H70) -> 7.4241653 | N70: =(C70-'Raw Data'!D76)/'Raw Data'!D76 -> 0.12952646 | O70: =I70/H70 -> 0.63365155 | P70: ='Raw Data'!L77 -> 12.25
A71: Nitin Spinners | B71: FY21-22 | C71: ='Raw Data'!D78 -> 2690 | D71: ='Raw Data'!E78 -> 652 | E71: ='Raw Data'!F78 -> 326 | F71: ='Raw Data'!G78+'Raw Data'!H78 -> 876 | G71: ='Raw Data'!I78 -> 689 | H71: ='Raw Data'!J78 -> 1824 | I71: ='Raw Data'!K78 -> 1012 | J71: =G71/F71 -> 0.78652968 | K71: =E71/F71 -> 0.37214612 | L71: =E71/H71 -> 0.17872807 | M71: =LN(H71) -> 7.5087872 | N71: =(C71-'Raw Data'!D77)/'Raw Data'!D77 -> 0.65844636 | O71: =I71/H71 -> 0.55482456 | P71: ='Raw Data'!L78 -> 58.01
A72: Nitin Spinners | B72: FY22-23 | C72: ='Raw Data'!D79 -> 2404 | D72: ='Raw Data'!E79 -> 297 | E72: ='Raw Data'!F79 -> 165 | F72: ='Raw Data'!G79+'Raw Data'!H79 -> 1029 | G72: ='Raw Data'!I79 -> 980 | H72: ='Raw Data'!J79 -> 2218 | I72: ='Raw Data'!K79 -> 1351 | J72: =G72/F72 -> 0.95238095 | K72: =E72/F72 -> 0.16034985 | L72: =E72/H72 -> 0.074391344 | M72: =LN(H72) -> 7.7043612 | N72: =(C72-'Raw Data'!D78)/'Raw Data'!D78 -> -0.1063197 | O72: =I72/H72 -> 0.6091073 | P72: ='Raw Data'!L79 -> 29.32
A73: Nitin Spinners | B73: FY23-24 | C73: ='Raw Data'!D80 -> 2902 | D73: ='Raw Data'!E80 -> 377 | E73: ='Raw Data'!F80 -> 132 | F73: ='Raw Data'!G80+'Raw Data'!H80 -> 1146 | G73: ='Raw Data'!I80 -> 1339 | H73: ='Raw Data'!J80 -> 2717 | I73: ='Raw Data'!K80 -> 1711 | J73: =G73/F73 -> 1.1684119 | K73: =E73/F73 -> 0.11518325 | L73: =E73/H73 -> 0.048582996 | M73: =LN(H73) -> 7.9072836 | N73: =(C73-'Raw Data'!D79)/'Raw Data'!D79 -> 0.20715474 | O73: =I73/H73 -> 0.62973868 | P73: ='Raw Data'!L80 -> 23.39
A74: Nitin Spinners | B74: FY24-25 | C74: ='Raw Data'!D81 -> 3300 | D74: ='Raw Data'!E81 -> 471 | E74: ='Raw Data'!F81 -> 175 | F74: ='Raw Data'!G81+'Raw Data'!H81 -> 1311 | G74: ='Raw Data'!I81 -> 1165 | H74: ='Raw Data'!J81 -> 2732 | I74: ='Raw Data'!K81 -> 1584 | J74: =G74/F74 -> 0.88863463 | K74: =E74/F74 -> 0.13348589 | L74: =E74/H74 -> 0.064055637 | M74: =LN(H74) -> 7.9127892 | N74: =(C74-'Raw Data'!D80)/'Raw Data'!D80 -> 0.1371468 | O74: =I74/H74 -> 0.57979502 | P74: ='Raw Data'!L81 -> 31.2
A75: Sutlej Textiles | B75: FY15-16 | C75: ='Raw Data'!D83 -> 2074 | D75: ='Raw Data'!E83 -> 263 | E75: ='Raw Data'!F83 -> 143 | F75: ='Raw Data'!G83+'Raw Data'!H83 -> 683 | G75: ='Raw Data'!I83 -> 804 | H75: ='Raw Data'!J83 -> 1675 | I75: ='Raw Data'!K83 -> 877 | J75: =G75/F75 -> 1.1771596 | K75: =E75/F75 -> 0.20937042 | L75: =E75/H75 -> 0.085373134 | M75: =LN(H75) -> 7.4235684 | N75: =(C75-'Raw Data'!D82)/'Raw Data'!D82 -> 0.11087306 | O75: =I75/H75 -> 0.52358209 | P75: ='Raw Data'!L83 -> 8.76
A76: Sutlej Textiles | B76: FY16-17 | C76: ='Raw Data'!D84 -> 2249 | D76: ='Raw Data'!E84 -> 282 | E76: ='Raw Data'!F84 -> 158 | F76: ='Raw Data'!G84+'Raw Data'!H84 -> 816 | G76: ='Raw Data'!I84 -> 1036 | H76: ='Raw Data'!J84 -> 2045 | I76: ='Raw Data'!K84 -> 1139 | J76: =G76/F76 -> 1.2696078 | K76: =E76/F76 -> 0.19362745 | L76: =E76/H76 -> 0.077261614 | M76: =LN(H76) -> 7.6231531 | N76: =(C76-'Raw Data'!D83)/'Raw Data'!D83 -> 0.084378014 | O76: =I76/H76 -> 0.55696822 | P76: ='Raw Data'!L84 -> 9.64
A77: Sutlej Textiles | B77: FY17-18 | C77: ='Raw Data'!D85 -> 2453 | D77: ='Raw Data'!E85 -> 247 | E77: ='Raw Data'!F85 -> 113 | F77: ='Raw Data'!G85+'Raw Data'!H85 -> 906 | G77: ='Raw Data'!I85 -> 1047 | H77: ='Raw Data'!J85 -> 2182 | I77: ='Raw Data'!K85 -> 1119 | J77: =G77/F77 -> 1.1556291 | K77: =E77/F77 -> 0.12472406 | L77: =E77/H77 -> 0.051787351 | M77: =LN(H77) -> 7.6879972 | N77: =(C77-'Raw Data'!D84)/'Raw Data'!D84 -> 0.090706981 | O77: =I77/H77 -> 0.51283226 | P77: ='Raw Data'!L85 -> 6.91
A78: Sutlej Textiles | B78: FY18-19 | C78: ='Raw Data'!D86 -> 2562 | D78: ='Raw Data'!E86 -> 219 | E78: ='Raw Data'!F86 -> 66 | F78: ='Raw Data'!G86+'Raw Data'!H86 -> 946 | G78: ='Raw Data'!I86 -> 923 | H78: ='Raw Data'!J86 -> 2131 | I78: ='Raw Data'!K86 -> 1074 | J78: =G78/F78 -> 0.9756871 | K78: =E78/F78 -> 0.069767442 | L78: =E78/H78 -> 0.030971375 | M78: =LN(H78) -> 7.6643466 | N78: =(C78-'Raw Data'!D85)/'Raw Data'!D85 -> 0.044435385 | O78: =I78/H78 -> 0.50398874 | P78: ='Raw Data'!L86 -> 4.01
A79: Sutlej Textiles | B79: FY19-20 | C79: ='Raw Data'!D87 -> 2379 | D79: ='Raw Data'!E87 -> 178 | E79: ='Raw Data'!F87 -> 36 | F79: ='Raw Data'!G87+'Raw Data'!H87 -> 971 | G79: ='Raw Data'!I87 -> 868 | H79: ='Raw Data'!J87 -> 2118 | I79: ='Raw Data'!K87 -> 1210 | J79: =G79/F79 -> 0.89392379 | K79: =E79/F79 -> 0.03707518 | L79: =E79/H79 -> 0.016997167 | M79: =LN(H79) -> 7.6582275 | N79: =(C79-'Raw Data'!D86)/'Raw Data'!D86 -> -0.071428571 | O79: =I79/H79 -> 0.57129367 | P79: ='Raw Data'!L87 -> 2.2
A80: Sutlej Textiles | B80: FY20-21 | C80: ='Raw Data'!D88 -> 1861 | D80: ='Raw Data'!E88 -> 115 | E80: ='Raw Data'!F88 -> 10 | F80: ='Raw Data'!G88+'Raw Data'!H88 -> 980 | G80: ='Raw Data'!I88 -> 901 | H80: ='Raw Data'!J88 -> 2149 | I80: ='Raw Data'!K88 -> 1231 | J80: =G80/F80 -> 0.91938776 | K80: =E80/F80 -> 0.010204082 | L80: =E80/H80 -> 0.0046533271 | M80: =LN(H80) -> 7.6727579 | N80: =(C80-'Raw Data'!D87)/'Raw Data'!D87 -> -0.21773855 | O80: =I80/H80 -> 0.57282457 | P80: ='Raw Data'!L88 -> 0.58
A81: Sutlej Textiles | B81: FY21-22 | C81: ='Raw Data'!D89 -> 3042 | D81: ='Raw Data'!E89 -> 387 | E81: ='Raw Data'!F89 -> 156 | F81: ='Raw Data'!G89+'Raw Data'!H89 -> 1130 | G81: ='Raw Data'!I89 -> 938 | H81: ='Raw Data'!J89 -> 2442 | I81: ='Raw Data'!K89 -> 1187 | J81: =G81/F81 -> 0.8300885 | K81: =E81/F81 -> 0.1380531 | L81: =E81/H81 -> 0.063882064 | M81: =LN(H81) -> 7.8005727 | N81: =(C81-'Raw Data'!D88)/'Raw Data'!D88 -> 0.63460505 | O81: =I81/H81 -> 0.48607699 | P81: ='Raw Data'!L89 -> 9.5
A82: Sutlej Textiles | B82: FY22-23 | C82: ='Raw Data'!D90 -> 3039 | D82: ='Raw Data'!E90 -> 264 | E82: ='Raw Data'!F90 -> 23 | F82: ='Raw Data'!G90+'Raw Data'!H90 -> 1123 | G82: ='Raw Data'!I90 -> 933 | H82: ='Raw Data'!J90 -> 2421 | I82: ='Raw Data'!K90 -> 1121 | J82: =G82/F82 -> 0.83081033 | K82: =E82/F82 -> 0.020480855 | L82: =E82/H82 -> 0.0095002065 | M82: =LN(H82) -> 7.791936 | N82: =(C82-'Raw Data'!D89)/'Raw Data'!D89 -> -0.00098619329 | O82: =I82/H82 -> 0.46303181 | P82: ='Raw Data'!L90 -> 1.39
A83: Sutlej Textiles | B83: FY23-24 | C83: ='Raw Data'!D91 -> 2672 | D83: ='Raw Data'!E91 -> -29 | E83: ='Raw Data'!F91 -> -135 | F83: ='Raw Data'!G91+'Raw Data'!H91 -> 976 | G83: ='Raw Data'!I91 -> 826 | H83: ='Raw Data'!J91 -> 2097 | I83: ='Raw Data'!K91 -> 1063 | J83: =G83/F83 -> 0.84631148 | K83: =E83/F83 -> -0.13831967 | L83: =E83/H83 -> -0.064377682 | M83: =LN(H83) -> 7.648263 | N83: =(C83-'Raw Data'!D90)/'Raw Data'!D90 -> -0.12076341 | O83: =I83/H83 -> 0.50691464 | P83: ='Raw Data'!L91 -> -8.22
A84: Sutlej Textiles | B84: FY24-25 | C84: ='Raw Data'!D92 -> 2642 | D84: ='Raw Data'!E92 -> 46 | E84: ='Raw Data'!F92 -> -84 | F84: ='Raw Data'!G92+'Raw Data'!H92 -> 894 | G84: ='Raw Data'!I92 -> 877 | H84: ='Raw Data'!J92 -> 2043 | I84: ='Raw Data'!K92 -> 1010 | J84: =G84/F84 -> 0.98098434 | K84: =E84/F84 -> -0.093959732 | L84: =E84/H84 -> -0.041116006 | M84: =LN(H84) -> 7.6221746 | N84: =(C84-'Raw Data'!D91)/'Raw Data'!D91 -> -0.011227545 | O84: =I84/H84 -> 0.49437102 | P84: ='Raw Data'!L92 -> -5.14
A85: Gokaldas Exports | B85: FY15-16 | C85: ='Raw Data'!D94 -> 1123 | D85: ='Raw Data'!E94 -> 37 | E85: ='Raw Data'!F94 -> 61 | F85: ='Raw Data'!G94+'Raw Data'!H94 -> 212 | G85: ='Raw Data'!I94 -> 343 | H85: ='Raw Data'!J94 -> 725 | I85: ='Raw Data'!K94 -> 94 | J85: =G85/F85 -> 1.6179245 | K85: =E85/F85 -> 0.28773585 | L85: =E85/H85 -> 0.084137931 | M85: =LN(H85) -> 6.5861717 | N85: =(C85-'Raw Data'!D93)/'Raw Data'!D93 -> 0.04953271 | O85: =I85/H85 -> 0.12965517 | P85: ='Raw Data'!L94 -> 17.44
A86: Gokaldas Exports | B86: FY16-17 | C86: ='Raw Data'!D95 -> 915 | D86: ='Raw Data'!E95 -> -31 | E86: ='Raw Data'!F95 -> -46 | F86: ='Raw Data'!G95+'Raw Data'!H95 -> 165 | G86: ='Raw Data'!I95 -> 474 | H86: ='Raw Data'!J95 -> 794 | I86: ='Raw Data'!K95 -> 95 | J86: =G86/F86 -> 2.8727273 | K86: =E86/F86 -> -0.27878788 | L86: =E86/H86 -> -0.057934509 | M86: =LN(H86) -> 6.6770835 | N86: =(C86-'Raw Data'!D94)/'Raw Data'!D94 -> -0.18521817 | O86: =I86/H86 -> 0.11964736 | P86: ='Raw Data'!L95 -> -13.23
A87: Gokaldas Exports | B87: FY17-18 | C87: ='Raw Data'!D96 -> 1031 | D87: ='Raw Data'!E96 -> -23 | E87: ='Raw Data'!F96 -> -31 | F87: ='Raw Data'!G96+'Raw Data'!H96 -> 130 | G87: ='Raw Data'!I96 -> 472 | H87: ='Raw Data'!J96 -> 794 | I87: ='Raw Data'!K96 -> 95 | J87: =G87/F87 -> 3.6307692 | K87: =E87/F87 -> -0.23846154 | L87: =E87/H87 -> -0.039042821 | M87: =LN(H87) -> 6.6770835 | N87: =(C87-'Raw Data'!D95)/'Raw Data'!D95 -> 0.12677596 | O87: =I87/H87 -> 0.11964736 | P87: ='Raw Data'!L96 -> -8.83
A88: Gokaldas Exports | B88: FY18-19 | C88: ='Raw Data'!D97 -> 1173 | D88: ='Raw Data'!E97 -> 62 | E88: ='Raw Data'!F97 -> 26 | F88: ='Raw Data'!G97+'Raw Data'!H97 -> 239 | G88: ='Raw Data'!I97 -> 381 | H88: ='Raw Data'!J97 -> 823 | I88: ='Raw Data'!K97 -> 108 | J88: =G88/F88 -> 1.5941423 | K88: =E88/F88 -> 0.10878661 | L88: =E88/H88 -> 0.031591738 | M88: =LN(H88) -> 6.7129562 | N88: =(C88-'Raw Data'!D96)/'Raw Data'!D96 -> 0.13773036 | O88: =I88/H88 -> 0.13122722 | P88: ='Raw Data'!L97 -> 5.99
A89: Gokaldas Exports | B89: FY19-20 | C89: ='Raw Data'!D98 -> 1368 | D89: ='Raw Data'!E98 -> 87 | E89: ='Raw Data'!F98 -> 32 | F89: ='Raw Data'!G98+'Raw Data'!H98 -> 228 | G89: ='Raw Data'!I98 -> 440 | H89: ='Raw Data'!J98 -> 939 | I89: ='Raw Data'!K98 -> 172 | J89: =G89/F89 -> 1.9298246 | K89: =E89/F89 -> 0.14035088 | L89: =E89/H89 -> 0.034078807 | M89: =LN(H89) -> 6.8448155 | N89: =(C89-'Raw Data'!D97)/'Raw Data'!D97 -> 0.16624041 | O89: =I89/H89 -> 0.18317359 | P89: ='Raw Data'!L98 -> 7.56
A90: Gokaldas Exports | B90: FY20-21 | C90: ='Raw Data'!D99 -> 1209 | D90: ='Raw Data'!E99 -> 101 | E90: ='Raw Data'!F99 -> 26 | F90: ='Raw Data'!G99+'Raw Data'!H99 -> 291 | G90: ='Raw Data'!I99 -> 476 | H90: ='Raw Data'!J99 -> 1005 | I90: ='Raw Data'!K99 -> 235 | J90: =G90/F90 -> 1.6357388 | K90: =E90/F90 -> 0.089347079 | L90: =E90/H90 -> 0.025870647 | M90: =LN(H90) -> 6.9127428 | N90: =(C90-'Raw Data'!D98)/'Raw Data'!D98 -> -0.11622807 | O90: =I90/H90 -> 0.23383085 | P90: ='Raw Data'!L99 -> 6.12
A91: Gokaldas Exports | B91: FY21-22 | C91: ='Raw Data'!D100 -> 1789 | D91: ='Raw Data'!E100 -> 204 | E91: ='Raw Data'!F100 -> 117 | F91: ='Raw Data'!G100+'Raw Data'!H100 -> 709 | G91: ='Raw Data'!I100 -> 191 | H91: ='Raw Data'!J100 -> 1226 | I91: ='Raw Data'!K100 -> 282 | J91: =G91/F91 -> 0.26939351 | K91: =E91/F91 -> 0.16502116 | L91: =E91/H91 -> 0.0954323 | M91: =LN(H91) -> 7.1115121 | N91: =(C91-'Raw Data'!D99)/'Raw Data'!D99 -> 0.47973532 | O91: =I91/H91 -> 0.23001631 | P91: ='Raw Data'!L100 -> 19.79
A92: Gokaldas Exports | B92: FY22-23 | C92: ='Raw Data'!D101 -> 2221 | D92: ='Raw Data'!E101 -> 269 | E92: ='Raw Data'!F101 -> 178 | F92: ='Raw Data'!G101+'Raw Data'!H101 -> 893 | G92: ='Raw Data'!I101 -> 141 | H92: ='Raw Data'!J101 -> 1343 | I92: ='Raw Data'!K101 -> 261 | J92: =G92/F92 -> 0.15789474 | K92: =E92/F92 -> 0.19932811 | L92: =E92/H92 -> 0.13253909 | M92: =LN(H92) -> 7.2026612 | N92: =(C92-'Raw Data'!D100)/'Raw Data'!D100 -> 0.24147568 | O92: =I92/H92 -> 0.19434103 | P92: ='Raw Data'!L101 -> 29.45
A93: Gokaldas Exports | B93: FY23-24 | C93: ='Raw Data'!D102 -> 2139 | D93: ='Raw Data'!E102 -> 255 | E93: ='Raw Data'!F102 -> 164 | F93: ='Raw Data'!G102+'Raw Data'!H102 -> 1342 | G93: ='Raw Data'!I102 -> 254 | H93: ='Raw Data'!J102 -> 1955 | I93: ='Raw Data'!K102 -> 254 | J93: =G93/F93 -> 0.18926975 | K93: =E93/F93 -> 0.12220566 | L93: =E93/H93 -> 0.083887468 | M93: =LN(H93) -> 7.5781455 | N93: =(C93-'Raw Data'!D101)/'Raw Data'!D101 -> -0.036920306 | O93: =I93/H93 -> 0.12992327 | P93: ='Raw Data'!L102 -> 25.9
A94: Gokaldas Exports | B94: FY24-25 | C94: ='Raw Data'!D103 -> 2477 | D94: ='Raw Data'!E103 -> 244 | E94: ='Raw Data'!F103 -> 191 | F94: ='Raw Data'!G103+'Raw Data'!H103 -> 2145 | G94: ='Raw Data'!I103 -> 192 | H94: ='Raw Data'!J103 -> 2763 | I94: ='Raw Data'!K103 -> 272 | J94: =G94/F94 -> 0.08951049 | K94: =E94/F94 -> 0.089044289 | L94: =E94/H94 -> 0.06912776 | M94: =LN(H94) -> 7.9240723 | N94: =(C94-'Raw Data'!D102)/'Raw Data'!D102 -> 0.15801777 | O94: =I94/H94 -> 0.098443721 | P94: ='Raw Data'!L103 -> 26.77
A95: Siyaram Silk Mills | B95: FY15-16 | C95: ='Raw Data'!D105 -> 1609 | D95: ='Raw Data'!E105 -> 196 | E95: ='Raw Data'!F105 -> 84 | F95: ='Raw Data'!G105+'Raw Data'!H105 -> 506 | G95: ='Raw Data'!I105 -> 408 | H95: ='Raw Data'!J105 -> 1195 | I95: ='Raw Data'!K105 -> 403 | J95: =G95/F95 -> 0.80632411 | K95: =E95/F95 -> 0.16600791 | L95: =E95/H95 -> 0.070292887 | M95: =LN(H95) -> 7.0859015 | N95: =(C95-'Raw Data'!D104)/'Raw Data'!D104 -> 0.075534759 | O95: =I95/H95 -> 0.33723849 | P95: ='Raw Data'!L105 -> 17.93
A96: Siyaram Silk Mills | B96: FY16-17 | C96: ='Raw Data'!D106 -> 1570 | D96: ='Raw Data'!E106 -> 197 | E96: ='Raw Data'!F106 -> 91 | F96: ='Raw Data'!G106+'Raw Data'!H106 -> 596 | G96: ='Raw Data'!I106 -> 305 | H96: ='Raw Data'!J106 -> 1159 | I96: ='Raw Data'!K106 -> 445 | J96: =G96/F96 -> 0.51174497 | K96: =E96/F96 -> 0.15268456 | L96: =E96/H96 -> 0.078515962 | M96: =LN(H96) -> 7.0553128 | N96: =(C96-'Raw Data'!D105)/'Raw Data'!D105 -> -0.024238658 | O96: =I96/H96 -> 0.38395168 | P96: ='Raw Data'!L106 -> 19.41
A97: Siyaram Silk Mills | B97: FY17-18 | C97: ='Raw Data'!D107 -> 1733 | D97: ='Raw Data'!E107 -> 246 | E97: ='Raw Data'!F107 -> 112 | F97: ='Raw Data'!G107+'Raw Data'!H107 -> 678 | G97: ='Raw Data'!I107 -> 573 | H97: ='Raw Data'!J107 -> 1553 | I97: ='Raw Data'!K107 -> 532 | J97: =G97/F97 -> 0.84513274 | K97: =E97/F97 -> 0.16519174 | L97: =E97/H97 -> 0.07211848 | M97: =LN(H97) -> 7.3479438 | N97: =(C97-'Raw Data'!D106)/'Raw Data'!D106 -> 0.10382166 | O97: =I97/H97 -> 0.34256278 | P97: ='Raw Data'!L107 -> 23.81
A98: Siyaram Silk Mills | B98: FY18-19 | C98: ='Raw Data'!D108 -> 1815 | D98: ='Raw Data'!E108 -> 241 | E98: ='Raw Data'!F108 -> 101 | F98: ='Raw Data'!G108+'Raw Data'!H108 -> 757 | G98: ='Raw Data'!I108 -> 444 | H98: ='Raw Data'!J108 -> 1505 | I98: ='Raw Data'!K108 -> 527 | J98: =G98/F98 -> 0.58652576 | K98: =E98/F98 -> 0.1334214 | L98: =E98/H98 -> 0.067109635 | M98: =LN(H98) -> 7.3165482 | N98: =(C98-'Raw Data'!D107)/'Raw Data'!D107 -> 0.047316792 | O98: =I98/H98 -> 0.35016611 | P98: ='Raw Data'!L108 -> 21.58
A99: Siyaram Silk Mills | B99: FY19-20 | C99: ='Raw Data'!D109 -> 1698 | D99: ='Raw Data'!E109 -> 169 | E99: ='Raw Data'!F109 -> 72 | F99: ='Raw Data'!G109+'Raw Data'!H109 -> 767 | G99: ='Raw Data'!I109 -> 428 | H99: ='Raw Data'!J109 -> 1503 | I99: ='Raw Data'!K109 -> 552 | J99: =G99/F99 -> 0.55801825 | K99: =E99/F99 -> 0.093872229 | L99: =E99/H99 -> 0.047904192 | M99: =LN(H99) -> 7.3152184 | N99: =(C99-'Raw Data'!D108)/'Raw Data'!D108 -> -0.06446281 | O99: =I99/H99 -> 0.36726547 | P99: ='Raw Data'!L109 -> 15.3
A100: Siyaram Silk Mills | B100: FY20-21 | C100: ='Raw Data'!D110 -> 1088 | D100: ='Raw Data'!E110 -> 55 | E100: ='Raw Data'!F110 -> 5 | F100: ='Raw Data'!G110+'Raw Data'!H110 -> 774 | G100: ='Raw Data'!I110 -> 139 | H100: ='Raw Data'!J110 -> 1217 | I100: ='Raw Data'!K110 -> 490 | J100: =G100/F100 -> 0.17958656 | K100: =E100/F100 -> 0.0064599483 | L100: =E100/H100 -> 0.0041084634 | M100: =LN(H100) -> 7.1041441 | N100: =(C100-'Raw Data'!D109)/'Raw Data'!D109 -> -0.35924617 | O100: =I100/H100 -> 0.40262942 | P100: ='Raw Data'!L110 -> 1.14
A101: Siyaram Silk Mills | B101: FY21-22 | C101: ='Raw Data'!D111 -> 1903 | D101: ='Raw Data'!E111 -> 334 | E101: ='Raw Data'!F111 -> 213 | F101: ='Raw Data'!G111+'Raw Data'!H111 -> 937 | G101: ='Raw Data'!I111 -> 223 | H101: ='Raw Data'!J111 -> 1515 | I101: ='Raw Data'!K111 -> 500 | J101: =G101/F101 -> 0.2379936 | K101: =E101/F101 -> 0.22732124 | L101: =E101/H101 -> 0.14059406 | M101: =LN(H101) -> 7.3231707 | N101: =(C101-'Raw Data'!D110)/'Raw Data'!D110 -> 0.74908088 | O101: =I101/H101 -> 0.330033 | P101: ='Raw Data'!L111 -> 45.34
...

Sheet Descriptive Stats
A1: Descriptive Statistics — by Company (FY2015-16 to FY2024-25, N=10 years each)
A3: Company | B3: Mean D/E | C3: SD D/E | D3: Min D/E | E3: Max D/E | F3: Mean ROE | G3: Mean ROA | H3: Mean EPS (Rs.) | I3: Mean Sales Growth | J3: Mean Tangibility | K3: Mean Size (ln TA)
A4: KPR Mill | B4: =AVERAGEIF('Ratios Panel'!$A$5:$A$104,A4,'Ratios Panel'!$J$5:$J$104) -> 0.26862496 | C4: =SQRT(SUMPRODUCT(('Ratios Panel'!$A$5:$A$104=A4)*('Ratios Panel'!$J$5:$J$104-B4)^2)/(COUNTIF('Ratios Panel'!$A$5:$A$104,A4)-1)) -> 0.1757145 | D4: =_xlfn.MINIFS('Ratios Panel'!$J$5:$J$104,'Ratios Panel'!$A$5:$A$104,A4) -> 0.0625 | E4: =_xlfn.MAXIFS('Ratios Panel'!$J$5:$J$104,'Ratios Panel'!$A$5:$A$104,A4) -> 0.60142712 | F4: =AVERAGEIF('Ratios Panel'!$A$5:$A$104,A4,'Ratios Panel'!$K$5:$K$104) -> 0.1979938 | G4: =AVERAGEIF('Ratios Panel'!$A$5:$A$104,A4,'Ratios Panel'!$L$5:$L$104) -> 0.14401401 | H4: =AVERAGEIF('Ratios Panel'!$A$5:$A$104,A4,'Ratios Panel'!$P$5:$P$104) -> 12.094 | I4: =AVERAGEIF('Ratios Panel'!$A$5:$A$104,A4,'Ratios Panel'!$N$5:$N$104) -> 0.082229385 | J4: =AVERAGEIF('Ratios Panel'!$A$5:$A$104,A4,'Ratios Panel'!$O$5:$O$104) -> 0.35665624 | K4: =AVERAGEIF('Ratios Panel'!$A$5:$A$104,A4,'Ratios Panel'!$M$5:$M$104) -> 7.8852056
A5: Welspun Living | B5: =AVERAGEIF('Ratios Panel'!$A$5:$A$104,A5,'Ratios Panel'!$J$5:$J$104) -> 0.78091842 | C5: =SQRT(SUMPRODUCT(('Ratios Panel'!$A$5:$A$104=A5)*('Ratios Panel'!$J$5:$J$104-B5)^2)/(COUNTIF('Ratios Panel'!$A$5:$A$104,A5)-1)) -> 0.37343586 | D5: =_xlfn.MINIFS('Ratios Panel'!$J$5:$J$104,'Ratios Panel'!$A$5:$A$104,A5) -> 0.37928058 | E5: =_xlfn.MAXIFS('Ratios Panel'!$J$5:$J$104,'Ratios Panel'!$A$5:$A$104,A5) -> 1.3512375 | F5: =AVERAGEIF('Ratios Panel'!$A$5:$A$104,A5,'Ratios Panel'!$K$5:$K$104) -> 0.1428065 | G5: =AVERAGEIF('Ratios Panel'!$A$5:$A$104,A5,'Ratios Panel'!$L$5:$L$104) -> 0.063211865 | H5: =AVERAGEIF('Ratios Panel'!$A$5:$A$104,A5,'Ratios Panel'!$P$5:$P$104) -> 4.044 | I5: =AVERAGEIF('Ratios Panel'!$A$5:$A$104,A5,'Ratios Panel'!$N$5:$N$104) -> 0.075440256 | J5: =AVERAGEIF('Ratios Panel'!$A$5:$A$104,A5,'Ratios Panel'!$O$5:$O$104) -> 0.41613998 | K5: =AVERAGEIF('Ratios Panel'!$A$5:$A$104,A5,'Ratios Panel'!$M$5:$M$104) -> 8.7676709
A6: Indo Count Industries | B6: =AVERAGEIF('Ratios Panel'!$A$5:$A$104,A6,'Ratios Panel'!$J$5:$J$104) -> 0.45668052 | C6: =SQRT(SUMPRODUCT(('Ratios Panel'!$A$5:$A$104=A6)*('Ratios Panel'!$J$5:$J$104-B6)^2)/(COUNTIF('Ratios Panel'!$A$5:$A$104,A6)-1)) -> 0.13300681 | D6: =_xlfn.MINIFS('Ratios Panel'!$J$5:$J$104,'Ratios Panel'!$A$5:$A$104,A6) -> 0.321875 | E6: =_xlfn.MAXIFS('Ratios Panel'!$J$5:$J$104,'Ratios Panel'!$A$5:$A$104,A6) -> 0.77030457 | F6: =AVERAGEIF('Ratios Panel'!$A$5:$A$104,A6,'Ratios Panel'!$K$5:$K$104) -> 0.17577552 | G6: =AVERAGEIF('Ratios Panel'!$A$5:$A$104,A6,'Ratios Panel'!$L$5:$L$104) -> 0.096709696 | H6: =AVERAGEIF('Ratios Panel'!$A$5:$A$104,A6,'Ratios Panel'!$P$5:$P$104) -> 10.749 | I6: =AVERAGEIF('Ratios Panel'!$A$5:$A$104,A6,'Ratios Panel'!$N$5:$N$104) -> 0.095288808 | J6: =AVERAGEIF('Ratios Panel'!$A$5:$A$104,A6,'Ratios Panel'!$O$5:$O$104) -> 0.33648802 | K6: =AVERAGEIF('Ratios Panel'!$A$5:$A$104,A6,'Ratios Panel'!$M$5:$M$104) -> 7.6722727
A7: Vardhman Textiles | B7: =AVERAGEIF('Ratios Panel'!$A$5:$A$104,A7,'Ratios Panel'!$J$5:$J$104) -> 0.37071413 | C7: =SQRT(SUMPRODUCT(('Ratios Panel'!$A$5:$A$104=A7)*('Ratios Panel'!$J$5:$J$104-B7)^2)/(COUNTIF('Ratios Panel'!$A$5:$A$104,A7)-1)) -> 0.17911154 | D7: =_xlfn.MINIFS('Ratios Panel'!$J$5:$J$104,'Ratios Panel'!$A$5:$A$104,A7) -> 0.12925454 | E7: =_xlfn.MAXIFS('Ratios Panel'!$J$5:$J$104,'Ratios Panel'!$A$5:$A$104,A7) -> 0.70352304 | F7: =AVERAGEIF('Ratios Panel'!$A$5:$A$104,A7,'Ratios Panel'!$K$5:$K$104) -> 0.13148297 | G7: =AVERAGEIF('Ratios Panel'!$A$5:$A$104,A7,'Ratios Panel'!$L$5:$L$104) -> 0.085213859 | H7: =AVERAGEIF('Ratios Panel'!$A$5:$A$104,A7,'Ratios Panel'!$P$5:$P$104) -> 26.643 | I7: =AVERAGEIF('Ratios Panel'!$A$5:$A$104,A7,'Ratios Panel'!$N$5:$N$104) -> 0.064918386 | J7: =AVERAGEIF('Ratios Panel'!$A$5:$A$104,A7,'Ratios Panel'!$O$5:$O$104) -> 0.36764949 | K7: =AVERAGEIF('Ratios Panel'!$A$5:$A$104,A7,'Ratios Panel'!$M$5:$M$104) -> 9.1158841
A8: Trident | B8: =AVERAGEIF('Ratios Panel'!$A$5:$A$104,A8,'Ratios Panel'!$J$5:$J$104) -> 0.71020611 | C8: =SQRT(SUMPRODUCT(('Ratios Panel'!$A$5:$A$104=A8)*('Ratios Panel'!$J$5:$J$104-B8)^2)/(COUNTIF('Ratios Panel'!$A$5:$A$104,A8)-1)) -> 0.37177203 | D8: =_xlfn.MINIFS('Ratios Panel'!$J$5:$J$104,'Ratios Panel'!$A$5:$A$104,A8) -> 0.34028114 | E8: =_xlfn.MAXIFS('Ratios Panel'!$J$5:$J$104,'Ratios Panel'!$A$5:$A$104,A8) -> 1.4505176 | F8: =AVERAGEIF('Ratios Panel'!$A$5:$A$104,A8,'Ratios Panel'!$K$5:$K$104) -> 0.11556729 | G8: =AVERAGEIF('Ratios Panel'!$A$5:$A$104,A8,'Ratios Panel'!$L$5:$L$104) -> 0.060904718 | H8: =AVERAGEIF('Ratios Panel'!$A$5:$A$104,A8,'Ratios Panel'!$P$5:$P$104) -> 0.765 | I8: =AVERAGEIF('Ratios Panel'!$A$5:$A$104,A8,'Ratios Panel'!$N$5:$N$104) -> 0.07808884 | J8: =AVERAGEIF('Ratios Panel'!$A$5:$A$104,A8,'Ratios Panel'!$O$5:$O$104) -> 0.65890352 | K8: =AVERAGEIF('Ratios Panel'!$A$5:$A$104,A8,'Ratios Panel'!$M$5:$M$104) -> 8.7629235
A9: Arvind | B9: =AVERAGEIF('Ratios Panel'!$A$5:$A$104,A9,'Ratios Panel'!$J$5:$J$104) -> 0.69507873 | C9: =SQRT(SUMPRODUCT(('Ratios Panel'!$A$5:$A$104=A9)*('Ratios Panel'!$J$5:$J$104-B9)^2)/(COUNTIF('Ratios Panel'!$A$5:$A$104,A9)-1)) -> 0.23377797 | D9: =_xlfn.MINIFS('Ratios Panel'!$J$5:$J$104,'Ratios Panel'!$A$5:$A$104,A9) -> 0.37963762 | E9: =_xlfn.MAXIFS('Ratios Panel'!$J$5:$J$104,'Ratios Panel'!$A$5:$A$104,A9) -> 1.0458808 | F9: =AVERAGEIF('Ratios Panel'!$A$5:$A$104,A9,'Ratios Panel'!$K$5:$K$104) -> 0.063429095 | G9: =AVERAGEIF('Ratios Panel'!$A$5:$A$104,A9,'Ratios Panel'!$L$5:$L$104) -> 0.029202486 | H9: =AVERAGEIF('Ratios Panel'!$A$5:$A$104,A9,'Ratios Panel'!$P$5:$P$104) -> 7.706 | I9: =AVERAGEIF('Ratios Panel'!$A$5:$A$104,A9,'Ratios Panel'!$N$5:$N$104) -> 0.041209065 | J9: =AVERAGEIF('Ratios Panel'!$A$5:$A$104,A9,'Ratios Panel'!$O$5:$O$104) -> 0.478467 | K9: =AVERAGEIF('Ratios Panel'!$A$5:$A$104,A9,'Ratios Panel'!$M$5:$M$104) -> 8.83518
A10: Nitin Spinners | B10: =AVERAGEIF('Ratios Panel'!$A$5:$A$104,A10,'Ratios Panel'!$J$5:$J$104) -> 1.4331148 | C10: =SQRT(SUMPRODUCT(('Ratios Panel'!$A$5:$A$104=A10)*('Ratios Panel'!$J$5:$J$104-B10)^2)/(COUNTIF('Ratios Panel'!$A$5:$A$104,A10)-1)) -> 0.51486684 | D10: =_xlfn.MINIFS('Ratios Panel'!$J$5:$J$104,'Ratios Panel'!$A$5:$A$104,A10) -> 0.78652968 | E10: =_xlfn.MAXIFS('Ratios Panel'!$J$5:$J$104,'Ratios Panel'!$A$5:$A$104,A10) -> 2.1515152 | F10: =AVERAGEIF('Ratios Panel'!$A$5:$A$104,A10,'Ratios Panel'!$K$5:$K$104) -> 0.16392875 | G10: =AVERAGEIF('Ratios Panel'!$A$5:$A$104,A10,'Ratios Panel'!$L$5:$L$104) -> 0.065575769 | H10: =AVERAGEIF('Ratios Panel'!$A$5:$A$104,A10,'Ratios Panel'!$P$5:$P$104) -> 20.138 | I10: =AVERAGEIF('Ratios Panel'!$A$5:$A$104,A10,'Ratios Panel'!$N$5:$N$104) -> 0.1955675 | J10: =AVERAGEIF('Ratios Panel'!$A$5:$A$104,A10,'Ratios Panel'!$O$5:$O$104) -> 0.63298045 | K10: =AVERAGEIF('Ratios Panel'!$A$5:$A$104,A10,'Ratios Panel'!$M$5:$M$104) -> 7.320582
A11: Sutlej Textiles | B11: =AVERAGEIF('Ratios Panel'!$A$5:$A$104,A11,'Ratios Panel'!$J$5:$J$104) -> 0.98795899 | C11: =SQRT(SUMPRODUCT(('Ratios Panel'!$A$5:$A$104=A11)*('Ratios Panel'!$J$5:$J$104-B11)^2)/(COUNTIF('Ratios Panel'!$A$5:$A$104,A11)-1)) -> 0.1586971 | D11: =_xlfn.MINIFS('Ratios Panel'!$J$5:$J$104,'Ratios Panel'!$A$5:$A$104,A11) -> 0.8300885 | E11: =_xlfn.MAXIFS('Ratios Panel'!$J$5:$J$104,'Ratios Panel'!$A$5:$A$104,A11) -> 1.2696078 | F11: =AVERAGEIF('Ratios Panel'!$A$5:$A$104,A11,'Ratios Panel'!$K$5:$K$104) -> 0.057102319 | G11: =AVERAGEIF('Ratios Panel'!$A$5:$A$104,A11,'Ratios Panel'!$L$5:$L$104) -> 0.023493255 | H11: =AVERAGEIF('Ratios Panel'!$A$5:$A$104,A11,'Ratios Panel'!$P$5:$P$104) -> 2.963 | I11: =AVERAGEIF('Ratios Panel'!$A$5:$A$104,A11,'Ratios Panel'!$N$5:$N$104) -> 0.054285422 | J11: =AVERAGEIF('Ratios Panel'!$A$5:$A$104,A11,'Ratios Panel'!$O$5:$O$104) -> 0.5191884 | K11: =AVERAGEIF('Ratios Panel'!$A$5:$A$104,A11,'Ratios Panel'!$M$5:$M$104) -> 7.6592997
A12: Gokaldas Exports | B12: =AVERAGEIF('Ratios Panel'!$A$5:$A$104,A12,'Ratios Panel'!$J$5:$J$104) -> 1.3987195 | C12: =SQRT(SUMPRODUCT(('Ratios Panel'!$A$5:$A$104=A12)*('Ratios Panel'!$J$5:$J$104-B12)^2)/(COUNTIF('Ratios Panel'!$A$5:$A$104,A12)-1)) -> 1.2279638 | D12: =_xlfn.MINIFS('Ratios Panel'!$J$5:$J$104,'Ratios Panel'!$A$5:$A$104,A12) -> 0.08951049 | E12: =_xlfn.MAXIFS('Ratios Panel'!$J$5:$J$104,'Ratios Panel'!$A$5:$A$104,A12) -> 3.6307692 | F12: =AVERAGEIF('Ratios Panel'!$A$5:$A$104,A12,'Ratios Panel'!$K$5:$K$104) -> 0.068457022 | G12: =AVERAGEIF('Ratios Panel'!$A$5:$A$104,A12,'Ratios Panel'!$L$5:$L$104) -> 0.045968841 | H12: =AVERAGEIF('Ratios Panel'!$A$5:$A$104,A12,'Ratios Panel'!$P$5:$P$104) -> 11.696 | I12: =AVERAGEIF('Ratios Panel'!$A$5:$A$104,A12,'Ratios Panel'!$N$5:$N$104) -> 0.10211417 | J12: =AVERAGEIF('Ratios Panel'!$A$5:$A$104,A12,'Ratios Panel'!$O$5:$O$104) -> 0.15699059 | K12: =AVERAGEIF('Ratios Panel'!$A$5:$A$104,A12,'Ratios Panel'!$M$5:$M$104) -> 7.0227244
A13: Siyaram Silk Mills | B13: =AVERAGEIF('Ratios Panel'!$A$5:$A$104,A13,'Ratios Panel'!$J$5:$J$104) -> 0.42249735 | C13: =SQRT(SUMPRODUCT(('Ratios Panel'!$A$5:$A$104=A13)*('Ratios Panel'!$J$5:$J$104-B13)^2)/(COUNTIF('Ratios Panel'!$A$5:$A$104,A13)-1)) -> 0.27301807 | D13: =_xlfn.MINIFS('Ratios Panel'!$J$5:$J$104,'Ratios Panel'!$A$5:$A$104,A13) -> 0.14285714 | E13: =_xlfn.MAXIFS('Ratios Panel'!$J$5:$J$104,'Ratios Panel'!$A$5:$A$104,A13) -> 0.84513274 | F13: =AVERAGEIF('Ratios Panel'!$A$5:$A$104,A13,'Ratios Panel'!$K$5:$K$104) -> 0.14824595 | G13: =AVERAGEIF('Ratios Panel'!$A$5:$A$104,A13,'Ratios Panel'!$L$5:$L$104) -> 0.085461938 | H13: =AVERAGEIF('Ratios Panel'!$A$5:$A$104,A13,'Ratios Panel'!$P$5:$P$104) -> 28.274 | I13: =AVERAGEIF('Ratios Panel'!$A$5:$A$104,A13,'Ratios Panel'!$N$5:$N$104) -> 0.069913705 | J13: =AVERAGEIF('Ratios Panel'!$A$5:$A$104,A13,'Ratios Panel'!$O$5:$O$104) -> 0.34274544 | K13: =AVERAGEIF('Ratios Panel'!$A$5:$A$104,A13,'Ratios Panel'!$M$5:$M$104) -> 7.2878111
A14: POOLED (all 100 firm-years) | B14: =AVERAGE('Ratios Panel'!$J$5:$J$104) -> 0.75245135 | C14: =STDEV('Ratios Panel'!$J$5:$J$104) -> 0.60097434 | D14: =MIN('Ratios Panel'!$J$5:$J$104) -> 0.0625 | E14: =MAX('Ratios Panel'!$J$5:$J$104) -> 3.6307692 | F14: =AVERAGE('Ratios Panel'!$K$5:$K$104) -> 0.12647892 | G14: =AVERAGE('Ratios Panel'!$L$5:$L$104) -> 0.069975643 | H14: =AVERAGE('Ratios Panel'!$P$5:$P$104) -> 12.5072 | I14: =AVERAGE('Ratios Panel'!$N$5:$N$104) -> 0.085905553 | J14: =AVERAGE('Ratios Panel'!$O$5:$O$104) -> 0.42662091 | K14: =AVERAGE('Ratios Panel'!$M$5:$M$104) -> 8.0329554
A16: Year-wise Trend (pooled across 10 companies)
A17: FY | B17: Mean D/E | C17: SD D/E | D17: Mean ROE | E17: Mean ROA | F17: Mean EPS (Rs.)
A18: FY15-16 | B18: =AVERAGEIF('Ratios Panel'!$B$5:$B$104,A18,'Ratios Panel'!$J$5:$J$104) -> 1.1017381 | C18: =SQRT(SUMPRODUCT(('Ratios Panel'!$B$5:$B$104=A18)*('Ratios Panel'!$J$5:$J$104-B18)^2)/(COUNTIF('Ratios Panel'!$B$5:$B$104,A18)-1)) -> 0.42466518 | D18: =AVERAGEIF('Ratios Panel'!$B$5:$B$104,A18,'Ratios Panel'!$K$5:$K$104) -> 0.21561211 | E18: =AVERAGEIF('Ratios Panel'!$B$5:$B$104,A18,'Ratios Panel'!$L$5:$L$104) -> 0.088551985 | F18: =AVERAGEIF('Ratios Panel'!$B$5:$B$104,A18,'Ratios Panel'!$P$5:$P$104) -> 11.054
A19: FY16-17 | B19: =AVERAGEIF('Ratios Panel'!$B$5:$B$104,A19,'Ratios Panel'!$J$5:$J$104) -> 1.1215308 | C19: =SQRT(SUMPRODUCT(('Ratios Panel'!$B$5:$B$104=A19)*('Ratios Panel'!$J$5:$J$104-B19)^2)/(COUNTIF('Ratios Panel'!$B$5:$B$104,A19)-1)) -> 0.82119837 | D19: =AVERAGEIF('Ratios Panel'!$B$5:$B$104,A19,'Ratios Panel'!$K$5:$K$104) -> 0.12931842 | E19: =AVERAGEIF('Ratios Panel'!$B$5:$B$104,A19,'Ratios Panel'!$L$5:$L$104) -> 0.070366617 | F19: =AVERAGEIF('Ratios Panel'!$B$5:$B$104,A19,'Ratios Panel'!$P$5:$P$104) -> 8.563
A20: FY17-18 | B20: =AVERAGEIF('Ratios Panel'!$B$5:$B$104,A20,'Ratios Panel'!$J$5:$J$104) -> 1.0825075 | C20: =SQRT(SUMPRODUCT(('Ratios Panel'!$B$5:$B$104=A20)*('Ratios Panel'!$J$5:$J$104-B20)^2)/(COUNTIF('Ratios Panel'!$B$5:$B$104,A20)-1)) -> 0.95048547 | D20: =AVERAGEIF('Ratios Panel'!$B$5:$B$104,A20,'Ratios Panel'!$K$5:$K$104) -> 0.09050075 | E20: =AVERAGEIF('Ratios Panel'!$B$5:$B$104,A20,'Ratios Panel'!$L$5:$L$104) -> 0.053559413 | F20: =AVERAGEIF('Ratios Panel'!$B$5:$B$104,A20,'Ratios Panel'!$P$5:$P$104) -> 7.627
A21: FY18-19 | B21: =AVERAGEIF('Ratios Panel'!$B$5:$B$104,A21,'Ratios Panel'!$J$5:$J$104) -> 0.89031656 | C21: =SQRT(SUMPRODUCT(('Ratios Panel'!$B$5:$B$104=A21)*('Ratios Panel'!$J$5:$J$104-B21)^2)/(COUNTIF('Ratios Panel'!$B$5:$B$104,A21)-1)) -> 0.49001751 | D21: =AVERAGEIF('Ratios Panel'!$B$5:$B$104,A21,'Ratios Panel'!$K$5:$K$104) -> 0.10845561 | E21: =AVERAGEIF('Ratios Panel'!$B$5:$B$104,A21,'Ratios Panel'!$L$5:$L$104) -> 0.052781871 | F21: =AVERAGEIF('Ratios Panel'!$B$5:$B$104,A21,'Ratios Panel'!$P$5:$P$104) -> 8.801
A22: FY19-20 | B22: =AVERAGEIF('Ratios Panel'!$B$5:$B$104,A22,'Ratios Panel'!$J$5:$J$104) -> 0.88798763 | C22: =SQRT(SUMPRODUCT(('Ratios Panel'!$B$5:$B$104=A22)*('Ratios Panel'!$J$5:$J$104-B22)^2)/(COUNTIF('Ratios Panel'!$B$5:$B$104,A22)-1)) -> 0.63169113 | D22: =AVERAGEIF('Ratios Panel'!$B$5:$B$104,A22,'Ratios Panel'!$K$5:$K$104) -> 0.10327311 | E22: =AVERAGEIF('Ratios Panel'!$B$5:$B$104,A22,'Ratios Panel'!$L$5:$L$104) -> 0.051676997 | F22: =AVERAGEIF('Ratios Panel'!$B$5:$B$104,A22,'Ratios Panel'!$P$5:$P$104) -> 7.259
A23: FY20-21 | B23: =AVERAGEIF('Ratios Panel'!$B$5:$B$104,A23,'Ratios Panel'!$J$5:$J$104) -> 0.69535497 | C23: =SQRT(SUMPRODUCT(('Ratios Panel'!$B$5:$B$104=A23)*('Ratios Panel'!$J$5:$J$104-B23)^2)/(COUNTIF('Ratios Panel'!$B$5:$B$104,A23)-1)) -> 0.5602645 | D23: =AVERAGEIF('Ratios Panel'!$B$5:$B$104,A23,'Ratios Panel'!$K$5:$K$104) -> 0.10134215 | E23: =AVERAGEIF('Ratios Panel'!$B$5:$B$104,A23,'Ratios Panel'!$L$5:$L$104) -> 0.056687263 | F23: =AVERAGEIF('Ratios Panel'!$B$5:$B$104,A23,'Ratios Panel'!$P$5:$P$104) -> 6.808
A24: FY21-22 | B24: =AVERAGEIF('Ratios Panel'!$B$5:$B$104,A24,'Ratios Panel'!$J$5:$J$104) -> 0.4707226 | C24: =SQRT(SUMPRODUCT(('Ratios Panel'!$B$5:$B$104=A24)*('Ratios Panel'!$J$5:$J$104-B24)^2)/(COUNTIF('Ratios Panel'!$B$5:$B$104,A24)-1)) -> 0.25375463 | D24: =AVERAGEIF('Ratios Panel'!$B$5:$B$104,A24,'Ratios Panel'!$K$5:$K$104) -> 0.19648027 | E24: =AVERAGEIF('Ratios Panel'!$B$5:$B$104,A24,'Ratios Panel'!$L$5:$L$104) -> 0.11625427 | F24: =AVERAGEIF('Ratios Panel'!$B$5:$B$104,A24,'Ratios Panel'!$P$5:$P$104) -> 23.689
A25: FY22-23 | B25: =AVERAGEIF('Ratios Panel'!$B$5:$B$104,A25,'Ratios Panel'!$J$5:$J$104) -> 0.42263928 | C25: =SQRT(SUMPRODUCT(('Ratios Panel'!$B$5:$B$104=A25)*('Ratios Panel'!$J$5:$J$104-B25)^2)/(COUNTIF('Ratios Panel'!$B$5:$B$104,A25)-1)) -> 0.28460462 | D25: =AVERAGEIF('Ratios Panel'!$B$5:$B$104,A25,'Ratios Panel'!$K$5:$K$104) -> 0.12830708 | E25: =AVERAGEIF('Ratios Panel'!$B$5:$B$104,A25,'Ratios Panel'!$L$5:$L$104) -> 0.081757065 | F25: =AVERAGEIF('Ratios Panel'!$B$5:$B$104,A25,'Ratios Panel'!$P$5:$P$104) -> 18.569
A26: FY23-24 | B26: =AVERAGEIF('Ratios Panel'!$B$5:$B$104,A26,'Ratios Panel'!$J$5:$J$104) -> 0.44934995 | C26: =SQRT(SUMPRODUCT(('Ratios Panel'!$B$5:$B$104=A26)*('Ratios Panel'!$J$5:$J$104-B26)^2)/(COUNTIF('Ratios Panel'!$B$5:$B$104,A26)-1)) -> 0.33913851 | D26: =AVERAGEIF('Ratios Panel'!$B$5:$B$104,A26,'Ratios Panel'!$K$5:$K$104) -> 0.09885248 | E26: =AVERAGEIF('Ratios Panel'!$B$5:$B$104,A26,'Ratios Panel'!$L$5:$L$104) -> 0.064592692 | F26: =AVERAGEIF('Ratios Panel'!$B$5:$B$104,A26,'Ratios Panel'!$P$5:$P$104) -> 15.372
A27: FY24-25 | B27: =AVERAGEIF('Ratios Panel'!$B$5:$B$104,A27,'Ratios Panel'!$J$5:$J$104) -> 0.40236607 | C27: =SQRT(SUMPRODUCT(('Ratios Panel'!$B$5:$B$104=A27)*('Ratios Panel'!$J$5:$J$104-B27)^2)/(COUNTIF('Ratios Panel'!$B$5:$B$104,A27)-1)) -> 0.31760833 | D27: =AVERAGEIF('Ratios Panel'!$B$5:$B$104,A27,'Ratios Panel'!$K$5:$K$104) -> 0.092647241 | E27: =AVERAGEIF('Ratios Panel'!$B$5:$B$104,A27,'Ratios Panel'!$L$5:$L$104) -> 0.06352826 | F27: =AVERAGEIF('Ratios Panel'!$B$5:$B$104,A27,'Ratios Panel'!$P$5:$P$104) -> 17.33

Sheet Correlation Matrix
A1: Correlation Matrix — Pooled Panel (100 firm-years)
B3: D/E | C3: ROE | D3: ROA | E3: EPS | F3: Size (ln TA) | G3: Sales Growth | H3: Tangibility
A4: D/E | B4: =CORREL('Ratios Panel'!$J$5:$J$104,'Ratios Panel'!$J$5:$J$104) -> 1 | C4: =CORREL('Ratios Panel'!$J$5:$J$104,'Ratios Panel'!$K$5:$K$104) -> -0.36134275 | D4: =CORREL('Ratios Panel'!$J$5:$J$104,'Ratios Panel'!$L$5:$L$104) -> -0.5105267 | E4: =CORREL('Ratios Panel'!$J$5:$J$104,'Ratios Panel'!$P$5:$P$104) -> -0.38517444 | F4: =CORREL('Ratios Panel'!$J$5:$J$104,'Ratios Panel'!$M$5:$M$104) -> -0.4036985 | G4: =CORREL('Ratios Panel'!$J$5:$J$104,'Ratios Panel'!$N$5:$N$104) -> -0.025696022 | H4: =CORREL('Ratios Panel'!$J$5:$J$104,'Ratios Panel'!$O$5:$O$104) -> 0.1477739
A5: ROE | B5: =CORREL('Ratios Panel'!$K$5:$K$104,'Ratios Panel'!$J$5:$J$104) -> -0.36134275 | C5: =CORREL('Ratios Panel'!$K$5:$K$104,'Ratios Panel'!$K$5:$K$104) -> 1 | D5: =CORREL('Ratios Panel'!$K$5:$K$104,'Ratios Panel'!$L$5:$L$104) -> 0.87685804 | E5: =CORREL('Ratios Panel'!$K$5:$K$104,'Ratios Panel'!$P$5:$P$104) -> 0.53325122 | F5: =CORREL('Ratios Panel'!$K$5:$K$104,'Ratios Panel'!$M$5:$M$104) -> -0.049009685 | G5: =CORREL('Ratios Panel'!$K$5:$K$104,'Ratios Panel'!$N$5:$N$104) -> 0.40629718 | H5: =CORREL('Ratios Panel'!$K$5:$K$104,'Ratios Panel'!$O$5:$O$104) -> -0.0093948253
A6: ROA | B6: =CORREL('Ratios Panel'!$L$5:$L$104,'Ratios Panel'!$J$5:$J$104) -> -0.5105267 | C6: =CORREL('Ratios Panel'!$L$5:$L$104,'Ratios Panel'!$K$5:$K$104) -> 0.87685804 | D6: =CORREL('Ratios Panel'!$L$5:$L$104,'Ratios Panel'!$L$5:$L$104) -> 1 | E6: =CORREL('Ratios Panel'!$L$5:$L$104,'Ratios Panel'!$P$5:$P$104) -> 0.61388946 | F6: =CORREL('Ratios Panel'!$L$5:$L$104,'Ratios Panel'!$M$5:$M$104) -> -0.003689579 | G6: =CORREL('Ratios Panel'!$L$5:$L$104,'Ratios Panel'!$N$5:$N$104) -> 0.4000793 | H6: =CORREL('Ratios Panel'!$L$5:$L$104,'Ratios Panel'!$O$5:$O$104) -> -0.22461519
A7: EPS | B7: =CORREL('Ratios Panel'!$P$5:$P$104,'Ratios Panel'!$J$5:$J$104) -> -0.38517444 | C7: =CORREL('Ratios Panel'!$P$5:$P$104,'Ratios Panel'!$K$5:$K$104) -> 0.53325122 | D7: =CORREL('Ratios Panel'!$P$5:$P$104,'Ratios Panel'!$L$5:$L$104) -> 0.61388946 | E7: =CORREL('Ratios Panel'!$P$5:$P$104,'Ratios Panel'!$P$5:$P$104) -> 1 | F7: =CORREL('Ratios Panel'!$P$5:$P$104,'Ratios Panel'!$M$5:$M$104) -> -0.025267278 | G7: =CORREL('Ratios Panel'!$P$5:$P$104,'Ratios Panel'!$N$5:$N$104) -> 0.36807829 | H7: =CORREL('Ratios Panel'!$P$5:$P$104,'Ratios Panel'!$O$5:$O$104) -> -0.27570381
A8: Size (ln TA) | B8: =CORREL('Ratios Panel'!$M$5:$M$104,'Ratios Panel'!$J$5:$J$104) -> -0.4036985 | C8: =CORREL('Ratios Panel'!$M$5:$M$104,'Ratios Panel'!$K$5:$K$104) -> -0.049009685 | D8: =CORREL('Ratios Panel'!$M$5:$M$104,'Ratios Panel'!$L$5:$L$104) -> -0.003689579 | E8: =CORREL('Ratios Panel'!$M$5:$M$104,'Ratios Panel'!$P$5:$P$104) -> -0.025267278 | F8: =CORREL('Ratios Panel'!$M$5:$M$104,'Ratios Panel'!$M$5:$M$104) -> 1 | G8: =CORREL('Ratios Panel'!$M$5:$M$104,'Ratios Panel'!$N$5:$N$104) -> -0.065802334 | H8: =CORREL('Ratios Panel'!$M$5:$M$104,'Ratios Panel'!$O$5:$O$104) -> 0.24106651
A9: Sales Growth | B9: =CORREL('Ratios Panel'!$N$5:$N$104,'Ratios Panel'!$J$5:$J$104) -> -0.025696022 | C9: =CORREL('Ratios Panel'!$N$5:$N$104,'Ratios Panel'!$K$5:$K$104) -> 0.40629718 | D9: =CORREL('Ratios Panel'!$N$5:$N$104,'Ratios Panel'!$L$5:$L$104) -> 0.4000793 | E9: =CORREL('Ratios Panel'!$N$5:$N$104,'Ratios Panel'!$P$5:$P$104) -> 0.36807829 | F9: =CORREL('Ratios Panel'!$N$5:$N$104,'Ratios Panel'!$M$5:$M$104) -> -0.065802334 | G9: =CORREL('Ratios Panel'!$N$5:$N$104,'Ratios Panel'!$N$5:$N$104) -> 1 | H9: =CORREL('Ratios Panel'!$N$5:$N$104,'Ratios Panel'!$O$5:$O$104) -> -0.026878496
A10: Tangibility | B10: =CORREL('Ratios Panel'!$O$5:$O$104,'Ratios Panel'!$J$5:$J$104) -> 0.1477739 | C10: =CORREL('Ratios Panel'!$O$5:$O$104,'Ratios Panel'!$K$5:$K$104) -> -0.0093948253 | D10: =CORREL('Ratios Panel'!$O$5:$O$104,'Ratios Panel'!$L$5:$L$104) -> -0.22461519 | E10: =CORREL('Ratios Panel'!$O$5:$O$104,'Ratios Panel'!$P$5:$P$104) -> -0.27570381 | F10: =CORREL('Ratios Panel'!$O$5:$O$104,'Ratios Panel'!$M$5:$M$104) -> 0.24106651 | G10: =CORREL('Ratios Panel'!$O$5:$O$104,'Ratios Panel'!$N$5:$N$104) -> -0.026878496 | H10: =CORREL('Ratios Panel'!$O$5:$O$104,'Ratios Panel'!$O$5:$O$104) -> 1
A12: Interpretation: Negative correlation between D/E and ROE/ROA/EPS indicates that more highly levered textile firms in the sample tend to report lower profitability — consistent with Pecking Order Theory (profitable firms rely first on internal accruals, borrowing only when internal funds are insufficient).

Sheet Regression Output
A1: Multiple Regression: ROE = β0 + β1(D/E) + β2(Size) + β3(Growth) + β4(Tangibility) + ε
A2: Estimated by Ordinary Least Squares (pooled cross-section, 100 firm-year observations, 10 companies × 10 years). Computed using Python statsmodels (OLS) on the Ratios Panel data; figures below are software output, reproducible from the 'Ratios Panel' sheet. EPS is reported as a performance measure elsewhere in this workbook (Ratios Panel, Descriptive Stats, Correlation Matrix, and each company sheet) but is not a regressor here, matching the assignment's own regression specification, which is defined only in terms of ROE.
A4: Variable | B4: Coefficient | C4: Std. Error | D4: t-Statistic | E4: p-value | F4: Significant at 5%?
A5: Intercept (β0) | B5: 0.3815 | C5: 0.1001 | D5: 3.81 | E5: 0.0002 | F5: Yes**
A6: D/E Ratio (β1) | B6: -0.0772 | C6: 0.0157 | D6: -4.9264 | E6: 0 | F6: Yes**
A7: Size — ln(Total Assets) (β2) | B7: -0.0311 | C7: 0.0124 | D7: -2.5143 | E7: 0.0136 | F7: Yes*
A8: Sales Growth (β3) | B8: 0.1964 | C8: 0.0432 | D8: 4.5452 | E8: 0 | F8: Yes**
A9: Tangibility (β4) | B9: 0.0835 | C9: 0.058 | D9: 1.4404 | E9: 0.153 | F9: No
A11: Model Summary
A12: R-squared | B12: 0.335409
A13: Adjusted R-squared | B13: 0.307426
A14: F-statistic | B14: 11.986248
A15: Prob (F-statistic) | B15: 0
A16: Number of observations | B16: 100
A18: Supplementary Model: ROA = β0 + β1(D/E) + β2(Size) + β3(Growth) + β4(Tangibility) + ε
A19: Variable | B19: Coefficient | C19: Std. Error | D19: t-Statistic | E19: p-value | F19: Significant at 5%?
A20: Intercept (β0) | B20: 0.2087 | C20: 0.0471 | D20: 4.4299 | E20: 0 | F20: Yes**
A21: D/E Ratio (β1) | B21: -0.0482 | C21: 0.0074 | D21: -6.5346 | E21: 0 | F21: Yes**
A22: Size — ln(Total Assets) (β2) | B22: -0.0123 | C22: 0.0058 | D22: -2.1114 | E22: 0.0374 | F22: Yes*
A23: Sales Growth (β3) | B23: 0.0993 | C23: 0.0203 | D23: 4.8853 | E23: 0 | F23: Yes**
A24: Tangibility (β4) | B24: -0.0291 | C24: 0.0273 | D24: -1.0682 | E24: 0.2882 | F24: No
A26: R-squared = 0.4561 | Adj. R-squared = 0.4332

Sheet Formulas Used
A1: Formulas Used in This Workbook
A2: Every ratio and statistic below is a live Excel formula, not a typed-in number — open any cell in Ratios Panel, Descriptive Stats, Correlation Matrix or a company sheet and the formula bar will show exactly this. Cell references below are illustrative (row 5 of Ratios Panel); the same formula pattern repeats down all 100 rows.
A4: 1. Core Ratios — Ratios Panel sheet (row 5 = KPR Mill, FY2015-16)
A5: Item | B5: Definition | C5: Excel Formula (as used in this workbook) | D5: Where to find it
A6: Total Equity | B6: Equity Capital + Reserves & Surplus | C6: ='Raw Data'!G5+'Raw Data'!H5 | D6: Ratios Panel, column F
A7: D/E Ratio | B7: Borrowings ÷ Total Equity | C7: =G5/F5 | D7: Ratios Panel, column J
A8: ROE | B8: Net Profit ÷ Total Equity | C8: =E5/F5 | D8: Ratios Panel, column K
A9: ROA | B9: Net Profit ÷ Total Assets | C9: =E5/H5 | D9: Ratios Panel, column L
A10: Size | B10: LN(Total Assets) | C10: =LN(H5) | D10: Ratios Panel, column M
A11: Sales Growth % | B11: (Sales this year − Sales last year) ÷ Sales last year | C11: =(C5-'Raw Data'!D4)/'Raw Data'!D4 | D11: Ratios Panel, column N
A12: Tangibility | B12: Fixed Assets ÷ Total Assets | C12: =I5/H5 | D12: Ratios Panel, column O
A13: EPS | B13: As reported by Screener.in (split-adjusted); not derived within the workbook | C13: ='Raw Data'!L5 | D13: Ratios Panel, column P
A15: 2. Descriptive Statistics — by company (Descriptive Stats sheet)
A16: Item | B16: Definition | C16: Excel Formula (as used in this workbook) | D16: Where to find it
A17: Mean D/E (per company) | B17: Average D/E across that company's 10 years | C17: =AVERAGEIF('Ratios Panel'!$A$5:$A$104,A5,'Ratios Panel'!$J$5:$J$104) | D17: Descriptive Stats, column B
A18: SD D/E (per company) | B18: Standard deviation of D/E across that company's 10 years | C18: =SQRT(SUMPRODUCT(('Ratios Panel'!$A$5:$A$104=A5)*('Ratios Panel'!$J$5:$J$104-B5)^2)/(COUNTIF('Ratios Panel'!$A$5:$A$104,A5)-1)) | D18: Descriptive Stats, column C
A19: Min / Max D/E | B19: Lowest / highest D/E for that company across its 10 years | C19: =MINIFS('Ratios Panel'!$J$5:$J$104,'Ratios Panel'!$A$5:$A$104,A5) | D19: Descriptive Stats, columns D & E
A20: Pooled Mean / SD / Min / Max | B20: Same statistic across all 100 firm-years at once | C20: =AVERAGE('Ratios Panel'!$J$5:$J$104) (and STDEV / MIN / MAX) | D20: Descriptive Stats, POOLED row
A22: 3. Correlation Matrix
A23: Item | B23: Definition | C23: Excel Formula (as used in this workbook) | D23: Where to find it
A24: Pearson correlation | B24: Correlation between any two variables across all 100 firm-years, e.g. D/E and ROE | C24: =CORREL('Ratios Panel'!$J$5:$J$104,'Ratios Panel'!$K$5:$K$104) | D24: Correlation Matrix, each cell
A26: 4. Company Sheets (e.g. 'KPR Mill' sheet) — same pattern as Ratios Panel, self-contained
A27: Item | B27: Definition | C27: Excel Formula (as used in this workbook) | D27: Where to find it
A28: D/E, ROE, ROA, Size, Growth, Tangibility | B28: Identical formulas to Section 1 above, but referencing only that company's own 10 rows on its own sheet | C28: e.g. =F10/E10 (Total Equity in col F, Borrowings in col G on that sheet) | D28: Each company sheet, its own ratio table
A29: 10-Yr Average row | B29: Mean of each ratio across that company's own 10 years | C29: =AVERAGE(J5:J14) | D29: Bottom of each company sheet
A30: SD (10-yr) row | B30: Standard deviation of D/E, ROE, ROA and EPS for that one company | C30: =STDEV(J5:J14) | D30: Bottom of each company sheet
A32: 5. Regression Analysis — NOT an Excel formula (see note)
A33: Multiple regression | B33: Excel's native formulas (SLOPE, INTERCEPT, CORREL) only handle one predictor at a time and cannot run a 4-variable multiple regression like ROE = β0 + β1(D/E) + β2(Size) + β3(Growth) + β4(Tangibility) + ε on their own. This was computed using Python's statsmodels library (Ordinary Least Squares) reading directly from the same Ratios Panel data shown in this workbook — the coefficients, R², t-statistics and p-values on the 'Regression Output' sheet are that software's output, pasted in as values because Excel has no live multi-variable regression formula. Re-running the underlying Python script on the Ratios Panel data reproduces the exact same numbers.
